Workbook

Sheet Menu

Sheet Resumo de Custo
A2: Menu | E2: Resumo de Custo | K2: =TODAY() -> 46101 | L2: =K3-K2 -> -95
K3: 46006
A4: Horas Trabalhadas
A5: 220
B6: Janeiro | L6: Fevereiro | V6: Março | AF6: Abril | AP6: Maio | AZ6: Junho | BJ6: Julho | BT6: Agosto | CD6: Setembro | CN6: Outubro | CX6: Novembro | DH6: Dezembro
A7: Linha | B7: Produto Químico | C7: M.O.D | D7: M.O.I | E7: Custo Variáveis | F7: Outros Custos | G7: Transporte | H7: Manutenção | I7: Investimentos | J7: Total | K7: Custo Hora | L7: Produto Químico | M7: M.O.D | N7: M.O.I | O7: Custo Variáveis | P7: Outros Custos | Q7: Transporte | R7: Manutenção | S7: Investimentos | T7: Total | U7: Custo Hora | V7: Produto Químico | W7: M.O.D | X7: M.O.I | Y7: Custo Variáveis | Z7: Outros Custos | AA7: Transporte | AB7: Manutenção | AC7: Investimentos | AD7: Total | AE7: Custo Hora | AF7: Produto Químico | AG7: M.O.D | AH7: M.O.I | AI7: Custo Variáveis | AJ7: Outros Custos | AK7: Transporte | AL7: Manutenção | AM7: Investimentos | AN7: Total | AO7: Custo Hora | AP7: Produto Químico | AQ7: M.O.D | AR7: M.O.I | AS7: Custo Variáveis | AT7: Outros Custos | AU7: Transporte | AV7: Manutenção | AW7: Investimentos | AX7: Total | AY7: Custo Hora | AZ7: Produto Químico | BA7: M.O.D | BB7: M.O.I | BC7: Custo Variáveis | BD7: Outros Custos | BE7: Transporte | BF7: Manutenção | BG7: Investimentos | BH7: Total | BI7: Custo Hora | BJ7: Produto Químico | BK7: M.O.D | BL7: M.O.I | BM7: Custo Variáveis | BN7: Outros Custos | BO7: Transporte | BP7: Manutenção | BQ7: Investimentos | BR7: Total | BS7: Custo Hora | BT7: Produto Químico | BU7: M.O.D | BV7: M.O.I | BW7: Custo Variáveis | BX7: Outros Custos | BY7: Transporte | BZ7: Manutenção | CA7: Investimentos | CB7: Total | CC7: Custo Hora | CD7: Produto Químico | CE7: M.O.D | CF7: M.O.I | CG7: Custo Variáveis | CH7: Outros Custos | CI7: Transporte | CJ7: Manutenção | CK7: Investimentos | CL7: Total | CM7: Custo Hora | CN7: Produto Químico | CO7: M.O.D | CP7: M.O.I | CQ7: Custo Variáveis | CR7: Outros Custos | CS7: Transporte | CT7: Manutenção | CU7: Investimentos | CV7: Total | CW7: Custo Hora | CX7: Produto Químico | CY7: M.O.D | CZ7: M.O.I | DA7: Custo Variáveis | DB7: Outros Custos | DC7: Transporte | DD7: Manutenção | DE7: Investimentos | DF7: Total | DG7: Custo Hora | DH7: Produto Químico | DI7: M.O.D | DJ7: M.O.I | DK7: Custo Variáveis | DL7: Outros Custos | DM7: Transporte | DN7: Manutenção | DO7: Investimentos | DP7: Total | DQ7: Custo Hora | DS7: Jan | DT7: Fev | DU7: Mar | DV7: Abr | DW7: Mai | DX7: Jun | DY7: Jul | DZ7: Ago | EA7: Set | EB7: Out | EC7: Nov | ED7: Dez | EF7: Jan | EG7: Fev | EH7: Mar | EI7: Abr | EJ7: Mai | EK7: Jun | EL7: Jul | EM7: Ago | EN7: Set | EO7: Out | EP7: Nov | EQ7: Dez
A8: Pré Tratamento | B8: ='Pré Tratamento'!G15 -> 0 | C8: ='Resumo M.O'!$C$14 -> 1490.6153 | D8: ='Resumo M.O'!$C$29 -> 2265.2114 | E8: ='Resumo Custos Variáveis'!$E$21 -> 0 | F8: ='Outros Custos'!$C$31 -> 0 | G8: =Transporte!$C$20 -> 0 | H8: =Manutenção!$C$21 -> 0 | I8: =Investimentos!G10 -> 0 | J8: =SUM(B8:I8) -> 3755.8267 | K8: =IF($L$2>=1,J8/$A$5,0) -> 0 | L8: ='Pré Tratamento'!J15 -> 0 | M8: ='Resumo M.O'!$D$14 -> 1490.6153 | N8: ='Resumo M.O'!$D$29 -> 2265.2114 | O8: ='Resumo Custos Variáveis'!$F$21 -> 0 | P8: ='Outros Custos'!$D$31 -> 0 | Q8: =Transporte!$D$20 -> 0 | R8: =Manutenção!$D$21 -> 0 | S8: =I8 -> 0 | T8: =SUM(L8:S8) -> 3755.8267 | U8: =IF($L$2>=1,T8/$A$5,0) -> 0 | V8: ='Pré Tratamento'!M15 -> 4019.75 | W8: ='Resumo M.O'!$E$14 -> 1490.6153 | X8: ='Resumo M.O'!$E$29 -> 2265.2114 | Y8: ='Resumo Custos Variáveis'!$G$21 -> 2404.5263 | Z8: ='Outros Custos'!$E$31 -> 0 | AA8: =Transporte!$E$20 -> 0 | AB8: =Manutenção!$E$21 -> 0 | AC8: =S8 -> 0 | AD8: =SUM(V8:AC8) -> 10180.103 | AE8: =IF($L$2>=1,AD8/$A$5,0) -> 0 | AF8: ='Pré Tratamento'!P15 -> 2903.5 | AG8: ='Resumo M.O'!$F$14 -> 1490.6153 | AH8: ='Resumo M.O'!$F$29 -> 2265.2114 | AI8: ='Resumo Custos Variáveis'!$H$21 -> 1573.8421 | AJ8: ='Outros Custos'!$F$31 -> 0 | AK8: =Transporte!$F$20 -> 0 | AL8: =Manutenção!$F$21 -> 0 | AM8: =AC8 -> 0 | AN8: =SUM(AF8:AM8) -> 8233.1688 | AO8: =IF(L2>=1,AN8/$A$5,0) -> 0 | AP8: ='Pré Tratamento'!S15 -> 129 | AQ8: ='Resumo M.O'!$G$14 -> 1490.6153 | AR8: ='Resumo M.O'!$G$29 -> 2265.2114 | AS8: ='Resumo Custos Variáveis'!$I$21 -> 0 | AT8: ='Outros Custos'!$G$31 -> 0 | AU8: =Transporte!$G$20 -> 0 | AV8: =Manutenção!$G$21 -> 0 | AW8: =AM8 -> 0 | AX8: =SUM(AP8:AW8) -> 3884.8267 | AY8: =IF(L2>=1,AX8/$A$5,0) -> 0 | AZ8: ='Pré Tratamento'!V15 -> 258 | BA8: ='Resumo M.O'!$H$14 -> 1490.6153 | BB8: ='Resumo M.O'!$H$29 -> 2265.2114 | BC8: ='Resumo Custos Variáveis'!$J$21 -> 0 | BD8: ='Outros Custos'!$H$31 -> 0 | BE8: =Transporte!$H$20 -> 0 | BF8: =Manutenção!$H$21 -> 3061.5385 | BG8: =AW8 -> 0 | BH8: =SUM(AZ8:BG8) -> 7075.3651 | BI8: =IF(L2>=1,BH8/$A$5,0) -> 0 | BJ8: ='Pré Tratamento'!Y15 -> 0 | BK8: ='Resumo M.O'!$I$14 -> 1490.6153 | BL8: ='Resumo M.O'!$I$29 -> 2265.2114 | BM8: ='Resumo Custos Variáveis'!$K$21 -> 0 | BN8: ='Outros Custos'!$I$31 -> 0 | BO8: =Transporte!$I$20 -> 0 | BP8: =Manutenção!$I$21 -> 3030.7692 | BQ8: =BG8 -> 0 | BR8: =SUM(BJ8:BQ8) -> 6786.5959 | BS8: =IF(L2>=1,BR8/$A$5,0) -> 0 | BT8: ='Pré Tratamento'!AB15 -> 0 | BU8: ='Resumo M.O'!$J$14 -> 1490.6153 | BV8: ='Resumo M.O'!$J$29 -> 2265.2114 | BW8: ='Resumo Custos Variáveis'!$L$21 -> 0 | BX8: ='Outros Custos'!$J$31 -> 0 | BY8: =Transporte!$J$20 -> 0 | BZ8: =Manutenção!$J$21 -> 0 | CA8: =BQ8 -> 0 | CB8: =SUM(BT8:CA8) -> 3755.8267 | CC8: =IF(L2>=1,CB8/$A$5,0) -> 0 | CD8: ='Pré Tratamento'!AE15 -> 0 | CE8: ='Resumo M.O'!$K$14 -> 1490.6153 | CF8: ='Resumo M.O'!$K$29 -> 2265.2114 | CG8: ='Resumo Custos Variáveis'!$M$21 -> 0 | CH8: ='Outros Custos'!$K$31 -> 0 | CI8: =Transporte!$K$20 -> 0 | CJ8: =Manutenção!$K$21 -> 0 | CK8: =CA8 -> 0 | CL8: =SUM(CD8:CK8) -> 3755.8267 | CM8: =IF(L2>=1,CL8/$A$5,0) -> 0 | CN8: ='Pré Tratamento'!AH15 -> 0 | CO8: ='Resumo M.O'!$L$14 -> 1490.6153 | CP8: ='Resumo M.O'!$L$29 -> 2265.2114 | CQ8: ='Resumo Custos Variáveis'!$N$21 -> 0 | CR8: ='Outros Custos'!$L$31 -> 0 | CS8: =Transporte!$L$20 -> 0 | CT8: =Manutenção!$L$21 -> 0 | CU8: =CK8 -> 0 | CV8: =SUM(CN8:CU8) -> 3755.8267 | CW8: =IF(L2>=1,CV8/$A$5,0) -> 0 | CX8: ='Pré Tratamento'!AK15 -> 0 | CY8: ='Resumo M.O'!$M$14 -> 1490.6153 | CZ8: ='Resumo M.O'!$M$29 -> 2265.2114 | DA8: ='Resumo Custos Variáveis'!$O$21 -> 0 | DB8: ='Outros Custos'!$M$31 -> 0 | DC8: =Transporte!$M$20 -> 0 | DD8: =Manutenção!$M$21 -> 0 | DE8: =CU8 -> 0 | DF8: =SUM(CX8:DE8) -> 3755.8267 | DG8: =IF(L2>=1,DF8/$A$5,0) -> 0 | DH8: ='Pré Tratamento'!AN15 -> 0 | DI8: ='Resumo M.O'!$N$14 -> 1490.6153 | DJ8: ='Resumo M.O'!$N$29 -> 2265.2114 | DK8: ='Resumo Custos Variáveis'!$P$21 -> 0 | DL8: ='Outros Custos'!$N$31 -> 0 | DM8: =Transporte!$N$20 -> 0 | DN8: =Manutenção!$N$21 -> 0 | DO8: =DE8 -> 0 | DP8: =SUM(DH8:DO8) -> 3755.8267 | DQ8: =IF(L2>=1,DP8/$A$5,0) -> 0 | DS8: =K8 -> 0 | DT8: =U8 -> 0 | DU8: =AE8 -> 0 | DV8: =AO8 -> 0 | DW8: =AY8 -> 0 | DX8: =BI8 -> 0 | DY8: =BS8 -> 0 | DZ8: =CC8 -> 0 | EA8: =CM8 -> 0 | EB8: =CW8 -> 0 | EC8: =DG8 -> 0 | ED8: =DQ8 -> 0 | EF8: =B8/$A$5 -> 0 | EG8: =L8/$A$5 -> 0 | EH8: =V8/$A$5 -> 18.271591 | EI8: =AF8/$A$5 -> 13.197727 | EJ8: =AP8/$A$5 -> 0.58636364 | EK8: =AZ8/$A$5 -> 1.1727273 | EL8: =BJ8/$A$5 -> 0 | EM8: =BT8/$A$5 -> 0 | EN8: =CD8/$A$5 -> 0 | EO8: =CN8/$A$5 -> 0 | EP8: =CX8/$A$5 -> 0 | EQ8: =DH8/$A$5 -> 0
A9: Cobre Alcalino | B9: ='Cobre Alcalino'!G16 -> 0 | C9: ='Resumo M.O'!$C$14 -> 1490.6153 | D9: ='Resumo M.O'!$C$29 -> 2265.2114 | E9: ='Resumo Custos Variáveis'!$E$21 -> 0 | F9: ='Outros Custos'!$C$31 -> 0 | G9: =Transporte!$C$20 -> 0 | H9: =Manutenção!$C$21 -> 0 | I9: =Investimentos!G14 -> 0 | J9: =SUM(B9:I9) -> 3755.8267 | K9: =IF($L$2>=1,J9/$A$5,0) -> 0 | L9: ='Cobre Alcalino'!J16 -> 0 | M9: ='Resumo M.O'!$D$14 -> 1490.6153 | N9: ='Resumo M.O'!$D$29 -> 2265.2114 | O9: ='Resumo Custos Variáveis'!$F$21 -> 0 | P9: ='Outros Custos'!$D$31 -> 0 | Q9: =Transporte!$D$20 -> 0 | R9: =Manutenção!$D$21 -> 0 | S9: =I9 -> 0 | T9: =SUM(L9:S9) -> 3755.8267 | U9: =IF($L$2>=1,T9/$A$5,0) -> 0 | V9: ='Cobre Alcalino'!M16 -> 13969.47 | W9: ='Resumo M.O'!$E$14 -> 1490.6153 | X9: ='Resumo M.O'!$E$29 -> 2265.2114 | Y9: ='Resumo Custos Variáveis'!$G$21 -> 2404.5263 | Z9: ='Outros Custos'!$E$31 -> 0 | AA9: =Transporte!$E$20 -> 0 | AB9: =Manutenção!$E$21 -> 0 | AC9: =S9 -> 0 | AD9: =SUM(V9:AC9) -> 20129.823 | AE9: =IF($L$2>=1,AD9/$A$5,0) -> 0 | AF9: ='Cobre Alcalino'!P16 -> 13481.89 | AG9: ='Resumo M.O'!$F$14 -> 1490.6153 | AH9: ='Resumo M.O'!$F$29 -> 2265.2114 | AI9: ='Resumo Custos Variáveis'!$H$21 -> 1573.8421 | AJ9: ='Outros Custos'!$F$31 -> 0 | AK9: =Transporte!$F$20 -> 0 | AL9: =Manutenção!$F$21 -> 0 | AM9: =AC9 -> 0 | AN9: =SUM(AF9:AM9) -> 18811.559 | AO9: =IF(L2>=1,AN9/$A$5,0) -> 0 | AP9: ='Cobre Alcalino'!S16 -> 669.8 | AQ9: ='Resumo M.O'!$G$14 -> 1490.6153 | AR9: ='Resumo M.O'!$G$29 -> 2265.2114 | AS9: ='Resumo Custos Variáveis'!$I$21 -> 0 | AT9: ='Outros Custos'!$G$31 -> 0 | AU9: =Transporte!$G$20 -> 0 | AV9: =Manutenção!$G$21 -> 0 | AW9: =AM9 -> 0 | AX9: =SUM(AP9:AW9) -> 4425.6267 | AY9: =IF(L2>=1,AX9/$A$5,0) -> 0 | AZ9: ='Cobre Alcalino'!V16 -> 669.8 | BA9: ='Resumo M.O'!$H$14 -> 1490.6153 | BB9: ='Resumo M.O'!$H$29 -> 2265.2114 | BC9: ='Resumo Custos Variáveis'!$J$21 -> 0 | BD9: ='Outros Custos'!$H$31 -> 0 | BE9: =Transporte!$H$20 -> 0 | BF9: =Manutenção!$H$21 -> 3061.5385 | BG9: =AW9 -> 0 | BH9: =SUM(AZ9:BG9) -> 7487.1651 | BI9: =IF(L2>=1,BH9/$A$5,0) -> 0 | BJ9: ='Cobre Alcalino'!Y16 -> 0 | BK9: ='Resumo M.O'!$I$14 -> 1490.6153 | BL9: ='Resumo M.O'!$I$29 -> 2265.2114 | BM9: ='Resumo Custos Variáveis'!$K$21 -> 0 | BN9: ='Outros Custos'!$I$31 -> 0 | BO9: =Transporte!$I$20 -> 0 | BP9: =Manutenção!$I$21 -> 3030.7692 | BQ9: =BG9 -> 0 | BR9: =SUM(BJ9:BQ9) -> 6786.5959 | BS9: =IF(L2>=1,BR9/$A$5,0) -> 0 | BT9: ='Cobre Alcalino'!AB16 -> 0 | BU9: ='Resumo M.O'!$J$14 -> 1490.6153 | BV9: ='Resumo M.O'!$J$29 -> 2265.2114 | BW9: ='Resumo Custos Variáveis'!$L$21 -> 0 | BX9: ='Outros Custos'!$J$31 -> 0 | BY9: =Transporte!$J$20 -> 0 | BZ9: =Manutenção!$J$21 -> 0 | CA9: =BQ9 -> 0 | CB9: =SUM(BT9:CA9) -> 3755.8267 | CC9: =IF(L2>=1,CB9/$A$5,0) -> 0 | CD9: ='Cobre Alcalino'!AE16 -> 0 | CE9: ='Resumo M.O'!$K$14 -> 1490.6153 | CF9: ='Resumo M.O'!$K$29 -> 2265.2114 | CG9: ='Resumo Custos Variáveis'!$M$21 -> 0 | CH9: ='Outros Custos'!$K$31 -> 0 | CI9: =Transporte!$K$20 -> 0 | CJ9: =Manutenção!$K$21 -> 0 | CK9: =CA9 -> 0 | CL9: =SUM(CD9:CK9) -> 3755.8267 | CM9: =IF(L2>=1,CL9/$A$5,0) -> 0 | CN9: ='Cobre Alcalino'!AH16 -> 0 | CO9: ='Resumo M.O'!$L$14 -> 1490.6153 | CP9: ='Resumo M.O'!$L$29 -> 2265.2114 | CQ9: ='Resumo Custos Variáveis'!$N$21 -> 0 | CR9: ='Outros Custos'!$L$31 -> 0 | CS9: =Transporte!$L$20 -> 0 | CT9: =Manutenção!$L$21 -> 0 | CU9: =CK9 -> 0 | CV9: =SUM(CN9:CU9) -> 3755.8267 | CW9: =IF(L2>=1,CV9/$A$5,0) -> 0 | CX9: ='Cobre Alcalino'!AK16 -> 0 | CY9: ='Resumo M.O'!$M$14 -> 1490.6153 | CZ9: ='Resumo M.O'!$M$29 -> 2265.2114 | DA9: ='Resumo Custos Variáveis'!$O$21 -> 0 | DB9: ='Outros Custos'!$M$31 -> 0 | DC9: =Transporte!$M$20 -> 0 | DD9: =Manutenção!$M$21 -> 0 | DE9: =CU9 -> 0 | DF9: =SUM(CX9:DE9) -> 3755.8267 | DG9: =IF(L2>=1,DF9/$A$5,0) -> 0 | DH9: ='Cobre Alcalino'!AN16 -> 0 | DI9: ='Resumo M.O'!$N$14 -> 1490.6153 | DJ9: ='Resumo M.O'!$N$29 -> 2265.2114 | DK9: ='Resumo Custos Variáveis'!$P$21 -> 0 | DL9: ='Outros Custos'!$N$31 -> 0 | DM9: =Transporte!$N$20 -> 0 | DN9: =Manutenção!$N$21 -> 0 | DO9: =DE9 -> 0 | DP9: =SUM(DH9:DO9) -> 3755.8267 | DQ9: =IF(L2>=1,DP9/$A$5,0) -> 0 | DS9: =K9 -> 0 | DT9: =U9 -> 0 | DU9: =AE9 -> 0 | DV9: =AO9 -> 0 | DW9: =AY9 -> 0 | DX9: =BI9 -> 0 | DY9: =BS9 -> 0 | DZ9: =CC9 -> 0 | EA9: =CM9 -> 0 | EB9: =CW9 -> 0 | EC9: =DG9 -> 0 | ED9: =DQ9 -> 0 | EF9: =B9/$A$5 -> 0 | EG9: =L9/$A$5 -> 0 | EH9: =V9/$A$5 -> 63.497591 | EI9: =AF9/$A$5 -> 61.281318 | EJ9: =AP9/$A$5 -> 3.0445455 | EK9: =AZ9/$A$5 -> 3.0445455 | EL9: =BJ9/$A$5 -> 0 | EM9: =BT9/$A$5 -> 0 | EN9: =CD9/$A$5 -> 0 | EO9: =CN9/$A$5 -> 0 | EP9: =CX9/$A$5 -> 0 | EQ9: =DH9/$A$5 -> 0
A10: Níquel Strik | B10: ='Níquel Strik'!G15 -> 0 | C10: ='Resumo M.O'!$C$14 -> 1490.6153 | D10: ='Resumo M.O'!$C$29 -> 2265.2114 | E10: ='Resumo Custos Variáveis'!$E$21 -> 0 | F10: ='Outros Custos'!$C$31 -> 0 | G10: =Transporte!$C$20 -> 0 | H10: =Manutenção!$C$21 -> 0 | I10: =Investimentos!G18 -> 0 | J10: =SUM(B10:I10) -> 3755.8267 | K10: =IF($L$2>=1,J10/$A$5,0) -> 0 | L10: ='Níquel Strik'!J15 -> 0 | M10: ='Resumo M.O'!$D$14 -> 1490.6153 | N10: ='Resumo M.O'!$D$29 -> 2265.2114 | O10: ='Resumo Custos Variáveis'!$F$21 -> 0 | P10: ='Outros Custos'!$D$31 -> 0 | Q10: =Transporte!$D$20 -> 0 | R10: =Manutenção!$D$21 -> 0 | S10: =I10 -> 0 | T10: =SUM(L10:S10) -> 3755.8267 | U10: =IF($L$2>=1,T10/$A$5,0) -> 0 | V10: ='Níquel Strik'!M15 -> 7666.505 | W10: ='Resumo M.O'!$E$14 -> 1490.6153 | X10: ='Resumo M.O'!$E$29 -> 2265.2114 | Y10: ='Resumo Custos Variáveis'!$G$21 -> 2404.5263 | Z10: ='Outros Custos'!$E$31 -> 0 | AA10: =Transporte!$E$20 -> 0 | AB10: =Manutenção!$E$21 -> 0 | AC10: =S10 -> 0 | AD10: =SUM(V10:AC10) -> 13826.858 | AE10: =IF($L$2>=1,AD10/$A$5,0) -> 0 | AF10: ='Níquel Strik'!P15 -> 3351.28 | AG10: ='Resumo M.O'!$F$14 -> 1490.6153 | AH10: ='Resumo M.O'!$F$29 -> 2265.2114 | AI10: ='Resumo Custos Variáveis'!$H$21 -> 1573.8421 | AJ10: ='Outros Custos'!$F$31 -> 0 | AK10: =Transporte!$F$20 -> 0 | AL10: =Manutenção!$F$21 -> 0 | AM10: =AC10 -> 0 | AN10: =SUM(AF10:AM10) -> 8680.9488 | AO10: =IF(L2>=1,AN10/$A$5,0) -> 0 | AP10: ='Níquel Strik'!S15 -> 5959.8 | AQ10: ='Resumo M.O'!$G$14 -> 1490.6153 | AR10: ='Resumo M.O'!$G$29 -> 2265.2114 | AS10: ='Resumo Custos Variáveis'!$I$21 -> 0 | AT10: ='Outros Custos'!$G$31 -> 0 | AU10: =Transporte!$G$20 -> 0 | AV10: =Manutenção!$G$21 -> 0 | AW10: =AM10 -> 0 | AX10: =SUM(AP10:AW10) -> 9715.6267 | AY10: =IF(L2>=1,AX10/$A$5,0) -> 0 | AZ10: ='Níquel Strik'!V15 -> 5959.8 | BA10: ='Resumo M.O'!$H$14 -> 1490.6153 | BB10: ='Resumo M.O'!$H$29 -> 2265.2114 | BC10: ='Resumo Custos Variáveis'!$J$21 -> 0 | BD10: ='Outros Custos'!$H$31 -> 0 | BE10: =Transporte!$H$20 -> 0 | BF10: =Manutenção!$H$21 -> 3061.5385 | BG10: =AW10 -> 0 | BH10: =SUM(AZ10:BG10) -> 12777.165 | BI10: =IF(L2>=1,BH10/$A$5,0) -> 0 | BJ10: ='Níquel Strik'!Y15 -> 0 | BK10: ='Resumo M.O'!$I$14 -> 1490.6153 | BL10: ='Resumo M.O'!$I$29 -> 2265.2114 | BM10: ='Resumo Custos Variáveis'!$K$21 -> 0 | BN10: ='Outros Custos'!$I$31 -> 0 | BO10: =Transporte!$I$20 -> 0 | BP10: =Manutenção!$I$21 -> 3030.7692 | BQ10: =BG10 -> 0 | BR10: =SUM(BJ10:BQ10) -> 6786.5959 | BS10: =IF(L2>=1,BR10/$A$5,0) -> 0 | BT10: ='Níquel Strik'!AB15 -> 0 | BU10: ='Resumo M.O'!$J$14 -> 1490.6153 | BV10: ='Resumo M.O'!$J$29 -> 2265.2114 | BW10: ='Resumo Custos Variáveis'!$L$21 -> 0 | BX10: ='Outros Custos'!$J$31 -> 0 | BY10: =Transporte!$J$20 -> 0 | BZ10: =Manutenção!$J$21 -> 0 | CA10: =BQ10 -> 0 | CB10: =SUM(BT10:CA10) -> 3755.8267 | CC10: =IF(L2>=1,CB10/$A$5,0) -> 0 | CD10: ='Níquel Strik'!AE15 -> 0 | CE10: ='Resumo M.O'!$K$14 -> 1490.6153 | CF10: ='Resumo M.O'!$K$29 -> 2265.2114 | CG10: ='Resumo Custos Variáveis'!$M$21 -> 0 | CH10: ='Outros Custos'!$K$31 -> 0 | CI10: =Transporte!$K$20 -> 0 | CJ10: =Manutenção!$K$21 -> 0 | CK10: =CA10 -> 0 | CL10: =SUM(CD10:CK10) -> 3755.8267 | CM10: =IF(L2>=1,CL10/$A$5,0) -> 0 | CN10: ='Níquel Strik'!AH15 -> 0 | CO10: ='Resumo M.O'!$L$14 -> 1490.6153 | CP10: ='Resumo M.O'!$L$29 -> 2265.2114 | CQ10: ='Resumo Custos Variáveis'!$N$21 -> 0 | CR10: ='Outros Custos'!$L$31 -> 0 | CS10: =Transporte!$L$20 -> 0 | CT10: =Manutenção!$L$21 -> 0 | CU10: =CK10 -> 0 | CV10: =SUM(CN10:CU10) -> 3755.8267 | CW10: =IF(L2>=1,CV10/$A$5,0) -> 0 | CX10: ='Níquel Strik'!AK15 -> 0 | CY10: ='Resumo M.O'!$M$14 -> 1490.6153 | CZ10: ='Resumo M.O'!$M$29 -> 2265.2114 | DA10: ='Resumo Custos Variáveis'!$O$21 -> 0 | DB10: ='Outros Custos'!$M$31 -> 0 | DC10: =Transporte!$M$20 -> 0 | DD10: =Manutenção!$M$21 -> 0 | DE10: =CU10 -> 0 | DF10: =SUM(CX10:DE10) -> 3755.8267 | DG10: =IF(L2>=1,DF10/$A$5,0) -> 0 | DH10: ='Níquel Strik'!AN15 -> 0 | DI10: ='Resumo M.O'!$N$14 -> 1490.6153 | DJ10: ='Resumo M.O'!$N$29 -> 2265.2114 | DK10: ='Resumo Custos Variáveis'!$P$21 -> 0 | DL10: ='Outros Custos'!$N$31 -> 0 | DM10: =Transporte!$N$20 -> 0 | DN10: =Manutenção!$N$21 -> 0 | DO10: =DE10 -> 0 | DP10: =SUM(DH10:DO10) -> 3755.8267 | DQ10: =IF(L2>=1,DP10/$A$5,0) -> 0 | DS10: =K10 -> 0 | DT10: =U10 -> 0 | DU10: =AE10 -> 0 | DV10: =AO10 -> 0 | DW10: =AY10 -> 0 | DX10: =BI10 -> 0 | DY10: =BS10 -> 0 | DZ10: =CC10 -> 0 | EA10: =CM10 -> 0 | EB10: =CW10 -> 0 | EC10: =DG10 -> 0 | ED10: =DQ10 -> 0 | EF10: =B10/$A$5 -> 0 | EG10: =L10/$A$5 -> 0 | EH10: =V10/$A$5 -> 34.84775 | EI10: =AF10/$A$5 -> 15.233091 | EJ10: =AP10/$A$5 -> 27.09 | EK10: =AZ10/$A$5 -> 27.09 | EL10: =BJ10/$A$5 -> 0 | EM10: =BT10/$A$5 -> 0 | EN10: =CD10/$A$5 -> 0 | EO10: =CN10/$A$5 -> 0 | EP10: =CX10/$A$5 -> 0 | EQ10: =DH10/$A$5 -> 0
A11: Cobre Ácido | B11: =+'Cobre Ácido'!G15 -> 0 | C11: ='Resumo M.O'!$C$14 -> 1490.6153 | D11: ='Resumo M.O'!$C$29 -> 2265.2114 | E11: ='Resumo Custos Variáveis'!$E$21 -> 0 | F11: ='Outros Custos'!$C$31 -> 0 | G11: =Transporte!$C$20 -> 0 | H11: =Manutenção!$C$21 -> 0 | I11: =Investimentos!G24 -> 0 | J11: =SUM(B11:I11) -> 3755.8267 | K11: =IF($L$2>=1,J11/$A$5,0) -> 0 | L11: ='Cobre Ácido'!J15 -> 0 | M11: ='Resumo M.O'!$D$14 -> 1490.6153 | N11: ='Resumo M.O'!$D$29 -> 2265.2114 | O11: ='Resumo Custos Variáveis'!$F$21 -> 0 | P11: ='Outros Custos'!$D$31 -> 0 | Q11: =Transporte!$D$20 -> 0 | R11: =Manutenção!$D$21 -> 0 | S11: =I11 -> 0 | T11: =SUM(L11:S11) -> 3755.8267 | U11: =IF($L$2>=1,T11/$A$5,0) -> 0 | V11: ='Cobre Ácido'!M15 -> 25728.56 | W11: ='Resumo M.O'!$E$14 -> 1490.6153 | X11: ='Resumo M.O'!$E$29 -> 2265.2114 | Y11: ='Resumo Custos Variáveis'!$G$21 -> 2404.5263 | Z11: ='Outros Custos'!$E$31 -> 0 | AA11: =Transporte!$E$20 -> 0 | AB11: =Manutenção!$E$21 -> 0 | AC11: =S11 -> 0 | AD11: =SUM(V11:AC11) -> 31888.913 | AE11: =IF($L$2>=1,AD11/$A$5,0) -> 0 | AF11: ='Cobre Ácido'!P15 -> 22757.76 | AG11: ='Resumo M.O'!$F$14 -> 1490.6153 | AH11: ='Resumo M.O'!$F$29 -> 2265.2114 | AI11: ='Resumo Custos Variáveis'!$H$21 -> 1573.8421 | AJ11: ='Outros Custos'!$F$31 -> 0 | AK11: =Transporte!$F$20 -> 0 | AL11: =Manutenção!$F$21 -> 0 | AM11: =AC11 -> 0 | AN11: =SUM(AF11:AM11) -> 28087.429 | AO11: =IF(L2>=1,AN11/$A$5,0) -> 0 | AP11: ='Cobre Ácido'!S15 -> 1926 | AQ11: ='Resumo M.O'!$G$14 -> 1490.6153 | AR11: ='Resumo M.O'!$G$29 -> 2265.2114 | AS11: ='Resumo Custos Variáveis'!$I$21 -> 0 | AT11: ='Outros Custos'!$G$31 -> 0 | AU11: =Transporte!$G$20 -> 0 | AV11: =Manutenção!$G$21 -> 0 | AW11: =AM11 -> 0 | AX11: =SUM(AP11:AW11) -> 5681.8267 | AY11: =IF(L2>=1,AX11/$A$5,0) -> 0 | AZ11: ='Cobre Ácido'!V15 -> 16768.63 | BA11: ='Resumo M.O'!$H$14 -> 1490.6153 | BB11: ='Resumo M.O'!$H$29 -> 2265.2114 | BC11: ='Resumo Custos Variáveis'!$J$21 -> 0 | BD11: ='Outros Custos'!$H$31 -> 0 | BE11: =Transporte!$H$20 -> 0 | BF11: =Manutenção!$H$21 -> 3061.5385 | BG11: =AW11 -> 0 | BH11: =SUM(AZ11:BG11) -> 23585.995 | BI11: =IF(L2>=1,BH11/$A$5,0) -> 0 | BJ11: ='Cobre Ácido'!Y15 -> 0 | BK11: ='Resumo M.O'!$I$14 -> 1490.6153 | BL11: ='Resumo M.O'!$I$29 -> 2265.2114 | BM11: ='Resumo Custos Variáveis'!$K$21 -> 0 | BN11: ='Outros Custos'!$I$31 -> 0 | BO11: =Transporte!$I$20 -> 0 | BP11: =Manutenção!$I$21 -> 3030.7692 | BQ11: =BG11 -> 0 | BR11: =SUM(BJ11:BQ11) -> 6786.5959 | BS11: =IF(L2>=1,BR11/$A$5,0) -> 0 | BT11: ='Cobre Ácido'!AB15 -> 0 | BU11: ='Resumo M.O'!$J$14 -> 1490.6153 | BV11: ='Resumo M.O'!$J$29 -> 2265.2114 | BW11: ='Resumo Custos Variáveis'!$L$21 -> 0 | BX11: ='Outros Custos'!$J$31 -> 0 | BY11: =Transporte!$J$20 -> 0 | BZ11: =Manutenção!$J$21 -> 0 | CA11: =BQ11 -> 0 | CB11: =SUM(BT11:CA11) -> 3755.8267 | CC11: =IF(L2>=1,CB11/$A$5,0) -> 0 | CD11: ='Cobre Ácido'!AE15 -> 0 | CE11: ='Resumo M.O'!$K$14 -> 1490.6153 | CF11: ='Resumo M.O'!$K$29 -> 2265.2114 | CG11: ='Resumo Custos Variáveis'!$M$21 -> 0 | CH11: ='Outros Custos'!$K$31 -> 0 | CI11: =Transporte!$K$20 -> 0 | CJ11: =Manutenção!$K$21 -> 0 | CK11: =CA11 -> 0 | CL11: =SUM(CD11:CK11) -> 3755.8267 | CM11: =IF(L2>=1,CL11/$A$5,0) -> 0 | CN11: ='Cobre Ácido'!AH15 -> 0 | CO11: ='Resumo M.O'!$L$14 -> 1490.6153 | CP11: ='Resumo M.O'!$L$29 -> 2265.2114 | CQ11: ='Resumo Custos Variáveis'!$N$21 -> 0 | CR11: ='Outros Custos'!$L$31 -> 0 | CS11: =Transporte!$L$20 -> 0 | CT11: =Manutenção!$L$21 -> 0 | CU11: =CK11 -> 0 | CV11: =SUM(CN11:CU11) -> 3755.8267 | CW11: =IF(L2>=1,CV11/$A$5,0) -> 0 | CX11: ='Cobre Ácido'!AK15 -> 0 | CY11: ='Resumo M.O'!$M$14 -> 1490.6153 | CZ11: ='Resumo M.O'!$M$29 -> 2265.2114 | DA11: ='Resumo Custos Variáveis'!$O$21 -> 0 | DB11: ='Outros Custos'!$M$31 -> 0 | DC11: =Transporte!$M$20 -> 0 | DD11: =Manutenção!$M$21 -> 0 | DE11: =CU11 -> 0 | DF11: =SUM(CX11:DE11) -> 3755.8267 | DG11: =IF(L2>=1,DF11/$A$5,0) -> 0 | DH11: ='Cobre Ácido'!AN15 -> 0 | DI11: ='Resumo M.O'!$N$14 -> 1490.6153 | DJ11: ='Resumo M.O'!$N$29 -> 2265.2114 | DK11: ='Resumo Custos Variáveis'!$P$21 -> 0 | DL11: ='Outros Custos'!$N$31 -> 0 | DM11: =Transporte!$N$20 -> 0 | DN11: =Manutenção!$N$21 -> 0 | DO11: =DE11 -> 0 | DP11: =SUM(DH11:DO11) -> 3755.8267 | DQ11: =IF(L2>=1,DP11/$A$5,0) -> 0 | DS11: =K11 -> 0 | DT11: =U11 -> 0 | DU11: =AE11 -> 0 | DV11: =AO11 -> 0 | DW11: =AY11 -> 0 | DX11: =BI11 -> 0 | DY11: =BS11 -> 0 | DZ11: =CC11 -> 0 | EA11: =CM11 -> 0 | EB11: =CW11 -> 0 | EC11: =DG11 -> 0 | ED11: =DQ11 -> 0 | EF11: =B11/$A$5 -> 0 | EG11: =L11/$A$5 -> 0 | EH11: =V11/$A$5 -> 116.948 | EI11: =AF11/$A$5 -> 103.44436 | EJ11: =AP11/$A$5 -> 8.7545455 | EK11: =AZ11/$A$5 -> 76.221045 | EL11: =BJ11/$A$5 -> 0 | EM11: =BT11/$A$5 -> 0 | EN11: =CD11/$A$5 -> 0 | EO11: =CN11/$A$5 -> 0 | EP11: =CX11/$A$5 -> 0 | EQ11: =DH11/$A$5 -> 0
A12: Desengraxante Quí | B12: ='Desengraxante Quí'!G15 -> 0 | C12: ='Resumo M.O'!$C$14 -> 1490.6153 | D12: ='Resumo M.O'!$C$29 -> 2265.2114 | E12: ='Resumo Custos Variáveis'!$E$21 -> 0 | F12: ='Outros Custos'!$C$31 -> 0 | G12: =Transporte!$C$20 -> 0 | H12: =Manutenção!$C$21 -> 0 | I12: =Investimentos!G28 -> 0 | J12: =SUM(B12:I12) -> 3755.8267 | K12: =IF($L$2>=1,J12/$A$5,0) -> 0 | L12: ='Desengraxante Quí'!J15 -> 0 | M12: ='Resumo M.O'!$D$14 -> 1490.6153 | N12: ='Resumo M.O'!$D$29 -> 2265.2114 | O12: ='Resumo Custos Variáveis'!$F$21 -> 0 | P12: ='Outros Custos'!$D$31 -> 0 | Q12: =Transporte!$D$20 -> 0 | R12: =Manutenção!$D$21 -> 0 | S12: =I12 -> 0 | T12: =SUM(L12:S12) -> 3755.8267 | U12: =IF($L$2>=1,T12/$A$5,0) -> 0 | V12: ='Desengraxante Quí'!M15 -> 58.05 | W12: ='Resumo M.O'!$E$14 -> 1490.6153 | X12: ='Resumo M.O'!$E$29 -> 2265.2114 | Y12: ='Resumo Custos Variáveis'!$G$21 -> 2404.5263 | Z12: ='Outros Custos'!$E$31 -> 0 | AA12: =Transporte!$E$20 -> 0 | AB12: =Manutenção!$E$21 -> 0 | AC12: =S12 -> 0 | AD12: =SUM(V12:AC12) -> 6218.403 | AE12: =IF($L$2>=1,AD12/$A$5,0) -> 0 | AF12: ='Desengraxante Quí'!P15 -> 11.61 | AG12: ='Resumo M.O'!$F$14 -> 1490.6153 | AH12: ='Resumo M.O'!$F$29 -> 2265.2114 | AI12: ='Resumo Custos Variáveis'!$H$21 -> 1573.8421 | AJ12: ='Outros Custos'!$F$31 -> 0 | AK12: =Transporte!$F$20 -> 0 | AL12: =Manutenção!$F$21 -> 0 | AM12: =AC12 -> 0 | AN12: =SUM(AF12:AM12) -> 5341.2788 | AO12: =IF(L2>=1,AN12/$A$5,0) -> 0 | AP12: ='Desengraxante Quí'!S15 -> 0 | AQ12: ='Resumo M.O'!$G$14 -> 1490.6153 | AR12: ='Resumo M.O'!$G$29 -> 2265.2114 | AS12: ='Resumo Custos Variáveis'!$I$21 -> 0 | AT12: ='Outros Custos'!$G$31 -> 0 | AU12: =Transporte!$G$20 -> 0 | AV12: =Manutenção!$G$21 -> 0 | AW12: =AM12 -> 0 | AX12: =SUM(AP12:AW12) -> 3755.8267 | AY12: =IF(L2>=1,AX12/$A$5,0) -> 0 | AZ12: ='Desengraxante Quí'!V15 -> 0 | BA12: ='Resumo M.O'!$H$14 -> 1490.6153 | BB12: ='Resumo M.O'!$H$29 -> 2265.2114 | BC12: ='Resumo Custos Variáveis'!$J$21 -> 0 | BD12: ='Outros Custos'!$H$31 -> 0 | BE12: =Transporte!$H$20 -> 0 | BF12: =Manutenção!$H$21 -> 3061.5385 | BG12: =AW12 -> 0 | BH12: =SUM(AZ12:BG12) -> 6817.3651 | BI12: =IF(L2>=1,BH12/$A$5,0) -> 0 | BJ12: ='Desengraxante Quí'!Y15 -> 0 | BK12: ='Resumo M.O'!$I$14 -> 1490.6153 | BL12: ='Resumo M.O'!$I$29 -> 2265.2114 | BM12: ='Resumo Custos Variáveis'!$K$21 -> 0 | BN12: ='Outros Custos'!$I$31 -> 0 | BO12: =Transporte!$I$20 -> 0 | BP12: =Manutenção!$I$21 -> 3030.7692 | BQ12: =BG12 -> 0 | BR12: =SUM(BJ12:BQ12) -> 6786.5959 | BS12: =IF(L2>=1,BR12/$A$5,0) -> 0 | BT12: ='Desengraxante Quí'!AB15 -> 0 | BU12: ='Resumo M.O'!$J$14 -> 1490.6153 | BV12: ='Resumo M.O'!$J$29 -> 2265.2114 | BW12: ='Resumo Custos Variáveis'!$L$21 -> 0 | BX12: ='Outros Custos'!$J$31 -> 0 | BY12: =Transporte!$J$20 -> 0 | BZ12: =Manutenção!$J$21 -> 0 | CA12: =BQ12 -> 0 | CB12: =SUM(BT12:CA12) -> 3755.8267 | CC12: =IF(L2>=1,CB12/$A$5,0) -> 0 | CD12: ='Desengraxante Quí'!AE15 -> 0 | CE12: ='Resumo M.O'!$K$14 -> 1490.6153 | CF12: ='Resumo M.O'!$K$29 -> 2265.2114 | CG12: ='Resumo Custos Variáveis'!$M$21 -> 0 | CH12: ='Outros Custos'!$K$31 -> 0 | CI12: =Transporte!$K$20 -> 0 | CJ12: =Manutenção!$K$21 -> 0 | CK12: =CA12 -> 0 | CL12: =SUM(CD12:CK12) -> 3755.8267 | CM12: =IF(L2>=1,CL12/$A$5,0) -> 0 | CN12: ='Desengraxante Quí'!AH15 -> 0 | CO12: ='Resumo M.O'!$L$14 -> 1490.6153 | CP12: ='Resumo M.O'!$L$29 -> 2265.2114 | CQ12: ='Resumo Custos Variáveis'!$N$21 -> 0 | CR12: ='Outros Custos'!$L$31 -> 0 | CS12: =Transporte!$L$20 -> 0 | CT12: =Manutenção!$L$21 -> 0 | CU12: =CK12 -> 0 | CV12: =SUM(CN12:CU12) -> 3755.8267 | CW12: =IF(L2>=1,CV12/$A$5,0) -> 0 | CX12: ='Desengraxante Quí'!AK15 -> 0 | CY12: ='Resumo M.O'!$M$14 -> 1490.6153 | CZ12: ='Resumo M.O'!$M$29 -> 2265.2114 | DA12: ='Resumo Custos Variáveis'!$O$21 -> 0 | DB12: ='Outros Custos'!$M$31 -> 0 | DC12: =Transporte!$M$20 -> 0 | DD12: =Manutenção!$M$21 -> 0 | DE12: =CU12 -> 0 | DF12: =SUM(CX12:DE12) -> 3755.8267 | DG12: =IF(L2>=1,DF12/$A$5,0) -> 0 | DH12: ='Desengraxante Quí'!AN15 -> 0 | DI12: ='Resumo M.O'!$N$14 -> 1490.6153 | DJ12: ='Resumo M.O'!$N$29 -> 2265.2114 | DK12: ='Resumo Custos Variáveis'!$P$21 -> 0 | DL12: ='Outros Custos'!$N$31 -> 0 | DM12: =Transporte!$N$20 -> 0 | DN12: =Manutenção!$N$21 -> 0 | DO12: =DE12 -> 0 | DP12: =SUM(DH12:DO12) -> 3755.8267 | DQ12: =IF(L2>=1,DP12/$A$5,0) -> 0 | DS12: =K12 -> 0 | DT12: =U12 -> 0 | DU12: =AE12 -> 0 | DV12: =AO12 -> 0 | DW12: =AY12 -> 0 | DX12: =BI12 -> 0 | DY12: =BS12 -> 0 | DZ12: =CC12 -> 0 | EA12: =CM12 -> 0 | EB12: =CW12 -> 0 | EC12: =DG12 -> 0 | ED12: =DQ12 -> 0 | EF12: =B12/$A$5 -> 0 | EG12: =L12/$A$5 -> 0 | EH12: =V12/$A$5 -> 0.26386364 | EI12: =AF12/$A$5 -> 0.052772727 | EJ12: =AP12/$A$5 -> 0 | EK12: =AZ12/$A$5 -> 0 | EL12: =BJ12/$A$5 -> 0 | EM12: =BT12/$A$5 -> 0 | EN12: =CD12/$A$5 -> 0 | EO12: =CN12/$A$5 -> 0 | EP12: =CX12/$A$5 -> 0 | EQ12: =DH12/$A$5 -> 0
A13: Níquel Brilhante | B13: ='Níquel Brilhante'!G15 -> 0 | C13: ='Resumo M.O'!$C$14 -> 1490.6153 | D13: ='Resumo M.O'!$C$29 -> 2265.2114 | E13: ='Resumo Custos Variáveis'!$E$21 -> 0 | F13: ='Outros Custos'!$C$31 -> 0 | G13: =Transporte!$C$20 -> 0 | H13: =Manutenção!$C$21 -> 0 | I13: =Investimentos!G32 -> 0 | J13: =SUM(B13:I13) -> 3755.8267 | K13: =IF($L$2>=1,J13/$A$5,0) -> 0 | L13: ='Níquel Brilhante'!J15 -> 0 | M13: ='Resumo M.O'!$D$14 -> 1490.6153 | N13: ='Resumo M.O'!$D$29 -> 2265.2114 | O13: ='Resumo Custos Variáveis'!$F$21 -> 0 | P13: ='Outros Custos'!$D$31 -> 0 | Q13: =Transporte!$D$20 -> 0 | R13: =Manutenção!$D$21 -> 0 | S13: =I13 -> 0 | T13: =SUM(L13:S13) -> 3755.8267 | U13: =IF($L$2>=1,T13/$A$5,0) -> 0 | V13: ='Níquel Brilhante'!M15 -> 37847.69 | W13: ='Resumo M.O'!$E$14 -> 1490.6153 | X13: ='Resumo M.O'!$E$29 -> 2265.2114 | Y13: ='Resumo Custos Variáveis'!$G$21 -> 2404.5263 | Z13: ='Outros Custos'!$E$31 -> 0 | AA13: =Transporte!$E$20 -> 0 | AB13: =Manutenção!$E$21 -> 0 | AC13: =S13 -> 0 | AD13: =SUM(V13:AC13) -> 44008.043 | AE13: =IF($L$2>=1,AD13/$A$5,0) -> 0 | AF13: ='Níquel Brilhante'!P15 -> 30695.13 | AG13: ='Resumo M.O'!$F$14 -> 1490.6153 | AH13: ='Resumo M.O'!$F$29 -> 2265.2114 | AI13: ='Resumo Custos Variáveis'!$H$21 -> 1573.8421 | AJ13: ='Outros Custos'!$F$31 -> 0 | AK13: =Transporte!$F$20 -> 0 | AL13: =Manutenção!$F$21 -> 0 | AM13: =AC13 -> 0 | AN13: =SUM(AF13:AM13) -> 36024.799 | AO13: =IF(L2>=1,(AN13/$A$5)/2,0) -> 0 | AP13: ='Níquel Brilhante'!S15 -> 171.54 | AQ13: ='Resumo M.O'!$G$14 -> 1490.6153 | AR13: ='Resumo M.O'!$G$29 -> 2265.2114 | AS13: ='Resumo Custos Variáveis'!$I$21 -> 0 | AT13: ='Outros Custos'!$G$31 -> 0 | AU13: =Transporte!$G$20 -> 0 | AV13: =Manutenção!$G$21 -> 0 | AW13: =AM13 -> 0 | AX13: =SUM(AP13:AW13) -> 3927.3667 | AY13: =IF(L2>=1,(AX13/$A$5)/2,0) -> 0 | AZ13: ='Níquel Brilhante'!V15 -> 121.68 | BA13: ='Resumo M.O'!$H$14 -> 1490.6153 | BB13: ='Resumo M.O'!$H$29 -> 2265.2114 | BC13: ='Resumo Custos Variáveis'!$J$21 -> 0 | BD13: ='Outros Custos'!$H$31 -> 0 | BE13: =Transporte!$H$20 -> 0 | BF13: =Manutenção!$H$21 -> 3061.5385 | BG13: =AW13 -> 0 | BH13: =SUM(AZ13:BG13) -> 6939.0451 | BI13: =IF(L2>=1,(BH13/$A$5)/2,0) -> 0 | BJ13: ='Níquel Brilhante'!Y15 -> 0 | BK13: ='Resumo M.O'!$I$14 -> 1490.6153 | BL13: ='Resumo M.O'!$I$29 -> 2265.2114 | BM13: ='Resumo Custos Variáveis'!$K$21 -> 0 | BN13: ='Outros Custos'!$I$31 -> 0 | BO13: =Transporte!$I$20 -> 0 | BP13: =Manutenção!$I$21 -> 3030.7692 | BQ13: =BG13 -> 0 | BR13: =SUM(BJ13:BQ13) -> 6786.5959 | BS13: =IF(L2>=1,(BR13/$A$5)/2,0) -> 0 | BT13: ='Níquel Brilhante'!AB15 -> 0 | BU13: ='Resumo M.O'!$J$14 -> 1490.6153 | BV13: ='Resumo M.O'!$J$29 -> 2265.2114 | BW13: ='Resumo Custos Variáveis'!$L$21 -> 0 | BX13: ='Outros Custos'!$J$31 -> 0 | BY13: =Transporte!$J$20 -> 0 | BZ13: =Manutenção!$J$21 -> 0 | CA13: =BQ13 -> 0 | CB13: =SUM(BT13:CA13) -> 3755.8267 | CC13: =IF(L2>=1,(CB13/$A$5)/2,0) -> 0 | CD13: ='Níquel Brilhante'!AE15 -> 0 | CE13: ='Resumo M.O'!$K$14 -> 1490.6153 | CF13: ='Resumo M.O'!$K$29 -> 2265.2114 | CG13: ='Resumo Custos Variáveis'!$M$21 -> 0 | CH13: ='Outros Custos'!$K$31 -> 0 | CI13: =Transporte!$K$20 -> 0 | CJ13: =Manutenção!$K$21 -> 0 | CK13: =CA13 -> 0 | CL13: =SUM(CD13:CK13) -> 3755.8267 | CM13: =IF(L2>=1,(CL13/$A$5)/2,0) -> 0 | CN13: ='Níquel Brilhante'!AH15 -> 0 | CO13: ='Resumo M.O'!$L$14 -> 1490.6153 | CP13: ='Resumo M.O'!$L$29 -> 2265.2114 | CQ13: ='Resumo Custos Variáveis'!$N$21 -> 0 | CR13: ='Outros Custos'!$L$31 -> 0 | CS13: =Transporte!$L$20 -> 0 | CT13: =Manutenção!$L$21 -> 0 | CU13: =CK13 -> 0 | CV13: =SUM(CN13:CU13) -> 3755.8267 | CW13: =IF(L2>=1,(CV13/$A$5)/2,0) -> 0 | CX13: ='Níquel Brilhante'!AK15 -> 0 | CY13: ='Resumo M.O'!$M$14 -> 1490.6153 | CZ13: ='Resumo M.O'!$M$29 -> 2265.2114 | DA13: ='Resumo Custos Variáveis'!$O$21 -> 0 | DB13: ='Outros Custos'!$M$31 -> 0 | DC13: =Transporte!$M$20 -> 0 | DD13: =Manutenção!$M$21 -> 0 | DE13: =CU13 -> 0 | DF13: =SUM(CX13:DE13) -> 3755.8267 | DG13: =IF(L2>=1,(DF13/$A$5)/2,0) -> 0 | DH13: ='Níquel Brilhante'!AN15 -> 0 | DI13: ='Resumo M.O'!$N$14 -> 1490.6153 | DJ13: ='Resumo M.O'!$N$29 -> 2265.2114 | DK13: ='Resumo Custos Variáveis'!$P$21 -> 0 | DL13: ='Outros Custos'!$N$31 -> 0 | DM13: =Transporte!$N$20 -> 0 | DN13: =Manutenção!$N$21 -> 0 | DO13: =DE13 -> 0 | DP13: =SUM(DH13:DO13) -> 3755.8267 | DQ13: =IF(L2>=1,(DP13/$A$5)/2,0) -> 0 | DS13: =K13 -> 0 | DT13: =U13 -> 0 | DU13: =AE13 -> 0 | DV13: =AO13 -> 0 | DW13: =AY13 -> 0 | DX13: =BI13 -> 0 | DY13: =BS13 -> 0 | DZ13: =CC13 -> 0 | EA13: =CM13 -> 0 | EB13: =CW13 -> 0 | EC13: =DG13 -> 0 | ED13: =DQ13 -> 0 | EF13: =(B13/$A$5) -> 0 | EG13: =L13/$A$5 -> 0 | EH13: =V13/$A$5 -> 172.03495 | EI13: =AF13/$A$5 -> 139.52332 | EJ13: =AP13/$A$5 -> 0.77972727 | EK13: =AZ13/$A$5 -> 0.55309091 | EL13: =BJ13/$A$5 -> 0 | EM13: =BT13/$A$5 -> 0 | EN13: =CD13/$A$5 -> 0 | EO13: =CN13/$A$5 -> 0 | EP13: =CX13/$A$5 -> 0 | EQ13: =DH13/$A$5 -> 0
A14: Níquel Strik (2) | B14: ='Níquel Strik (2)'!G14 -> 0 | C14: ='Resumo M.O'!$C$14 -> 1490.6153 | D14: ='Resumo M.O'!$C$29 -> 2265.2114 | E14: ='Resumo Custos Variáveis'!$E$21 -> 0 | F14: ='Outros Custos'!$C$31 -> 0 | G14: =Transporte!$C$20 -> 0 | H14: =Manutenção!$C$21 -> 0 | I14: =Investimentos!G36 -> 0 | J14: =SUM(B14:I14) -> 3755.8267 | K14: =IF($L$2>=1,J14/$A$5,0) -> 0 | L14: ='Níquel Strik (2)'!J14 -> 0 | M14: ='Resumo M.O'!$D$14 -> 1490.6153 | N14: ='Resumo M.O'!$D$29 -> 2265.2114 | O14: ='Resumo Custos Variáveis'!$F$21 -> 0 | P14: ='Outros Custos'!$D$31 -> 0 | Q14: =Transporte!$D$20 -> 0 | R14: =Manutenção!$D$21 -> 0 | S14: =I14 -> 0 | T14: =SUM(L14:S14) -> 3755.8267 | U14: =IF($L$2>=1,T14/$A$5,0) -> 0 | V14: ='Níquel Strik (2)'!M14 -> 3135.25 | W14: ='Resumo M.O'!$E$14 -> 1490.6153 | X14: ='Resumo M.O'!$E$29 -> 2265.2114 | Y14: ='Resumo Custos Variáveis'!$G$21 -> 2404.5263 | Z14: ='Outros Custos'!$E$31 -> 0 | AA14: =Transporte!$E$20 -> 0 | AB14: =Manutenção!$E$21 -> 0 | AC14: =S14 -> 0 | AD14: =SUM(V14:AC14) -> 9295.603 | AE14: =IF($L$2>=1,AD14/$A$5,0) -> 0 | AF14: ='Níquel Strik (2)'!P14 -> 6041.56 | AG14: ='Resumo M.O'!$F$14 -> 1490.6153 | AH14: ='Resumo M.O'!$F$29 -> 2265.2114 | AI14: ='Resumo Custos Variáveis'!$H$21 -> 1573.8421 | AJ14: ='Outros Custos'!$F$31 -> 0 | AK14: =Transporte!$F$20 -> 0 | AL14: =Manutenção!$F$21 -> 0 | AM14: =AC14 -> 0 | AN14: =SUM(AF14:AM14) -> 11371.229 | AO14: =IF(L2>=1,(AN14/$A$5)/2,0) -> 0 | AP14: ='Níquel Strik (2)'!S14 -> 11919.6 | AQ14: ='Resumo M.O'!$G$14 -> 1490.6153 | AR14: ='Resumo M.O'!$G$29 -> 2265.2114 | AS14: ='Resumo Custos Variáveis'!$I$21 -> 0 | AT14: ='Outros Custos'!$G$31 -> 0 | AU14: =Transporte!$G$20 -> 0 | AV14: =Manutenção!$G$21 -> 0 | AW14: =AM14 -> 0 | AX14: =SUM(AP14:AW14) -> 15675.427 | AY14: =IF(L2>=1,(AX14/$A$5)/2,0) -> 0 | AZ14: ='Níquel Strik (2)'!V14 -> 0 | BA14: ='Resumo M.O'!$H$14 -> 1490.6153 | BB14: ='Resumo M.O'!$H$29 -> 2265.2114 | BC14: ='Resumo Custos Variáveis'!$J$21 -> 0 | BD14: ='Outros Custos'!$H$31 -> 0 | BE14: =Transporte!$H$20 -> 0 | BF14: =Manutenção!$H$21 -> 3061.5385 | BG14: =AW14 -> 0 | BH14: =SUM(AZ14:BG14) -> 6817.3651 | BI14: =IF(L2>=1,(BH14/$A$5)/2,0) -> 0 | BJ14: ='Níquel Strik (2)'!Y14 -> 0 | BK14: ='Resumo M.O'!$I$14 -> 1490.6153 | BL14: ='Resumo M.O'!$I$29 -> 2265.2114 | BM14: ='Resumo Custos Variáveis'!$K$21 -> 0 | BN14: ='Outros Custos'!$I$31 -> 0 | BO14: =Transporte!$I$20 -> 0 | BP14: =Manutenção!$I$21 -> 3030.7692 | BQ14: =BG14 -> 0 | BR14: =SUM(BJ14:BQ14) -> 6786.5959 | BS14: =IF(L2>=1,(BR14/$A$5),0) -> 0 | BT14: ='Níquel Strik (2)'!AB14 -> 0 | BU14: ='Resumo M.O'!$J$14 -> 1490.6153 | BV14: ='Resumo M.O'!$J$29 -> 2265.2114 | BW14: ='Resumo Custos Variáveis'!$L$21 -> 0 | BX14: ='Outros Custos'!$J$31 -> 0 | BY14: =Transporte!$J$20 -> 0 | BZ14: =Manutenção!$J$21 -> 0 | CA14: =BQ14 -> 0 | CB14: =SUM(BT14:CA14) -> 3755.8267 | CC14: =IF(L2>=1,(CB14/$A$5)/2,0) -> 0 | CD14: ='Níquel Strik (2)'!AE14 -> 0 | CE14: ='Resumo M.O'!$K$14 -> 1490.6153 | CF14: ='Resumo M.O'!$K$29 -> 2265.2114 | CG14: ='Resumo Custos Variáveis'!$M$21 -> 0 | CH14: ='Outros Custos'!$K$31 -> 0 | CI14: =Transporte!$K$20 -> 0 | CJ14: =Manutenção!$K$21 -> 0 | CK14: =CA14 -> 0 | CL14: =SUM(CD14:CK14) -> 3755.8267 | CM14: =IF(L2>=1,(CL14/$A$5)/2,0) -> 0 | CN14: ='Níquel Strik (2)'!AH14 -> 0 | CO14: ='Resumo M.O'!$L$14 -> 1490.6153 | CP14: ='Resumo M.O'!$L$29 -> 2265.2114 | CQ14: ='Resumo Custos Variáveis'!$N$21 -> 0 | CR14: ='Outros Custos'!$L$31 -> 0 | CS14: =Transporte!$L$20 -> 0 | CT14: =Manutenção!$L$21 -> 0 | CU14: =CK14 -> 0 | CV14: =SUM(CN14:CU14) -> 3755.8267 | CW14: =IF(L2>=1,(CV14/$A$5)/2,0) -> 0 | CX14: ='Níquel Strik (2)'!AK14 -> 0 | CY14: ='Resumo M.O'!$M$14 -> 1490.6153 | CZ14: ='Resumo M.O'!$M$29 -> 2265.2114 | DA14: ='Resumo Custos Variáveis'!$O$21 -> 0 | DB14: ='Outros Custos'!$M$31 -> 0 | DC14: =Transporte!$M$20 -> 0 | DD14: =Manutenção!$M$21 -> 0 | DE14: =CU14 -> 0 | DF14: =SUM(CX14:DE14) -> 3755.8267 | DG14: =IF(L2>=1,(DF14/$A$5)/2,0) -> 0 | DH14: ='Níquel Strik (2)'!AN14 -> 0 | DI14: ='Resumo M.O'!$N$14 -> 1490.6153 | DJ14: ='Resumo M.O'!$N$29 -> 2265.2114 | DK14: ='Resumo Custos Variáveis'!$P$21 -> 0 | DL14: ='Outros Custos'!$N$31 -> 0 | DM14: =Transporte!$N$20 -> 0 | DN14: =Manutenção!$N$21 -> 0 | DO14: =DE14 -> 0 | DP14: =SUM(DH14:DO14) -> 3755.8267 | DQ14: =IF(L2>=1,(DP14/$A$5)/2,0) -> 0 | DS14: =K14 -> 0 | DT14: =U14 -> 0 | DU14: =AE14 -> 0 | DV14: =AO14 -> 0 | DW14: =AY14 -> 0 | DX14: =BI14 -> 0 | DY14: =BS14 -> 0 | DZ14: =CC14 -> 0 | EA14: =CM14 -> 0 | EB14: =CW14 -> 0 | EC14: =DG14 -> 0 | ED14: =DQ14 -> 0 | EF14: =(B14/$A$5) -> 0 | EG14: =L14/$A$5 -> 0 | EH14: =V14/$A$5 -> 14.251136 | EI14: =AF14/$A$5 -> 27.461636 | EJ14: =AP14/$A$5 -> 54.18 | EK14: =AZ14/$A$5 -> 0 | EL14: =BJ14/$A$5 -> 0 | EM14: =BT14/$A$5 -> 0 | EN14: =CD14/$A$5 -> 0 | EO14: =CN14/$A$5 -> 0 | EP14: =CX14/$A$5 -> 0 | EQ14: =DH14/$A$5 -> 0
A15: Cromo | B15: =Cromo!G14 -> 0 | C15: ='Resumo M.O'!$C$14 -> 1490.6153 | D15: ='Resumo M.O'!$C$29 -> 2265.2114 | E15: ='Resumo Custos Variáveis'!$E$21 -> 0 | F15: ='Outros Custos'!$C$31 -> 0 | G15: =Transporte!$C$20 -> 0 | H15: =Manutenção!$C$21 -> 0 | I15: =Investimentos!G40 -> 0 | J15: =SUM(B15:I15) -> 3755.8267 | K15: =IF($L$2>=1,J15/$A$5,0) -> 0 | L15: =Cromo!J14 -> 0 | M15: ='Resumo M.O'!$D$14 -> 1490.6153 | N15: ='Resumo M.O'!$D$29 -> 2265.2114 | O15: ='Resumo Custos Variáveis'!$F$21 -> 0 | P15: ='Outros Custos'!$D$31 -> 0 | Q15: =Transporte!$D$20 -> 0 | R15: =Manutenção!$D$21 -> 0 | S15: =I15 -> 0 | T15: =SUM(L15:S15) -> 3755.8267 | U15: =IF($L$2>=1,T15/$A$5,0) -> 0 | V15: =Cromo!M14 -> 29778.51 | W15: ='Resumo M.O'!$E$14 -> 1490.6153 | X15: ='Resumo M.O'!$E$29 -> 2265.2114 | Y15: ='Resumo Custos Variáveis'!$G$21 -> 2404.5263 | Z15: ='Outros Custos'!$E$31 -> 0 | AA15: =Transporte!$E$20 -> 0 | AB15: =Manutenção!$E$21 -> 0 | AC15: =S15 -> 0 | AD15: =SUM(V15:AC15) -> 35938.863 | AE15: =IF($L$2>=1,AD15/$A$5,0) -> 0 | AF15: =Cromo!P14 -> 29439.66 | AG15: ='Resumo M.O'!$F$14 -> 1490.6153 | AH15: ='Resumo M.O'!$F$29 -> 2265.2114 | AI15: ='Resumo Custos Variáveis'!$H$21 -> 1573.8421 | AJ15: ='Outros Custos'!$F$31 -> 0 | AK15: =Transporte!$F$20 -> 0 | AL15: =Manutenção!$F$21 -> 0 | AM15: =AC15 -> 0 | AN15: =SUM(AF15:AM15) -> 34769.329 | AO15: =IF(L2>=1,(AN15/$A$5)/2,0) -> 0 | AP15: =Cromo!S14 -> 24196.5 | AQ15: ='Resumo M.O'!$G$14 -> 1490.6153 | AR15: ='Resumo M.O'!$G$29 -> 2265.2114 | AS15: ='Resumo Custos Variáveis'!$I$21 -> 0 | AT15: ='Outros Custos'!$G$31 -> 0 | AU15: =Transporte!$G$20 -> 0 | AV15: =Manutenção!$G$21 -> 0 | AW15: =AM15 -> 0 | AX15: =SUM(AP15:AW15) -> 27952.327 | AY15: =IF($L$2>=1,(AX15/$A$5)/2,0) -> 0 | AZ15: =Cromo!V14 -> 24196.5 | BA15: ='Resumo M.O'!$H$14 -> 1490.6153 | BB15: ='Resumo M.O'!$H$29 -> 2265.2114 | BC15: ='Resumo Custos Variáveis'!$J$21 -> 0 | BD15: ='Outros Custos'!$H$31 -> 0 | BE15: =Transporte!$H$20 -> 0 | BF15: =Manutenção!$H$21 -> 3061.5385 | BG15: =AW15 -> 0 | BH15: =SUM(AZ15:BG15) -> 31013.865 | BI15: =IF($L$2>=1,(BH15/$A$5)/2,0) -> 0 | BJ15: =Cromo!Y14 -> 0 | BK15: ='Resumo M.O'!$I$14 -> 1490.6153 | BL15: ='Resumo M.O'!$I$29 -> 2265.2114 | BM15: ='Resumo Custos Variáveis'!$K$21 -> 0 | BN15: ='Outros Custos'!$I$31 -> 0 | BO15: =Transporte!$I$20 -> 0 | BP15: =Manutenção!$I$21 -> 3030.7692 | BQ15: =BG15 -> 0 | BR15: =SUM(BJ15:BQ15) -> 6786.5959 | BS15: =IF($L$2>=1,(BR15/$A$5),0) -> 0 | BT15: =Cromo!AB14 -> 0 | BU15: ='Resumo M.O'!$J$14 -> 1490.6153 | BV15: ='Resumo M.O'!$J$29 -> 2265.2114 | BW15: ='Resumo Custos Variáveis'!$L$21 -> 0 | BX15: ='Outros Custos'!$J$31 -> 0 | BY15: =Transporte!$J$20 -> 0 | BZ15: =Manutenção!$J$21 -> 0 | CA15: =BQ15 -> 0 | CB15: =SUM(BT15:CA15) -> 3755.8267 | CC15: =IF($L$2>=1,(CB15/$A$5)/2,0) -> 0 | CD15: =Cromo!AE14 -> 0 | CE15: ='Resumo M.O'!$K$14 -> 1490.6153 | CF15: ='Resumo M.O'!$K$29 -> 2265.2114 | CG15: ='Resumo Custos Variáveis'!$M$21 -> 0 | CH15: ='Outros Custos'!$K$31 -> 0 | CI15: =Transporte!$K$20 -> 0 | CJ15: =Manutenção!$K$21 -> 0 | CK15: =CA15 -> 0 | CL15: =SUM(CD15:CK15) -> 3755.8267 | CM15: =IF($L$2>=1,(CL15/$A$5)/2,0) -> 0 | CN15: =Cromo!AH14 -> 0 | CO15: ='Resumo M.O'!$L$14 -> 1490.6153 | CP15: ='Resumo M.O'!$L$29 -> 2265.2114 | CQ15: ='Resumo Custos Variáveis'!$N$21 -> 0 | CR15: ='Outros Custos'!$L$31 -> 0 | CS15: =Transporte!$L$20 -> 0 | CT15: =Manutenção!$L$21 -> 0 | CU15: =CK15 -> 0 | CV15: =SUM(CN15:CU15) -> 3755.8267 | CW15: =IF($L$2>=1,(CV15/$A$5)/2,0) -> 0 | CX15: =Cromo!AK14 -> 0 | CY15: ='Resumo M.O'!$M$14 -> 1490.6153 | CZ15: ='Resumo M.O'!$M$29 -> 2265.2114 | DA15: ='Resumo Custos Variáveis'!$O$21 -> 0 | DB15: ='Outros Custos'!$M$31 -> 0 | DC15: =Transporte!$M$20 -> 0 | DD15: =Manutenção!$M$21 -> 0 | DE15: =CU15 -> 0 | DF15: =SUM(CX15:DE15) -> 3755.8267 | DG15: =IF($L$2>=1,(DF15/$A$5)/2,0) -> 0 | DH15: =Cromo!AN14 -> 0 | DI15: ='Resumo M.O'!$N$14 -> 1490.6153 | DJ15: ='Resumo M.O'!$N$29 -> 2265.2114 | DK15: ='Resumo Custos Variáveis'!$P$21 -> 0 | DL15: ='Outros Custos'!$N$31 -> 0 | DM15: =Transporte!$N$20 -> 0 | DN15: =Manutenção!$N$21 -> 0 | DO15: =DE15 -> 0 | DP15: =SUM(DH15:DO15) -> 3755.8267 | DQ15: =IF(L2>=1,(DP15/$A$5)/2,0) -> 0 | DS15: =K15 -> 0 | DT15: =U15 -> 0 | DU15: =AE15 -> 0 | DV15: =AO15 -> 0 | DW15: =AY15 -> 0 | DX15: =BI15 -> 0 | DY15: =BS15 -> 0 | DZ15: =CC15 -> 0 | EA15: =CM15 -> 0 | EB15: =CW15 -> 0 | EC15: =DG15 -> 0 | ED15: =DQ15 -> 0 | EF15: =(B15/$A$5) -> 0 | EG15: =L15/$A$5 -> 0 | EH15: =V15/$A$5 -> 135.35686 | EI15: =AF15/$A$5 -> 133.81664 | EJ15: =AP15/$A$5 -> 109.98409 | EK15: =AZ15/$A$5 -> 109.98409 | EL15: =BJ15/$A$5 -> 0 | EM15: =BT15/$A$5 -> 0 | EN15: =CD15/$A$5 -> 0 | EO15: =CN15/$A$5 -> 0 | EP15: =CX15/$A$5 -> 0 | EQ15: =DH15/$A$5 -> 0
A16: Desplacante | B16: ='Desplacante '!G14 -> 0 | C16: ='Resumo M.O'!$C$14 -> 1490.6153 | D16: ='Resumo M.O'!$C$29 -> 2265.2114 | E16: ='Resumo Custos Variáveis'!$E$21 -> 0 | F16: ='Outros Custos'!$C$31 -> 0 | G16: =Transporte!$C$20 -> 0 | H16: =Manutenção!$C$21 -> 0 | I16: 0 | J16: =SUM(B16:I16) -> 3755.8267 | K16: =IF($L$2>=1,J16/$A$5,0) -> 0 | L16: ='Desplacante '!J14 -> 0 | M16: ='Resumo M.O'!$D$14 -> 1490.6153 | N16: ='Resumo M.O'!$D$29 -> 2265.2114 | O16: ='Resumo Custos Variáveis'!$F$21 -> 0 | P16: ='Outros Custos'!$D$31 -> 0 | Q16: =Transporte!$D$20 -> 0 | R16: =Manutenção!$D$21 -> 0 | S16: =I16 -> 0 | T16: =SUM(L16:S16) -> 3755.8267 | U16: =IF($L$2>=1,T16/$A$5,0) -> 0 | V16: ='Desplacante '!M14 -> 0 | W16: ='Resumo M.O'!$E$14 -> 1490.6153 | X16: ='Resumo M.O'!$E$29 -> 2265.2114 | Y16: ='Resumo Custos Variáveis'!$G$21 -> 2404.5263 | Z16: ='Outros Custos'!$E$31 -> 0 | AA16: =Transporte!$E$20 -> 0 | AB16: =Manutenção!$E$21 -> 0 | AC16: =S16 -> 0 | AD16: =SUM(V16:AC16) -> 6160.353 | AE16: =IF($L$2>=1,AD16/$A$5,0) -> 0 | AF16: ='Desplacante '!P14 -> 0 | AG16: ='Resumo M.O'!$F$14 -> 1490.6153 | AH16: ='Resumo M.O'!$F$29 -> 2265.2114 | AI16: ='Resumo Custos Variáveis'!$H$21 -> 1573.8421 | AJ16: ='Outros Custos'!$F$31 -> 0 | AK16: =Transporte!$F$20 -> 0 | AL16: =Manutenção!$F$21 -> 0 | AM16: =AC16 -> 0 | AN16: =SUM(AF16:AM16) -> 5329.6688 | AO16: =IF($L$2>=1,AN16/$A$5,0) -> 0 | AP16: ='Desplacante '!S14 -> 0 | AQ16: ='Resumo M.O'!$G$14 -> 1490.6153 | AR16: ='Resumo M.O'!$G$29 -> 2265.2114 | AS16: ='Resumo Custos Variáveis'!$I$21 -> 0 | AT16: ='Outros Custos'!$G$31 -> 0 | AU16: =Transporte!$G$20 -> 0 | AV16: =Manutenção!$G$21 -> 0 | AW16: =AM16 -> 0 | AX16: =SUM(AP16:AW16) -> 3755.8267 | AY16: =IF($L$2>=1,AX16/$A$5,0) -> 0 | AZ16: ='Desplacante '!V14 -> 0 | BA16: ='Resumo M.O'!$H$14 -> 1490.6153 | BB16: ='Resumo M.O'!$H$29 -> 2265.2114 | BC16: ='Resumo Custos Variáveis'!$J$21 -> 0 | BD16: ='Outros Custos'!$H$31 -> 0 | BE16: =Transporte!$H$20 -> 0 | BF16: =Manutenção!$H$21 -> 3061.5385 | BG16: =AW16 -> 0 | BH16: =SUM(AZ16:BG16) -> 6817.3651 | BI16: =IF($L$2>=1,BH16/$A$5,0) -> 0 | BJ16: ='Desplacante '!Y14 -> 0 | BK16: ='Resumo M.O'!$I$14 -> 1490.6153 | BL16: ='Resumo M.O'!$I$29 -> 2265.2114 | BM16: ='Resumo Custos Variáveis'!$K$21 -> 0 | BN16: ='Outros Custos'!$I$31 -> 0 | BO16: =Transporte!$I$20 -> 0 | BP16: =Manutenção!$I$21 -> 3030.7692 | BQ16: =BG16 -> 0 | BR16: =SUM(BJ16:BQ16) -> 6786.5959 | BS16: =IF($L$2>=1,BR16/$A$5,0) -> 0 | BT16: ='Desplacante '!AB14 -> 0 | BU16: ='Resumo M.O'!$J$14 -> 1490.6153 | BV16: ='Resumo M.O'!$J$29 -> 2265.2114 | BW16: ='Resumo Custos Variáveis'!$L$21 -> 0 | BX16: ='Outros Custos'!$J$31 -> 0 | BY16: =Transporte!$J$20 -> 0 | BZ16: =Manutenção!$J$21 -> 0 | CA16: =BQ16 -> 0 | CB16: =SUM(BT16:CA16) -> 3755.8267 | CC16: =IF($L$2>=1,CB16/$A$5,0) -> 0 | CD16: ='Desplacante '!AE14 -> 0 | CE16: ='Resumo M.O'!$K$14 -> 1490.6153 | CF16: ='Resumo M.O'!$K$29 -> 2265.2114 | CG16: ='Resumo Custos Variáveis'!$M$21 -> 0 | CH16: ='Outros Custos'!$K$31 -> 0 | CI16: =Transporte!$K$20 -> 0 | CJ16: =Manutenção!$K$21 -> 0 | CK16: =CA16 -> 0 | CL16: =SUM(CD16:CK16) -> 3755.8267 | CM16: =IF($L$2>=1,CL16/$A$5,0) -> 0 | CN16: ='Desplacante '!AH14 -> 0 | CO16: ='Resumo M.O'!$L$14 -> 1490.6153 | CP16: ='Resumo M.O'!$L$29 -> 2265.2114 | CQ16: ='Resumo Custos Variáveis'!$N$21 -> 0 | CR16: ='Outros Custos'!$L$31 -> 0 | CS16: =Transporte!$L$20 -> 0 | CT16: =Manutenção!$L$21 -> 0 | CU16: =CK16 -> 0 | CV16: =SUM(CN16:CU16) -> 3755.8267 | CW16: =IF($L$2>=1,CV16/$A$5,0) -> 0 | CX16: ='Desplacante '!AK14 -> 0 | CY16: ='Resumo M.O'!$M$14 -> 1490.6153 | CZ16: ='Resumo M.O'!$M$29 -> 2265.2114 | DA16: ='Resumo Custos Variáveis'!$O$21 -> 0 | DB16: ='Outros Custos'!$M$31 -> 0 | DC16: =Transporte!$M$20 -> 0 | DD16: =Manutenção!$M$21 -> 0 | DE16: =CU16 -> 0 | DF16: =SUM(CX16:DE16) -> 3755.8267 | DG16: =IF($L$2>=1,DF16/$A$5,0) -> 0 | DH16: ='Desplacante '!AN14 -> 0 | DI16: ='Resumo M.O'!$N$14 -> 1490.6153 | DJ16: ='Resumo M.O'!$N$29 -> 2265.2114 | DK16: ='Resumo Custos Variáveis'!$P$21 -> 0 | DL16: ='Outros Custos'!$N$31 -> 0 | DM16: =Transporte!$N$20 -> 0 | DN16: =Manutenção!$N$21 -> 0 | DO16: =DE16 -> 0 | DP16: =SUM(DH16:DO16) -> 3755.8267 | DQ16: =IF($L$2>=1,DP16/$A$5,0) -> 0 | DS16: =K16 -> 0 | DT16: =U16 -> 0 | DU16: =AE16 -> 0 | DV16: =AO16 -> 0 | DW16: =AY16 -> 0 | DX16: =BI16 -> 0 | DY16: =BS16 -> 0 | DZ16: =CC16 -> 0 | EA16: =CM16 -> 0 | EB16: =CW16 -> 0 | EC16: =DG16 -> 0 | ED16: =DQ16 -> 0 | EF16: =B16/$A$5 -> 0 | EG16: =L16/$A$5 -> 0 | EH16: =V16/$A$5 -> 0 | EI16: =AF16/$A$5 -> 0 | EJ16: =AP16/$A$5 -> 0 | EK16: =AZ16/$A$5 -> 0 | EL16: =BJ16/$A$5 -> 0 | EM16: =BT16/$A$5 -> 0 | EN16: =CD16/$A$5 -> 0 | EO16: =CN16/$A$5 -> 0 | EP16: =CX16/$A$5 -> 0 | EQ16: =DH16/$A$5 -> 0
A17: Pré Tratamento Verniz | B17: ='Pré Tratamento Verniz'!G14 -> 0 | C17: ='Resumo M.O'!$C$27 -> 1907.3422 | D17: ='Resumo M.O'!$C$31 -> 1526.3289 | E17: ='Resumo Custos Variáveis'!$E$21 -> 0 | F17: ='Outros Custos'!$C$31 -> 0 | G17: =Transporte!$C$20 -> 0 | H17: =Manutenção!$C$21 -> 0 | I17: 0 | J17: =SUM(B17:I17) -> 3433.6711 | K17: =IF($L$2>=1,J17/$A$5,0) -> 0 | L17: ='Pré Tratamento Verniz'!J14 -> 0 | M17: ='Resumo M.O'!$D$27 -> 1907.3422 | N17: ='Resumo M.O'!$D$31 -> 1526.3289 | O17: ='Resumo Custos Variáveis'!$F$21 -> 0 | P17: ='Outros Custos'!$D$31 -> 0 | Q17: =Transporte!$D$20 -> 0 | R17: =Manutenção!$D$21 -> 0 | S17: =I17 -> 0 | T17: =SUM(L17:S17) -> 3433.6711 | U17: =IF($L$2>=1,T17/$A$5,0) -> 0 | V17: ='Pré Tratamento Verniz'!M14 -> 140 | W17: ='Resumo M.O'!$E$27 -> 1907.3422 | X17: ='Resumo M.O'!$E$31 -> 1526.3289 | Y17: ='Resumo Custos Variáveis'!$G$21 -> 2404.5263 | Z17: ='Outros Custos'!$E$31 -> 0 | AA17: =Transporte!$E$20 -> 0 | AB17: =Manutenção!$E$21 -> 0 | AC17: =S17 -> 0 | AD17: =SUM(V17:AC17) -> 5978.1974 | AE17: =IF($L$2>=1,AD17/$A$5,0) -> 0 | AF17: ='Pré Tratamento Verniz'!P14 -> 0 | AG17: ='Resumo M.O'!$F$27 -> 1907.3422 | AH17: ='Resumo M.O'!$F$31 -> 1526.3289 | AI17: ='Resumo Custos Variáveis'!$H$21 -> 1573.8421 | AJ17: ='Outros Custos'!$F$31 -> 0 | AK17: =Transporte!$F$20 -> 0 | AL17: =Manutenção!$F$21 -> 0 | AM17: =AC17 -> 0 | AN17: =SUM(AF17:AM17) -> 5007.5132 | AO17: =IF($L$2>=1,AN17/$A$5,0) -> 0 | AP17: ='Pré Tratamento Verniz'!S14 -> 0 | AQ17: ='Resumo M.O'!$G$27 -> 1907.3422 | AR17: ='Resumo M.O'!$G$31 -> 1526.3289 | AS17: ='Resumo Custos Variáveis'!$I$21 -> 0 | AT17: ='Outros Custos'!$G$31 -> 0 | AU17: =Transporte!$G$20 -> 0 | AV17: =Manutenção!$G$21 -> 0 | AW17: =AM17 -> 0 | AX17: =SUM(AP17:AW17) -> 3433.6711 | AY17: =IF($L$2>=1,AX17/$A$5,0) -> 0 | AZ17: ='Pré Tratamento Verniz'!V14 -> 0 | BA17: ='Resumo M.O'!$H$27 -> 1907.3422 | BB17: ='Resumo M.O'!$H$31 -> 1526.3289 | BC17: ='Resumo Custos Variáveis'!$J$21 -> 0 | BD17: ='Outros Custos'!$H$31 -> 0 | BE17: =Transporte!$H$20 -> 0 | BF17: =Manutenção!$H$21 -> 3061.5385 | BG17: =AW17 -> 0 | BH17: =SUM(AZ17:BG17) -> 6495.2095 | BI17: =IF($L$2>=1,BH17/$A$5,0) -> 0 | BJ17: ='Pré Tratamento Verniz'!Y14 -> 0 | BK17: ='Resumo M.O'!$I$27 -> 1907.3422 | BL17: ='Resumo M.O'!$I$31 -> 1526.3289 | BM17: ='Resumo Custos Variáveis'!$K$21 -> 0 | BN17: ='Outros Custos'!$I$31 -> 0 | BO17: =Transporte!$I$20 -> 0 | BP17: =Manutenção!$I$21 -> 3030.7692 | BQ17: =BG17 -> 0 | BR17: =SUM(BJ17:BQ17) -> 6464.4403 | BS17: =IF($L$2>=1,BR17/$A$5,0) -> 0 | BT17: ='Pré Tratamento Verniz'!AB14 -> 0 | BU17: ='Resumo M.O'!$J$27 -> 1907.3422 | BV17: ='Resumo M.O'!$J$31 -> 1526.3289 | BW17: ='Resumo Custos Variáveis'!$L$21 -> 0 | BX17: ='Outros Custos'!$J$31 -> 0 | BY17: =Transporte!$J$20 -> 0 | BZ17: =Manutenção!$J$21 -> 0 | CA17: =BQ17 -> 0 | CB17: =SUM(BT17:CA17) -> 3433.6711 | CC17: =IF($L$2>=1,CB17/$A$5,0) -> 0 | CD17: ='Pré Tratamento Verniz'!AE14 -> 0 | CE17: ='Resumo M.O'!$K$27 -> 1907.3422 | CF17: ='Resumo M.O'!$K$31 -> 1526.3289 | CG17: ='Resumo Custos Variáveis'!$M$21 -> 0 | CH17: ='Outros Custos'!$K$31 -> 0 | CI17: =Transporte!$K$20 -> 0 | CJ17: =Manutenção!$K$21 -> 0 | CK17: =CA17 -> 0 | CL17: =SUM(CD17:CK17) -> 3433.6711 | CM17: =IF($L$2>=1,CL17/$A$5,0) -> 0 | CN17: ='Pré Tratamento Verniz'!AH14 -> 0 | CO17: ='Resumo M.O'!$L$27 -> 1907.3422 | CP17: ='Resumo M.O'!$L$31 -> 1526.3289 | CQ17: ='Resumo Custos Variáveis'!$N$21 -> 0 | CR17: ='Outros Custos'!$L$31 -> 0 | CS17: =Transporte!$L$20 -> 0 | CT17: =Manutenção!$L$21 -> 0 | CU17: =CK17 -> 0 | CV17: =SUM(CN17:CU17) -> 3433.6711 | CW17: =IF($L$2>=1,CV17/$A$5,0) -> 0 | CX17: ='Pré Tratamento Verniz'!AK14 -> 0 | CY17: ='Resumo M.O'!$M$27 -> 1907.3422 | CZ17: ='Resumo M.O'!$M$31 -> 1526.3289 | DA17: ='Resumo Custos Variáveis'!$O$21 -> 0 | DB17: ='Outros Custos'!$M$31 -> 0 | DC17: =Transporte!$M$20 -> 0 | DD17: =Manutenção!$M$21 -> 0 | DE17: =CU17 -> 0 | DF17: =SUM(CX17:DE17) -> 3433.6711 | DG17: =IF($L$2>=1,DF17/$A$5,0) -> 0 | DH17: ='Pré Tratamento Verniz'!AN14 -> 0 | DI17: ='Resumo M.O'!$N$27 -> 1907.3422 | DJ17: ='Resumo M.O'!$N$31 -> 1526.3289 | DK17: ='Resumo Custos Variáveis'!$P$21 -> 0 | DL17: ='Outros Custos'!$N$31 -> 0 | DM17: =Transporte!$N$20 -> 0 | DN17: =Manutenção!$N$21 -> 0 | DO17: =DE17 -> 0 | DP17: =SUM(DH17:DO17) -> 3433.6711 | DQ17: =IF($L$2>=1,DP17/$A$5,0) -> 0 | DS17: =K17 -> 0 | DT17: =U17 -> 0 | DU17: =AE17 -> 0 | DV17: =AO17 -> 0 | DW17: =AY17 -> 0 | DX17: =BI17 -> 0 | DY17: =BS17 -> 0 | DZ17: =CC17 -> 0 | EA17: =CM17 -> 0 | EB17: =CW17 -> 0 | EC17: =DG17 -> 0 | ED17: =DQ17 -> 0 | EF17: =B17/$A$5 -> 0 | EG17: =L17/$A$5 -> 0 | EH17: =V17/$A$5 -> 0.63636364 | EI17: =AF17/$A$5 -> 0 | EJ17: =AP17/$A$5 -> 0 | EK17: =AZ17/$A$5 -> 0 | EL17: =BJ17/$A$5 -> 0 | EM17: =BT17/$A$5 -> 0 | EN17: =CD17/$A$5 -> 0 | EO17: =CN17/$A$5 -> 0 | EP17: =CX17/$A$5 -> 0 | EQ17: =DH17/$A$5 -> 0
A18: Cobre Gold 15 | B18: ='Verniz Cataforético'!F11 -> 0 | C18: ='Resumo M.O'!$C$27 -> 1907.3422 | D18: ='Resumo M.O'!$C$31 -> 1526.3289 | E18: ='Resumo Custos Variáveis'!$E$21 -> 0 | F18: ='Outros Custos'!$C$31 -> 0 | G18: =Transporte!$C$20 -> 0 | H18: =Manutenção!$C$21 -> 0 | I18: =Investimentos!O10 -> 0 | J18: =SUM(B18:I18) -> 3433.6711 | K18: =IF($L$2>=1,J18/$A$5,0) -> 0 | L18: ='Verniz Cataforético'!I11 -> 0 | M18: ='Resumo M.O'!$D$27 -> 1907.3422 | N18: ='Resumo M.O'!$D$31 -> 1526.3289 | O18: ='Resumo Custos Variáveis'!$F$21 -> 0 | P18: ='Outros Custos'!$D$31 -> 0 | Q18: =Transporte!$D$20 -> 0 | R18: =Manutenção!$D$21 -> 0 | S18: =I18 -> 0 | T18: =SUM(L18:S18) -> 3433.6711 | U18: =IF($L$2>=1,T18/$A$5,0) -> 0 | V18: ='Verniz Cataforético'!L11 -> 23978.81 | W18: ='Resumo M.O'!$E$27 -> 1907.3422 | X18: ='Resumo M.O'!$E$31 -> 1526.3289 | Y18: ='Resumo Custos Variáveis'!$G$21 -> 2404.5263 | Z18: ='Outros Custos'!$E$31 -> 0 | AA18: =Transporte!$E$20 -> 0 | AB18: =Manutenção!$E$21 -> 0 | AC18: =S18 -> 0 | AD18: =SUM(V18:AC18) -> 29817.007 | AE18: =IF($L$2>=1,AD18/$A$5,0) -> 0 | AF18: ='Verniz Cataforético'!O11 -> 15749.42 | AG18: ='Resumo M.O'!$F$27 -> 1907.3422 | AH18: ='Resumo M.O'!$F$31 -> 1526.3289 | AI18: ='Resumo Custos Variáveis'!$H$21 -> 1573.8421 | AJ18: ='Outros Custos'!$F$31 -> 0 | AK18: =Transporte!$F$20 -> 0 | AL18: =Manutenção!$F$21 -> 0 | AM18: =AC18 -> 0 | AN18: =SUM(AF18:AM18) -> 20756.933 | AO18: =IF($L$2>=1,AN18/$A$5,0) -> 0 | AP18: ='Verniz Cataforético'!R11 -> 0 | AQ18: ='Resumo M.O'!$G$27 -> 1907.3422 | AR18: ='Resumo M.O'!$G$31 -> 1526.3289 | AS18: ='Resumo Custos Variáveis'!$I$21 -> 0 | AT18: ='Outros Custos'!$G$31 -> 0 | AU18: =Transporte!$G$20 -> 0 | AV18: =Manutenção!$G$21 -> 0 | AW18: =AM18 -> 0 | AX18: =SUM(AP18:AW18) -> 3433.6711 | AY18: =IF($L$2>=1,AX18/$A$5,0) -> 0 | AZ18: ='Verniz Cataforético'!U11 -> 0 | BA18: ='Resumo M.O'!$H$27 -> 1907.3422 | BB18: ='Resumo M.O'!$H$31 -> 1526.3289 | BC18: ='Resumo Custos Variáveis'!$J$21 -> 0 | BD18: ='Outros Custos'!$H$31 -> 0 | BE18: =Transporte!$H$20 -> 0 | BF18: =Manutenção!$H$21 -> 3061.5385 | BG18: =AW18 -> 0 | BH18: =SUM(AZ18:BG18) -> 6495.2095 | BI18: =IF($L$2>=1,BH18/$A$5,0) -> 0 | BJ18: ='Verniz Cataforético'!X11 -> 0 | BK18: ='Resumo M.O'!$I$27 -> 1907.3422 | BL18: ='Resumo M.O'!$I$31 -> 1526.3289 | BM18: ='Resumo Custos Variáveis'!$K$21 -> 0 | BN18: ='Outros Custos'!$I$31 -> 0 | BO18: =Transporte!$I$20 -> 0 | BP18: =Manutenção!$I$21 -> 3030.7692 | BQ18: =BG18 -> 0 | BR18: =SUM(BJ18:BQ18) -> 6464.4403 | BS18: =IF($L$2>=1,BR18/$A$5,0) -> 0 | BT18: ='Verniz Cataforético'!AA11 -> 0 | BU18: ='Resumo M.O'!$J$27 -> 1907.3422 | BV18: ='Resumo M.O'!$J$31 -> 1526.3289 | BW18: ='Resumo Custos Variáveis'!$L$21 -> 0 | BX18: ='Outros Custos'!$J$31 -> 0 | BY18: =Transporte!$J$20 -> 0 | BZ18: =Manutenção!$J$21 -> 0 | CA18: =BQ18 -> 0 | CB18: =SUM(BT18:CA18) -> 3433.6711 | CC18: =IF($L$2>=1,CB18/$A$5,0) -> 0 | CD18: ='Verniz Cataforético'!AD11 -> 0 | CE18: ='Resumo M.O'!$K$27 -> 1907.3422 | CF18: ='Resumo M.O'!$K$31 -> 1526.3289 | CG18: ='Resumo Custos Variáveis'!$M$21 -> 0 | CH18: ='Outros Custos'!$K$31 -> 0 | CI18: =Transporte!$K$20 -> 0 | CJ18: =Manutenção!$K$21 -> 0 | CK18: =CA18 -> 0 | CL18: =SUM(CD18:CK18) -> 3433.6711 | CM18: =IF($L$2>=1,CL18/$A$5,0) -> 0 | CN18: ='Verniz Cataforético'!AG11 -> 0 | CO18: ='Resumo M.O'!$L$27 -> 1907.3422 | CP18: ='Resumo M.O'!$L$31 -> 1526.3289 | CQ18: ='Resumo Custos Variáveis'!$N$21 -> 0 | CR18: ='Outros Custos'!$L$31 -> 0 | CS18: =Transporte!$L$20 -> 0 | CT18: =Manutenção!$L$21 -> 0 | CU18: =CK18 -> 0 | CV18: =SUM(CN18:CU18) -> 3433.6711 | CW18: =IF($L$2>=1,CV18/$A$5,0) -> 0 | CX18: ='Verniz Cataforético'!AJ11 -> 0 | CY18: ='Resumo M.O'!$M$27 -> 1907.3422 | CZ18: ='Resumo M.O'!$M$31 -> 1526.3289 | DA18: ='Resumo Custos Variáveis'!$O$21 -> 0 | DB18: ='Outros Custos'!$M$31 -> 0 | DC18: =Transporte!$M$20 -> 0 | DD18: =Manutenção!$M$21 -> 0 | DE18: =CU18 -> 0 | DF18: =SUM(CX18:DE18) -> 3433.6711 | DG18: =IF($L$2>=1,DF18/$A$5,0) -> 0 | DH18: ='Verniz Cataforético'!AM11 -> 0 | DI18: ='Resumo M.O'!$N$27 -> 1907.3422 | DJ18: ='Resumo M.O'!$N$31 -> 1526.3289 | DK18: ='Resumo Custos Variáveis'!$P$21 -> 0 | DL18: ='Outros Custos'!$N$31 -> 0 | DM18: =Transporte!$N$20 -> 0 | DN18: =Manutenção!$N$21 -> 0 | DO18: =DE18 -> 0 | DP18: =SUM(DH18:DO18) -> 3433.6711 | DQ18: =IF($L$2>=1,DP18/$A$5,0) -> 0 | DS18: =K18 -> 0 | DT18: =U18 -> 0 | DU18: =AE18 -> 0 | DV18: =AO18 -> 0 | DW18: =AY18 -> 0 | DX18: =BI18 -> 0 | DY18: =BS18 -> 0 | DZ18: =CC18 -> 0 | EA18: =CM18 -> 0 | EB18: =CW18 -> 0 | EC18: =DG18 -> 0 | ED18: =DQ18 -> 0 | EF18: =B18/$A$5 -> 0 | EG18: =L18/$A$5 -> 0 | EH18: =V18/$A$5 -> 108.99459 | EI18: =AF18/$A$5 -> 71.588273 | EJ18: =AP18/$A$5 -> 0 | EK18: =AZ18/$A$5 -> 0 | EL18: =BJ18/$A$5 -> 0 | EM18: =BT18/$A$5 -> 0 | EN18: =CD18/$A$5 -> 0 | EO18: =CN18/$A$5 -> 0 | EP18: =CX18/$A$5 -> 0 | EQ18: =DH18/$A$5 -> 0
A19: Preto Fosco | B19: ='Verniz Cataforético'!F17 -> 0 | C19: ='Resumo M.O'!$C$27 -> 1907.3422 | D19: ='Resumo M.O'!$C$31 -> 1526.3289 | E19: ='Resumo Custos Variáveis'!$E$21 -> 0 | F19: ='Outros Custos'!$C$31 -> 0 | G19: =Transporte!$C$20 -> 0 | H19: =Manutenção!$C$21 -> 0 | I19: =Investimentos!O14 -> 0 | J19: =SUM(B19:I19) -> 3433.6711 | K19: =IF($L$2>=1,J19/$A$5,0) -> 0 | L19: ='Verniz Cataforético'!I17 -> 0 | M19: ='Resumo M.O'!$D$27 -> 1907.3422 | N19: ='Resumo M.O'!$D$31 -> 1526.3289 | O19: ='Resumo Custos Variáveis'!$F$21 -> 0 | P19: ='Outros Custos'!$D$31 -> 0 | Q19: =Transporte!$D$20 -> 0 | R19: =Manutenção!$D$21 -> 0 | S19: =I19 -> 0 | T19: =SUM(L19:S19) -> 3433.6711 | U19: =IF($L$2>=1,T19/$A$5,0) -> 0 | V19: ='Verniz Cataforético'!L17 -> 39908.76 | W19: ='Resumo M.O'!$E$27 -> 1907.3422 | X19: ='Resumo M.O'!$E$31 -> 1526.3289 | Y19: ='Resumo Custos Variáveis'!$G$21 -> 2404.5263 | Z19: ='Outros Custos'!$E$31 -> 0 | AA19: =Transporte!$E$20 -> 0 | AB19: =Manutenção!$E$21 -> 0 | AC19: =S19 -> 0 | AD19: =SUM(V19:AC19) -> 45746.957 | AE19: =IF($L$2>=1,AD19/$A$5,0) -> 0 | AF19: ='Verniz Cataforético'!O17 -> 42991.42 | AG19: ='Resumo M.O'!$F$27 -> 1907.3422 | AH19: ='Resumo M.O'!$F$31 -> 1526.3289 | AI19: ='Resumo Custos Variáveis'!$H$21 -> 1573.8421 | AJ19: ='Outros Custos'!$F$31 -> 0 | AK19: =Transporte!$F$20 -> 0 | AL19: =Manutenção!$F$21 -> 0 | AM19: =AC19 -> 0 | AN19: =SUM(AF19:AM19) -> 47998.933 | AO19: =IF($L$2>=1,AN19/$A$5,0) -> 0 | AP19: ='Verniz Cataforético'!R17 -> 0 | AQ19: ='Resumo M.O'!$G$27 -> 1907.3422 | AR19: ='Resumo M.O'!$G$31 -> 1526.3289 | AS19: ='Resumo Custos Variáveis'!$I$21 -> 0 | AT19: ='Outros Custos'!$G$31 -> 0 | AU19: =Transporte!$G$20 -> 0 | AV19: =Manutenção!$G$21 -> 0 | AW19: =AM19 -> 0 | AX19: =SUM(AP19:AW19) -> 3433.6711 | AY19: =IF($L$2>=1,AX19/$A$5,0) -> 0 | AZ19: ='Verniz Cataforético'!U17 -> 0 | BA19: ='Resumo M.O'!$H$27 -> 1907.3422 | BB19: ='Resumo M.O'!$H$31 -> 1526.3289 | BC19: ='Resumo Custos Variáveis'!$J$21 -> 0 | BD19: ='Outros Custos'!$H$31 -> 0 | BE19: =Transporte!$H$20 -> 0 | BF19: =Manutenção!$H$21 -> 3061.5385 | BG19: =AW19 -> 0 | BH19: =SUM(AZ19:BG19) -> 6495.2095 | BI19: =IF($L$2>=1,BH19/$A$5,0) -> 0 | BJ19: ='Verniz Cataforético'!X17 -> 0 | BK19: ='Resumo M.O'!$I$27 -> 1907.3422 | BL19: ='Resumo M.O'!$I$31 -> 1526.3289 | BM19: ='Resumo Custos Variáveis'!$K$21 -> 0 | BN19: ='Outros Custos'!$I$31 -> 0 | BO19: =Transporte!$I$20 -> 0 | BP19: =Manutenção!$I$21 -> 3030.7692 | BQ19: =BG19 -> 0 | BR19: =SUM(BJ19:BQ19) -> 6464.4403 | BS19: =IF($L$2>=1,BR19/$A$5,0) -> 0 | BT19: ='Verniz Cataforético'!AA17 -> 0 | BU19: ='Resumo M.O'!$J$27 -> 1907.3422 | BV19: ='Resumo M.O'!$J$31 -> 1526.3289 | BW19: ='Resumo Custos Variáveis'!$L$21 -> 0 | BX19: ='Outros Custos'!$J$31 -> 0 | BY19: =Transporte!$J$20 -> 0 | BZ19: =Manutenção!$J$21 -> 0 | CA19: =BQ19 -> 0 | CB19: =SUM(BT19:CA19) -> 3433.6711 | CC19: =IF($L$2>=1,CB19/$A$5,0) -> 0 | CD19: ='Verniz Cataforético'!AD17 -> 0 | CE19: ='Resumo M.O'!$K$27 -> 1907.3422 | CF19: ='Resumo M.O'!$K$31 -> 1526.3289 | CG19: ='Resumo Custos Variáveis'!$M$21 -> 0 | CH19: ='Outros Custos'!$K$31 -> 0 | CI19: =Transporte!$K$20 -> 0 | CJ19: =Manutenção!$K$21 -> 0 | CK19: =CA19 -> 0 | CL19: =SUM(CD19:CK19) -> 3433.6711 | CM19: =IF($L$2>=1,CL19/$A$5,0) -> 0 | CN19: ='Verniz Cataforético'!AG17 -> 0 | CO19: ='Resumo M.O'!$L$27 -> 1907.3422 | CP19: ='Resumo M.O'!$L$31 -> 1526.3289 | CQ19: ='Resumo Custos Variáveis'!$N$21 -> 0 | CR19: ='Outros Custos'!$L$31 -> 0 | CS19: =Transporte!$L$20 -> 0 | CT19: =Manutenção!$L$21 -> 0 | CU19: =CK19 -> 0 | CV19: =SUM(CN19:CU19) -> 3433.6711 | CW19: =IF($L$2>=1,CV19/$A$5,0) -> 0 | CX19: ='Verniz Cataforético'!AJ17 -> 0 | CY19: ='Resumo M.O'!$M$27 -> 1907.3422 | CZ19: ='Resumo M.O'!$M$31 -> 1526.3289 | DA19: ='Resumo Custos Variáveis'!$O$21 -> 0 | DB19: ='Outros Custos'!$M$31 -> 0 | DC19: =Transporte!$M$20 -> 0 | DD19: =Manutenção!$M$21 -> 0 | DE19: =CU19 -> 0 | DF19: =SUM(CX19:DE19) -> 3433.6711 | DG19: =IF($L$2>=1,DF19/$A$5,0) -> 0 | DH19: ='Verniz Cataforético'!AM17 -> 0 | DI19: ='Resumo M.O'!$N$27 -> 1907.3422 | DJ19: ='Resumo M.O'!$N$31 -> 1526.3289 | DK19: ='Resumo Custos Variáveis'!$P$21 -> 0 | DL19: ='Outros Custos'!$N$31 -> 0 | DM19: =Transporte!$N$20 -> 0 | DN19: =Manutenção!$N$21 -> 0 | DO19: =DE19 -> 0 | DP19: =SUM(DH19:DO19) -> 3433.6711 | DQ19: =IF($L$2>=1,DP19/$A$5,0) -> 0 | DS19: =K19 -> 0 | DT19: =U19 -> 0 | DU19: =AE19 -> 0 | DV19: =AO19 -> 0 | DW19: =AY19 -> 0 | DX19: =BI19 -> 0 | DY19: =BS19 -> 0 | DZ19: =CC19 -> 0 | EA19: =CM19 -> 0 | EB19: =CW19 -> 0 | EC19: =DG19 -> 0 | ED19: =DQ19 -> 0 | EF19: =B19/$A$5 -> 0 | EG19: =L19/$A$5 -> 0 | EH19: =V19/$A$5 -> 181.40345 | EI19: =AF19/$A$5 -> 195.41555 | EJ19: =AP19/$A$5 -> 0 | EK19: =AZ19/$A$5 -> 0 | EL19: =BJ19/$A$5 -> 0 | EM19: =BT19/$A$5 -> 0 | EN19: =CD19/$A$5 -> 0 | EO19: =CN19/$A$5 -> 0 | EP19: =CX19/$A$5 -> 0 | EQ19: =DH19/$A$5 -> 0
A20: Preto Brilhante | B20: ='Verniz Cataforético'!F23 -> 0 | C20: ='Resumo M.O'!$C$27 -> 1907.3422 | D20: ='Resumo M.O'!$C$31 -> 1526.3289 | E20: ='Resumo Custos Variáveis'!$E$21 -> 0 | F20: ='Outros Custos'!$C$31 -> 0 | G20: =Transporte!$C$20 -> 0 | H20: =Manutenção!$C$21 -> 0 | I20: =Investimentos!O18 -> 0 | J20: =SUM(B20:I20) -> 3433.6711 | K20: =IF($L$2>=1,J20/$A$5,0) -> 0 | L20: ='Verniz Cataforético'!I23 -> 0 | M20: ='Resumo M.O'!$D$27 -> 1907.3422 | N20: ='Resumo M.O'!$D$31 -> 1526.3289 | O20: ='Resumo Custos Variáveis'!$F$21 -> 0 | P20: ='Outros Custos'!$D$31 -> 0 | Q20: =Transporte!$D$20 -> 0 | R20: =Manutenção!$D$21 -> 0 | S20: =I20 -> 0 | T20: =SUM(L20:S20) -> 3433.6711 | U20: =IF($L$2>=1,T20/$A$5,0) -> 0 | V20: ='Verniz Cataforético'!L23 -> 3804.04 | W20: ='Resumo M.O'!$E$27 -> 1907.3422 | X20: ='Resumo M.O'!$E$31 -> 1526.3289 | Y20: ='Resumo Custos Variáveis'!$G$21 -> 2404.5263 | Z20: ='Outros Custos'!$E$31 -> 0 | AA20: =Transporte!$E$20 -> 0 | AB20: =Manutenção!$E$21 -> 0 | AC20: =S20 -> 0 | AD20: =SUM(V20:AC20) -> 9642.2374 | AE20: =IF($L$2>=1,AD20/$A$5,0) -> 0 | AF20: ='Verniz Cataforético'!O23 -> 1195.4 | AG20: ='Resumo M.O'!$F$27 -> 1907.3422 | AH20: ='Resumo M.O'!$F$31 -> 1526.3289 | AI20: ='Resumo Custos Variáveis'!$H$21 -> 1573.8421 | AJ20: ='Outros Custos'!$F$31 -> 0 | AK20: =Transporte!$F$20 -> 0 | AL20: =Manutenção!$F$21 -> 0 | AM20: =AC20 -> 0 | AN20: =SUM(AF20:AM20) -> 6202.9132 | AO20: =IF($L$2>=1,AN20/$A$5,0) -> 0 | AP20: ='Verniz Cataforético'!R23 -> 0 | AQ20: ='Resumo M.O'!$G$27 -> 1907.3422 | AR20: ='Resumo M.O'!$G$31 -> 1526.3289 | AS20: ='Resumo Custos Variáveis'!$I$21 -> 0 | AT20: ='Outros Custos'!$G$31 -> 0 | AU20: =Transporte!$G$20 -> 0 | AV20: =Manutenção!$G$21 -> 0 | AW20: =AM20 -> 0 | AX20: =SUM(AP20:AW20) -> 3433.6711 | AY20: =IF($L$2>=1,AX20/$A$5,0) -> 0 | AZ20: ='Verniz Cataforético'!U23 -> 0 | BA20: ='Resumo M.O'!$H$27 -> 1907.3422 | BB20: ='Resumo M.O'!$H$31 -> 1526.3289 | BC20: ='Resumo Custos Variáveis'!$J$21 -> 0 | BD20: ='Outros Custos'!$H$31 -> 0 | BE20: =Transporte!$H$20 -> 0 | BF20: =Manutenção!$H$21 -> 3061.5385 | BG20: =AW20 -> 0 | BH20: =SUM(AZ20:BG20) -> 6495.2095 | BI20: =IF($L$2>=1,BH20/$A$5,0) -> 0 | BJ20: ='Verniz Cataforético'!X23 -> 0 | BK20: ='Resumo M.O'!$I$27 -> 1907.3422 | BL20: ='Resumo M.O'!$I$31 -> 1526.3289 | BM20: ='Resumo Custos Variáveis'!$K$21 -> 0 | BN20: ='Outros Custos'!$I$31 -> 0 | BO20: =Transporte!$I$20 -> 0 | BP20: =Manutenção!$I$21 -> 3030.7692 | BQ20: =BG20 -> 0 | BR20: =SUM(BJ20:BQ20) -> 6464.4403 | BS20: =IF($L$2>=1,BR20/$A$5,0) -> 0 | BT20: ='Verniz Cataforético'!AA23 -> 0 | BU20: ='Resumo M.O'!$J$27 -> 1907.3422 | BV20: ='Resumo M.O'!$J$31 -> 1526.3289 | BW20: ='Resumo Custos Variáveis'!$L$21 -> 0 | BX20: ='Outros Custos'!$J$31 -> 0 | BY20: =Transporte!$J$20 -> 0 | BZ20: =Manutenção!$J$21 -> 0 | CA20: =BQ20 -> 0 | CB20: =SUM(BT20:CA20) -> 3433.6711 | CC20: =IF($L$2>=1,CB20/$A$5,0) -> 0 | CD20: ='Verniz Cataforético'!AD23 -> 0 | CE20: ='Resumo M.O'!$K$27 -> 1907.3422 | CF20: ='Resumo M.O'!$K$31 -> 1526.3289 | CG20: ='Resumo Custos Variáveis'!$M$21 -> 0 | CH20: ='Outros Custos'!$K$31 -> 0 | CI20: =Transporte!$K$20 -> 0 | CJ20: =Manutenção!$K$21 -> 0 | CK20: =CA20 -> 0 | CL20: =SUM(CD20:CK20) -> 3433.6711 | CM20: =IF($L$2>=1,CL20/$A$5,0) -> 0 | CN20: ='Verniz Cataforético'!AG23 -> 0 | CO20: ='Resumo M.O'!$L$27 -> 1907.3422 | CP20: ='Resumo M.O'!$L$31 -> 1526.3289 | CQ20: ='Resumo Custos Variáveis'!$N$21 -> 0 | CR20: ='Outros Custos'!$L$31 -> 0 | CS20: =Transporte!$L$20 -> 0 | CT20: =Manutenção!$L$21 -> 0 | CU20: =CK20 -> 0 | CV20: =SUM(CN20:CU20) -> 3433.6711 | CW20: =IF($L$2>=1,CV20/$A$5,0) -> 0 | CX20: ='Verniz Cataforético'!AJ23 -> 0 | CY20: ='Resumo M.O'!$M$27 -> 1907.3422 | CZ20: ='Resumo M.O'!$M$31 -> 1526.3289 | DA20: ='Resumo Custos Variáveis'!$O$21 -> 0 | DB20: ='Outros Custos'!$M$31 -> 0 | DC20: =Transporte!$M$20 -> 0 | DD20: =Manutenção!$M$21 -> 0 | DE20: =CU20 -> 0 | DF20: =SUM(CX20:DE20) -> 3433.6711 | DG20: =IF($L$2>=1,DF20/$A$5,0) -> 0 | DH20: ='Verniz Cataforético'!AM23 -> 0 | DI20: ='Resumo M.O'!$N$27 -> 1907.3422 | DJ20: ='Resumo M.O'!$N$31 -> 1526.3289 | DK20: ='Resumo Custos Variáveis'!$P$21 -> 0 | DL20: ='Outros Custos'!$N$31 -> 0 | DM20: =Transporte!$N$20 -> 0 | DN20: =Manutenção!$N$21 -> 0 | DO20: =DE20 -> 0 | DP20: =SUM(DH20:DO20) -> 3433.6711 | DQ20: =IF($L$2>=1,DP20/$A$5,0) -> 0 | DS20: =K20 -> 0 | DT20: =U20 -> 0 | DU20: =AE20 -> 0 | DV20: =AO20 -> 0 | DW20: =AY20 -> 0 | DX20: =BI20 -> 0 | DY20: =BS20 -> 0 | DZ20: =CC20 -> 0 | EA20: =CM20 -> 0 | EB20: =CW20 -> 0 | EC20: =DG20 -> 0 | ED20: =DQ20 -> 0 | EF20: =B20/$A$5 -> 0 | EG20: =L20/$A$5 -> 0 | EH20: =V20/$A$5 -> 17.291091 | EI20: =AF20/$A$5 -> 5.4336364 | EJ20: =AP20/$A$5 -> 0 | EK20: =AZ20/$A$5 -> 0 | EL20: =BJ20/$A$5 -> 0 | EM20: =BT20/$A$5 -> 0 | EN20: =CD20/$A$5 -> 0 | EO20: =CN20/$A$5 -> 0 | EP20: =CX20/$A$5 -> 0 | EQ20: =DH20/$A$5 -> 0
A21: Ouro Fosco Gold | B21: ='Verniz Cataforético'!F29 -> 0 | C21: ='Resumo M.O'!$C$27 -> 1907.3422 | D21: ='Resumo M.O'!$C$31 -> 1526.3289 | E21: ='Resumo Custos Variáveis'!$E$21 -> 0 | F21: ='Outros Custos'!$C$31 -> 0 | G21: =Transporte!$C$20 -> 0 | H21: =Manutenção!$C$21 -> 0 | I21: =Investimentos!O22 -> 0 | J21: =SUM(B21:I21) -> 3433.6711 | K21: =IF($L$2>=1,J21/$A$5,0) -> 0 | L21: ='Verniz Cataforético'!I29 -> 0 | M21: ='Resumo M.O'!$D$27 -> 1907.3422 | N21: ='Resumo M.O'!$D$31 -> 1526.3289 | O21: ='Resumo Custos Variáveis'!$F$21 -> 0 | P21: ='Outros Custos'!$D$31 -> 0 | Q21: =Transporte!$D$20 -> 0 | R21: =Manutenção!$D$21 -> 0 | S21: =I21 -> 0 | T21: =SUM(L21:S21) -> 3433.6711 | U21: =IF($L$2>=1,T21/$A$5,0) -> 0 | V21: ='Verniz Cataforético'!L29 -> 22284.89 | W21: ='Resumo M.O'!$E$27 -> 1907.3422 | X21: ='Resumo M.O'!$E$31 -> 1526.3289 | Y21: ='Resumo Custos Variáveis'!$G$21 -> 2404.5263 | Z21: ='Outros Custos'!$E$31 -> 0 | AA21: =Transporte!$E$20 -> 0 | AB21: =Manutenção!$E$21 -> 0 | AC21: =S21 -> 0 | AD21: =SUM(V21:AC21) -> 28123.087 | AE21: =IF($L$2>=1,AD21/$A$5,0) -> 0 | AF21: ='Verniz Cataforético'!O29 -> 14010 | AG21: ='Resumo M.O'!$F$27 -> 1907.3422 | AH21: ='Resumo M.O'!$F$31 -> 1526.3289 | AI21: ='Resumo Custos Variáveis'!$H$21 -> 1573.8421 | AJ21: ='Outros Custos'!$F$31 -> 0 | AK21: =Transporte!$F$20 -> 0 | AL21: =Manutenção!$F$21 -> 0 | AM21: =AC21 -> 0 | AN21: =SUM(AF21:AM21) -> 19017.513 | AO21: =IF($L$2>=1,AN21/$A$5,0) -> 0 | AP21: ='Verniz Cataforético'!R29 -> 0 | AQ21: ='Resumo M.O'!$G$27 -> 1907.3422 | AR21: ='Resumo M.O'!$G$31 -> 1526.3289 | AS21: ='Resumo Custos Variáveis'!$I$21 -> 0 | AT21: ='Outros Custos'!$G$31 -> 0 | AU21: =Transporte!$G$20 -> 0 | AV21: =Manutenção!$G$21 -> 0 | AW21: =AM21 -> 0 | AX21: =SUM(AP21:AW21) -> 3433.6711 | AY21: =IF($L$2>=1,AX21/$A$5,0) -> 0 | AZ21: ='Verniz Cataforético'!U29 -> 0 | BA21: ='Resumo M.O'!$H$27 -> 1907.3422 | BB21: ='Resumo M.O'!$H$31 -> 1526.3289 | BC21: ='Resumo Custos Variáveis'!$J$21 -> 0 | BD21: ='Outros Custos'!$H$31 -> 0 | BE21: =Transporte!$H$20 -> 0 | BF21: =Manutenção!$H$21 -> 3061.5385 | BG21: =AW21 -> 0 | BH21: =SUM(AZ21:BG21) -> 6495.2095 | BI21: =IF($L$2>=1,BH21/$A$5,0) -> 0 | BJ21: ='Verniz Cataforético'!X29 -> 0 | BK21: ='Resumo M.O'!$I$27 -> 1907.3422 | BL21: ='Resumo M.O'!$I$31 -> 1526.3289 | BM21: ='Resumo Custos Variáveis'!$K$21 -> 0 | BN21: ='Outros Custos'!$I$31 -> 0 | BO21: =Transporte!$I$20 -> 0 | BP21: =Manutenção!$I$21 -> 3030.7692 | BQ21: =BG21 -> 0 | BR21: =SUM(BJ21:BQ21) -> 6464.4403 | BS21: =IF($L$2>=1,BR21/$A$5,0) -> 0 | BT21: ='Verniz Cataforético'!AA29 -> 0 | BU21: ='Resumo M.O'!$J$27 -> 1907.3422 | BV21: ='Resumo M.O'!$J$31 -> 1526.3289 | BW21: ='Resumo Custos Variáveis'!$L$21 -> 0 | BX21: ='Outros Custos'!$J$31 -> 0 | BY21: =Transporte!$J$20 -> 0 | BZ21: =Manutenção!$J$21 -> 0 | CA21: =BQ21 -> 0 | CB21: =SUM(BT21:CA21) -> 3433.6711 | CC21: =IF($L$2>=1,CB21/$A$5,0) -> 0 | CD21: ='Verniz Cataforético'!AD29 -> 0 | CE21: ='Resumo M.O'!$K$27 -> 1907.3422 | CF21: ='Resumo M.O'!$K$31 -> 1526.3289 | CG21: ='Resumo Custos Variáveis'!$M$21 -> 0 | CH21: ='Outros Custos'!$K$31 -> 0 | CI21: =Transporte!$K$20 -> 0 | CJ21: =Manutenção!$K$21 -> 0 | CK21: =CA21 -> 0 | CL21: =SUM(CD21:CK21) -> 3433.6711 | CM21: =IF(L2>=1,CL21/$A$5,0) -> 0 | CN21: ='Verniz Cataforético'!AG29 -> 0 | CO21: ='Resumo M.O'!$L$27 -> 1907.3422 | CP21: ='Resumo M.O'!$L$31 -> 1526.3289 | CQ21: ='Resumo Custos Variáveis'!$N$21 -> 0 | CR21: ='Outros Custos'!$L$31 -> 0 | CS21: =Transporte!$L$20 -> 0 | CT21: =Manutenção!$L$21 -> 0 | CU21: =CK21 -> 0 | CV21: =SUM(CN21:CU21) -> 3433.6711 | CW21: =IF($L$2>=1,CV21/$A$5,0) -> 0 | CX21: ='Verniz Cataforético'!AJ29 -> 0 | CY21: ='Resumo M.O'!$M$27 -> 1907.3422 | CZ21: ='Resumo M.O'!$M$31 -> 1526.3289 | DA21: ='Resumo Custos Variáveis'!$O$21 -> 0 | DB21: ='Outros Custos'!$M$31 -> 0 | DC21: =Transporte!$M$20 -> 0 | DD21: =Manutenção!$M$21 -> 0 | DE21: =CU21 -> 0 | DF21: =SUM(CX21:DE21) -> 3433.6711 | DG21: =IF($L$2>=1,DF21/$A$5,0) -> 0 | DH21: ='Verniz Cataforético'!AM29 -> 0 | DI21: ='Resumo M.O'!$N$27 -> 1907.3422 | DJ21: ='Resumo M.O'!$N$31 -> 1526.3289 | DK21: ='Resumo Custos Variáveis'!$P$21 -> 0 | DL21: ='Outros Custos'!$N$31 -> 0 | DM21: =Transporte!$N$20 -> 0 | DN21: =Manutenção!$N$21 -> 0 | DO21: =DE21 -> 0 | DP21: =SUM(DH21:DO21) -> 3433.6711 | DQ21: =IF($L$2>=1,DP21/$A$5,0) -> 0 | DS21: =K21 -> 0 | DT21: =U21 -> 0 | DU21: =AE21 -> 0 | DV21: =AO21 -> 0 | DW21: =AY21 -> 0 | DX21: =BI21 -> 0 | DY21: =BS21 -> 0 | DZ21: =CC21 -> 0 | EA21: =CM21 -> 0 | EB21: =CW21 -> 0 | EC21: =DG21 -> 0 | ED21: =DQ21 -> 0 | EF21: =B21/$A$5 -> 0 | EG21: =L21/$A$5 -> 0 | EH21: =V21/$A$5 -> 101.29495 | EI21: =AF21/$A$5 -> 63.681818 | EJ21: =AP21/$A$5 -> 0 | EK21: =AZ21/$A$5 -> 0 | EL21: =BJ21/$A$5 -> 0 | EM21: =BT21/$A$5 -> 0 | EN21: =CD21/$A$5 -> 0 | EO21: =CN21/$A$5 -> 0 | EP21: =CX21/$A$5 -> 0 | EQ21: =DH21/$A$5 -> 0
A22: Champagne | B22: ='Verniz Cataforético'!F35 -> 0 | C22: ='Resumo M.O'!$C$27 -> 1907.3422 | D22: ='Resumo M.O'!$C$31 -> 1526.3289 | E22: ='Resumo Custos Variáveis'!$E$21 -> 0 | F22: ='Outros Custos'!$C$31 -> 0 | G22: =Transporte!$C$20 -> 0 | H22: =Manutenção!$C$21 -> 0 | I22: =Investimentos!O26 -> 0 | J22: =SUM(B22:I22) -> 3433.6711 | K22: =IF($L$2>=1,J22/$A$5,0) -> 0 | L22: ='Verniz Cataforético'!I35 -> 0 | M22: ='Resumo M.O'!$D$27 -> 1907.3422 | N22: ='Resumo M.O'!$D$31 -> 1526.3289 | O22: ='Resumo Custos Variáveis'!$F$21 -> 0 | P22: ='Outros Custos'!$D$31 -> 0 | Q22: =Transporte!$D$20 -> 0 | R22: =Manutenção!$D$21 -> 0 | S22: =I22 -> 0 | T22: =SUM(L22:S22) -> 3433.6711 | U22: =IF($L$2>=1,T22/$A$5,0) -> 0 | V22: ='Verniz Cataforético'!L35 -> 13737.29 | W22: ='Resumo M.O'!$E$27 -> 1907.3422 | X22: ='Resumo M.O'!$E$31 -> 1526.3289 | Y22: ='Resumo Custos Variáveis'!$G$21 -> 2404.5263 | Z22: ='Outros Custos'!$E$31 -> 0 | AA22: =Transporte!$E$20 -> 0 | AB22: =Manutenção!$E$21 -> 0 | AC22: =S22 -> 0 | AD22: =SUM(V22:AC22) -> 19575.487 | AE22: =IF($L$2>=1,AD22/$A$5,0) -> 0 | AF22: ='Verniz Cataforético'!O35 -> 20651.82 | AG22: ='Resumo M.O'!$F$27 -> 1907.3422 | AH22: ='Resumo M.O'!$F$31 -> 1526.3289 | AI22: ='Resumo Custos Variáveis'!$H$21 -> 1573.8421 | AJ22: ='Outros Custos'!$F$31 -> 0 | AK22: =Transporte!$F$20 -> 0 | AL22: =Manutenção!$F$21 -> 0 | AM22: =AC22 -> 0 | AN22: =SUM(AF22:AM22) -> 25659.333 | AO22: =IF($L$2>=1,AN22/$A$5,0) -> 0 | AP22: ='Verniz Cataforético'!R35 -> 0 | AQ22: ='Resumo M.O'!$G$27 -> 1907.3422 | AR22: ='Resumo M.O'!$G$31 -> 1526.3289 | AS22: ='Resumo Custos Variáveis'!$I$21 -> 0 | AT22: ='Outros Custos'!$G$31 -> 0 | AU22: =Transporte!$G$20 -> 0 | AV22: =Manutenção!$G$21 -> 0 | AW22: =AM22 -> 0 | AX22: =SUM(AP22:AW22) -> 3433.6711 | AY22: =IF($L$2>=1,AX22/$A$5,0) -> 0 | AZ22: ='Verniz Cataforético'!U35 -> 0 | BA22: ='Resumo M.O'!$H$27 -> 1907.3422 | BB22: ='Resumo M.O'!$H$31 -> 1526.3289 | BC22: ='Resumo Custos Variáveis'!$J$21 -> 0 | BD22: ='Outros Custos'!$H$31 -> 0 | BE22: =Transporte!$H$20 -> 0 | BF22: =Manutenção!$H$21 -> 3061.5385 | BG22: =AW22 -> 0 | BH22: =SUM(AZ22:BG22) -> 6495.2095 | BI22: =IF($L$2>=1,BH22/$A$5,0) -> 0 | BJ22: ='Verniz Cataforético'!X35 -> 0 | BK22: ='Resumo M.O'!$I$27 -> 1907.3422 | BL22: ='Resumo M.O'!$I$31 -> 1526.3289 | BM22: ='Resumo Custos Variáveis'!$K$21 -> 0 | BN22: ='Outros Custos'!$I$31 -> 0 | BO22: =Transporte!$I$20 -> 0 | BP22: =Manutenção!$I$21 -> 3030.7692 | BQ22: =BG22 -> 0 | BR22: =SUM(BJ22:BQ22) -> 6464.4403 | BS22: =IF($L$2>=1,BR22/$A$5,0) -> 0 | BT22: ='Verniz Cataforético'!AA35 -> 0 | BU22: ='Resumo M.O'!$J$27 -> 1907.3422 | BV22: ='Resumo M.O'!$J$31 -> 1526.3289 | BW22: ='Resumo Custos Variáveis'!$L$21 -> 0 | BX22: ='Outros Custos'!$J$31 -> 0 | BY22: =Transporte!$J$20 -> 0 | BZ22: =Manutenção!$J$21 -> 0 | CA22: =BQ22 -> 0 | CB22: =SUM(BT22:CA22) -> 3433.6711 | CC22: =IF($L$2>=1,CB22/$A$5,0) -> 0 | CD22: ='Verniz Cataforético'!AD35 -> 0 | CE22: ='Resumo M.O'!$K$27 -> 1907.3422 | CF22: ='Resumo M.O'!$K$31 -> 1526.3289 | CG22: ='Resumo Custos Variáveis'!$M$21 -> 0 | CH22: ='Outros Custos'!$K$31 -> 0 | CI22: =Transporte!$K$20 -> 0 | CJ22: =Manutenção!$K$21 -> 0 | CK22: =CA22 -> 0 | CL22: =SUM(CD22:CK22) -> 3433.6711 | CM22: =IF(L2>=1,CL22/$A$5,0) -> 0 | CN22: ='Verniz Cataforético'!AG35 -> 0 | CO22: ='Resumo M.O'!$L$27 -> 1907.3422 | CP22: ='Resumo M.O'!$L$31 -> 1526.3289 | CQ22: ='Resumo Custos Variáveis'!$N$21 -> 0 | CR22: ='Outros Custos'!$L$31 -> 0 | CS22: =Transporte!$L$20 -> 0 | CT22: =Manutenção!$L$21 -> 0 | CU22: =CK22 -> 0 | CV22: =SUM(CN22:CU22) -> 3433.6711 | CW22: =IF($L$2>=1,CV22/$A$5,0) -> 0 | CX22: ='Verniz Cataforético'!AJ35 -> 0 | CY22: ='Resumo M.O'!$M$27 -> 1907.3422 | CZ22: ='Resumo M.O'!$M$31 -> 1526.3289 | DA22: ='Resumo Custos Variáveis'!$O$21 -> 0 | DB22: ='Outros Custos'!$M$31 -> 0 | DC22: =Transporte!$M$20 -> 0 | DD22: =Manutenção!$M$21 -> 0 | DE22: =CU22 -> 0 | DF22: =SUM(CX22:DE22) -> 3433.6711 | DG22: =IF($L$2>=1,DF22/$A$5,0) -> 0 | DH22: ='Verniz Cataforético'!AM35 -> 0 | DI22: ='Resumo M.O'!$N$27 -> 1907.3422 | DJ22: ='Resumo M.O'!$N$31 -> 1526.3289 | DK22: ='Resumo Custos Variáveis'!$P$21 -> 0 | DL22: ='Outros Custos'!$N$31 -> 0 | DM22: =Transporte!$N$20 -> 0 | DN22: =Manutenção!$N$21 -> 0 | DO22: =DE22 -> 0 | DP22: =SUM(DH22:DO22) -> 3433.6711 | DQ22: =IF($L$2>=1,DP22/$A$5,0) -> 0 | DS22: =K22 -> 0 | DT22: =U22 -> 0 | DU22: =AE22 -> 0 | DV22: =AO22 -> 0 | DW22: =AY22 -> 0 | DX22: =BI22 -> 0 | DY22: =BS22 -> 0 | DZ22: =CC22 -> 0 | EA22: =CM22 -> 0 | EB22: =CW22 -> 0 | EC22: =DG22 -> 0 | ED22: =DQ22 -> 0 | EF22: =B22/$A$5 -> 0 | EG22: =L22/$A$5 -> 0 | EH22: =V22/$A$5 -> 62.442227 | EI22: =AF22/$A$5 -> 93.871909 | EJ22: =AP22/$A$5 -> 0 | EK22: =AZ22/$A$5 -> 0 | EL22: =BJ22/$A$5 -> 0 | EM22: =BT22/$A$5 -> 0 | EN22: =CD22/$A$5 -> 0 | EO22: =CN22/$A$5 -> 0 | EP22: =CX22/$A$5 -> 0 | EQ22: =DH22/$A$5 -> 0
A23: Grafite Omix | B23: ='Verniz Cataforético'!F41 -> 0 | C23: ='Resumo M.O'!$C$27 -> 1907.3422 | D23: ='Resumo M.O'!$C$31 -> 1526.3289 | E23: ='Resumo Custos Variáveis'!$E$21 -> 0 | F23: ='Outros Custos'!$C$31 -> 0 | G23: =Transporte!$C$20 -> 0 | H23: =Manutenção!$C$21 -> 0 | I23: =Investimentos!O30 -> 0 | J23: =SUM(B23:I23) -> 3433.6711 | K23: =IF($L$2>=1,J23/$A$5,0) -> 0 | L23: ='Verniz Cataforético'!I41 -> 0 | M23: ='Resumo M.O'!$D$27 -> 1907.3422 | N23: ='Resumo M.O'!$D$31 -> 1526.3289 | O23: ='Resumo Custos Variáveis'!$F$21 -> 0 | P23: ='Outros Custos'!$D$31 -> 0 | Q23: =Transporte!$D$20 -> 0 | R23: =Manutenção!$D$21 -> 0 | S23: =I23 -> 0 | T23: =SUM(L23:S23) -> 3433.6711 | U23: =IF($L$2>=1,T23/$A$5,0) -> 0 | V23: ='Verniz Cataforético'!L41 -> 2068.25 | W23: ='Resumo M.O'!$E$27 -> 1907.3422 | X23: ='Resumo M.O'!$E$31 -> 1526.3289 | Y23: ='Resumo Custos Variáveis'!$G$21 -> 2404.5263 | Z23: ='Outros Custos'!$E$31 -> 0 | AA23: =Transporte!$E$20 -> 0 | AB23: =Manutenção!$E$21 -> 0 | AC23: =S23 -> 0 | AD23: =SUM(V23:AC23) -> 7906.4474 | AE23: =IF($L$2>=1,AD23/$A$5,0) -> 0 | AF23: ='Verniz Cataforético'!O41 -> 4177.24 | AG23: ='Resumo M.O'!$F$27 -> 1907.3422 | AH23: ='Resumo M.O'!$F$31 -> 1526.3289 | AI23: ='Resumo Custos Variáveis'!$H$21 -> 1573.8421 | AJ23: ='Outros Custos'!$F$31 -> 0 | AK23: =Transporte!$F$20 -> 0 | AL23: =Manutenção!$F$21 -> 0 | AM23: =AC23 -> 0 | AN23: =SUM(AF23:AM23) -> 9184.7532 | AO23: =IF(L2>=1,AN23/$A$5,0) -> 0 | AP23: ='Verniz Cataforético'!R41 -> 0 | AQ23: ='Resumo M.O'!$G$27 -> 1907.3422 | AR23: ='Resumo M.O'!$G$31 -> 1526.3289 | AS23: ='Resumo Custos Variáveis'!$I$21 -> 0 | AT23: ='Outros Custos'!$G$31 -> 0 | AU23: =Transporte!$G$20 -> 0 | AV23: =Manutenção!$G$21 -> 0 | AW23: =AM23 -> 0 | AX23: =SUM(AP23:AW23) -> 3433.6711 | AY23: =IF(L2>=1,AX23/$A$5,0) -> 0 | AZ23: ='Verniz Cataforético'!U41 -> 0 | BA23: ='Resumo M.O'!$H$27 -> 1907.3422 | BB23: ='Resumo M.O'!$H$31 -> 1526.3289 | BC23: ='Resumo Custos Variáveis'!$J$21 -> 0 | BD23: ='Outros Custos'!$H$31 -> 0 | BE23: =Transporte!$H$20 -> 0 | BF23: =Manutenção!$H$21 -> 3061.5385 | BG23: =AW23 -> 0 | BH23: =SUM(AZ23:BG23) -> 6495.2095 | BI23: =IF(L2>=1,BH23/$A$5,0) -> 0 | BJ23: ='Verniz Cataforético'!X41 -> 0 | BK23: ='Resumo M.O'!$I$27 -> 1907.3422 | BL23: ='Resumo M.O'!$I$31 -> 1526.3289 | BM23: ='Resumo Custos Variáveis'!$K$21 -> 0 | BN23: ='Outros Custos'!$I$31 -> 0 | BO23: =Transporte!$I$20 -> 0 | BP23: =Manutenção!$I$21 -> 3030.7692 | BQ23: =BG23 -> 0 | BR23: =SUM(BJ23:BQ23) -> 6464.4403 | BS23: =IF(L2>=1,BR23/$A$5,0) -> 0 | BT23: ='Verniz Cataforético'!AA41 -> 0 | BU23: ='Resumo M.O'!$J$27 -> 1907.3422 | BV23: ='Resumo M.O'!$J$31 -> 1526.3289 | BW23: ='Resumo Custos Variáveis'!$L$21 -> 0 | BX23: ='Outros Custos'!$J$31 -> 0 | BY23: =Transporte!$J$20 -> 0 | BZ23: =Manutenção!$J$21 -> 0 | CA23: =BQ23 -> 0 | CB23: =SUM(BT23:CA23) -> 3433.6711 | CC23: =IF(L2>=1,CB23/$A$5,0) -> 0 | CD23: ='Verniz Cataforético'!AD41 -> 0 | CE23: ='Resumo M.O'!$K$27 -> 1907.3422 | CF23: ='Resumo M.O'!$K$31 -> 1526.3289 | CG23: ='Resumo Custos Variáveis'!$M$21 -> 0 | CH23: ='Outros Custos'!$K$31 -> 0 | CI23: =Transporte!$K$20 -> 0 | CJ23: =Manutenção!$K$21 -> 0 | CK23: =CA23 -> 0 | CL23: =SUM(CD23:CK23) -> 3433.6711 | CM23: =IF(L2>=1,CL23/$A$5,0) -> 0 | CN23: ='Verniz Cataforético'!AG41 -> 0 | CO23: ='Resumo M.O'!$L$27 -> 1907.3422 | CP23: ='Resumo M.O'!$L$31 -> 1526.3289 | CQ23: ='Resumo Custos Variáveis'!$N$21 -> 0 | CR23: ='Outros Custos'!$L$31 -> 0 | CS23: =Transporte!$L$20 -> 0 | CT23: =Manutenção!$L$21 -> 0 | CU23: =CK23 -> 0 | CV23: =SUM(CN23:CU23) -> 3433.6711 | CW23: =IF(L2>=1,CV23/$A$5,0) -> 0 | CX23: ='Verniz Cataforético'!AJ41 -> 0 | CY23: ='Resumo M.O'!$M$27 -> 1907.3422 | CZ23: ='Resumo M.O'!$M$31 -> 1526.3289 | DA23: ='Resumo Custos Variáveis'!$O$21 -> 0 | DB23: ='Outros Custos'!$M$31 -> 0 | DC23: =Transporte!$M$20 -> 0 | DD23: =Manutenção!$M$21 -> 0 | DE23: =CU23 -> 0 | DF23: =SUM(CX23:DE23) -> 3433.6711 | DG23: =IF(L2>=1,DF23/$A$5,0) -> 0 | DH23: ='Verniz Cataforético'!AM41 -> 0 | DI23: ='Resumo M.O'!$N$27 -> 1907.3422 | DJ23: ='Resumo M.O'!$N$31 -> 1526.3289 | DK23: ='Resumo Custos Variáveis'!$P$21 -> 0 | DL23: ='Outros Custos'!$N$31 -> 0 | DM23: =Transporte!$N$20 -> 0 | DN23: =Manutenção!$N$21 -> 0 | DO23: =DE23 -> 0 | DP23: =SUM(DH23:DO23) -> 3433.6711 | DQ23: =IF(L2>=1,DP23/$A$5,0) -> 0 | DS23: =K23 -> 0 | DT23: =U23 -> 0 | DU23: =AE23 -> 0 | DV23: =AO23 -> 0 | DW23: =AY23 -> 0 | DX23: =BI23 -> 0 | DY23: =BS23 -> 0 | DZ23: =CC23 -> 0 | EA23: =CM23 -> 0 | EB23: =CW23 -> 0 | EC23: =DG23 -> 0 | ED23: =DQ23 -> 0 | EF23: =B23/$A$5 -> 0 | EG23: =L23/$A$5 -> 0 | EH23: =V23/$A$5 -> 9.4011364 | EI23: =AF23/$A$5 -> 18.987455 | EJ23: =AP23/$A$5 -> 0 | EK23: =AZ23/$A$5 -> 0 | EL23: =BJ23/$A$5 -> 0 | EM23: =BT23/$A$5 -> 0 | EN23: =CD23/$A$5 -> 0 | EO23: =CN23/$A$5 -> 0 | EP23: =CX23/$A$5 -> 0 | EQ23: =DH23/$A$5 -> 0
A24: Verniz Imersão | B24: ='Verniz Imersão'!F22 -> 0 | C24: ='Resumo M.O'!$C$27 -> 1907.3422 | D24: ='Resumo M.O'!$C$31 -> 1526.3289 | E24: ='Resumo Custos Variáveis'!$E$21 -> 0 | F24: ='Outros Custos'!$C$31 -> 0 | G24: =Transporte!$C$20 -> 0 | H24: =Manutenção!$C$21 -> 0 | I24: =Investimentos!O34 -> 0 | J24: =SUM(B24:I24) -> 3433.6711 | K24: =IF($L$2>=1,J24/$A$5,0) -> 0 | L24: ='Verniz Imersão'!I22 -> 0 | M24: ='Resumo M.O'!$D$27 -> 1907.3422 | N24: ='Resumo M.O'!$D$31 -> 1526.3289 | O24: ='Resumo Custos Variáveis'!$F$21 -> 0 | P24: ='Outros Custos'!$D$31 -> 0 | Q24: =Transporte!$D$20 -> 0 | R24: =Manutenção!$D$21 -> 0 | S24: =I24 -> 0 | T24: =SUM(L24:S24) -> 3433.6711 | U24: =IF($L$2>=1,T24/$A$5,0) -> 0 | V24: ='Verniz Imersão'!L22 -> 3638.5 | W24: ='Resumo M.O'!$E$27 -> 1907.3422 | X24: ='Resumo M.O'!$E$31 -> 1526.3289 | Y24: ='Resumo Custos Variáveis'!$G$21 -> 2404.5263 | Z24: ='Outros Custos'!$E$31 -> 0 | AA24: =Transporte!$E$20 -> 0 | AB24: =Manutenção!$E$21 -> 0 | AC24: =S24 -> 0 | AD24: =SUM(V24:AC24) -> 9476.6974 | AE24: =IF($L$2>=1,AD24/$A$5,0) -> 0 | AF24: ='Verniz Imersão'!O22 -> 0 | AG24: ='Resumo M.O'!$F$27 -> 1907.3422 | AH24: ='Resumo M.O'!$F$31 -> 1526.3289 | AI24: ='Resumo Custos Variáveis'!$H$21 -> 1573.8421 | AJ24: ='Outros Custos'!$F$31 -> 0 | AK24: =Transporte!$F$20 -> 0 | AL24: =Manutenção!$F$21 -> 0 | AM24: =AC24 -> 0 | AN24: =SUM(AF24:AM24) -> 5007.5132 | AO24: =IF(L2>=1,AN24/$A$5,0) -> 0 | AP24: ='Verniz Imersão'!R22 -> 0 | AQ24: ='Resumo M.O'!$G$27 -> 1907.3422 | AR24: ='Resumo M.O'!$G$31 -> 1526.3289 | AS24: ='Resumo Custos Variáveis'!$I$21 -> 0 | AT24: ='Outros Custos'!$G$31 -> 0 | AU24: =Transporte!$G$20 -> 0 | AV24: =Manutenção!$G$21 -> 0 | AW24: =AM24 -> 0 | AX24: =SUM(AP24:AW24) -> 3433.6711 | AY24: =IF(L2>=1,AX24/$A$5,0) -> 0 | AZ24: ='Verniz Imersão'!U22 -> 0 | BA24: ='Resumo M.O'!$H$27 -> 1907.3422 | BB24: ='Resumo M.O'!$H$31 -> 1526.3289 | BC24: ='Resumo Custos Variáveis'!$J$21 -> 0 | BD24: ='Outros Custos'!$H$31 -> 0 | BE24: =Transporte!$H$20 -> 0 | BF24: =Manutenção!$H$21 -> 3061.5385 | BG24: =AW24 -> 0 | BH24: =SUM(AZ24:BG24) -> 6495.2095 | BI24: =IF(L2>=1,BH24/$A$5,0) -> 0 | BJ24: ='Verniz Imersão'!X22 -> 0 | BK24: ='Resumo M.O'!$I$27 -> 1907.3422 | BL24: ='Resumo M.O'!$I$31 -> 1526.3289 | BM24: ='Resumo Custos Variáveis'!$K$21 -> 0 | BN24: ='Outros Custos'!$I$31 -> 0 | BO24: =Transporte!$I$20 -> 0 | BP24: =Manutenção!$I$21 -> 3030.7692 | BQ24: =BG24 -> 0 | BR24: =SUM(BJ24:BQ24) -> 6464.4403 | BS24: =IF(L2>=1,BR24/$A$5,0) -> 0 | BT24: ='Verniz Imersão'!AA22 -> 0 | BU24: ='Resumo M.O'!$J$27 -> 1907.3422 | BV24: ='Resumo M.O'!$J$31 -> 1526.3289 | BW24: ='Resumo Custos Variáveis'!$L$21 -> 0 | BX24: ='Outros Custos'!$J$31 -> 0 | BY24: =Transporte!$J$20 -> 0 | BZ24: =Manutenção!$J$21 -> 0 | CA24: =BQ24 -> 0 | CB24: =SUM(BT24:CA24) -> 3433.6711 | CC24: =IF(L2>=1,CB24/$A$5,0) -> 0 | CD24: ='Verniz Imersão'!AD22 -> 0 | CE24: ='Resumo M.O'!$K$27 -> 1907.3422 | CF24: ='Resumo M.O'!$K$31 -> 1526.3289 | CG24: ='Resumo Custos Variáveis'!$M$21 -> 0 | CH24: ='Outros Custos'!$K$31 -> 0 | CI24: =Transporte!$K$20 -> 0 | CJ24: =Manutenção!$K$21 -> 0 | CK24: =CA24 -> 0 | CL24: =SUM(CD24:CK24) -> 3433.6711 | CM24: =IF(L2>=1,CL24/$A$5,0) -> 0 | CN24: ='Verniz Imersão'!AG22 -> 0 | CO24: ='Resumo M.O'!$L$27 -> 1907.3422 | CP24: ='Resumo M.O'!$L$31 -> 1526.3289 | CQ24: ='Resumo Custos Variáveis'!$N$21 -> 0 | CR24: ='Outros Custos'!$L$31 -> 0 | CS24: =Transporte!$L$20 -> 0 | CT24: =Manutenção!$L$21 -> 0 | CU24: =CK24 -> 0 | CV24: =SUM(CN24:CU24) -> 3433.6711 | CW24: =IF(L2>=1,CV24/$A$5,0) -> 0 | CX24: ='Verniz Imersão'!AJ22 -> 0 | CY24: ='Resumo M.O'!$M$27 -> 1907.3422 | CZ24: ='Resumo M.O'!$M$31 -> 1526.3289 | DA24: ='Resumo Custos Variáveis'!$O$21 -> 0 | DB24: ='Outros Custos'!$M$31 -> 0 | DC24: =Transporte!$M$20 -> 0 | DD24: =Manutenção!$M$21 -> 0 | DE24: =CU24 -> 0 | DF24: =SUM(CX24:DE24) -> 3433.6711 | DG24: =IF(L2>=1,DF24/$A$5,0) -> 0 | DH24: ='Verniz Imersão'!AM22 -> 0 | DI24: ='Resumo M.O'!$N$27 -> 1907.3422 | DJ24: ='Resumo M.O'!$N$31 -> 1526.3289 | DK24: ='Resumo Custos Variáveis'!$P$21 -> 0 | DL24: ='Outros Custos'!$N$31 -> 0 | DM24: =Transporte!$N$20 -> 0 | DN24: =Manutenção!$N$21 -> 0 | DO24: =DE24 -> 0 | DP24: =SUM(DH24:DO24) -> 3433.6711 | DQ24: =IF(L2>=1,DP24/$A$5,0) -> 0 | DS24: =K24 -> 0 | DT24: =U24 -> 0 | DU24: =AE24 -> 0 | DV24: =AO24 -> 0 | DW24: =AY24 -> 0 | DX24: =BI24 -> 0 | DY24: =BS24 -> 0 | DZ24: =CC24 -> 0 | EA24: =CM24 -> 0 | EB24: =CW24 -> 0 | EC24: =DG24 -> 0 | ED24: =DQ24 -> 0 | EF24: =B24/$A$5 -> 0 | EG24: =L24/$A$5 -> 0 | EH24: =V24/$A$5 -> 16.538636 | EI24: =AF24/$A$5 -> 0 | EJ24: =AP24/$A$5 -> 0 | EK24: =AZ24/$A$5 -> 0 | EL24: =BJ24/$A$5 -> 0 | EM24: =BT24/$A$5 -> 0 | EN24: =CD24/$A$5 -> 0 | EO24: =CN24/$A$5 -> 0 | EP24: =CX24/$A$5 -> 0 | EQ24: =DH24/$A$5 -> 0
A25: Desplacante De Gancheira | B25: ='Desplacante de gancheira '!G14 -> 0 | C25: ='Resumo M.O'!$C$27 -> 1907.3422 | D25: ='Resumo M.O'!$C$31 -> 1526.3289 | E25: ='Resumo Custos Variáveis'!$E$21 -> 0 | F25: ='Outros Custos'!$C$31 -> 0 | G25: =Transporte!$C$20 -> 0 | H25: =Manutenção!$C$21 -> 0 | I25: 0 | J25: =SUM(B25:I25) -> 3433.6711 | K25: =IF($L$2>=1,J25/$A$5,0) -> 0 | L25: ='Desplacante de gancheira '!J14 -> 0 | M25: ='Resumo M.O'!$D$27 -> 1907.3422 | N25: ='Resumo M.O'!$D$31 -> 1526.3289 | O25: ='Resumo Custos Variáveis'!$F$21 -> 0 | P25: ='Outros Custos'!$D$31 -> 0 | Q25: =Transporte!$D$20 -> 0 | R25: =Manutenção!$D$21 -> 0 | S25: =I25 -> 0 | T25: =SUM(L25:S25) -> 3433.6711 | U25: =IF($L$2>=1,T25/$A$5,0) -> 0 | V25: ='Desplacante de gancheira '!M14 -> 8453 | W25: ='Resumo M.O'!$E$27 -> 1907.3422 | X25: ='Resumo M.O'!$E$31 -> 1526.3289 | Y25: ='Resumo Custos Variáveis'!$G$21 -> 2404.5263 | Z25: ='Outros Custos'!$E$31 -> 0 | AA25: =Transporte!$E$20 -> 0 | AB25: =Manutenção!$E$21 -> 0 | AC25: =S25 -> 0 | AD25: =SUM(V25:AC25) -> 14291.197 | AE25: =IF($L$2>=1,AD25/$A$5,0) -> 0 | AF25: ='Desplacante de gancheira '!P14 -> 8453 | AG25: ='Resumo M.O'!$F$27 -> 1907.3422 | AH25: ='Resumo M.O'!$F$31 -> 1526.3289 | AI25: ='Resumo Custos Variáveis'!$H$21 -> 1573.8421 | AJ25: ='Outros Custos'!$F$31 -> 0 | AK25: =Transporte!$F$20 -> 0 | AL25: =Manutenção!$F$21 -> 0 | AM25: =AC25 -> 0 | AN25: =SUM(AF25:AM25) -> 13460.513 | AO25: =IF(L2>=1,AN25/$A$5,0) -> 0 | AP25: ='Desplacante de gancheira '!S14 -> 0 | AQ25: ='Resumo M.O'!$G$27 -> 1907.3422 | AR25: ='Resumo M.O'!$G$31 -> 1526.3289 | AS25: ='Resumo Custos Variáveis'!$I$21 -> 0 | AT25: ='Outros Custos'!$G$31 -> 0 | AU25: =Transporte!$G$20 -> 0 | AV25: =Manutenção!$G$21 -> 0 | AW25: =AM25 -> 0 | AX25: =SUM(AP25:AW25) -> 3433.6711 | AY25: =IF(L2>=1,AX25/$A$5,0) -> 0 | AZ25: ='Desplacante de gancheira '!V14 -> 0 | BA25: ='Resumo M.O'!$H$27 -> 1907.3422 | BB25: ='Resumo M.O'!$H$31 -> 1526.3289 | BC25: ='Resumo Custos Variáveis'!$J$21 -> 0 | BD25: ='Outros Custos'!$H$31 -> 0 | BE25: =Transporte!$H$20 -> 0 | BF25: =Manutenção!$H$21 -> 3061.5385 | BG25: =AW25 -> 0 | BH25: =SUM(AZ25:BG25) -> 6495.2095 | BI25: =IF(L2>=1,BH25/$A$5,0) -> 0 | BJ25: ='Desplacante de gancheira '!Y14 -> 0 | BK25: ='Resumo M.O'!$I$27 -> 1907.3422 | BL25: ='Resumo M.O'!$I$31 -> 1526.3289 | BM25: ='Resumo Custos Variáveis'!$K$21 -> 0 | BN25: ='Outros Custos'!$I$31 -> 0 | BO25: =Transporte!$I$20 -> 0 | BP25: =Manutenção!$I$21 -> 3030.7692 | BQ25: =BG25 -> 0 | BR25: =SUM(BJ25:BQ25) -> 6464.4403 | BS25: =IF(L2>=1,BR25/$A$5,0) -> 0 | BT25: ='Desplacante de gancheira '!AB14 -> 0 | BU25: ='Resumo M.O'!$J$27 -> 1907.3422 | BV25: ='Resumo M.O'!$J$31 -> 1526.3289 | BW25: ='Resumo Custos Variáveis'!$L$21 -> 0 | BX25: ='Outros Custos'!$J$31 -> 0 | BY25: =Transporte!$J$20 -> 0 | BZ25: =Manutenção!$J$21 -> 0 | CA25: =BQ25 -> 0 | CB25: =SUM(BT25:CA25) -> 3433.6711 | CC25: =IF(L2>=1,CB25/$A$5,0) -> 0 | CD25: ='Desplacante de gancheira '!AE14 -> 0 | CE25: ='Resumo M.O'!$K$27 -> 1907.3422 | CF25: ='Resumo M.O'!$K$31 -> 1526.3289 | CG25: ='Resumo Custos Variáveis'!$M$21 -> 0 | CH25: ='Outros Custos'!$K$31 -> 0 | CI25: =Transporte!$K$20 -> 0 | CJ25: =Manutenção!$K$21 -> 0 | CK25: =CA25 -> 0 | CL25: =SUM(CD25:CK25) -> 3433.6711 | CM25: =IF(L2>=1,CL25/$A$5,0) -> 0 | CN25: ='Desplacante de gancheira '!AH14 -> 0 | CO25: ='Resumo M.O'!$L$27 -> 1907.3422 | CP25: ='Resumo M.O'!$L$31 -> 1526.3289 | CQ25: ='Resumo Custos Variáveis'!$N$21 -> 0 | CR25: ='Outros Custos'!$L$31 -> 0 | CS25: =Transporte!$L$20 -> 0 | CT25: =Manutenção!$L$21 -> 0 | CU25: =CK25 -> 0 | CV25: =SUM(CN25:CU25) -> 3433.6711 | CW25: =IF(L2>=1,CV25/$A$5,0) -> 0 | CX25: ='Desplacante de gancheira '!AK14 -> 0 | CY25: ='Resumo M.O'!$M$27 -> 1907.3422 | CZ25: ='Resumo M.O'!$M$31 -> 1526.3289 | DA25: ='Resumo Custos Variáveis'!$O$21 -> 0 | DB25: ='Outros Custos'!$M$31 -> 0 | DC25: =Transporte!$M$20 -> 0 | DD25: =Manutenção!$M$21 -> 0 | DE25: =CU25 -> 0 | DF25: =SUM(CX25:DE25) -> 3433.6711 | DG25: =IF(L2>=1,DF25/$A$5,0) -> 0 | DH25: ='Desplacante de gancheira '!AN14 -> 0 | DI25: ='Resumo M.O'!$N$27 -> 1907.3422 | DJ25: ='Resumo M.O'!$N$31 -> 1526.3289 | DK25: ='Resumo Custos Variáveis'!$P$21 -> 0 | DL25: ='Outros Custos'!$N$31 -> 0 | DM25: =Transporte!$N$20 -> 0 | DN25: =Manutenção!$N$21 -> 0 | DO25: =DE25 -> 0 | DP25: =SUM(DH25:DO25) -> 3433.6711 | DQ25: =IF(L2>=1,DP25/$A$5,0) -> 0 | DS25: =K25 -> 0 | DT25: =U25 -> 0 | DU25: =AE25 -> 0 | DV25: =AO25 -> 0 | DW25: =AY25 -> 0 | DX25: =BI25 -> 0 | DY25: =BS25 -> 0 | DZ25: =CC25 -> 0 | EA25: =CM25 -> 0 | EB25: =CW25 -> 0 | EC25: =DG25 -> 0 | ED25: =DQ25 -> 0 | EF25: =B25/$A$5 -> 0 | EG25: =L25/$A$5 -> 0 | EH25: =V25/$A$5 -> 38.422727 | EI25: =AF25/$A$5 -> 38.422727 | EJ25: =AP25/$A$5 -> 0 | EK25: =AZ25/$A$5 -> 0 | EL25: =BJ25/$A$5 -> 0 | EM25: =BT25/$A$5 -> 0 | EN25: =CD25/$A$5 -> 0 | EO25: =CN25/$A$5 -> 0 | EP25: =CX25/$A$5 -> 0 | EQ25: =DH25/$A$5 -> 0
A26: E.T.E | B26: ='E.T.E'!G14 -> 0 | C26: ='Resumo M.O'!$C$27 -> 1907.3422 | D26: ='Resumo M.O'!$C$31 -> 1526.3289 | E26: ='Resumo Custos Variáveis'!$E$21 -> 0 | F26: ='Outros Custos'!$C$31 -> 0 | G26: =Transporte!$C$20 -> 0 | H26: =Manutenção!$C$21 -> 0 | I26: =Investimentos!O38 -> 0 | J26: =SUM(B26:I26) -> 3433.6711 | K26: =IF($L$2>=1,J26/$A$5,0) -> 0 | L26: ='E.T.E'!J14 -> 0 | M26: ='Resumo M.O'!$D$27 -> 1907.3422 | N26: ='Resumo M.O'!$D$31 -> 1526.3289 | O26: ='Resumo Custos Variáveis'!$F$21 -> 0 | P26: ='Outros Custos'!$D$31 -> 0 | Q26: =Transporte!$D$20 -> 0 | R26: =Manutenção!$D$21 -> 0 | S26: =I26 -> 0 | T26: =SUM(L26:S26) -> 3433.6711 | U26: =IF($L$2>=1,T26/$A$5,0) -> 0 | V26: ='E.T.E'!M14 -> 3 | W26: ='Resumo M.O'!$E$27 -> 1907.3422 | X26: ='Resumo M.O'!$E$31 -> 1526.3289 | Y26: ='Resumo Custos Variáveis'!$G$21 -> 2404.5263 | Z26: ='Outros Custos'!$E$31 -> 0 | AA26: =Transporte!$E$20 -> 0 | AB26: =Manutenção!$E$21 -> 0 | AC26: =S26 -> 0 | AD26: =SUM(V26:AC26) -> 5841.1974 | AE26: =IF($L$2>=1,AD26/$A$5,0) -> 0 | AF26: ='E.T.E'!P14 -> 0 | AG26: ='Resumo M.O'!$F$27 -> 1907.3422 | AH26: ='Resumo M.O'!$F$31 -> 1526.3289 | AI26: ='Resumo Custos Variáveis'!$H$21 -> 1573.8421 | AJ26: ='Outros Custos'!$F$31 -> 0 | AK26: =Transporte!$F$20 -> 0 | AL26: =Manutenção!$F$21 -> 0 | AM26: =AC26 -> 0 | AN26: =SUM(AF26:AM26) -> 5007.5132 | AO26: =IF(L2>=1,AN26/$A$5,0) -> 0 | AP26: ='E.T.E'!S14 -> 0 | AQ26: ='Resumo M.O'!$G$27 -> 1907.3422 | AR26: ='Resumo M.O'!$G$31 -> 1526.3289 | AS26: ='Resumo Custos Variáveis'!$I$21 -> 0 | AT26: ='Outros Custos'!$G$31 -> 0 | AU26: =Transporte!$G$20 -> 0 | AV26: =Manutenção!$G$21 -> 0 | AW26: =AM26 -> 0 | AX26: =SUM(AP26:AW26) -> 3433.6711 | AY26: =IF(L2>=1,AX26/$A$5,0) -> 0 | AZ26: ='E.T.E'!V14 -> 0 | BA26: ='Resumo M.O'!$H$27 -> 1907.3422 | BB26: ='Resumo M.O'!$H$31 -> 1526.3289 | BC26: ='Resumo Custos Variáveis'!$J$21 -> 0 | BD26: ='Outros Custos'!$H$31 -> 0 | BE26: =Transporte!$H$20 -> 0 | BF26: =Manutenção!$H$21 -> 3061.5385 | BG26: =AW26 -> 0 | BH26: =SUM(AZ26:BG26) -> 6495.2095 | BI26: =IF(L2>=1,BH26/$A$5,0) -> 0 | BJ26: ='E.T.E'!Y14 -> 0 | BK26: ='Resumo M.O'!$I$27 -> 1907.3422 | BL26: ='Resumo M.O'!$I$31 -> 1526.3289 | BM26: ='Resumo Custos Variáveis'!$K$21 -> 0 | BN26: ='Outros Custos'!$I$31 -> 0 | BO26: =Transporte!$I$20 -> 0 | BP26: =Manutenção!$I$21 -> 3030.7692 | BQ26: =BG26 -> 0 | BR26: =SUM(BJ26:BQ26) -> 6464.4403 | BS26: =IF(L2>=1,BR26/$A$5,0) -> 0 | BT26: ='E.T.E'!AB14 -> 0 | BU26: ='Resumo M.O'!$J$27 -> 1907.3422 | BV26: ='Resumo M.O'!$J$31 -> 1526.3289 | BW26: ='Resumo Custos Variáveis'!$L$21 -> 0 | BX26: ='Outros Custos'!$J$31 -> 0 | BY26: =Transporte!$J$20 -> 0 | BZ26: =Manutenção!$J$21 -> 0 | CA26: =BQ26 -> 0 | CB26: =SUM(BT26:CA26) -> 3433.6711 | CC26: =IF(L2>=1,CB26/$A$5,0) -> 0 | CD26: ='E.T.E'!AE14 -> 0 | CE26: ='Resumo M.O'!$K$27 -> 1907.3422 | CF26: ='Resumo M.O'!$K$31 -> 1526.3289 | CG26: ='Resumo Custos Variáveis'!$M$21 -> 0 | CH26: ='Outros Custos'!$K$31 -> 0 | CI26: =Transporte!$K$20 -> 0 | CJ26: =Manutenção!$K$21 -> 0 | CK26: =CA26 -> 0 | CL26: =SUM(CD26:CK26) -> 3433.6711 | CM26: =IF(L2>=1,CL26/$A$5,0) -> 0 | CN26: ='E.T.E'!AH14 -> 0 | CO26: ='Resumo M.O'!$L$27 -> 1907.3422 | CP26: ='Resumo M.O'!$L$31 -> 1526.3289 | CQ26: ='Resumo Custos Variáveis'!$N$21 -> 0 | CR26: ='Outros Custos'!$L$31 -> 0 | CS26: =Transporte!$L$20 -> 0 | CT26: =Manutenção!$L$21 -> 0 | CU26: =CK26 -> 0 | CV26: =SUM(CN26:CU26) -> 3433.6711 | CW26: =IF(L2>=1,CV26/$A$5,0) -> 0 | CX26: ='E.T.E'!AK14 -> 0 | CY26: ='Resumo M.O'!$M$27 -> 1907.3422 | CZ26: ='Resumo M.O'!$M$31 -> 1526.3289 | DA26: ='Resumo Custos Variáveis'!$O$21 -> 0 | DB26: ='Outros Custos'!$M$31 -> 0 | DC26: =Transporte!$M$20 -> 0 | DD26: =Manutenção!$M$21 -> 0 | DE26: =CU26 -> 0 | DF26: =SUM(CX26:DE26) -> 3433.6711 | DG26: =IF(L2>=1,DF26/$A$5,0) -> 0 | DH26: ='E.T.E'!AN14 -> 0 | DI26: ='Resumo M.O'!$N$27 -> 1907.3422 | DJ26: ='Resumo M.O'!$N$31 -> 1526.3289 | DK26: ='Resumo Custos Variáveis'!$P$21 -> 0 | DL26: ='Outros Custos'!$N$31 -> 0 | DM26: =Transporte!$N$20 -> 0 | DN26: =Manutenção!$N$21 -> 0 | DO26: =DE26 -> 0 | DP26: =SUM(DH26:DO26) -> 3433.6711 | DQ26: =IF(L2>=1,DP26/$A$5,0) -> 0 | DS26: =K26 -> 0 | DT26: =U26 -> 0 | DU26: =AE26 -> 0 | DV26: =AO26 -> 0 | DW26: =AY26 -> 0 | DX26: =BI26 -> 0 | DY26: =BS26 -> 0 | DZ26: =CC26 -> 0 | EA26: =CM26 -> 0 | EB26: =CW26 -> 0 | EC26: =DG26 -> 0 | ED26: =DQ26 -> 0 | EF26: =B26/$A$5 -> 0 | EG26: =L26/$A$5 -> 0 | EH26: =V26/$A$5 -> 0.013636364 | EI26: =AF26/$A$5 -> 0 | EJ26: =AP26/$A$5 -> 0 | EK26: =AZ26/$A$5 -> 0 | EL26: =BJ26/$A$5 -> 0 | EM26: =BT26/$A$5 -> 0 | EN26: =CD26/$A$5 -> 0 | EO26: =CN26/$A$5 -> 0 | EP26: =CX26/$A$5 -> 0 | EQ26: =DH26/$A$5 -> 0

Sheet Custo Galvanoplastia (2)
A2: Menu | C2: Custo Por Peça Galvanoplastia
E6: Mar
B8: Cromo | C8: Custo / Peça | D8: Custo/ Peça P.Q | F8: Cromo | G8: Custo/ Total | I8: Prod. Químico
B9: Pré Tratamento | C9: =G9/'Peças por Hora Galvanoplast (2'!B11 -> #DIV/0! | D9: =I9/'Peças por Hora Galvanoplast (2'!B11 -> #DIV/0! | F9: Pré Tratamento | G9: =IF(H9=1,HLOOKUP(E6,'Resumo de Custo'!DS7:ED27,2,0),0) -> 0 | H9: 1 | I9: =IF(H9=1,HLOOKUP(E6,'Resumo de Custo'!EF7:EQ28,2,0),0) -> 18.271591
B10: Cobre Alcalino | C10: =G10/'Peças por Hora Galvanoplast (2'!B19 -> #DIV/0! | D10: =I10/'Peças por Hora Galvanoplast (2'!B19 -> #DIV/0! | F10: Cobre Alcalino | G10: =IF(H10=1,HLOOKUP(E6,'Resumo de Custo'!DS7:ED29,3,0),0) -> 0 | H10: 1 | I10: =IF(H10=1,HLOOKUP(E6,'Resumo de Custo'!EF7:EQ28,3,0),0) -> 63.497591
B11: Cobre Ácido | C11: =G11/'Peças por Hora Galvanoplast (2'!B27 -> #DIV/0! | D11: =I11/'Peças por Hora Galvanoplast (2'!B27 -> #DIV/0! | F11: Cobre Ácido | G11: =IF(H11=1,HLOOKUP(E6,'Resumo de Custo'!DS7:ED26,5,0),0) -> 0 | H11: 1 | I11: =IF(H11=1,HLOOKUP(E6,'Resumo de Custo'!EF7:EQ26,5,0),0) -> 116.948
B12: Desengraxante Químico | C12: =G12/'Peças por Hora Galvanoplast (2'!B35 -> #DIV/0! | D12: =I12/'Peças por Hora Galvanoplast (2'!B35 -> #DIV/0! | F12: Desengraxante Químico | G12: =IF(H12=1,HLOOKUP(E6,'Resumo de Custo'!DS7:ED28,6,0),0) -> 0 | H12: 1 | I12: =IF(H12=1,HLOOKUP(E6,'Resumo de Custo'!EF7:EQ28,6,0),0) -> 0.26386364
B13: Níquel Brilhante | C13: =G13/'Peças por Hora Galvanoplast (2'!B43 -> #DIV/0! | D13: =I13/'Peças por Hora Galvanoplast (2'!B43 -> #DIV/0! | F13: Níquel Brilhante | G13: =IF(H13=1,HLOOKUP(E6,'Resumo de Custo'!DS7:ED28,7,0),0) -> 0 | H13: 1 | I13: =IF(H13=1,HLOOKUP(E6,'Resumo de Custo'!EF7:EQ26,7,0),0) -> 172.03495
B14: Cromo | C14: =G14/'Peças por Hora Galvanoplast (2'!B51 -> #DIV/0! | D14: =I14/'Peças por Hora Galvanoplast (2'!B51 -> #DIV/0! | F14: Cromo | G14: =IF(H14=1,HLOOKUP(E6,'Resumo de Custo'!DS7:ED28,9,0),0) -> 0 | H14: 1 | I14: =IF(H14=1,HLOOKUP(E6,'Resumo de Custo'!EF7:EQ29,9,0),0) -> 135.35686
B15: E.T.E | C15: =G15/'Peças por Hora Galvanoplast (2'!B51 -> #DIV/0! | D15: =I15/'Peças por Hora Galvanoplast (2'!B51 -> #DIV/0! | F15: E.T.E | G15: =IF(H15=1,HLOOKUP(E6,'Resumo de Custo'!DS7:ED28,20,0),0) -> 0 | H15: 0 | I15: =IF(H15=1,HLOOKUP(E6,'Resumo de Custo'!EF7:EQ28,20,0),0) -> 0
F18: Total | G18: =SUM(G9:G17) -> 0 | I18: =SUM(I9:I17) -> 506.37286
B20: Total | C20: =SUM(C9:C19) -> #DIV/0! | D20: =SUM(D9:D19) -> #DIV/0!
B23: Cromo ll | C23: Custo / Peça | D23: Custo/ Peça P.Q | F23: Cromo ll | G23: Custo/ Total | I23: Prod. Químico
B24: Pré Tratamento | C24: =G24/'Peças por Hora Galvanoplast (2'!B11 -> #DIV/0! | D24: =I24/'Peças por Hora Galvanoplast (2'!B11 -> #DIV/0! | F24: Pré Tratamento | G24: =IF(H24=1,HLOOKUP(E6,'Resumo de Custo'!DS7:ED29,2,0),0) -> 0 | H24: 1 | I24: =IF(H24=1,HLOOKUP(E6,'Resumo de Custo'!EF7:EQ29,2,0),0) -> 18.271591
B25: Níquel Strik | C25: =G25/'Peças por Hora Galvanoplast (2'!B59 -> #DIV/0! | D25: =I25/'Peças por Hora Galvanoplast (2'!B59 -> #DIV/0! | F25: Níquel Strik | G25: =IF(H25=1,HLOOKUP(E6,'Resumo de Custo'!DS7:ED26,4,0),0) -> 0 | H25: 1 | I25: =IF(H25=1,HLOOKUP(E6,'Resumo de Custo'!EF7:EQ29,4,0),0) -> 34.84775
B26: Cobre Ácido | C26: =G26/'Peças por Hora Galvanoplast (2'!B27 -> #DIV/0! | D26: =I26/'Peças por Hora Galvanoplast (2'!B27 -> #DIV/0! | F26: Cobre Ácido | G26: =IF(H26=1,HLOOKUP(E6,'Resumo de Custo'!DS7:ED29,5,0),0) -> 0 | H26: 1 | I26: =IF(H26=1,HLOOKUP(E6,'Resumo de Custo'!EF7:EQ29,5,0),0) -> 116.948
B27: Desengraxante Químico | C27: =G27/'Peças por Hora Galvanoplast (2'!B35 -> #DIV/0! | D27: =I27/'Peças por Hora Galvanoplast (2'!B35 -> #DIV/0! | F27: Desengraxante Químico | G27: =IF(H27=1,HLOOKUP(E6,'Resumo de Custo'!DS7:ED29,6,0),0) -> 0 | H27: 1 | I27: =IF(H27=1,HLOOKUP(E6,'Resumo de Custo'!EF7:EQ29,6,0),0) -> 0.26386364
B28: Níquel Brilhante | C28: =G28/'Peças por Hora Galvanoplast (2'!B43 -> #DIV/0! | D28: =I28/'Peças por Hora Galvanoplast (2'!B43 -> #DIV/0! | F28: Níquel Brilhante | G28: =IF(H28=1,HLOOKUP(E6,'Resumo de Custo'!DS7:ED29,7,0),0) -> 0 | H28: 1 | I28: =IF(H28=1,HLOOKUP(E6,'Resumo de Custo'!EF7:EQ29,7,0),0) -> 172.03495
B29: Cromo | C29: =G29/'Peças por Hora Galvanoplast (2'!B51 -> #DIV/0! | D29: =I29/'Peças por Hora Galvanoplast (2'!B51 -> #DIV/0! | F29: Cromo | G29: =IF(H29=1,HLOOKUP(E6,'Resumo de Custo'!DS7:ED29,9,0),0) -> 0 | H29: 1 | I29: =IF(H29=1,HLOOKUP(E6,'Resumo de Custo'!EF7:EQ29,9,0),0) -> 135.35686
B30: E.T.E | C30: =G30/'Peças por Hora Galvanoplast (2'!B51 -> #DIV/0! | D30: =I30/'Peças por Hora Galvanoplast (2'!B51 -> #DIV/0! | F30: E.T.E | G30: =IF(H30=1,HLOOKUP(E6,'Resumo de Custo'!DS7:ED29,20,0),0) -> 0 | H30: 0 | I30: =IF(H30=1,HLOOKUP(E6,'Resumo de Custo'!EF7:EQ29,20,0),0) -> 0
F33: Total | G33: =SUM(G24:G32) -> 0 | I33: =SUM(I24:I32) -> 477.72302
B35: Total | C35: =SUM(C25:C34) -> #DIV/0! | D35: =SUM(D25:D34) -> #DIV/0!
B37: Níquel Strik | C37: Custo / Peça | D37: Custo/ Peça P.Q | F37: Níquel Strik | G37: Custo/ Total | I37: Prod. Químico
B38: Pré Tratamento | C38: =G38/'Peças por Hora Galvanoplast (2'!B11 -> #DIV/0! | D38: =I38/'Peças por Hora Galvanoplast (2'!B11 -> #DIV/0! | F38: Pré Tratamento | G38: =IF(H38=1,HLOOKUP(E6,'Resumo de Custo'!DS7:ED29,2,0),0) -> 0 | H38: 1 | I38: =IF(H38=1,HLOOKUP(E6,'Resumo de Custo'!EF7:EQ29,2,0),0) -> 18.271591
B39: Níquel Strik | C39: =G39/'Peças por Hora Galvanoplast (2'!B59 -> #DIV/0! | D39: =I39/'Peças por Hora Galvanoplast (2'!B59 -> #DIV/0! | F39: Níquel Strik | G39: =IF(H39=1,HLOOKUP(E6,'Resumo de Custo'!DS7:ED29,4,0),0) -> 0 | H39: 1 | I39: =IF(H39=1,HLOOKUP(E6,'Resumo de Custo'!EF7:EQ29,4,0),0) -> 34.84775
B40: Cobre Ácido | C40: =G40/'Peças por Hora Galvanoplast (2'!B27 -> #DIV/0! | D40: =I40/'Peças por Hora Galvanoplast (2'!B27 -> #DIV/0! | F40: Cobre Ácido | G40: =IF(H40=1,HLOOKUP(E6,'Resumo de Custo'!DS7:ED29,5,0),0) -> 0 | H40: 1 | I40: =IF(H40=1,HLOOKUP(E6,'Resumo de Custo'!EF7:EQ29,5,0),0) -> 116.948
B41: Desengraxante Químico | C41: =G41/'Peças por Hora Galvanoplast (2'!B35 -> #DIV/0! | D41: =I41/'Peças por Hora Galvanoplast (2'!B35 -> #DIV/0! | F41: Desengraxante Químico | G41: =IF(H41=1,HLOOKUP(E6,'Resumo de Custo'!DS7:ED29,6,0),0) -> 0 | H41: 1 | I41: =IF(H41=1,HLOOKUP(E6,'Resumo de Custo'!EF7:EQ29,6,0),0) -> 0.26386364
B42: Níquel Strik-2 | C42: =G42/'Peças por Hora Galvanoplast (2'!B67 -> #DIV/0! | D42: =I42/'Peças por Hora Galvanoplast (2'!B67 -> #DIV/0! | F42: Níquel Strik-2 | G42: =IF(H42=1,HLOOKUP(E6,'Resumo de Custo'!DS7:ED29,8,0),0) -> 0 | H42: 1 | I42: =IF(H42=1,HLOOKUP(E6,'Resumo de Custo'!EF7:EQ29,8,0),0) -> 14.251136
B43: E.T.E | C43: =G43/'Peças por Hora Galvanoplast (2'!B51 -> #DIV/0! | D43: =I43/'Peças por Hora Galvanoplast (2'!B51 -> #DIV/0! | F43: E.T.E | G43: =IF(H43=1,HLOOKUP(E6,'Resumo de Custo'!DS7:ED29,20,0),0) -> 0 | H43: 0 | I43: =IF(H43=1,HLOOKUP(E6,'Resumo de Custo'!EF7:EQ29,20,0),0) -> 0
F46: Total | G46: =SUM(G38:G45) -> 0 | I46: =SUM(I38:I45) -> 184.58234
B47: Total | C47: =SUM(C38:C46) -> #DIV/0! | D47: =SUM(D38:D46) -> #DIV/0!
A96: Jan
A97: Fev
A98: Mar
A99: Abr
A100: Mai
A101: Jun
A102: Jul
A103: Ago
A104: Set
A105: Out
A106: Nov
A107: Dez

Sheet Peças por Hora Galvanoplast (2
A2: Menu | C2: Peças por Hora Galvanoplastia
B5: Pré Tratamento
B6: Área de 1 peça (dm²) | C6: Peso de 1 peça (Kg) | D6: Kg / Carga | E6: Peças/carga | F6: Area da Carga / Dm²
B7: 0 | C7: 0.7 | D7: 0 | E7: =D7/C7 -> 0 | F7: =(E7*B7)*F25 -> 0
B8: Rendimento de corrente (%) | C8: Espessura (mm) | E8: Amperagem | F8: Número de Gancheira
B9: 90 | C9: 4 | E9: 71 | F9: 2
B10: Peças por hora | C10: Kg por hora | E10: Densidade de Corrente | F10: Tempo de banho
B11: =(60/F11)*E7*F9 -> 0 | C11: =(60/F11)*D7*F9 -> 0 | E11: =E9/F7 -> #DIV/0! | F11: 10
B13: Cobre Alcalino
B14: Área de 1 peça (dm²) | C14: Peso de 1 peça (Kg) | D14: Kg/ Carga | E14: Peças por carga | F14: Area da Carga / Dm² | H14: pe
B15: 0 | C15: 0.7 | D15: 0 | E15: =D15/C15 -> 0 | F15: =(B15*E15)*F17 -> 0 | H15: 8.9
B16: Rendimento de corrente (%) | C16: Espessura (mm) | E16: Amperagem | F16: Número de Gancheira | H16: E Q
B17: 90 | C17: 4 | E17: 71 | F17: 2 | H17: 1.095
B18: Peças por hora | C18: Kg por hora | E18: Densidade de Corrente | F18: Tempo de banho
B19: =(60/F19)*E15*F17 -> 0 | C19: =(60/F19)*D15*F17 -> 0 | E19: =E17/F15 -> #DIV/0! | F19: 60
B21: Cobre Ácido
B22: Área de 1 peça (dm²) | C22: Peso de 1 peça (Kg) | D22: Kg/ Carga | E22: Peças por carga | F22: Area da Carga / Dm² | H22: pe
B23: 0 | C23: 0.7 | D23: 0 | E23: =D23/C23 -> 0 | F23: =(E23*B23)*F25 -> 0 | H23: 8.92
B24: Rendimento de corrente (%) | C24: Espessura (mm) | E24: Amperagem | F24: Número de Gancheira | H24: E Q
B25: 90 | C25: 4 | E25: 66 | F25: 2 | H25: 1.186
B26: Peças por hora | C26: Kg por hora | E26: Densidade de Corrente | F26: Tempo de banho
B27: =(60/F27)*E23*F25 -> 0 | C27: =(60/F27)*D23*F25 -> 0 | E27: =E25/F23 -> #DIV/0! | F27: 60
B29: Desengraxante Químico
B30: Área de 1 peça (dm²) | C30: Peso de 1 peça (Kg) | D30: Kg / Carga | E30: Peças/carga | F30: Area da Carga / Dm²
B31: 0 | C31: 0.7 | D31: 0 | E31: =D31/C31 -> 0 | F31: =B31*E31*F41 -> 0
B32: Rendimento de corrente (%) | C32: Espessura (mm) | E32: Amperagem | F32: Número de Gancheira
B33: 90 | C33: 4 | E33: 66 | F33: 2
B34: Peças por hora | C34: Kg por hora | E34: Densidade de Corrente | F34: Tempo de banho
B35: =(60/F35)*E31*F33 -> 0 | C35: =(60/F35)*D31*F33 -> 0 | E35: =E33/F31 -> #DIV/0! | F35: 10
B37: Níquel Brilhante
B38: Área de 1 peça (dm²) | C38: Peso de 1 peça (Kg) | D38: Kg / Carga | E38: Peças por carga | F38: Area da Carga / Dm² | H38: pe
B39: 0 | C39: 0.7 | D39: 0 | E39: =D39/C39 -> 0 | F39: =(E39*B39)*F41 -> 0 | H39: 8.9
B40: Rendimento de corrente (%) | C40: Espessura (mm) | E40: Amperagem | F40: Número de Gancheira | H40: E Q
B41: 90 | C41: 4 | E41: 71 | F41: 2 | H41: 1.095
B42: Peças por hora | C42: Kg por hora | E42: Densidade de Corrente | F42: Tempo de banho
B43: =(60/F43)*E39*F41 -> #DIV/0! | C43: =(60/F43)*D31*F41 -> #DIV/0! | E43: =E41/F39 -> #DIV/0! | F43: =(60*C41*H39)/(H41*E43*B41) -> #DIV/0!
B45: Cromo
B46: Área de 1 peça (dm²) | C46: Peso de 1 peça (Kg) | D46: Kg / Carga | E46: Peças por carga | F46: Area da Carga / Dm² | H46: pe
B47: 0 | C47: 0.7 | D47: 0 | E47: =D47/C47 -> 0 | F47: =(E47*B47)*F49 -> 0 | H47: 7.1
B48: Rendimento de corrente (%) | C48: Espessura (mm) | E48: Amperagem | F48: Número de Gancheira | H48: E Q
B49: 90 | C49: 4 | E49: 192 | F49: 2 | H49: 0.323
B50: Peças por hora | C50: Kg por hora | E50: Densidade de Corrente | F50: Tempo de banho
B51: =(60/F51)*E47*F49 -> 0 | C51: =(60/F51)*D47*F49 -> 0 | E51: =E49/F47 -> #DIV/0! | F51: 60
B53: Níquel Strik
B54: Área de 1 peça (dm²) | C54: Peso de 1 peça (Kg) | D54: Kg / Carga | E54: Peças por carga | F54: Area da Carga / Dm² | H54: pe
B55: 0 | C55: 0.7 | D55: 0 | E55: =D55/C55 -> 0 | F55: =E55*B55*F57 -> 0 | H55: 8.9
B56: Rendimento de corrente (%) | C56: Espessura (mm) | E56: Amperagem | F56: Número de Gancheira | H56: E Q
B57: 89 | C57: 2 | E57: 43 | F57: 2 | H57: 1.095
B58: Peças por hora | C58: Kg por hora | E58: Densidade de Corrente | F58: Tempo de banho
B59: =(60/F59)*E55*F57 -> 0 | C59: =(60/F59)*D55*F57 -> 0 | E59: =E57/F55 -> #DIV/0! | F59: 50
B61: Níquel Strik ll
B62: Área de 1 peça (dm²) | C62: Peso de 1 peça (Kg) | D62: Kg / Carga | E62: Peças por carga | F62: Area da Carga / Dm² | H62: pe
B63: 0 | C63: 0.7 | D63: 0 | E63: =D63/C63 -> 0 | F63: =E63*B63*F65 -> 0 | H63: 8.9
B64: Rendimento de corrente (%) | C64: Espessura (mm) | E64: Amperagem | F64: Número de Gancheira | H64: E Q
B65: 89 | C65: 2 | E65: 43 | F65: 2 | H65: 1.095
B66: Peças por hora | C66: Kg por hora | E66: Densidade de Corrente | F66: Tempo de banho
B67: =(60/F67)*E63*F65 -> #DIV/0! | C67: =(60/F67)*D63*F65 -> #DIV/0! | E67: =E65/F63 -> #DIV/0! | F67: =(60*C65*H63)/(H65*E67*B65) -> #DIV/0!

Sheet Custo Galvanoplastia
A2: Menu | C2: Custo Por Peça Galvanoplastia
E6: Mar
B8: Cromo | C8: Custo / Peça | D8: Custo/ Peça P.Q | F8: Cromo | G8: Custo/ Total | I8: Prod. Químico
B9: Pré Tratamento | C9: =G9/'Peças por Hora Galvanoplastia'!B11 -> 0 | D9: =I9/'Peças por Hora Galvanoplastia'!B11 -> 0.035528093 | F9: Pré Tratamento | G9: =IF(H9=1,HLOOKUP(E6,'Resumo de Custo'!DS7:ED27,2,0),0) -> 0 | H9: 1 | I9: =IF(H9=1,HLOOKUP(E6,'Resumo de Custo'!EF7:EQ28,2,0),0) -> 18.271591
B10: Cobre Alcalino | C10: =G10/'Peças por Hora Galvanoplastia'!B19 -> 0 | D10: =I10/'Peças por Hora Galvanoplastia'!B19 -> 0.74305354 | F10: Cobre Alcalino | G10: =IF(H10=1,HLOOKUP(E6,'Resumo de Custo'!DS7:ED29,3,0),0) -> 0 | H10: 1 | I10: =IF(H10=1,HLOOKUP(E6,'Resumo de Custo'!EF7:EQ28,3,0),0) -> 63.497591
B11: Cobre Ácido | C11: =G11/'Peças por Hora Galvanoplastia'!B27 -> 0 | D11: =I11/'Peças por Hora Galvanoplastia'!B27 -> 1.362305 | F11: Cobre Ácido | G11: =IF(H11=1,HLOOKUP(E6,'Resumo de Custo'!DS7:ED26,5,0),0) -> 0 | H11: 1 | I11: =IF(H11=1,HLOOKUP(E6,'Resumo de Custo'!EF7:EQ26,5,0),0) -> 116.948
B12: Desengraxante Químico | C12: =G12/'Peças por Hora Galvanoplastia'!B35 -> 0 | D12: =I12/'Peças por Hora Galvanoplastia'!B35 -> 0.00051306818 | F12: Desengraxante Químico | G12: =IF(H12=1,HLOOKUP(E6,'Resumo de Custo'!DS7:ED28,6,0),0) -> 0 | H12: 1 | I12: =IF(H12=1,HLOOKUP(E6,'Resumo de Custo'!EF7:EQ28,6,0),0) -> 0.26386364
B13: Níquel Brilhante | C13: =G13/'Peças por Hora Galvanoplastia'!B42 -> 0 | D13: =I13/'Peças por Hora Galvanoplastia'!B42 -> 2.0131658 | F13: Níquel Brilhante | G13: =IF(H13=1,HLOOKUP(E6,'Resumo de Custo'!DS7:ED28,7,0),0) -> 0 | H13: 1 | I13: =IF(H13=1,HLOOKUP(E6,'Resumo de Custo'!EF7:EQ26,7,0),0) -> 172.03495
B14: Cromo | C14: =G14/'Peças por Hora Galvanoplastia'!B50 -> 0 | D14: =I14/'Peças por Hora Galvanoplastia'!B50 -> 1.5840913 | F14: Cromo | G14: =IF(H14=1,HLOOKUP(E6,'Resumo de Custo'!DS7:ED28,9,0),0) -> 0 | H14: 1 | I14: =IF(H14=1,HLOOKUP(E6,'Resumo de Custo'!EF7:EQ29,9,0),0) -> 135.35686
B15: E.T.E | C15: =G15/'Peças por Hora Galvanoplastia'!B50 -> 0 | D15: =I15/'Peças por Hora Galvanoplastia'!B50 -> 0.00015958736 | F15: E.T.E | G15: =IF(H15=1,HLOOKUP(E6,'Resumo de Custo'!DS7:ED28,20,0),0) -> 0 | H15: 1 | I15: =IF(H15=1,HLOOKUP(E6,'Resumo de Custo'!EF7:EQ28,20,0),0) -> 0.013636364
F18: Total | G18: =SUM(G9:G17) -> 0 | I18: =SUM(I9:I17) -> 506.3865
B20: Total | C20: =SUM(C9:C19) -> 0 | D20: =SUM(D9:D19) -> 5.7388164
B23: Cromo ll | C23: Custo / Peça | D23: Custo/ Peça P.Q | F23: Cromo ll | G23: Custo/ Total | I23: Prod. Químico
B24: Pré Tratamento | C24: =G24/'Peças por Hora Galvanoplastia'!B11 -> 0 | D24: =I24/'Peças por Hora Galvanoplastia'!B11 -> 0.035528093 | F24: Pré Tratamento | G24: =IF(H24=1,HLOOKUP(E6,'Resumo de Custo'!DS7:ED29,2,0),0) -> 0 | H24: 1 | I24: =IF(H24=1,HLOOKUP(E6,'Resumo de Custo'!EF7:EQ29,2,0),0) -> 18.271591
B25: Níquel Strik | C25: =G25/'Peças por Hora Galvanoplastia'!B58 -> 0 | D25: =I25/'Peças por Hora Galvanoplastia'!B58 -> 0.34044738 | F25: Níquel Strik | G25: =IF(H25=1,HLOOKUP(E6,'Resumo de Custo'!DS7:ED26,4,0),0) -> 0 | H25: 1 | I25: =IF(H25=1,HLOOKUP(E6,'Resumo de Custo'!EF7:EQ29,4,0),0) -> 34.84775
B26: Cobre Ácido | C26: =G26/'Peças por Hora Galvanoplastia'!B27 -> 0 | D26: =I26/'Peças por Hora Galvanoplastia'!B27 -> 1.362305 | F26: Cobre Ácido | G26: =IF(H26=1,HLOOKUP(E6,'Resumo de Custo'!DS7:ED29,5,0),0) -> 0 | H26: 1 | I26: =IF(H26=1,HLOOKUP(E6,'Resumo de Custo'!EF7:EQ29,5,0),0) -> 116.948
B27: Desengraxante Químico | C27: =G27/'Peças por Hora Galvanoplastia'!B35 -> 0 | D27: =I27/'Peças por Hora Galvanoplastia'!B35 -> 0.00051306818 | F27: Desengraxante Químico | G27: =IF(H27=1,HLOOKUP(E6,'Resumo de Custo'!DS7:ED29,6,0),0) -> 0 | H27: 1 | I27: =IF(H27=1,HLOOKUP(E6,'Resumo de Custo'!EF7:EQ29,6,0),0) -> 0.26386364
B28: Níquel Brilhante | C28: =G28/'Peças por Hora Galvanoplastia'!B42 -> 0 | D28: =I28/'Peças por Hora Galvanoplastia'!B42 -> 2.0131658 | F28: Níquel Brilhante | G28: =IF(H28=1,HLOOKUP(E6,'Resumo de Custo'!DS7:ED29,7,0),0) -> 0 | H28: 1 | I28: =IF(H28=1,HLOOKUP(E6,'Resumo de Custo'!EF7:EQ29,7,0),0) -> 172.03495
B29: Cromo | C29: =G29/'Peças por Hora Galvanoplastia'!B50 -> 0 | D29: =I29/'Peças por Hora Galvanoplastia'!B50 -> 1.5840913 | F29: Cromo | G29: =IF(H29=1,HLOOKUP(E6,'Resumo de Custo'!DS7:ED29,9,0),0) -> 0 | H29: 1 | I29: =IF(H29=1,HLOOKUP(E6,'Resumo de Custo'!EF7:EQ29,9,0),0) -> 135.35686
B30: E.T.E | C30: =G30/'Peças por Hora Galvanoplastia'!B50 -> 0 | D30: =I30/'Peças por Hora Galvanoplastia'!B50 -> 0.00015958736 | F30: E.T.E | G30: =IF(H30=1,HLOOKUP(E6,'Resumo de Custo'!DS7:ED29,20,0),0) -> 0 | H30: 1 | I30: =IF(H30=1,HLOOKUP(E6,'Resumo de Custo'!EF7:EQ29,20,0),0) -> 0.013636364
F33: Total | G33: =SUM(G24:G32) -> 0 | I33: =SUM(I24:I32) -> 477.73666
B35: Total | C35: =SUM(C24:C34) -> 0 | D35: =SUM(D25:D34) -> 5.3006821
B37: Níquel Strik | C37: Custo / Peça | D37: Custo/ Peça P.Q | F37: Níquel Strik | G37: Custo/ Total | I37: Prod. Químico
B38: Pré Tratamento | C38: =G38/'Peças por Hora Galvanoplastia'!B11 -> 0 | D38: =I38/'Peças por Hora Galvanoplastia'!B11 -> 0.035528093 | F38: Pré Tratamento | G38: =IF(H38=1,HLOOKUP(E6,'Resumo de Custo'!DS7:ED29,2,0),0) -> 0 | H38: 1 | I38: =IF(H38=1,HLOOKUP(E6,'Resumo de Custo'!EF7:EQ29,2,0),0) -> 18.271591
B39: Níquel Strik | C39: =G39/'Peças por Hora Galvanoplastia'!B58 -> 0 | D39: =I39/'Peças por Hora Galvanoplastia'!B58 -> 0.34044738 | F39: Níquel Strik | G39: =IF(H39=1,HLOOKUP(E6,'Resumo de Custo'!DS7:ED29,4,0),0) -> 0 | H39: 1 | I39: =IF(H39=1,HLOOKUP(E6,'Resumo de Custo'!EF7:EQ29,4,0),0) -> 34.84775
B40: Cobre Ácido | C40: =G40/'Peças por Hora Galvanoplastia'!B27 -> 0 | D40: =I40/'Peças por Hora Galvanoplastia'!B27 -> 1.362305 | F40: Cobre Ácido | G40: =IF(H40=1,HLOOKUP(E6,'Resumo de Custo'!DS7:ED29,5,0),0) -> 0 | H40: 1 | I40: =IF(H40=1,HLOOKUP(E6,'Resumo de Custo'!EF7:EQ29,5,0),0) -> 116.948
B41: Desengraxante Químico | C41: =G41/'Peças por Hora Galvanoplastia'!B35 -> 0 | D41: =I41/'Peças por Hora Galvanoplastia'!B35 -> 0.00051306818 | F41: Desengraxante Químico | G41: =IF(H41=1,HLOOKUP(E6,'Resumo de Custo'!DS7:ED29,6,0),0) -> 0 | H41: 1 | I41: =IF(H41=1,HLOOKUP(E6,'Resumo de Custo'!EF7:EQ29,6,0),0) -> 0.26386364
B42: Níquel Strik-2 | C42: =G42/'Peças por Hora Galvanoplastia'!B66 -> 0 | D42: =I42/'Peças por Hora Galvanoplastia'!B66 -> 0.13922741 | F42: Níquel Strik-2 | G42: =IF(H42=1,HLOOKUP(E6,'Resumo de Custo'!DS7:ED29,8,0),0) -> 0 | H42: 1 | I42: =IF(H42=1,HLOOKUP(E6,'Resumo de Custo'!EF7:EQ29,8,0),0) -> 14.251136
B43: E.T.E | C43: =G43/'Peças por Hora Galvanoplastia'!B50 -> 0 | D43: =I43/'Peças por Hora Galvanoplastia'!B50 -> 0.00015958736 | F43: E.T.E | G43: =IF(H43=1,HLOOKUP(E6,'Resumo de Custo'!DS7:ED29,20,0),0) -> 0 | H43: 1 | I43: =IF(H43=1,HLOOKUP(E6,'Resumo de Custo'!EF7:EQ29,20,0),0) -> 0.013636364
F46: Total | G46: =SUM(G38:G45) -> 0 | I46: =SUM(I38:I45) -> 184.59598
B47: Total | C47: =SUM(C38:C46) -> 0 | D47: =SUM(D38:D46) -> 1.8781805
A96: Jan
A97: Fev
A98: Mar
A99: Abr
A100: Mai
A101: Jun
A102: Jul
A103: Ago
A104: Set
A105: Out
A106: Nov
A107: Dez

Sheet Peças por Hora Galvanoplastia
A2: Menu | C2: Peças por Hora Galvanoplastia
B5: Pré Tratamento
B6: Área de 1 peça (dm²) | C6: Peso de 1 peça (Kg) | D6: Kg / Carga | E6: Peças/carga | F6: Area da Carga / Dm²
B7: 2.3 | C7: 0.7 | D7: 30 | E7: =D7/C7 -> 42.857143 | F7: =(E7*B7)*F25 -> 197.14286
B8: Rendimento de corrente (%) | C8: Espessura (mm) | E8: Amperagem | F8: Número de Gancheira
B9: 90 | C9: 4 | E9: 71 | F9: 2
B10: Peças por hora | C10: Kg por hora | E10: Densidade de Corrente | F10: Tempo de banho
B11: =(60/F11)*E7*F9 -> 514.28571 | C11: =(60/F11)*D7*F9 -> 360 | E11: =E9/F7 -> 0.36014493 | F11: 10
B13: Cobre Alcalino
B14: Área de 1 peça (dm²) | C14: Peso de 1 peça (Kg) | D14: Kg/ Carga | E14: Peças por carga | F14: Area da Carga / Dm² | H14: pe
B15: 2.3 | C15: 0.7 | D15: 30 | E15: =D15/C15 -> 42.857143 | F15: =(B15*E15)*F17 -> 197.14286 | H15: 8.9
B16: Rendimento de corrente (%) | C16: Espessura (mm) | E16: Amperagem | F16: Número de Tambores | H16: E Q
B17: 90 | C17: 4 | E17: 71 | F17: 2 | H17: 1.095
B18: Peças por hora | C18: Kg por hora | E18: Densidade de Corrente | F18: Tempo de banho
B19: =(60/F19)*(E15*F17) -> 85.454934 | C19: =(60/F19)*(D15*F17) -> 59.818454 | E19: =E17/F15 -> 0.36014493 | F19: =(60*C17*H15)/(H17*E19*B17) -> 60.182097
B21: Cobre Ácido
B22: Área de 1 peça (dm²) | C22: Peso de 1 peça (Kg) | D22: Kg/ Carga | E22: Peças por carga | F22: Area da Carga / Dm² | H22: pe
B23: 2.3 | C23: 0.7 | D23: 30 | E23: =D23/C23 -> 42.857143 | F23: =(E23*B23)*F25 -> 197.14286 | H23: 8.92
B24: Rendimento de corrente (%) | C24: Espessura (mm) | E24: Amperagem | F24: Número de Tambores | H24: E Q
B25: 90 | C25: 4 | E25: 66 | F25: 2 | H25: 1.186
B26: Peças por hora | C26: Kg por hora | E26: Densidade de Corrente | F26: Tempo de banho
B27: =(60/F27)*(E23*F25) -> 85.845681 | C27: =(60/F27)*(D23*F25) -> 60.091977 | E27: =E25/F23 -> 0.33478261 | F27: =(60*C25*H23)/(H25*E27*B25) -> 59.908164
B29: Desengraxante Químico
B30: Área de 1 peça (dm²) | C30: Peso de 1 peça (Kg) | D30: Kg / Carga | E30: Peças/carga | F30: Area da Carga / Dm²
B31: 2.3 | C31: 0.7 | D31: 30 | E31: =D31/C31 -> 42.857143 | F31: =B31*E31*F40 -> 197.14286
B32: Rendimento de corrente (%) | C32: Espessura (mm) | E32: Amperagem | F32: Número de Gancheira
B33: 90 | C33: 4 | E33: 71 | F33: 2
B34: Peças por hora | C34: Kg por hora | E34: Densidade de Corrente | F34: Tempo de banho
B35: =(60/F35)*E31*F33 -> 514.28571 | C35: =(60/F35)*D31*F33 -> 360 | E35: =E33/F31 -> 0.36014493 | F35: 10
B36: Níquel Brilhante
B37: Área de 1 peça (dm²) | C37: Peso de 1 peça (Kg) | D37: Kg / Carga | E37: Peças por carga | F37: Area da Carga / Dm² | H37: pe
B38: 2.3 | C38: 0.7 | D38: 30 | E38: =D38/C38 -> 42.857143 | F38: =(E38*B38)*F40 -> 197.14286 | H38: 8.9
B39: Rendimento de corrente (%) | C39: Espessura (mm) | E39: Amperagem | F39: Número de Tambores | H39: E Q
B40: 90 | C40: 4 | E40: 71 | F40: 2 | H40: 1.095
B41: Peças por hora | C41: Kg por hora | E41: Densidade de Corrente | F41: Tempo de banho
B42: =(60/F42)*(E38*F40) -> 85.454934 | C42: =(60/F42)*(D38*F40) -> 59.818454 | E42: =E40/F38 -> 0.36014493 | F42: =(60*C40*H38)/(H40*E42*B40) -> 60.182097
B44: Cromo
B45: Área de 1 peça (dm²) | C45: Peso de 1 peça (Kg) | D45: Kg / Carga | E45: Peças por carga | F45: Area da Carga / Dm² | H45: pe
B46: 2.3 | C46: 0.7 | D46: 30 | E46: =D46/C46 -> 42.857143 | F46: =(E46*B46)*F48 -> 197.14286 | H46: 7.1
B47: Rendimento de corrente (%) | C47: Espessura (mm) | E47: Amperagem | F47: Número de Tambores | H47: E Q
B48: 90 | C48: 4 | E48: 192 | F48: 2 | H48: 0.323
B49: Peças por hora | C49: Kg por hora | E49: Densidade de Corrente | F49: Tempo de banho
B50: =(60/F50)*(E46*F48) -> 85.447642 | C50: =(60/F50)*(D46*F48) -> 59.81335 | E50: =E48/F46 -> 0.97391304 | F50: =(60*C48*H46)/(H48*E50*B48) -> 60.187233
B52: Níquel Strik
B53: Área de 1 peça (dm²) | C53: Peso de 1 peça (Kg) | D53: Kg / Carga | E53: Peças por carga | F53: Area da Carga / Dm² | H53: pe
B54: 2.3 | C54: 0.7 | D54: 30 | E54: =D54/C54 -> 42.857143 | F54: =E54*B54*F56 -> 197.14286 | H54: 8.9
B55: Rendimento de corrente (%) | C55: Espessura (mm) | E55: Amperagem | F55: Número de Tambores | H55: E Q
B56: 89 | C56: 2 | E56: 43 | F56: 2 | H56: 1.095
B57: Peças por hora | C57: Kg por hora | E57: Densidade de Corrente | F57: Tempo de banho
B58: =(60/F58)*(E54*F56) -> 102.3587 | C58: =(60/F58)*(D54*F56) -> 71.651087 | E58: =E56/F54 -> 0.21811594 | F58: =(60*C56*H54)/(H56*E58*B56) -> 50.243481
B60: Níquel Strik ll
B61: Área de 1 peça (dm²) | C61: Peso de 1 peça (Kg) | D61: Kg / Carga | E61: Peças por carga | F61: Area da Carga / Dm² | H61: pe
B62: 2.3 | C62: 0.7 | D62: 30 | E62: =D62/C62 -> 42.857143 | F62: =E62*B62*F64 -> 197.14286 | H62: 8.9
B63: Rendimento de corrente (%) | C63: Espessura (mm) | E63: Amperagem | F63: Número de Tambores | H63: E Q
B64: 89 | C64: 2 | E64: 43 | F64: 2 | H64: 1.095
B65: Peças por hora | C65: Kg por hora | E65: Densidade de Corrente | F65: Tempo de banho
B66: =(60/F66)*(E62*F64) -> 102.3587 | C66: =(60/F66)*(D62*F64) -> 71.651087 | E66: =E64/F62 -> 0.21811594 | F66: =(60*C64*H62)/(H64*E66*B64) -> 50.243481

Sheet Custo Verniz
A2: Menu | C2: Custo Por Peça Verniz
E6: Mar
B8: Verniz Cataforético Cobre | C8: Custo / Peça | D8: Custo/ Peça P.Q | F8: Verniz Cataforético Cobre | G8: Custo / Total | I8: Prod. Químico
B9: Níquel Strik | C9: =IF(E9=1,'Custo Galvanoplastia'!C47,0) -> 0 | D9: =IF(E9=1,'Custo Galvanoplastia'!D47,0) -> 1.8781805 | E9: 1
B10: Pré Tratamento | C10: =G10/'Peças por Hora Verniz'!B11 -> #DIV/0! | D10: =I10/'Peças por Hora Verniz'!B11 -> #DIV/0! | F10: Pré Tratamento | G10: =IF(H10=1,HLOOKUP(E6,'Resumo de Custo'!DS7:ED26,11,0),0) -> 0 | H10: 1 | I10: =IF(H10=1,HLOOKUP(E6,'Resumo de Custo'!EF7:EQ28,11,0),0) -> 0.63636364
B11: Verniz Cataforético Cobre | C11: =G11/'Peças por Hora Verniz'!B19 -> #DIV/0! | D11: =I11/'Peças por Hora Verniz'!B19 -> #DIV/0! | F11: Verniz Cataforético Cobre | G11: =IF(H11=1,HLOOKUP(E6,'Resumo de Custo'!DS7:ED28,12,0),0) -> 0 | H11: 1 | I11: =IF(H11=1,HLOOKUP(E6,'Resumo de Custo'!EF7:EQ28,12,0),0) -> 108.99459
B12: Desplacante | C12: =G12/'Peças por Hora Verniz'!B67 -> #DIV/0! | D12: =I12/'Peças por Hora Verniz'!B67 -> #DIV/0! | F12: Desplacante | G12: =IF(H12=1,HLOOKUP(E6,'Resumo de Custo'!DS7:ED28,19,0),0) -> 0 | H12: 1 | I12: =IF(H12=1,HLOOKUP(E6,'Resumo de Custo'!EF7:EQ28,19,0),0) -> 38.422727
B13: E.T.E | C13: =G13/'Peças por Hora Verniz'!B67 -> #DIV/0! | D13: =I13/'Peças por Hora Verniz'!B67 -> #DIV/0! | F13: E.T.E | G13: =IF(H13=1,HLOOKUP(E6,'Resumo de Custo'!DS7:ED28,20,0),0) -> 0 | H13: 1 | I13: =IF(H13=1,HLOOKUP(E6,'Resumo de Custo'!EF7:EQ28,20,0),0) -> 0.013636364
F19: Total | G19: =SUM(G10:G18) -> 0 | I19: =SUM(I10:I18) -> 148.06732
B21: Total | C21: =SUM(C9:C20) -> #DIV/0! | D21: =SUM(D9:D20) -> #DIV/0!
B24: Verniz Cataforético Preto Fosco | C24: Custo / Peça | D24: Custo/ Peça P.Q | F24: Verniz Cataforético Preto Fosco | G24: Custo / Total | I24: Prod. Químico
B25: Níquel Strik | C25: =IF(E25=1,'Custo Galvanoplastia'!C47,0) -> 0 | D25: =IF(E25=1,'Custo Galvanoplastia'!D47,0) -> 1.8781805 | E25: 1
B26: Pré Tratamento | C26: =G26/'Peças por Hora Verniz'!B11 -> #DIV/0! | D26: =I26/'Peças por Hora Verniz'!B11 -> #DIV/0! | F26: Pré Tratamento | G26: =IF(H26=1,HLOOKUP(E6,'Resumo de Custo'!DS7:ED28,11,0),0) -> 0 | H26: 1 | I26: =IF(H26=1,HLOOKUP(E6,'Resumo de Custo'!EF7:EQ28,11,0),0) -> 0.63636364
B27: Verniz Cataforético Preto Fosco | C27: =G27/'Peças por Hora Verniz'!B27 -> #DIV/0! | D27: =I27/'Peças por Hora Verniz'!B27 -> #DIV/0! | F27: Verniz Cataforético Preto Fosco | G27: =IF(H27=1,HLOOKUP(E6,'Resumo de Custo'!DS7:ED28,13,0),0) -> 0 | H27: 1 | I27: =IF(H27=1,HLOOKUP(E6,'Resumo de Custo'!EF7:EQ28,13,0),0) -> 181.40345
B28: Desplacante | C28: =G28/'Peças por Hora Verniz'!B67 -> #DIV/0! | D28: =I28/'Peças por Hora Verniz'!B67 -> #DIV/0! | F28: Desplacante | G28: =IF(H28=1,HLOOKUP(E6,'Resumo de Custo'!DS7:ED28,19,0),0) -> 0 | H28: 1 | I28: =IF(H28=1,HLOOKUP(E6,'Resumo de Custo'!EF7:EQ28,19,0),0) -> 38.422727
B29: E.T.E | C29: =G29/'Peças por Hora Verniz'!B67 -> #DIV/0! | D29: =I29/'Peças por Hora Verniz'!B67 -> #DIV/0! | F29: E.T.E | G29: =IF(H29=1,HLOOKUP(E6,'Resumo de Custo'!DS7:ED28,20,0),0) -> 0 | H29: 1 | I29: =IF(H29=1,HLOOKUP(E6,'Resumo de Custo'!EF7:EQ28,20,0),0) -> 0.013636364
F35: Total | G35: =SUM(G26:G34) -> 0 | I35: =SUM(I26:I34) -> 220.47618
B37: Total | C37: =SUM(C25:C36) -> #DIV/0! | D37: =SUM(D25:D36) -> #DIV/0!
B39: Verniz Cataforético Preto Brilhante | C39: Custo / Peça | D39: Custo/ Peça P.Q | F39: Verniz Cataforético Preto Brilhante | G39: Custo / Total | I39: Prod. Químico
B40: Níquel Strik | C40: =IF(E40=1,'Custo Galvanoplastia'!C47,0) -> 0 | D40: =IF(E40=1,'Custo Galvanoplastia'!D47,0) -> 1.8781805 | E40: 1
B41: Pré Tratamento | C41: =G41/'Peças por Hora Verniz'!B11 -> #DIV/0! | D41: =I41/'Peças por Hora Verniz'!B11 -> #DIV/0! | F41: Pré Tratamento | G41: =IF(H41=1,HLOOKUP(E6,'Resumo de Custo'!DS7:ED28,11,0),0) -> 0 | H41: 1 | I41: =IF(H41=1,HLOOKUP(E6,'Resumo de Custo'!EF7:EQ28,11,0),0) -> 0.63636364
B42: Verniz Cataforético Preto Brilhante | C42: =G42/'Peças por Hora Verniz'!B35 -> #DIV/0! | D42: =I42/'Peças por Hora Verniz'!B35 -> #DIV/0! | F42: Verniz Cataforético Preto Brilhante | G42: =IF(H42=1,HLOOKUP(E6,'Resumo de Custo'!DS7:ED28,14,0),0) -> 0 | H42: 1 | I42: =IF(H42=1,HLOOKUP(E6,'Resumo de Custo'!EF7:EQ28,14,0),0) -> 17.291091
B43: Desplacante | C43: =G43/'Peças por Hora Verniz'!B67 -> #DIV/0! | D43: =I43/'Peças por Hora Verniz'!B67 -> #DIV/0! | F43: Desplacante | G43: =IF(H43=1,HLOOKUP(E6,'Resumo de Custo'!DS7:ED28,19,0),0) -> 0 | H43: 1 | I43: =IF(H43=1,HLOOKUP(E6,'Resumo de Custo'!EF7:EQ28,19,0),0) -> 38.422727
B44: E.T.E | C44: =G44/'Peças por Hora Verniz'!B67 -> #DIV/0! | D44: =I44/'Peças por Hora Verniz'!B67 -> #DIV/0! | F44: E.T.E | G44: =IF(H44=1,HLOOKUP(E6,'Resumo de Custo'!DS7:ED28,20,0),0) -> 0 | H44: 1 | I44: =IF(H44=1,HLOOKUP(E6,'Resumo de Custo'!EF7:EQ28,20,0),0) -> 0.013636364
F49: Total | G49: =SUM(G41:G48) -> 0 | I49: =SUM(I41:I48) -> 56.363818
B50: Total | C50: =SUM(C40:C49) -> #DIV/0! | D50: =SUM(D40:D49) -> #DIV/0!
B52: Verniz Cataforético Gold | C52: Custo / Peça | D52: Custo/ Peça P.Q | F52: Verniz Cataforético Gold | G52: Custo / Total | I52: Prod. Químico
B53: Níquel Strik | C53: =IF(E53=1,'Custo Galvanoplastia'!C47,0) -> 0 | D53: =IF(E53=1,'Custo Galvanoplastia'!D47,0) -> 1.8781805 | E53: 1
B54: Pré Tratamento | C54: =G54/'Peças por Hora Verniz'!B11 -> #DIV/0! | D54: =I54/'Peças por Hora Verniz'!B11 -> #DIV/0! | F54: Pré Tratamento | G54: =IF(H54=1,HLOOKUP(E6,'Resumo de Custo'!DS7:ED28,11,0),0) -> 0 | H54: 1 | I54: =IF(H54=1,HLOOKUP(E6,'Resumo de Custo'!EF7:EQ28,11,0),0) -> 0.63636364
B55: Verniz Cataforético Gold | C55: =G55/'Peças por Hora Verniz'!B43 -> #DIV/0! | D55: =I55/'Peças por Hora Verniz'!B43 -> #DIV/0! | F55: Verniz Cataforético Gold | G55: =IF(H55=1,HLOOKUP(E6,'Resumo de Custo'!DS7:ED28,15,0),0) -> 0 | H55: 1 | I55: =IF(H55=1,HLOOKUP(E6,'Resumo de Custo'!EF7:EQ28,15,0),0) -> 101.29495
B56: Desplacante | C56: =G56/'Peças por Hora Verniz'!B67 -> #DIV/0! | D56: =I56/'Peças por Hora Verniz'!B67 -> #DIV/0! | F56: Desplacante | G56: =IF(H56=1,HLOOKUP(E6,'Resumo de Custo'!DS7:ED28,19,0),0) -> 0 | H56: 1 | I56: =IF(H56=1,HLOOKUP(E6,'Resumo de Custo'!EF7:EQ28,19,0),0) -> 38.422727
B57: E.T.E | C57: =G57/'Peças por Hora Verniz'!B67 -> #DIV/0! | D57: =I57/'Peças por Hora Verniz'!B67 -> #DIV/0! | F57: E.T.E | G57: =IF(H57=1,HLOOKUP(E6,'Resumo de Custo'!DS7:ED28,20,0),0) -> 0 | H57: 1 | I57: =IF(H57=1,HLOOKUP(E6,'Resumo de Custo'!EF7:EQ28,20,0),0) -> 0.013636364
F62: Total | G62: =SUM(G54:G61) -> 0 | I62: =SUM(I54:I61) -> 140.36768
B63: Total | C63: =SUM(C53:C62) -> #DIV/0! | D63: =SUM(D53:D62) -> #DIV/0!
B65: Verniz Cataforético Champagne | C65: Custo / Peça | D65: Custo/ Peça P.Q | F65: Verniz Cataforético Champagne | G65: Custo / Total | I65: Prod. Químico
B66: Níquel Strik | C66: =IF(E66=1,'Custo Galvanoplastia'!C47,0) -> 0 | D66: ='Custo Galvanoplastia'!D47 -> 1.8781805 | E66: 1
B67: Pré Tratamento | C67: =G67/'Peças por Hora Verniz'!B11 -> #DIV/0! | D67: =I67/'Peças por Hora Verniz'!B11 -> #DIV/0! | F67: Pré Tratamento | G67: =IF(H67=1,HLOOKUP(E6,'Resumo de Custo'!DS7:ED28,11,0),0) -> 0 | H67: 1 | I67: =IF(H67=1,HLOOKUP(E6,'Resumo de Custo'!EF7:EQ28,11,0),0) -> 0.63636364
B68: Verniz Cataforético Champagne | C68: =G68/'Peças por Hora Verniz'!B51 -> #DIV/0! | D68: =I68/'Peças por Hora Verniz'!B51 -> #DIV/0! | F68: Verniz Cataforético Champagne | G68: =IF(H68=1,HLOOKUP(E6,'Resumo de Custo'!DS7:ED28,16,0),0) -> 0 | H68: 1 | I68: =IF(H68=1,HLOOKUP(E6,'Resumo de Custo'!EF7:EQ28,16,0),0) -> 62.442227
B69: Desplacante | C69: =G69/'Peças por Hora Verniz'!B67 -> #DIV/0! | D69: =I69/'Peças por Hora Verniz'!B67 -> #DIV/0! | F69: Desplacante | G69: =IF(H69=1,HLOOKUP(E6,'Resumo de Custo'!DS7:ED28,19,0),0) -> 0 | H69: 1 | I69: =IF(H69=1,HLOOKUP(E6,'Resumo de Custo'!EF7:EQ28,19,0),0) -> 38.422727
B70: E.T.E | C70: =G70/'Peças por Hora Verniz'!B67 -> #DIV/0! | D70: =I70/'Peças por Hora Verniz'!B67 -> #DIV/0! | F70: E.T.E | G70: =IF(H70=1,HLOOKUP(E6,'Resumo de Custo'!DS7:ED28,20,0),0) -> 0 | H70: 1 | I70: =IF(H70=1,HLOOKUP(E6,'Resumo de Custo'!EF7:EQ28,20,0),0) -> 0.013636364
F75: Total | G75: =SUM(G67:G74) -> 0 | I75: =SUM(I67:I74) -> 101.51495
B76: Total | C76: =SUM(C66:C75) -> #DIV/0! | D76: =SUM(D66:D75) -> #DIV/0!
B78: Verniz Cataforético Grafite Onix | C78: Custo / Peça | D78: Custo/ Peça P.Q | F78: Verniz Cataforético Grafite Onix | G78: Custo / Total | I78: Prod. Químico
B79: Níquel Strik | C79: =IF(E79=1,'Custo Galvanoplastia'!C47,0) -> 0 | D79: =IF(E79=1,'Custo Galvanoplastia'!D47,0) -> 1.8781805 | E79: 1
B80: Pré Tratamento | C80: =G80/'Peças por Hora Verniz'!B11 -> #DIV/0! | D80: =I80/'Peças por Hora Verniz'!B11 -> #DIV/0! | F80: Pré Tratamento | G80: =IF(H80=1,HLOOKUP(E6,'Resumo de Custo'!DS7:ED28,11,0),0) -> 0 | H80: 1 | I80: =IF(H80=1,HLOOKUP(E6,'Resumo de Custo'!EF7:EQ28,11,0),0) -> 0.63636364
B81: Verniz Cataforético Grafite Onix | C81: =G81/'Peças por Hora Verniz'!B59 -> #DIV/0! | D81: =I81/'Peças por Hora Verniz'!B59 -> #DIV/0! | F81: Verniz Cataforético Grafite Onix | G81: =IF(H81=1,HLOOKUP(E6,'Resumo de Custo'!DS7:ED28,17,0),0) -> 0 | H81: 1 | I81: =IF(H81=1,HLOOKUP(E6,'Resumo de Custo'!EF7:EQ28,17,0),0) -> 9.4011364
B82: Desplacante | C82: =G82/'Peças por Hora Verniz'!B67 -> #DIV/0! | D82: =I82/'Peças por Hora Verniz'!B67 -> #DIV/0! | F82: Desplacante | G82: =IF(H82=1,HLOOKUP(E6,'Resumo de Custo'!DS7:ED28,19,0),0) -> 0 | H82: 1 | I82: =IF(H82=1,HLOOKUP(E6,'Resumo de Custo'!EF7:EQ28,19,0),0) -> 38.422727
B83: E.T.E | C83: =G83/'Peças por Hora Verniz'!B67 -> #DIV/0! | D83: =I83/'Peças por Hora Verniz'!B67 -> #DIV/0! | F83: E.T.E | G83: =IF(H83=1,HLOOKUP(E6,'Resumo de Custo'!DS7:ED28,20,0),0) -> 0 | H83: 1 | I83: =IF(H83=1,HLOOKUP(E6,'Resumo de Custo'!EF7:EQ28,20,0),0) -> 0.013636364
F88: Total | G88: =SUM(G80:G87) -> 0 | I88: =SUM(I80:I87) -> 48.473864
B89: Total | C89: =SUM(C79:C88) -> #DIV/0! | D89: =SUM(D79:D88) -> #DIV/0!
B91: Verniz Imersão | C91: Custo / Peça | D91: Custo/ Peça P.Q | F91: Verniz Imersão | G91: Custo / Total | I91: Prod. Químico
B92: Níquel Strik | C92: =IF(E92=1,'Custo Galvanoplastia'!C47,0) -> 0 | D92: =IF(E92=1,'Custo Galvanoplastia'!D47,0) -> 1.8781805 | E92: 1
B93: Pré Tratamento | C93: =G93/'Peças por Hora Verniz'!B11 -> #DIV/0! | D93: =I93/'Peças por Hora Verniz'!B11 -> #DIV/0! | F93: Pré Tratamento | G93: =IF(H93=1,HLOOKUP(E6,'Resumo de Custo'!DS7:ED28,11,0),0) -> 0 | H93: 1 | I93: =IF(H93=1,HLOOKUP(E6,'Resumo de Custo'!EF7:EQ28,11,0),0) -> 0.63636364
B94: Verniz Imersão | C94: =G94/'Peças por Hora Verniz'!B75 -> #DIV/0! | D94: =I94/'Peças por Hora Verniz'!B75 -> #DIV/0! | F94: Verniz Imersão | G94: =IF(H94=1,HLOOKUP(E6,'Resumo de Custo'!DS7:ED28,18,0),0) -> 0 | H94: 1 | I94: =IF(H94=1,HLOOKUP(E6,'Resumo de Custo'!EF7:EQ28,18,0),0) -> 16.538636
B95: Desplacante | C95: =G95/'Peças por Hora Verniz'!B67 -> #DIV/0! | D95: =I95/'Peças por Hora Verniz'!B67 -> #DIV/0! | F95: Desplacante | G95: =IF(H95=1,HLOOKUP(E6,'Resumo de Custo'!DS7:ED28,19,0),0) -> 0 | H95: 1 | I95: =IF(H95=1,HLOOKUP(E6,'Resumo de Custo'!EF7:EQ28,19,0),0) -> 38.422727
B96: E.T.E | C96: =G96/'Peças por Hora Verniz'!B67 -> #DIV/0! | D96: =I96/'Peças por Hora Verniz'!B75 -> #DIV/0! | F96: E.T.E | G96: =IF(H96=1,HLOOKUP(E6,'Resumo de Custo'!DS7:ED28,20,0),0) -> 0 | H96: 1 | I96: =IF(H96=1,HLOOKUP(E6,'Resumo de Custo'!EF7:EQ28,20,0),0) -> 0.013636364
F101: Total | G101: =SUM(G93:G100) -> 0 | I101: =SUM(I93:I100) -> 55.611364
B102: Total | C102: =SUM(C92:C101) -> #DIV/0! | D102: =SUM(D92:D101) -> #DIV/0!
A103: Jan
A104: Fev
A105: Mar
A106: Abr
A107: Mai
A108: Jun
A109: Jul
A110: Ago
A111: Set
A112: Out
A113: Nov
A114: Dez

Sheet Peças por Hora Verniz
A2: Menu | C2: Peças por Hora Verniz
B5: Pré Tratamento Verniz Cataforético
B6: Área de 1 peça (dm²) | C6: Peso de 1 peça (Kg) | D6: Kg / Carga | E6: Peças/carga | F6: Area da Carga / Dm²
B7: 0 | C7: 0.7 | D7: 0 | E7: =D7/C7 -> 0 | F7: =(B7*E7)*F17 -> 0
B8: Rendimento de corrente (%) | C8: Espessura (mm) | E8: Amperagem | F8: Número de Gancheiras
B9: 90 | C9: 4 | E9: 71 | F9: 2
B10: Peças por hora | C10: Kg por hora | E10: Densidade de Corrente | F10: Tempo de banho
B11: =(60/F11)*(E7*F17) -> 0 | C11: =(60/F11)*(D7*F9) -> 0 | E11: =E9/F7 -> #DIV/0! | F11: 2
B13: Verniz Cataforético Cobre
B14: Área de 1 peça (dm²) | C14: Peso de 1 peça (Kg) | D14: Kg/ Carga | E14: Peças por carga | F14: Area da Carga / Dm²
B15: 0 | C15: 0.7 | D15: 0 | E15: =D15/C15 -> 0 | F15: =B15*E15*F17 -> 0
B16: Rendimento de corrente (%) | C16: Espessura (mm) | E16: Amperagem | F16: Número de Gancheiras
B17: 90 | C17: 4 | E17: 71 | F17: 2
B18: Peças por hora | C18: Kg por hora | E18: Densidade de Corrente | F18: Tempo de banho
B19: =(60/F19)*(E15*F17) -> 0 | C19: =(60/F19)*(D15*F17) -> 0 | E19: =E17/F15 -> #DIV/0! | F19: 2
B21: Verniz Cataforético Preto Fosco
B22: Área de 1 peça (dm²) | C22: Peso de 1 peça (Kg) | D22: Kg/ Carga | E22: Peças por carga | F22: Area da Carga / Dm²
B23: 0 | C23: 0.7 | D23: 0 | E23: =D23/C23 -> 0 | F23: =E23*B23*F25 -> 0
B24: Rendimento de corrente (%) | C24: Espessura (mm) | D24: Peças por carga | E24: Amperagem | F24: Número de Gancheiras
B25: 90 | C25: 4 | D25: =E23*F25 -> 0 | E25: 66 | F25: 1
B26: Peças por hora | C26: Kg por hora | E26: Densidade de Corrente | F26: Tempo de banho
B27: =(60/F27)*(E23*F25) -> 0 | C27: =(60/F27)*(D23*F25) -> 0 | E27: =E25/F23 -> #DIV/0! | F27: 2
B29: Verniz Cataforético Preto Brilhante
B30: Área de 1 peça (dm²) | C30: Peso de 1 peça (Kg) | D30: Kg / Carga | E30: Peças/carga | F30: Area da Carga / Dm²
B31: 0 | C31: 0.7 | D31: 0 | E31: =D31/C31 -> 0 | F31: =(B31*E31)*F33 -> 0
B32: Rendimento de corrente (%) | C32: Espessura (mm) | D32: Peças por carga | E32: Amperagem | F32: Número de Gancheiras
B33: 90 | C33: 4 | D33: =E31*F33 -> 0 | E33: 66 | F33: 1
B34: Peças por hora | C34: Kg por hora | E34: Densidade de Corrente | F34: Tempo de banho
B35: =(60/F35)*(E31*F33) -> 0 | C35: =(60/F35)*(D31*F33) -> 0 | E35: =E33/F31 -> #DIV/0! | F35: 2
B37: Verniz Cataforético Gold
B38: Área de 1 peça (dm²) | C38: Peso de 1 peça (Kg) | D38: Kg / Carga | E38: Peças por carga | F38: Area da Carga / Dm²
B39: 0 | C39: 0.7 | D39: 0 | E39: =D39/C39 -> 0 | F39: =(E39*B39)*F41 -> 0
B40: Rendimento de corrente (%) | C40: Espessura (mm) | E40: Amperagem | F40: Número de Gancheiras
B41: 90 | C41: 4 | E41: 71 | F41: 1
B42: Peças por hora | C42: Kg por hora | E42: Densidade de Corrente | F42: Tempo de banho
B43: =(60/F43)*(E39*F41) -> 0 | C43: =(60/F43)*(D39*F41) -> 0 | E43: =E41/F39 -> #DIV/0! | F43: 2
B45: Verniz Cataforético Champagne
B46: Área de 1 peça (dm²) | C46: Peso de 1 peça (Kg) | D46: Kg / Carga | E46: Peças por carga | F46: Area da Carga / Dm²
B47: 0 | C47: 0.7 | D47: 0 | E47: =D47/C47 -> 0 | F47: =E47*B47*F49 -> 0
B48: Rendimento de corrente (%) | C48: Espessura (mm) | E48: Amperagem | F48: Número de Gancheiras
B49: 90 | C49: 4 | E49: 192 | F49: 1
B50: Peças por hora | C50: Kg por hora | E50: Densidade de Corrente | F50: Tempo de banho
B51: =(60/F51)*(E47*F49) -> 0 | C51: =(60/F51)*(D47*F49) -> 0 | E51: =E49/F47 -> #DIV/0! | F51: 2
B53: Verniz Cataforético Grafite Onix
B54: Área de 1 peça (dm²) | C54: Peso de 1 peça (Kg) | D54: Kg / Carga | E54: Peças por carga | F54: Area da Carga / Dm²
B55: 0 | C55: 0.7 | D55: 0 | E55: =D55/C55 -> 0 | F55: =E55*B55*F57 -> 0
B56: Rendimento de corrente (%) | C56: Espessura (mm) | E56: Amperagem | F56: Número de Gancheiras
B57: 89 | C57: 2 | E57: 43 | F57: 1
B58: Peças por hora | C58: Kg por hora | E58: Densidade de Corrente | F58: Tempo de banho
B59: =(60/F59)*(E55*F57) -> 0 | C59: =(60/F59)*(D55*F57) -> 0 | E59: =E57/F55 -> #DIV/0! | F59: 2
B61: Desplacante
B62: Área de 1 peça (dm²) | C62: Peso de 1 peça (Kg) | D62: Kg / Carga | E62: Peças por carga | F62: Area da Carga / Dm²
B63: 0 | C63: 0.7 | D63: 0 | E63: =D63/C63 -> 0 | F63: =E63*B63*F65 -> 0
B64: Rendimento de corrente (%) | C64: Espessura (mm) | E64: Amperagem | F64: Número de Gancheiras
B65: 89 | C65: 2 | E65: 43 | F65: 1
B66: Peças por hora | C66: Kg por hora | E66: Densidade de Corrente | F66: Tempo de banho
B67: =(60/F67)*(E63*F65) -> 0 | C67: =(60/F67)*(D63*F65) -> 0 | E67: =E65/F63 -> #DIV/0! | F67: 2
B69: Verniz por Imersão
B70: Área de 1 peça (dm²) | C70: Peso de 1 peça (Kg) | D70: Kg / Carga | E70: Peças por carga | F70: Area da Carga / Dm²
B71: 0 | C71: 0.7 | D71: 0 | E71: =D71/C71 -> 0 | F71: =E71*B71*F73 -> 0
B72: Rendimento de corrente (%) | C72: Espessura (mm) | E72: Amperagem | F72: Número de Gancheiras
B73: 89 | C73: 2 | E73: 43 | F73: 1
B74: Peças por hora | C74: Kg por hora | E74: Densidade de Corrente | F74: Tempo de banho
B75: =(60/F75)*(E71*F73) -> 0 | C75: =(60/F75)*(D71*F73) -> 0 | E75: =E73/F71 -> #DIV/0! | F75: 2

Sheet Pré Tratamento
A2: Menu
A3: Pré Tratamento
E5: 45292 | F5: 45292 | G5: 45292 | H5: 45323 | I5: 45323 | J5: 45323 | K5: 45352 | L5: 45352 | M5: 45352 | N5: 45383 | O5: 45383 | P5: 45383 | Q5: 45413 | R5: 45413 | S5: 45413 | T5: 45444 | U5: 45444 | V5: 45444 | W5: 45474 | X5: 45474 | Y5: 45474 | Z5: 45505 | AA5: 45505 | AB5: 45505 | AC5: 45536 | AD5: 45536 | AE5: 45536 | AF5: 45566 | AG5: 45566 | AH5: 45566 | AI5: 45597 | AJ5: 45597 | AK5: 45597 | AL5: 45627 | AM5: 45627 | AN5: 45627
A6: Produto | B6: ID | C6: Volume tanque / lts | D6: Concentração g/lt | E6: Consumo Kg/lt | F6: Custo/Kg | G6: Custo Total | H6: Consumo Kg/lt | I6: Custo/Kg | J6: Custo Total | K6: Consumo Kg/lt | L6: Custo Kg/lt | M6: Custo Total | N6: Consumo Kg/lt | O6: Custo/Kg | P6: Custo Total | Q6: Consumo Kg/lt | R6: Custo/Kg | S6: Custo Total | T6: Consumo Kg/lt | U6: Custo/Kg | V6: Custo Total | W6: Consumo Kg/lt | X6: Custo/Kg | Y6: Custo Total | Z6: Consumo Kg/lt | AA6: Custo/Kg | AB6: Custo Total | AC6: Consumo Kg/lt | AD6: Custo/Kg | AE6: Custo Total | AF6: Consumo Kg/lt | AG6: Custo/Kg | AH6: Custo Total | AI6: Consumo Kg/lt | AJ6: Custo/Kg | AK6: Custo Total | AL6: Consumo Kg/lt | AM6: Custo/Kg | AN6: Custo Total
A7: SODA | B7: 5643 | C7: 3000 | D7: 0 | E7: 0 | F7: 0 | G7: =F7*E7 -> 0 | H7: 0 | I7: 0 | J7: =I7*H7 -> 0 | K7: 125 | L7: 5.16 | M7: =L7*K7 -> 645 | N7: 75 | O7: 5.16 | P7: =O7*N7 -> 387 | Q7: 25 | R7: 5.16 | S7: =R7*Q7 -> 129 | T7: 50 | U7: 5.16 | V7: =U7*T7 -> 258 | W7: 0 | X7: 0 | Y7: =X7*W7 -> 0 | Z7: 0 | AA7: 0 | AB7: =AA7*Z7 -> 0 | AC7: 0 | AD7: 0 | AE7: =AD7*AC7 -> 0 | AF7: 0 | AG7: 0 | AH7: =AG7*AF7 -> 0 | AI7: 0 | AJ7: 0 | AK7: =AJ7*AI7 -> 0 | AL7: 0 | AM7: 0 | AN7: =AM7*AL7 -> 0
A8: ACTIVE ZMC | C8: 0 | D8: 0 | E8: 0 | F8: 0 | G8: =F8*E8 -> 0 | H8: 0 | I8: 0 | J8: =I8*H8 -> 0 | K8: 75 | L8: 10.5 | M8: =L8*K8 -> 787.5 | N8: 75 | O8: 10.5 | P8: =O8*N8 -> 787.5 | Q8: 25 | R8: 0 | S8: =R8*Q8 -> 0 | T8: 50 | U8: 0 | V8: =U8*T8 -> 0 | W8: 0 | X8: 0 | Y8: =X8*W8 -> 0 | Z8: 0 | AA8: 0 | AB8: =AA8*Z8 -> 0 | AC8: 0 | AD8: 0 | AE8: =AD8*AC8 -> 0 | AF8: 0 | AG8: 0 | AH8: =AG8*AF8 -> 0 | AI8: 0 | AJ8: 0 | AK8: =AJ8*AI8 -> 0 | AL8: 0 | AM8: 0 | AN8: =AM8*AL8 -> 0
A9: COMPOSTO C-10 | C9: 0 | D9: 0 | E9: 0 | F9: 0 | G9: =F9*E9 -> 0 | H9: 0 | I9: 0 | J9: =I9*H9 -> 0 | K9: 0 | L9: 0 | M9: =L9*K9 -> 0 | N9: 0 | O9: 48.59 | P9: =O9*N9 -> 0 | Q9: 0 | R9: 0 | S9: =R9*Q9 -> 0 | T9: 0 | U9: 0 | V9: =U9*T9 -> 0 | W9: 0 | X9: 0 | Y9: =X9*W9 -> 0 | Z9: 0 | AA9: 0 | AB9: =AA9*Z9 -> 0 | AC9: 0 | AD9: 0 | AE9: =AD9*AC9 -> 0 | AF9: 0 | AG9: 0 | AH9: =AG9*AF9 -> 0 | AI9: 0 | AJ9: 0 | AK9: =AJ9*AI9 -> 0 | AL9: 0 | AM9: 0 | AN9: =AM9*AL9 -> 0
A10: METAL CLEAN 7E_F | C10: 0 | D10: 0 | E10: 0 | F10: 0 | G10: =F10*E10 -> 0 | H10: 0 | I10: 0 | J10: =I10*H10 -> 0 | K10: 50 | L10: 11.11 | M10: =L10*K10 -> 555.5 | N10: 25 | O10: 11.11 | P10: =O10*N10 -> 277.75 | Q10: 25 | R10: 0 | S10: =R10*Q10 -> 0 | T10: 0 | U10: 0 | V10: =U10*T10 -> 0 | W10: 0 | X10: 0 | Y10: =X10*W10 -> 0 | Z10: 0 | AA10: 0 | AB10: =AA10*Z10 -> 0 | AC10: 0 | AD10: 0 | AE10: =AD10*AC10 -> 0 | AF10: 0 | AG10: 0 | AH10: =AG10*AF10 -> 0 | AI10: 0 | AJ10: 0 | AK10: =AJ10*AI10 -> 0 | AL10: 0 | AM10: 0 | AN10: =AM10*AL10 -> 0
A11: METAL CLEAN FE-05 | B11: 65073 | C11: 600 | D11: 0 | E11: 0 | F11: 0 | G11: =F11*E11 -> 0 | H11: 0 | I11: 0 | J11: =I11*H11 -> 0 | K11: 175 | L11: 11.61 | M11: =L11*K11 -> 2031.75 | N11: 125 | O11: 11.61 | P11: =O11*N11 -> 1451.25 | Q11: 125 | R11: 0 | S11: =R11*Q11 -> 0 | T11: 25 | U11: 0 | V11: =U11*T11 -> 0 | W11: 0 | X11: 0 | Y11: =X11*W11 -> 0 | Z11: 0 | AA11: 0 | AB11: =AA11*Z11 -> 0 | AC11: 0 | AD11: 0 | AE11: =AD11*AC11 -> 0 | AF11: 0 | AG11: 0 | AH11: =AG11*AF11 -> 0 | AI11: 0 | AJ11: 0 | AK11: =AJ11*AI11 -> 0 | AL11: 0 | AM11: 0 | AN11: =AM11*AL11 -> 0
A12: Ácido Sulfurico | B12: 64965 | C12: 300 | D12: 0 | E12: 0 | F12: 0 | G12: =F12*E12 -> 0 | H12: 0 | I12: 0 | J12: =I12*H12 -> 0 | K12: 0 | L12: 3.5 | M12: =L12*K12 -> 0 | N12: 0 | O12: 3.5 | P12: =O12*N12 -> 0 | Q12: 0 | R12: 0 | S12: =R12*Q12 -> 0 | T12: 0 | U12: 0 | V12: =U12*T12 -> 0 | W12: 0 | X12: 0 | Y12: =X12*W12 -> 0 | Z12: 0 | AA12: 0 | AB12: =AA12*Z12 -> 0 | AC12: 0 | AD12: 0 | AE12: =AD12*AC12 -> 0 | AF12: 0 | AG12: 0 | AH12: =AG12*AF12 -> 0 | AI12: 0 | AJ12: 0 | AK12: =AJ12*AI12 -> 0 | AL12: 0 | AM12: 0 | AN12: =AM12*AL12 -> 0
A13: Átivação Mista | B13: 67567 | C13: 400 | D13: 0 | E13: 0 | F13: 0 | G13: =F13*E13 -> 0 | H13: 0 | I13: 0 | J13: =I13*H13 -> 0 | M13: =L13*K13 -> 0 | N13: 0 | O13: 0 | P13: =O13*N13 -> 0 | Q13: 0 | R13: 0 | S13: =R13*Q13 -> 0 | T13: 0 | U13: 0 | V13: =U13*T13 -> 0 | W13: 0 | X13: 0 | Y13: =X13*W13 -> 0 | Z13: 0 | AA13: 0 | AB13: =AA13*Z13 -> 0 | AC13: 0 | AD13: 0 | AE13: =AD13*AC13 -> 0 | AF13: 0 | AG13: 0 | AH13: =AG13*AF13 -> 0 | AI13: 0 | AJ13: 0 | AK13: =AJ13*AI13 -> 0 | AL13: 0 | AM13: 0 | AN13: =AM13*AL13 -> 0
C14: 0 | D14: 0 | E14: 0
F15: Total | G15: =SUM(G7:G14) -> 0 | I15: Total | J15: =SUM(J7:J14) -> 0 | L15: Total | M15: =SUM(M7:M14) -> 4019.75 | O15: Total | P15: =SUM(P7:P14) -> 2903.5 | R15: Total | S15: =SUM(S7:S14) -> 129 | U15: Total | V15: =SUM(V7:V14) -> 258 | X15: Total | Y15: =SUM(Y7:Y14) -> 0 | AA15: Total | AB15: =SUM(AB7:AB14) -> 0 | AD15: Total | AE15: =SUM(AE7:AE14) -> 0 | AG15: Total | AH15: =SUM(AH7:AH14) -> 0 | AJ15: Total | AK15: =SUM(AK7:AK14) -> 0 | AM15: Total | AN15: =SUM(AN7:AN14) -> 0

Sheet Cobre Alcalino
A2: Menu
A3: Cobre Alcalino
E5: 45292 | F5: 45292 | G5: 45292 | H5: 45323 | I5: 45323 | J5: 45323 | K5: 45352 | L5: 45352 | M5: 45352 | N5: 45383 | O5: 45383 | P5: 45383 | Q5: 45413 | R5: 45413 | S5: 45413 | T5: 45444 | U5: 45444 | V5: 45444 | W5: 45474 | X5: 45474 | Y5: 45474 | Z5: 45505 | AA5: 45505 | AB5: 45505 | AC5: 45536 | AD5: 45536 | AE5: 45536 | AF5: 45566 | AG5: 45566 | AH5: 45566 | AI5: 45597 | AJ5: 45597 | AK5: 45597 | AL5: 45627 | AM5: 45627 | AN5: 45627
A6: Produto | B6: ID | C6: Volume tanque / lts | D6: Concentração /% | E6: Consumo Kg/lt | F6: Custo/Kg | G6: Custo Total | H6: Consumo Kg/lt | I6: Custo/Kg | J6: Custo Total | K6: Consumo Kg/lt | L6: Custo Kg/lt | M6: Custo Total | N6: Consumo Kg/lt | O6: Custo/Kg | P6: Custo Total | Q6: Consumo Kg/lt | R6: Custo/Kg | S6: Custo Total | T6: Consumo Kg/lt | U6: Custo/Kg | V6: Custo Total | W6: Consumo Kg/lt | X6: Custo/Kg | Y6: Custo Total | Z6: Consumo Kg/lt | AA6: Custo/Kg | AB6: Custo Total | AC6: Consumo Kg/lt | AD6: Custo/Kg | AE6: Custo Total | AF6: Consumo Kg/lt | AG6: Custo/Kg | AH6: Custo Total | AI6: Consumo Kg/lt | AJ6: Custo/Kg | AK6: Custo Total | AL6: Consumo Kg/lt | AM6: Custo/Kg | AN6: Custo Total
A7: Anodo de Cobre | B7: 56574 | C7: 2500 | D7: 250 | E7: 0 | F7: 0 | G7: =F7*E7 -> 0 | H7: 0 | I7: 0 | J7: =I7*H7 -> 0 | K7: 10 | L7: 66.98 | M7: =L7*K7 -> 669.8 | N7: 10 | O7: 66.98 | P7: =O7*N7 -> 669.8 | Q7: 10 | R7: 66.98 | S7: =R7*Q7 -> 669.8 | T7: 10 | U7: 66.98 | V7: =U7*T7 -> 669.8 | W7: 0 | X7: 0 | Y7: =X7*W7 -> 0 | Z7: 0 | AA7: 0 | AB7: =AA7*Z7 -> 0 | AC7: 0 | AD7: 0 | AE7: =AD7*AC7 -> 0 | AF7: 0 | AG7: 0 | AH7: =AG7*AF7 -> 0 | AI7: 0 | AJ7: 0 | AK7: =AJ7*AI7 -> 0 | AL7: 0 | AM7: 0 | AN7: =AM7*AL7 -> 0
A8: ENVIROCOPPER ADJUSTER H | C8: 2500 | D8: 1 | E8: 0 | F8: 0 | G8: =F8*E8 -> 0 | H8: 0 | I8: 0 | J8: =I8*H8 -> 0 | K8: 16 | L8: 10.11 | M8: =L8*K8 -> 161.76 | N8: 15 | O8: 10.11 | P8: =O8*N8 -> 151.65 | Q8: 18 | R8: 0 | S8: =R8*Q8 -> 0 | T8: 15 | U8: 0 | V8: =U8*T8 -> 0 | W8: 0 | X8: 0 | Y8: =X8*W8 -> 0 | Z8: 0 | AA8: 0 | AB8: =AA8*Z8 -> 0 | AC8: 0 | AD8: 0 | AE8: =AD8*AC8 -> 0 | AF8: 0 | AG8: 0 | AH8: =AG8*AF8 -> 0 | AI8: 0 | AJ8: 0 | AK8: =AJ8*AI8 -> 0 | AL8: 0 | AM8: 0 | AN8: =AM8*AL8 -> 0
A9: ENVIROCOPPER BRIGHTENER | B9: 56579 | C9: 2500 | D9: 1 | E9: 0 | F9: 0 | G9: =F9*E9 -> 0 | H9: 0 | I9: 0 | J9: =I9*H9 -> 0 | K9: 8 | L9: 8.63 | M9: =L9*K9 -> 69.04 | N9: 7 | O9: 8.63 | P9: =O9*N9 -> 60.41 | Q9: 9 | R9: 0 | S9: =R9*Q9 -> 0 | T9: 10 | U9: 0 | V9: =U9*T9 -> 0 | W9: 0 | X9: 0 | Y9: =X9*W9 -> 0 | Z9: 0 | AA9: 0 | AB9: =AA9*Z9 -> 0 | AC9: 0 | AD9: 0 | AE9: =AD9*AC9 -> 0 | AF9: 0 | AG9: 0 | AH9: =AG9*AF9 -> 0 | AI9: 0 | AJ9: 0 | AK9: =AJ9*AI9 -> 0 | AL9: 0 | AM9: 0 | AN9: =AM9*AL9 -> 0
A10: ENVIROCOPPER MAKE-UP | C10: 0 | D10: 0 | E10: 0 | F10: 0 | G10: =F10*E10 -> 0 | H10: 0 | I10: 0 | J10: =I10*H10 -> 0 | K10: 40 | L10: 81.66 | M10: =L10*K10 -> 3266.4 | N10: 38 | O10: 81.66 | P10: =O10*N10 -> 3103.08 | Q10: 42 | R10: 0 | S10: =R10*Q10 -> 0 | T10: 35 | U10: 0 | V10: =U10*T10 -> 0 | W10: 0 | X10: 0 | Y10: =X10*W10 -> 0 | Z10: 0 | AA10: 0 | AB10: =AA10*Z10 -> 0 | AC10: 0 | AD10: 0 | AE10: =AD10*AC10 -> 0 | AF10: 0 | AG10: 0 | AH10: =AG10*AF10 -> 0 | AI10: 0 | AJ10: 0 | AK10: =AJ10*AI10 -> 0 | AL10: 0 | AM10: 0 | AN10: =AM10*AL10 -> 0
A11: ENVIROCOPPER REFINER | B11: 64964 | C11: 0 | D11: 0 | E11: 0 | F11: 0 | G11: =F11*E11 -> 0 | H11: 0 | I11: 0 | J11: =I11*H11 -> 0 | K11: 25 | L11: 85.68 | M11: =L11*K11 -> 2142 | N11: 24 | O11: 85.68 | P11: =O11*N11 -> 2056.32 | Q11: 26 | R11: 0 | S11: =R11*Q11 -> 0 | T11: 30 | U11: 0 | V11: =U11*T11 -> 0 | W11: 0 | X11: 0 | Y11: =X11*W11 -> 0 | Z11: 0 | AA11: 0 | AB11: =AA11*Z11 -> 0 | AC11: 0 | AD11: 0 | AE11: =AD11*AC11 -> 0 | AF11: 0 | AG11: 0 | AH11: =AG11*AF11 -> 0 | AI11: 0 | AJ11: 0 | AK11: =AJ11*AI11 -> 0 | AL11: 0 | AM11: 0 | AN11: =AM11*AL11 -> 0
A12: ENVIROCOPPER SOLUTION | C12: 0 | D12: 0 | E12: 0 | F12: 0 | G12: =F12*E12 -> 0 | H12: 0 | I12: 0 | J12: =I12*H12 -> 0 | K12: 180 | L12: 42.43 | M12: =L12*K12 -> 7637.4 | N12: 175 | O12: 42.43 | P12: =O12*N12 -> 7425.25 | Q12: 200 | R12: 0 | S12: =R12*Q12 -> 0 | T12: 175 | U12: 0 | V12: =U12*T12 -> 0 | W12: 0 | X12: 0 | Y12: =X12*W12 -> 0 | Z12: 0 | AA12: 0 | AB12: =AA12*Z12 -> 0 | AC12: 0 | AD12: 0 | AE12: =AD12*AC12 -> 0 | AF12: 0 | AG12: 0 | AH12: =AG12*AF12 -> 0 | AI12: 0 | AJ12: 0 | AK12: =AJ12*AI12 -> 0 | AL12: 0 | AM12: 0 | AN12: =AM12*AL12 -> 0
A13: ENVIROCOPPER WETTER | C13: 0 | D13: 0 | E13: 0 | F13: 0 | G13: =F13*E13 -> 0 | H13: 0 | I13: 0 | J13: =I13*H13 -> 0 | K13: 3 | L13: 7.69 | M13: =L13*K13 -> 23.07 | N13: 2 | O13: 7.69 | P13: =O13*N13 -> 15.38 | Q13: 3 | R13: 0 | S13: =R13*Q13 -> 0 | T13: 2 | U13: 0 | V13: =U13*T13 -> 0 | W13: 0 | X13: 0 | Y13: =X13*W13 -> 0 | Z13: 0 | AA13: 0 | AB13: =AA13*Z13 -> 0 | AC13: 0 | AD13: 0 | AE13: =AD13*AC13 -> 0 | AF13: 0 | AG13: 0 | AH13: =AG13*AF13 -> 0 | AI13: 0 | AJ13: 0 | AK13: =AJ13*AI13 -> 0 | AL13: 0 | AM13: 0 | AN13: =AM13*AL13 -> 0
C14: 0 | D14: 0 | E14: 0 | F14: 0 | G14: =F14*E14 -> 0 | H14: 0 | I14: 0 | J14: =I14*H14 -> 0 | M14: =L14*K14 -> 0 | N14: 0 | O14: 0 | P14: =O14*N14 -> 0 | Q14: 0 | R14: 0 | S14: =R14*Q14 -> 0 | T14: 0 | U14: 0 | V14: =U14*T14 -> 0 | W14: 0 | X14: 0 | Y14: =X14*W14 -> 0 | Z14: 0 | AA14: 0 | AB14: =AA14*Z14 -> 0 | AC14: 0 | AD14: 0 | AE14: =AD14*AC14 -> 0 | AF14: 0 | AG14: 0 | AH14: =AG14*AF14 -> 0 | AI14: 0 | AJ14: 0 | AK14: =AJ14*AI14 -> 0 | AL14: 0 | AM14: 0 | AN14: =AM14*AL14 -> 0
C15: 0 | D15: 0 | E15: 0 | F15: 0 | G15: =F15*E15 -> 0 | H15: 0 | I15: 0 | J15: =I15*H15 -> 0 | K15: 0 | L15: 0 | M15: =L15*K15 -> 0 | N15: 0 | O15: 0 | P15: =O15*N15 -> 0 | Q15: 0 | R15: 0 | S15: =R15*Q15 -> 0 | T15: 0 | U15: 0 | V15: =U15*T15 -> 0 | W15: 0 | X15: 0 | Y15: =X15*W15 -> 0 | Z15: 0 | AA15: 0 | AB15: =AA15*Z15 -> 0 | AC15: 0 | AD15: 0 | AE15: =AD15*AC15 -> 0 | AF15: 0 | AG15: 0 | AH15: =AG15*AF15 -> 0 | AI15: 0 | AJ15: 0 | AK15: =AJ15*AI15 -> 0 | AL15: 0 | AM15: 0 | AN15: =AM15*AL15 -> 0
F16: Total | G16: =SUM(G7:G15) -> 0 | I16: Total | J16: =SUM(J7:J15) -> 0 | L16: Total | M16: =SUM(M7:M15) -> 13969.47 | O16: Total | P16: =SUM(P7:P15) -> 13481.89 | R16: Total | S16: =SUM(S7:S15) -> 669.8 | U16: Total | V16: =SUM(V7:V15) -> 669.8 | X16: Total | Y16: =SUM(Y7:Y15) -> 0 | AA16: Total | AB16: =SUM(AB7:AB15) -> 0 | AD16: Total | AE16: =SUM(AE7:AE15) -> 0 | AG16: Total | AH16: =SUM(AH7:AH15) -> 0 | AJ16: Total | AK16: =SUM(AK7:AK15) -> 0 | AM16: Total | AN16: =SUM(AN7:AN15) -> 0

Sheet Níquel Strik
A2: Menu
A3: Níquel Strik
E5: 45292 | F5: 45292 | G5: 45292 | H5: 45323 | I5: 45323 | J5: 45323 | K5: 45352 | L5: 45352 | M5: 45352 | N5: 45383 | O5: 45383 | P5: 45383 | Q5: 45413 | R5: 45413 | S5: 45413 | T5: 45444 | U5: 45444 | V5: 45444 | W5: 45474 | X5: 45474 | Y5: 45474 | Z5: 45505 | AA5: 45505 | AB5: 45505 | AC5: 45536 | AD5: 45536 | AE5: 45536 | AF5: 45566 | AG5: 45566 | AH5: 45566 | AI5: 45597 | AJ5: 45597 | AK5: 45597 | AL5: 45627 | AM5: 45627 | AN5: 45627
A6: Produto | B6: ID | C6: Volume tanque / lts | D6: Concentração g/lt | E6: Consumo Kg/lt | F6: Custo/Kg | G6: Custo Total | H6: Consumo Kg/lt | I6: Custo/Kg | J6: Custo Total | K6: Consumo Kg/lt | L6: Custo Kg/lt | M6: Custo Total | N6: Consumo Kg/lt | O6: Custo/Kg | P6: Custo Total | Q6: Consumo Kg/lt | R6: Custo/Kg | S6: Custo Total | T6: Consumo Kg/lt | U6: Custo/Kg | V6: Custo Total | W6: Consumo Kg/lt | X6: Custo/Kg | Y6: Custo Total | Z6: Consumo Kg/lt | AA6: Custo/Kg | AB6: Custo Total | AC6: Consumo Kg/lt | AD6: Custo/Kg | AE6: Custo Total | AF6: Consumo Kg/lt | AG6: Custo/Kg | AH6: Custo Total | AI6: Consumo Kg/lt | AJ6: Custo/Kg | AK6: Custo Total | AL6: Consumo Kg/lt | AM6: Custo/Kg | AN6: Custo Total
A7: Ânodo de Níquel | B7: 56944 | C7: 3500 | D7: 275 | E7: 0 | F7: 0 | G7: =F7*E7 -> 0 | H7: 0 | I7: 5 | J7: =I7*H7 -> 0 | K7: 40 | L7: 141.9 | M7: =L7*K7 -> 5676 | N7: 15 | O7: 141.9 | P7: =O7*N7 -> 2128.5 | Q7: 42 | R7: 141.9 | S7: =R7*Q7 -> 5959.8 | T7: 42 | U7: 141.9 | V7: =U7*T7 -> 5959.8 | W7: 0 | X7: 5 | Y7: =X7*W7 -> 0 | Z7: 0 | AA7: 0 | AB7: =AA7*Z7 -> 0 | AC7: 0 | AD7: 0 | AE7: =AD7*AC7 -> 0 | AF7: 0 | AG7: 0 | AH7: =AG7*AF7 -> 0 | AI7: 0 | AJ7: 0 | AK7: =AJ7*AI7 -> 0 | AL7: 0 | AM7: 0 | AN7: =AM7*AL7 -> 0
A8: NIVELADOR MC INFINITY | B8: 73191 | C8: 3500 | D8: 70 | E8: 0 | F8: 0 | G8: =F8*E8 -> 0 | H8: 0 | I8: 0 | J8: =I8*H8 -> 0 | K8: 6 | L8: 30.78 | M8: =L8*K8 -> 184.68 | N8: 4 | O8: 30.78 | P8: =O8*N8 -> 123.12 | Q8: 6 | R8: 0 | S8: =R8*Q8 -> 0 | T8: 6 | U8: 0 | V8: =U8*T8 -> 0 | W8: 0 | X8: 0 | Y8: =X8*W8 -> 0 | Z8: 0 | AA8: 0 | AB8: =AA8*Z8 -> 0 | AC8: 0 | AD8: 0 | AE8: =AD8*AC8 -> 0 | AF8: 0 | AG8: 0 | AH8: =AG8*AF8 -> 0 | AI8: 0 | AJ8: 0 | AK8: =AJ8*AI8 -> 0 | AL8: 0 | AM8: 0 | AN8: =AM8*AL8 -> 0
A9: SULFATO DE NIQUEL SOLUCAO 60% | B9: 100490 | C9: 3500 | D9: 45 | E9: 0 | F9: 0 | G9: =F9*E9 -> 0 | H9: 0 | I9: 0 | J9: =I9*H9 -> 0 | K9: 50 | L9: 35.1 | M9: =L9*K9 -> 1755 | N9: 30 | O9: 35.1 | P9: =O9*N9 -> 1053 | Q9: 8 | R9: 0 | S9: =R9*Q9 -> 0 | T9: 5 | U9: 0 | V9: =U9*T9 -> 0 | W9: 0 | X9: 0 | Y9: =X9*W9 -> 0 | Z9: 0 | AA9: 0 | AB9: =AA9*Z9 -> 0 | AC9: 0 | AD9: 0 | AE9: =AD9*AC9 -> 0 | AF9: 0 | AG9: 0 | AH9: =AG9*AF9 -> 0 | AI9: 0 | AJ9: 0 | AK9: =AJ9*AI9 -> 0 | AL9: 0 | AM9: 0 | AN9: =AM9*AL9 -> 0
A10: MOLHADOR MC/P | B10: 56563 | C10: 3500 | D10: 0.75 | E10: 0 | F10: 0 | G10: =F10*E10 -> 0 | H10: 0 | I10: 0 | J10: =I10*H10 -> 0 | K10: 2.5 | L10: 9.08 | M10: =L10*K10 -> 22.7 | N10: 2 | O10: 9.08 | P10: =O10*N10 -> 18.16 | Q10: 2 | R10: 0 | S10: =R10*Q10 -> 0 | T10: 3 | U10: 0 | V10: =U10*T10 -> 0 | W10: 0 | X10: 0 | Y10: =X10*W10 -> 0 | Z10: 0 | AA10: 0 | AB10: =AA10*Z10 -> 0 | AC10: 0 | AD10: 0 | AE10: =AD10*AC10 -> 0 | AF10: 0 | AG10: 0 | AH10: =AG10*AF10 -> 0 | AI10: 0 | AJ10: 0 | AK10: =AJ10*AI10 -> 0 | AL10: 0 | AM10: 0 | AN10: =AM10*AL10 -> 0
A11: PURIFICADOR NIMC | B11: 56566 | C11: 3500 | D11: 10 | E11: 0 | F11: 0 | G11: =F11*E11 -> 0 | H11: 0 | I11: 0 | J11: =I11*H11 -> 0 | K11: 1.5 | L11: 18.75 | M11: =L11*K11 -> 28.125 | N11: 1 | O11: 28.5 | P11: =O11*N11 -> 28.5 | Q11: 1 | R11: 0 | S11: =R11*Q11 -> 0 | T11: 2 | U11: 0 | V11: =U11*T11 -> 0 | W11: 0 | X11: 0 | Y11: =X11*W11 -> 0 | Z11: 0 | AA11: 0 | AB11: =AA11*Z11 -> 0 | AC11: 0 | AD11: 0 | AE11: =AD11*AC11 -> 0 | AF11: 0 | AG11: 0 | AH11: =AG11*AF11 -> 0 | AI11: 0 | AJ11: 0 | AK11: =AJ11*AI11 -> 0 | AL11: 0 | AM11: 0 | AN11: =AM11*AL11 -> 0
B12: 65078 | C12: 3500 | D12: 10 | E12: 0 | F12: 0 | G12: =F12*E12 -> 0 | H12: 0 | I12: 0 | J12: =I12*H12 -> 0 | K12: 0 | L12: 0 | M12: =L12*K12 -> 0 | N12: 0 | O12: 0 | P12: =O12*N12 -> 0 | Q12: 0 | R12: 0 | S12: =R12*Q12 -> 0 | T12: 0 | U12: 0 | V12: =U12*T12 -> 0 | W12: 0 | X12: 0 | Y12: =X12*W12 -> 0 | Z12: 0 | AA12: 0 | AB12: =AA12*Z12 -> 0 | AC12: 0 | AD12: 0 | AE12: =AD12*AC12 -> 0 | AF12: 0 | AG12: 0 | AH12: =AG12*AF12 -> 0 | AI12: 0 | AJ12: 0 | AK12: =AJ12*AI12 -> 0 | AL12: 0 | AM12: 0 | AN12: =AM12*AL12 -> 0
B13: 56317 | C13: 0 | D13: 0 | E13: 0 | F13: 0 | G13: =F13*E13 -> 0 | H13: 0 | I13: 0 | J13: =I13*H13 -> 0 | K13: 0 | L13: 0 | M13: =L13*K13 -> 0 | N13: 0 | O13: 0 | P13: =O13*N13 -> 0 | Q13: 0 | R13: 0 | S13: =R13*Q13 -> 0 | T13: 0 | U13: 0 | V13: =U13*T13 -> 0 | W13: 0 | X13: 0 | Y13: =X13*W13 -> 0 | Z13: 0 | AA13: 0 | AB13: =AA13*Z13 -> 0 | AC13: 0 | AD13: 0 | AE13: =AD13*AC13 -> 0 | AF13: 0 | AG13: 0 | AH13: =AG13*AF13 -> 0 | AI13: 0 | AJ13: 0 | AK13: =AJ13*AI13 -> 0 | AL13: 0 | AM13: 0 | AN13: =AM13*AL13 -> 0
B14: 56576 | C14: 0 | D14: 0 | E14: 0 | H14: 0 | K14: 0 | L14: 0 | M14: =L14*K14 -> 0 | N14: 0
F15: Total | G15: =SUM(G7:G14) -> 0 | I15: Total | J15: =SUM(J7:J14) -> 0 | L15: Total | M15: =SUM(M7:M14) -> 7666.505 | O15: Total | P15: =SUM(P7:P14) -> 3351.28 | R15: Total | S15: =SUM(S7:S14) -> 5959.8 | U15: Total | V15: =SUM(V7:V14) -> 5959.8 | X15: Total | Y15: =SUM(Y7:Y14) -> 0 | AA15: Total | AB15: =SUM(AB7:AB14) -> 0 | AD15: Total | AE15: =SUM(AE7:AE14) -> 0 | AG15: Total | AH15: =SUM(AH7:AH14) -> 0 | AJ15: Total | AK15: =SUM(AK7:AK14) -> 0 | AM15: Total | AN15: =SUM(AN7:AN14) -> 0

Sheet Cobre Ácido
A2: Menu
A3: Cobre Ácido
E5: 45292 | F5: 45292 | G5: 45292 | H5: 45323 | I5: 45323 | J5: 45323 | K5: 45352 | L5: 45352 | M5: 45352 | N5: 45383 | O5: 45383 | P5: 45383 | Q5: 45413 | R5: 45413 | S5: 45413 | T5: 45444 | U5: 45444 | V5: 45444 | W5: 45474 | X5: 45474 | Y5: 45474 | Z5: 45505 | AA5: 45505 | AB5: 45505 | AC5: 45536 | AD5: 45536 | AE5: 45536 | AF5: 45566 | AG5: 45566 | AH5: 45566 | AI5: 45597 | AJ5: 45597 | AK5: 45597 | AL5: 45627 | AM5: 45627 | AN5: 45627
A6: Produto | B6: ID | C6: Volume tanque / lts | D6: Concentração g/lt | E6: Consumo Kg/lt | F6: Custo/Kg | G6: Custo Total | H6: Consumo Kg/lt | I6: Custo/Kg | J6: Custo Total | K6: Consumo Kg/lt | L6: Custo Kg/lt | M6: Custo Total | N6: Consumo Kg/lt | O6: Custo/Kg | P6: Custo Total | Q6: Consumo Kg/lt | R6: Custo/Kg | S6: Custo Total | T6: Consumo Kg/lt | U6: Custo/Kg | V6: Custo Total | W6: Consumo Kg/lt | X6: Custo/Kg | Y6: Custo Total | Z6: Consumo Kg/lt | AA6: Custo/Kg | AB6: Custo Total | AC6: Consumo Kg/lt | AD6: Custo/Kg | AE6: Custo Total | AF6: Consumo Kg/lt | AG6: Custo/Kg | AH6: Custo Total | AI6: Consumo Kg/lt | AJ6: Custo/Kg | AK6: Custo Total | AL6: Consumo Kg/lt | AM6: Custo/Kg | AN6: Custo Total
A7: Sufato de Cobre | B7: 56951 | C7: 0 | D7: 0 | E7: 0 | F7: 0 | G7: =F7*E7 -> 0 | H7: 0 | I7: 0 | J7: =I7*H7 -> 0 | K7: 110 | L7: 24.98 | M7: =L7*K7 -> 2747.8 | N7: 55 | O7: 24.98 | P7: =O7*N7 -> 1373.9 | Q7: 75 | R7: 24.98 | S7: =R7*Q7 -> 1873.5 | T7: 50 | U7: 24.98 | V7: =U7*T7 -> 1249 | W7: 0 | X7: 0 | Y7: =X7*W7 -> 0 | Z7: 0 | AA7: 0 | AB7: =AA7*Z7 -> 0 | AC7: 0 | AD7: 0 | AE7: =AD7*AC7 -> 0 | AF7: 0 | AG7: 0 | AH7: =AG7*AF7 -> 0 | AI7: 0 | AJ7: 0 | AK7: =AJ7*AI7 -> 0 | AL7: 0 | AM7: 5 | AN7: =AM7*AL7 -> 0
A8: Ácido Sulfurico | B8: 56124 | C8: 0 | D8: 0 | E8: 0 | F8: 0 | G8: =F8*E8 -> 0 | H8: 0 | I8: 0 | J8: =I8*H8 -> 0 | K8: 35 | L8: 3.5 | M8: =L8*K8 -> 122.5 | N8: 8 | O8: 3.5 | P8: =O8*N8 -> 28 | Q8: 15 | R8: 3.5 | S8: =R8*Q8 -> 52.5 | T8: 13.5 | U8: 3.5 | V8: =U8*T8 -> 47.25 | W8: 0 | X8: 0 | Y8: =X8*W8 -> 0 | Z8: 0 | AA8: 0 | AB8: =AA8*Z8 -> 0 | AC8: 0 | AD8: 0 | AE8: =AD8*AC8 -> 0 | AF8: 0 | AG8: 0 | AH8: =AG8*AF8 -> 0 | AI8: 0 | AJ8: 0 | AK8: =AJ8*AI8 -> 0 | AL8: 0 | AM8: 0 | AN8: =AM8*AL8 -> 0
A9: Anodo de Cobre | C9: 0 | D9: 0 | E9: 0 | F9: 0 | G9: =F9*E9 -> 0 | H9: 0 | I9: 0 | J9: =I9*H9 -> 0 | K9: 300 | L9: 66.98 | M9: =L9*K9 -> 20094 | N9: 280 | O9: 66.98 | P9: =O9*N9 -> 18754.4 | Q9: 0 | R9: 0 | S9: =R9*Q9 -> 0 | T9: 231 | U9: 66.98 | V9: =U9*T9 -> 15472.38 | W9: 0 | X9: 0 | Y9: =X9*W9 -> 0 | Z9: 0 | AA9: 0 | AB9: =AA9*Z9 -> 0 | AC9: 0 | AD9: 0 | AE9: =AD9*AC9 -> 0 | AF9: 0 | AG9: 0 | AH9: =AG9*AF9 -> 0 | AI9: 0 | AJ9: 0 | AK9: =AJ9*AI9 -> 0 | AL9: 0 | AM9: 0 | AN9: =AM9*AL9 -> 0
A10: MC COPPER EVOLUTION M.U | B10: 71927 | C10: 0 | D10: 0 | E10: 0 | F10: 0 | G10: =F10*E10 -> 0 | H10: 0 | I10: 0 | J10: =I10*H10 -> 0 | K10: 12 | L10: 79.33 | M10: =L10*K10 -> 951.96 | N10: 11 | O10: 79.33 | P10: =O10*N10 -> 872.63 | Q10: 13 | R10: 0 | S10: =R10*Q10 -> 0 | T10: 18 | U10: 0 | V10: =U10*T10 -> 0 | W10: 0 | X10: 0 | Y10: =X10*W10 -> 0 | Z10: 0 | AA10: 0 | AB10: =AA10*Z10 -> 0 | AC10: 0 | AD10: 0 | AE10: =AD10*AC10 -> 0 | AF10: 0 | AG10: 0 | AH10: =AG10*AF10 -> 0 | AI10: 0 | AJ10: 0 | AK10: =AJ10*AI10 -> 0 | AL10: 0 | AM10: 0 | AN10: =AM10*AL10 -> 0
A11: MC COPPER EVOLUTION PARTE A | B11: 71928 | C11: 0 | D11: 0 | E11: 0 | F11: 0 | G11: =F11*E11 -> 0 | H11: 0 | I11: 0 | J11: =I11*H11 -> 0 | K11: 8 | L11: 84.02 | M11: =L11*K11 -> 672.16 | N11: 9 | O11: 84.02 | P11: =O11*N11 -> 756.18 | Q11: 10 | R11: 0 | S11: =R11*Q11 -> 0 | T11: 15 | U11: 0 | V11: =U11*T11 -> 0 | W11: 0 | X11: 0 | Y11: =X11*W11 -> 0 | Z11: 0 | AA11: 0 | AB11: =AA11*Z11 -> 0 | AC11: 0 | AD11: 0 | AE11: =AD11*AC11 -> 0 | AF11: 0 | AG11: 0 | AH11: =AG11*AF11 -> 0 | AI11: 0 | AJ11: 0 | AK11: =AJ11*AI11 -> 0 | AL11: 0 | AM11: 0 | AN11: =AM11*AL11 -> 0
A12: MC COPPER EVOLUTION PARTE B | B12: 71930 | C12: 0 | D12: 0 | E12: 0 | F12: 0 | G12: =F12*E12 -> 0 | H12: 0 | I12: 0 | J12: =I12*H12 -> 0 | K12: 6 | L12: 78.94 | M12: =L12*K12 -> 473.64 | N12: 5 | O12: 78.94 | P12: =O12*N12 -> 394.7 | Q12: 7 | R12: 0 | S12: =R12*Q12 -> 0 | T12: 10 | U12: 0 | V12: =U12*T12 -> 0 | W12: 0 | X12: 0 | Y12: =X12*W12 -> 0 | Z12: 0 | AA12: 0 | AB12: =AA12*Z12 -> 0 | AC12: 0 | AD12: 0 | AE12: =AD12*AC12 -> 0 | AF12: 0 | AG12: 0 | AH12: =AG12*AF12 -> 0 | AI12: 0 | AJ12: 0 | AK12: =AJ12*AI12 -> 0 | AL12: 0 | AM12: 0 | AN12: =AM12*AL12 -> 0
A13: MC COPPER EVOLUTION UMECTANTE | B13: 71926 | C13: 0 | D13: 0 | E13: 0 | F13: 0 | G13: =F13*E13 -> 0 | H13: 0 | I13: 0 | J13: =I13*H13 -> 0 | K13: 10 | L13: 44.75 | M13: =L13*K13 -> 447.5 | N13: 9 | O13: 44.75 | P13: =O13*N13 -> 402.75 | Q13: 10 | R13: 0 | S13: =R13*Q13 -> 0 | T13: 5 | U13: 0 | V13: =U13*T13 -> 0 | W13: 0 | X13: 0 | Y13: =X13*W13 -> 0 | Z13: 0 | AA13: 0 | AB13: =AA13*Z13 -> 0 | AC13: 0 | AD13: 0 | AE13: =AD13*AC13 -> 0 | AF13: 0 | AG13: 0 | AH13: =AG13*AF13 -> 0 | AI13: 0 | AJ13: 0 | AK13: =AJ13*AI13 -> 0 | AL13: 0 | AM13: 0 | AN13: =AM13*AL13 -> 0
A14: MC COPPER CORRECTOR | B14: 56332 | C14: 0 | D14: 0 | E14: 0 | F14: 0 | G14: =F14*E14 -> 0 | K14: 5 | L14: 43.8 | M14: =L14*K14 -> 219 | N14: 4 | O14: 43.8 | P14: =O14*N14 -> 175.2 | Q14: 5 | R14: 0 | S14: =R14*Q14 -> 0 | T14: 6 | U14: 0 | V14: =U14*T14 -> 0
F15: Total | G15: =SUM(G7:G14) -> 0 | I15: Total | J15: =SUM(J7:J14) -> 0 | L15: Total | M15: =SUM(M7:M14) -> 25728.56 | O15: Total | P15: =SUM(P7:P14) -> 22757.76 | R15: Total | S15: =SUM(S7:S14) -> 1926 | U15: Total | V15: =SUM(V7:V14) -> 16768.63 | X15: Total | Y15: =SUM(Y7:Y14) -> 0 | AA15: Total | AB15: =SUM(AB7:AB14) -> 0 | AD15: Total | AE15: =SUM(AE7:AE14) -> 0 | AG15: Total | AH15: =SUM(AH7:AH14) -> 0 | AJ15: Total | AK15: =SUM(AK7:AK14) -> 0 | AM15: Total | AN15: =SUM(AN7:AN14) -> 0

Sheet Desengraxante Quí
A2: Menu
A3: Desengraxante Químico
E5: 45292 | F5: 45292 | G5: 45292 | H5: 45323 | I5: 45323 | J5: 45323 | K5: 45352 | L5: 45352 | M5: 45352 | N5: 45383 | O5: 45383 | P5: 45383 | Q5: 45413 | R5: 45413 | S5: 45413 | T5: 45444 | U5: 45444 | V5: 45444 | W5: 45474 | X5: 45474 | Y5: 45474 | Z5: 45505 | AA5: 45505 | AB5: 45505 | AC5: 45536 | AD5: 45536 | AE5: 45536 | AF5: 45566 | AG5: 45566 | AH5: 45566 | AI5: 45597 | AJ5: 45597 | AK5: 45597 | AL5: 45627 | AM5: 45627 | AN5: 45627
A6: Produto | B6: ID | C6: Volume tanque / lts | D6: Concentração g/lt | E6: Consumo Kg/lt | F6: Custo/Kg | G6: Custo Total | H6: Consumo Kg/lt | I6: Custo/Kg | J6: Custo Total | K6: Consumo Kg/lt | L6: Custo Kg/lt | M6: Custo Total | N6: Consumo Kg/lt | O6: Custo/Kg | P6: Custo Total | Q6: Consumo Kg/lt | R6: Custo/Kg | S6: Custo Total | T6: Consumo Kg/lt | U6: Custo/Kg | V6: Custo Total | W6: Consumo Kg/lt | X6: Custo/Kg | Y6: Custo Total | Z6: Consumo Kg/lt | AA6: Custo/Kg | AB6: Custo Total | AC6: Consumo Kg/lt | AD6: Custo/Kg | AE6: Custo Total | AF6: Consumo Kg/lt | AG6: Custo/Kg | AH6: Custo Total | AI6: Consumo Kg/lt | AJ6: Custo/Kg | AK6: Custo Total | AL6: Consumo Kg/lt | AM6: Custo/Kg | AN6: Custo Total
A7: METAL CLEAN FE-05 | B7: 56951 | C7: 0 | D7: 0 | E7: 0 | F7: 5 | G7: =F7*E7 -> 0 | H7: 0 | I7: 0 | J7: =I7*H7 -> 0 | K7: 5 | L7: 11.61 | M7: =L7*K7 -> 58.05 | N7: 1 | O7: 11.61 | P7: =O7*N7 -> 11.61 | Q7: 0 | R7: 0 | S7: =R7*Q7 -> 0 | T7: 0 | U7: 0 | V7: =U7*T7 -> 0 | W7: 0 | X7: 10 | Y7: =X7*W7 -> 0 | Z7: 0 | AA7: 0 | AB7: =AA7*Z7 -> 0 | AC7: 0 | AD7: 12 | AE7: =AD7*AC7 -> 0 | AF7: 0 | AG7: 0 | AH7: =AG7*AF7 -> 0 | AI7: 0 | AJ7: 0 | AK7: =AJ7*AI7 -> 0 | AL7: 0 | AM7: 15 | AN7: =AM7*AL7 -> 0
B8: 56124 | C8: 0 | D8: 0 | E8: 0 | F8: 0 | G8: =F8*E8 -> 0 | H8: 0 | I8: 0 | J8: =I8*H8 -> 0 | K8: 0 | L8: 0 | M8: =L8*K8 -> 0 | N8: 0 | O8: 0 | P8: =O8*N8 -> 0 | Q8: 0 | R8: 0 | S8: =R8*Q8 -> 0 | T8: 0 | U8: 0 | V8: =U8*T8 -> 0 | W8: 0 | X8: 0 | Y8: =X8*W8 -> 0 | Z8: 0 | AA8: 0 | AB8: =AA8*Z8 -> 0 | AC8: 0 | AD8: 0 | AE8: =AD8*AC8 -> 0 | AF8: 0 | AG8: 0 | AH8: =AG8*AF8 -> 0 | AI8: 0 | AJ8: 0 | AK8: =AJ8*AI8 -> 0 | AL8: 0 | AM8: 0 | AN8: =AM8*AL8 -> 0
C9: 0 | D9: 0 | E9: 0 | F9: 0 | G9: =F9*E9 -> 0 | H9: 0 | I9: 0 | J9: =I9*H9 -> 0 | K9: 0 | L9: 0 | M9: =L9*K9 -> 0 | N9: 0 | O9: 0 | P9: =O9*N9 -> 0 | Q9: 0 | R9: 0 | S9: =R9*Q9 -> 0 | T9: 0 | U9: 0 | V9: =U9*T9 -> 0 | W9: 0 | X9: 0 | Y9: =X9*W9 -> 0 | Z9: 0 | AA9: 0 | AB9: =AA9*Z9 -> 0 | AC9: 0 | AD9: 0 | AE9: =AD9*AC9 -> 0 | AF9: 0 | AG9: 0 | AH9: =AG9*AF9 -> 0 | AI9: 0 | AJ9: 0 | AK9: =AJ9*AI9 -> 0 | AL9: 0 | AM9: 0 | AN9: =AM9*AL9 -> 0
B10: 71927 | C10: 0 | D10: 0 | E10: 0 | F10: 0 | G10: =F10*E10 -> 0 | H10: 0 | I10: 0 | J10: =I10*H10 -> 0 | K10: 0 | L10: 0 | M10: =L10*K10 -> 0 | N10: 0 | O10: 0 | P10: =O10*N10 -> 0 | Q10: 0 | R10: 0 | S10: =R10*Q10 -> 0 | T10: 0 | U10: 0 | V10: =U10*T10 -> 0 | W10: 0 | X10: 0 | Y10: =X10*W10 -> 0 | Z10: 0 | AA10: 0 | AB10: =AA10*Z10 -> 0 | AC10: 0 | AD10: 0 | AE10: =AD10*AC10 -> 0 | AF10: 0 | AG10: 0 | AH10: =AG10*AF10 -> 0 | AI10: 0 | AJ10: 0 | AK10: =AJ10*AI10 -> 0 | AL10: 0 | AM10: 0 | AN10: =AM10*AL10 -> 0
B11: 71928 | C11: 0 | D11: 0 | E11: 0 | F11: 0 | G11: =F11*E11 -> 0 | H11: 0 | I11: 0 | J11: =I11*H11 -> 0 | K11: 0 | L11: 0 | M11: =L11*K11 -> 0 | N11: 0 | O11: 0 | P11: =O11*N11 -> 0 | Q11: 0 | R11: 0 | S11: =R11*Q11 -> 0 | T11: 0 | U11: 0 | V11: =U11*T11 -> 0 | W11: 0 | X11: 0 | Y11: =X11*W11 -> 0 | Z11: 0 | AA11: 0 | AB11: =AA11*Z11 -> 0 | AC11: 0 | AD11: 0 | AE11: =AD11*AC11 -> 0 | AF11: 0 | AG11: 0 | AH11: =AG11*AF11 -> 0 | AI11: 0 | AJ11: 0 | AK11: =AJ11*AI11 -> 0 | AL11: 0 | AM11: 0 | AN11: =AM11*AL11 -> 0
B12: 71930 | C12: 0 | D12: 0 | E12: 0 | F12: 0 | G12: =F12*E12 -> 0 | H12: 0 | I12: 0 | J12: =I12*H12 -> 0 | K12: 0 | L12: 0 | M12: =L12*K12 -> 0 | N12: 0 | O12: 0 | P12: =O12*N12 -> 0 | Q12: 0 | R12: 0 | S12: =R12*Q12 -> 0 | T12: 0 | U12: 0 | V12: =U12*T12 -> 0 | W12: 0 | X12: 0 | Y12: =X12*W12 -> 0 | Z12: 0 | AA12: 0 | AB12: =AA12*Z12 -> 0 | AC12: 0 | AD12: 0 | AE12: =AD12*AC12 -> 0 | AF12: 0 | AG12: 0 | AH12: =AG12*AF12 -> 0 | AI12: 0 | AJ12: 0 | AK12: =AJ12*AI12 -> 0 | AL12: 0 | AM12: 0 | AN12: =AM12*AL12 -> 0
B13: 71926 | C13: 0 | D13: 0 | E13: 0 | F13: 0 | G13: =F13*E13 -> 0 | H13: 0 | I13: 0 | J13: =I13*H13 -> 0 | K13: 0 | L13: 0 | M13: =L13*K13 -> 0 | N13: 0 | O13: 0 | P13: =O13*N13 -> 0 | Q13: 0 | R13: 0 | S13: =R13*Q13 -> 0 | T13: 0 | U13: 0 | V13: =U13*T13 -> 0 | W13: 0 | X13: 0 | Y13: =X13*W13 -> 0 | Z13: 0 | AA13: 0 | AB13: =AA13*Z13 -> 0 | AC13: 0 | AD13: 0 | AE13: =AD13*AC13 -> 0 | AF13: 0 | AG13: 0 | AH13: =AG13*AF13 -> 0 | AI13: 0 | AJ13: 0 | AK13: =AJ13*AI13 -> 0 | AL13: 0 | AM13: 0 | AN13: =AM13*AL13 -> 0
B14: 56332 | C14: 0 | D14: 0 | E14: 0 | G14: =F14*E14 -> 0 | K14: 0 | L14: 0 | M14: =L14*K14 -> 0 | AD14: 0
F15: Total | G15: =SUM(G7:G14) -> 0 | I15: Total | J15: =SUM(J7:J14) -> 0 | L15: Total | M15: =SUM(M7:M14) -> 58.05 | O15: Total | P15: =SUM(P7:P14) -> 11.61 | R15: Total | S15: =SUM(S7:S14) -> 0 | U15: Total | V15: =SUM(V7:V14) -> 0 | X15: Total | Y15: =SUM(Y7:Y14) -> 0 | AA15: Total | AB15: =SUM(AB7:AB14) -> 0 | AD15: Total | AE15: =SUM(AE7:AE14) -> 0 | AG15: Total | AH15: =SUM(AH7:AH14) -> 0 | AJ15: Total | AK15: =SUM(AK7:AK14) -> 0 | AM15: Total | AN15: =SUM(AN7:AN14) -> 0

Sheet Níquel Brilhante
A2: Menu
A3: Níquel Brilhante
E5: 45292 | F5: 45292 | G5: 45292 | H5: 45323 | I5: 45323 | J5: 45323 | K5: 45352 | L5: 45352 | M5: 45352 | N5: 45383 | O5: 45383 | P5: 45383 | Q5: 45413 | R5: 45413 | S5: 45413 | T5: 45444 | U5: 45444 | V5: 45444 | W5: 45474 | X5: 45474 | Y5: 45474 | Z5: 45505 | AA5: 45505 | AB5: 45505 | AC5: 45536 | AD5: 45536 | AE5: 45536 | AF5: 45566 | AG5: 45566 | AH5: 45566 | AI5: 45597 | AJ5: 45597 | AK5: 45597 | AL5: 45627 | AM5: 45627 | AN5: 45627
A6: Produto | B6: ID | C6: Volume tanque / lts | D6: Concentração g/lt | E6: Consumo Kg/lt | F6: Custo/Kg | G6: Custo Total | H6: Consumo Kg/lt | I6: Custo/Kg | J6: Custo Total | K6: Consumo Kg/lt | L6: Custo Kg/lt | M6: Custo Total | N6: Consumo Kg/lt | O6: Custo/Kg | P6: Custo Total | Q6: Consumo Kg/lt | R6: Custo/Kg | S6: Custo Total | T6: Consumo Kg/lt | U6: Custo/Kg | V6: Custo Total | W6: Consumo Kg/lt | X6: Custo/Kg | Y6: Custo Total | Z6: Consumo Kg/lt | AA6: Custo/Kg | AB6: Custo Total | AC6: Consumo Kg/lt | AD6: Custo/Kg | AE6: Custo Total | AF6: Consumo Kg/lt | AG6: Custo/Kg | AH6: Custo Total | AI6: Consumo Kg/lt | AJ6: Custo/Kg | AK6: Custo Total | AL6: Consumo Kg/lt | AM6: Custo/Kg | AN6: Custo Total
A7: Ânodo de Níquel | B7: 56944 | C7: 0 | D7: 0 | E7: 0 | F7: 0 | G7: =F7*E7 -> 0 | H7: 0 | I7: 0 | J7: =I7*H7 -> 0 | K7: 180 | L7: 141.9 | M7: =L7*K7 -> 25542 | N7: 170 | O7: 141.9 | P7: =O7*N7 -> 24123 | Q7: 0 | R7: 141.9 | S7: =R7*Q7 -> 0 | T7: 0 | U7: 141.9 | V7: =U7*T7 -> 0 | W7: 0 | X7: 0 | Y7: =X7*W7 -> 0 | Z7: 0 | AA7: 0 | AB7: =AA7*Z7 -> 0 | AC7: 0 | AD7: 0 | AE7: =AD7*AC7 -> 0 | AF7: 0 | AG7: 0 | AH7: =AG7*AF7 -> 0 | AI7: 0 | AJ7: 0 | AK7: =AJ7*AI7 -> 0 | AL7: 0 | AM7: 0 | AN7: =AM7*AL7 -> 0
A8: SULFATO DE NIQUEL SOLUCAO 60% | B8: 73191 | C8: 0 | D8: 0 | E8: 0 | F8: 0 | G8: =F8*E8 -> 0 | H8: 0 | I8: 0 | J8: =I8*H8 -> 0 | K8: 175 | L8: 35.1 | M8: =L8*K8 -> 6142.5 | N8: 165 | O8: 22.65 | P8: =O8*N8 -> 3737.25 | Q8: 35 | R8: 0 | S8: =R8*Q8 -> 0 | T8: 25 | U8: 0 | V8: =U8*T8 -> 0 | W8: 0 | X8: 0 | Y8: =X8*W8 -> 0 | Z8: 0 | AA8: 0 | AB8: =AA8*Z8 -> 0 | AC8: 0 | AD8: 0 | AE8: =AD8*AC8 -> 0 | AF8: 0 | AG8: 0 | AH8: =AG8*AF8 -> 0 | AI8: 0 | AJ8: 0 | AK8: =AJ8*AI8 -> 0 | AL8: 0 | AM8: 0 | AN8: =AM8*AL8 -> 0
A9: Cloreto de Níquel | B9: 100490 | C9: 0 | D9: 0 | E9: 0 | F9: 0 | G9: =F9*E9 -> 0 | H9: 0 | I9: 0 | J9: =I9*H9 -> 0 | K9: 9 | L9: 40.56 | M9: =L9*K9 -> 365.04 | N9: 8 | O9: 40.56 | P9: =O9*N9 -> 324.48 | Q9: 4 | R9: 40.56 | S9: =R9*Q9 -> 162.24 | T9: 3 | U9: 40.56 | V9: =U9*T9 -> 121.68 | W9: 0 | X9: 0 | Y9: =X9*W9 -> 0 | Z9: 0 | AA9: 0 | AB9: =AA9*Z9 -> 0 | AC9: 0 | AD9: 0 | AE9: =AD9*AC9 -> 0 | AF9: 0 | AG9: 0 | AH9: =AG9*AF9 -> 0 | AI9: 0 | AJ9: 0 | AK9: =AJ9*AI9 -> 0 | AL9: 0 | AM9: 0 | AN9: =AM9*AL9 -> 0
A10: Ácido Borico | B10: 56563 | C10: 0 | D10: 0 | E10: 0 | F10: 0 | G10: =F10*E10 -> 0 | H10: 0 | I10: 0 | J10: =I10*H10 -> 0 | K10: 3 | L10: 9.3 | M10: =L10*K10 -> 27.9 | N10: 2 | O10: 9.3 | P10: =O10*N10 -> 18.6 | Q10: 1 | R10: 9.3 | S10: =R10*Q10 -> 9.3 | T10: 0 | U10: 0 | V10: =U10*T10 -> 0 | W10: 0 | X10: 0 | Y10: =X10*W10 -> 0 | Z10: 0 | AA10: 0 | AB10: =AA10*Z10 -> 0 | AC10: 0 | AD10: 0 | AE10: =AD10*AC10 -> 0 | AF10: 0 | AG10: 0 | AH10: =AG10*AF10 -> 0 | AI10: 0 | AJ10: 0 | AK10: =AJ10*AI10 -> 0 | AL10: 0 | AM10: 0 | AN10: =AM10*AL10 -> 0
A11: ABRILHANTADOR MC INFINITY | B11: 56566 | C11: 0 | D11: 0 | E11: 0 | F11: 0 | G11: =F11*E11 -> 0 | H11: 0 | I11: 0 | J11: =I11*H11 -> 0 | K11: 35 | L11: 45.2 | M11: =L11*K11 -> 1582 | N11: 30 | O11: 40.04 | P11: 0 | Q11: 25 | R11: 0 | S11: =R11*Q11 -> 0 | T11: 25 | U11: 0 | V11: =U11*T11 -> 0 | W11: 0 | X11: 0 | Y11: =X11*W11 -> 0 | Z11: 0 | AA11: 0 | AB11: =AA11*Z11 -> 0 | AC11: 0 | AD11: 0 | AE11: =AD11*AC11 -> 0 | AF11: 0 | AG11: 0 | AH11: =AG11*AF11 -> 0 | AI11: 0 | AJ11: 0 | AK11: =AJ11*AI11 -> 0 | AL11: 0 | AM11: 0 | AN11: =AM11*AL11 -> 0
A12: MOLHADOR MC/P | B12: 65078 | C12: 0 | D12: 0 | E12: 0 | F12: 0 | G12: =F12*E12 -> 0 | H12: 0 | I12: 0 | J12: =I12*H12 -> 0 | K12: 50 | L12: 9.08 | M12: =L12*K12 -> 454 | N12: 45 | O12: 8.05 | P12: =O12*N12 -> 362.25 | Q12: 25 | R12: 0 | S12: =R12*Q12 -> 0 | T12: 25 | U12: 0 | V12: =U12*T12 -> 0 | W12: 0 | X12: 0 | Y12: =X12*W12 -> 0 | Z12: 0 | AA12: 0 | AB12: =AA12*Z12 -> 0 | AC12: 0 | AD12: 0 | AE12: =AD12*AC12 -> 0 | AF12: 0 | AG12: 0 | AH12: =AG12*AF12 -> 0 | AI12: 0 | AJ12: 0 | AK12: =AJ12*AI12 -> 0 | AL12: 0 | AM12: 0 | AN12: =AM12*AL12 -> 0
A13: NIVELADOR MC INFINITY | B13: 56317 | C13: 0 | D13: 0 | E13: 0 | F13: 0 | G13: =F13*E13 -> 0 | H13: 0 | I13: 0 | J13: =I13*H13 -> 0 | K13: 100 | L13: 30.78 | M13: =L13*K13 -> 3078 | N13: 75 | O13: 21.75 | P13: =O13*N13 -> 1631.25 | Q13: 75 | R13: 0 | S13: =R13*Q13 -> 0 | T13: 80 | U13: 0 | V13: =U13*T13 -> 0 | W13: 0 | X13: 0 | Y13: =X13*W13 -> 0 | Z13: 0 | AA13: 0 | AB13: =AA13*Z13 -> 0 | AC13: 0 | AD13: 0 | AE13: =AD13*AC13 -> 0 | AF13: 0 | AG13: 0 | AH13: =AG13*AF13 -> 0 | AI13: 0 | AJ13: 0 | AK13: =AJ13*AI13 -> 0 | AL13: 0 | AM13: 0 | AN13: =AM13*AL13 -> 0
A14: PURIFICADOR NIMC | B14: 56576 | C14: 0 | D14: 0 | E14: 0 | G14: =F14*E14 -> 0 | K14: 35 | L14: 18.75 | M14: =L14*K14 -> 656.25 | N14: 30 | O14: 16.61 | P14: =O14*N14 -> 498.3 | Q14: 22 | R14: 0 | S14: =R14*Q14 -> 0 | T14: 15 | U14: 0 | V14: =U14*T14 -> 0
F15: Total | G15: =SUM(G7:G14) -> 0 | I15: Total | J15: =SUM(J7:J14) -> 0 | L15: Total | M15: =SUM(M7:M14) -> 37847.69 | O15: Total | P15: =SUM(P7:P14) -> 30695.13 | R15: Total | S15: =SUM(S7:S14) -> 171.54 | U15: Total | V15: =SUM(V7:V14) -> 121.68 | X15: Total | Y15: =SUM(Y7:Y14) -> 0 | AA15: Total | AB15: =SUM(AB7:AB14) -> 0 | AD15: Total | AE15: =SUM(AE7:AE14) -> 0 | AG15: Total | AH15: =SUM(AH7:AH14) -> 0 | AJ15: Total | AK15: =SUM(AK7:AK14) -> 0 | AM15: Total | AN15: =SUM(AN7:AN14) -> 0

Sheet Níquel Strik (2)
A2: Menu
A3: Níquel Strik (2)
E4: 45292 | F4: 45292 | G4: 45292 | H4: 45323 | I4: 45323 | J4: 45323 | K4: 45352 | L4: 45352 | M4: 45352 | N4: 45383 | O4: 45383 | P4: 45383 | Q4: 45413 | R4: 45413 | S4: 45413 | T4: 45444 | U4: 45444 | V4: 45444 | W4: 45474 | X4: 45474 | Y4: 45474 | Z4: 45505 | AA4: 45505 | AB4: 45505 | AC4: 45536 | AD4: 45536 | AE4: 45536 | AF4: 45566 | AG4: 45566 | AH4: 45566 | AI4: 45597 | AJ4: 45597 | AK4: 45597 | AL4: 45627 | AM4: 45627 | AN4: 45627
A5: Produto | B5: ID | C5: Volume tanque / lts | D5: Concentração g/lt | E5: Consumo Kg/lt | F5: Custo/Kg | G5: Custo Total | H5: Consumo Kg/lt | I5: Custo/Kg | J5: Custo Total | K5: Consumo Kg/lt | L5: CustoKg/lt | M5: Custo Total | N5: Consumo Kg/lt | O5: Custo/Kg | P5: Custo Total | Q5: Consumo Kg/lt | R5: Custo/Kg | S5: Custo Total | T5: Consumo Kg/lt | U5: Custo/Kg | V5: Custo Total | W5: Consumo Kg/lt | X5: Custo/Kg | Y5: Custo Total | Z5: Consumo Kg/lt | AA5: Custo/Kg | AB5: Custo Total | AC5: Consumo Kg/lt | AD5: Custo/Kg | AE5: Custo Total | AF5: Consumo Kg/lt | AG5: Custo/Kg | AH5: Custo Total | AI5: Consumo Kg/lt | AJ5: Custo/Kg | AK5: Custo Total | AL5: Consumo Kg/lt | AM5: Custo/Kg | AN5: Custo Total
A6: Ânodo de Níquel | B6: 56944 | C6: 0 | D6: 0 | E6: 0 | F6: 0 | G6: =F6*E6 -> 0 | H6: 0 | I6: 0 | J6: =I6*H6 -> 0 | K6: 15 | L6: 141.9 | M6: =L6*K6 -> 2128.5 | N6: 35 | O6: 141.9 | P6: =O6*N6 -> 4966.5 | Q6: 84 | R6: 141.9 | S6: =R6*Q6 -> 11919.6 | T6: 0 | U6: 141.9 | V6: =U6*T6 -> 0 | W6: 0 | X6: 0 | Y6: =X6*W6 -> 0 | Z6: 0 | AA6: 0 | AB6: =AA6*Z6 -> 0 | AC6: 0 | AD6: 0 | AE6: =AD6*AC6 -> 0 | AF6: 0 | AG6: 0 | AH6: =AG6*AF6 -> 0 | AI6: 0 | AJ6: 0 | AK6: =AJ6*AI6 -> 0 | AL6: 0 | AM6: 0 | AN6: =AM6*AL6 -> 0
A7: NIVELADOR MC INFINITY | B7: 73191 | C7: 0 | D7: 0 | E7: 0 | F7: 0 | G7: =F7*E7 -> 0 | H7: 0 | I7: 0 | J7: =I7*H7 -> 0 | K7: 3 | L7: 30.78 | M7: =L7*K7 -> 92.34 | N7: 5 | O7: 27.27 | P7: =O7*N7 -> 136.35 | Q7: 9 | R7: 0 | S7: =R7*Q7 -> 0 | T7: 7 | U7: 0 | V7: =U7*T7 -> 0 | W7: 0 | X7: 0 | Y7: =X7*W7 -> 0 | Z7: 0 | AA7: 0 | AB7: =AA7*Z7 -> 0 | AC7: 0 | AD7: 0 | AE7: =AD7*AC7 -> 0 | AF7: 0 | AG7: 0 | AH7: =AG7*AF7 -> 0 | AI7: 0 | AJ7: 0 | AK7: =AJ7*AI7 -> 0 | AL7: 0 | AM7: 0 | AN7: =AM7*AL7 -> 0
A8: SULFATO DE NIQUEL SOLUCAO 60% | B8: 100490 | C8: 0 | D8: 0 | E8: 0 | F8: 0 | G8: =F8*E8 -> 0 | H8: 0 | I8: 0 | J8: =I8*H8 -> 0 | K8: 25 | L8: 35.1 | M8: =L8*K8 -> 877.5 | N8: 40 | O8: 22.65 | P8: =O8*N8 -> 906 | Q8: 12 | R8: 0 | S8: =R8*Q8 -> 0 | T8: 7 | U8: 0 | V8: =U8*T8 -> 0 | W8: 0 | X8: 0 | Y8: =X8*W8 -> 0 | Z8: 0 | AA8: 0 | AB8: =AA8*Z8 -> 0 | AC8: 0 | AD8: 0 | AE8: =AD8*AC8 -> 0 | AF8: 0 | AG8: 0 | AH8: =AG8*AF8 -> 0 | AI8: 0 | AJ8: 0 | AK8: =AJ8*AI8 -> 0 | AL8: 0 | AM8: 0 | AN8: =AM8*AL8 -> 0
A9: MOLHADOR MC/P | B9: 56563 | C9: 0 | D9: 0 | E9: 0 | F9: 0 | G9: =F9*E9 -> 0 | H9: 0 | I9: 0 | J9: =I9*H9 -> 0 | K9: 2 | L9: 9.08 | M9: =L9*K9 -> 18.16 | N9: 2 | O9: 8.05 | P9: =O9*N9 -> 16.1 | Q9: 2 | R9: 0 | S9: =R9*Q9 -> 0 | T9: 3 | U9: 0 | V9: =U9*T9 -> 0 | W9: 0 | X9: 0 | Y9: =X9*W9 -> 0 | Z9: 0 | AA9: 0 | AB9: =AA9*Z9 -> 0 | AC9: 0 | AD9: 0 | AE9: =AD9*AC9 -> 0 | AF9: 0 | AG9: 0 | AH9: =AG9*AF9 -> 0 | AI9: 0 | AJ9: 0 | AK9: =AJ9*AI9 -> 0 | AL9: 0 | AM9: 0 | AN9: =AM9*AL9 -> 0
A10: PURIFICADOR NIMC | B10: 56566 | C10: 0 | D10: 0 | E10: 0 | F10: 0 | G10: =F10*E10 -> 0 | H10: 0 | I10: 0 | J10: =I10*H10 -> 0 | K10: 1 | L10: 18.75 | M10: =L10*K10 -> 18.75 | N10: 1 | O10: 16.61 | P10: =O10*N10 -> 16.61 | Q10: 2 | R10: 0 | S10: =R10*Q10 -> 0 | T10: 2 | U10: 0 | V10: =U10*T10 -> 0 | W10: 0 | X10: 0 | Y10: =X10*W10 -> 0 | Z10: 0 | AA10: 0 | AB10: =AA10*Z10 -> 0 | AC10: 0 | AD10: 0 | AE10: =AD10*AC10 -> 0 | AF10: 0 | AG10: 0 | AH10: =AG10*AF10 -> 0 | AI10: 0 | AJ10: 0 | AK10: =AJ10*AI10 -> 0 | AL10: 0 | AM10: 0 | AN10: =AM10*AL10 -> 0
B11: 65078 | C11: 0 | D11: 0 | E11: 0 | F11: 0 | G11: =F11*E11 -> 0 | H11: 0 | I11: 0 | J11: =I11*H11 -> 0 | K11: 0 | L11: 0 | M11: =L11*K11 -> 0 | N11: 0 | O11: 0 | P11: =O11*N11 -> 0 | Q11: 0 | R11: 0 | S11: =R11*Q11 -> 0 | T11: 0 | U11: 0 | V11: =U11*T11 -> 0 | W11: 0 | X11: 0 | Y11: =X11*W11 -> 0 | Z11: 0 | AA11: 0 | AB11: =AA11*Z11 -> 0 | AC11: 0 | AD11: 0 | AE11: =AD11*AC11 -> 0 | AF11: 0 | AG11: 0 | AH11: =AG11*AF11 -> 0 | AI11: 0 | AJ11: 0 | AK11: =AJ11*AI11 -> 0 | AL11: 0 | AM11: 0 | AN11: =AM11*AL11 -> 0
B12: 56317 | C12: 0 | D12: 0 | E12: 0 | F12: 0 | G12: =F12*E12 -> 0 | H12: 0 | I12: 0 | J12: =I12*H12 -> 0 | K12: 0 | L12: 0 | M12: =L12*K12 -> 0 | N12: 0 | O12: 0 | P12: =O12*N12 -> 0 | Q12: 0 | R12: 0 | S12: =R12*Q12 -> 0 | T12: 0 | U12: 0 | V12: =U12*T12 -> 0 | W12: 0 | X12: 0 | Y12: =X12*W12 -> 0 | Z12: 0 | AA12: 0 | AB12: =AA12*Z12 -> 0 | AC12: 0 | AD12: 0 | AE12: =AD12*AC12 -> 0 | AF12: 0 | AG12: 0 | AH12: =AG12*AF12 -> 0 | AI12: 0 | AJ12: 0 | AK12: =AJ12*AI12 -> 0 | AL12: 0 | AM12: 0 | AN12: =AM12*AL12 -> 0
B13: 56576 | C13: 0 | D13: 0 | E13: 0 | G13: =F13*E13 -> 0 | K13: 0 | L13: 0 | M13: =L13*K13 -> 0
F14: Total | G14: =+SUM(G6:G13) -> 0 | I14: Total | J14: =SUM(J6:J13) -> 0 | L14: Total | M14: =SUM(M6:M13) -> 3135.25 | O14: Total | P14: =SUM(P6:P13) -> 6041.56 | R14: Total | S14: =SUM(S6:S13) -> 11919.6 | U14: Total | V14: =SUM(V6:V13) -> 0 | X14: Total | Y14: =SUM(Y6:Y13) -> 0 | AA14: Total | AB14: =SUM(AB6:AB13) -> 0 | AD14: Total | AE14: =SUM(AE6:AE13) -> 0 | AG14: Total | AH14: =SUM(AH6:AH13) -> 0 | AJ14: Total | AK14: =SUM(AK6:AK13) -> 0 | AM14: Total | AN14: =SUM(AN6:AN13) -> 0

Sheet Cromo
A2: Menu
A3: Cromo
E4: 45292 | F4: 45292 | G4: 45292 | H4: 45323 | I4: 45323 | J4: 45323 | K4: 45352 | L4: 45352 | M4: 45352 | N4: 45383 | O4: 45383 | P4: 45383 | Q4: 45413 | R4: 45413 | S4: 45413 | T4: 45444 | U4: 45444 | V4: 45444 | W4: 45474 | X4: 45474 | Y4: 45474 | Z4: 45505 | AA4: 45505 | AB4: 45505 | AC4: 45536 | AD4: 45536 | AE4: 45536 | AF4: 45566 | AG4: 45566 | AH4: 45566 | AI4: 45597 | AJ4: 45597 | AK4: 45597 | AL4: 45627 | AM4: 45627 | AN4: 45627
A5: Produto | B5: ID | C5: Volume tanque / lts | D5: Concentração g/lt | E5: Consumo Kg/lt | F5: Custo/Kg | G5: Custo Total | H5: Consumo Kg/lt | I5: Custo/Kg | J5: Custo Total | K5: Consumo Kg/lt | L5: Custo Kg/lt | M5: Custo Total | N5: Consumo Kg/lt | O5: Custo/Kg | P5: Custo Total | Q5: Consumo Kg/lt | R5: Custo/Kg | S5: Custo Total | T5: Consumo Kg/lt | U5: Custo/Kg | V5: Custo Total | W5: Consumo Kg/lt | X5: Custo/Kg | Y5: Custo Total | Z5: Consumo Kg/lt | AA5: Custo/Kg | AB5: Custo Total | AC5: Consumo Kg/lt | AD5: Custo/Kg | AE5: Custo Total | AF5: Consumo Kg/lt | AG5: Custo/Kg | AH5: Custo Total | AI5: Consumo Kg/lt | AJ5: Custo/Kg | AK5: Custo Total | AL5: Consumo Kg/lt | AM5: Custo/Kg | AN5: Custo Total
A6: Ânodo Chumbo | B6: 56574 | C6: 0 | D6: 0 | E6: 0 | F6: 0 | G6: =F6*E6 -> 0 | H6: 0 | I6: 0 | J6: =I6*H6 -> 0 | K6: 22.5 | L6: 1075.4 | M6: =L6*K6 -> 24196.5 | N6: 22.5 | O6: 1075.4 | P6: =O6*N6 -> 24196.5 | Q6: 22.5 | R6: 1075.4 | S6: =R6*Q6 -> 24196.5 | T6: 22.5 | U6: 1075.4 | V6: =U6*T6 -> 24196.5 | W6: 0 | X6: 0 | Y6: =X6*W6 -> 0 | Z6: 0 | AA6: 11 | AB6: =AA6*Z6 -> 0 | AC6: 0 | AD6: 12 | AE6: =AD6*AC6 -> 0 | AF6: 0 | AG6: 0 | AH6: =AG6*AF6 -> 0 | AI6: 0 | AJ6: 0 | AK6: =AJ6*AI6 -> 0 | AL6: 0 | AM6: 0 | AN6: =AM6*AL6 -> 0
A7: COMPOSTO CRMC | C7: 0 | D7: 0 | E7: 0 | F7: 0 | G7: =F7*E7 -> 0 | H7: 0 | I7: 0 | J7: =I7*H7 -> 0 | K7: 75 | L7: 67.77 | M7: =L7*K7 -> 5082.75 | N7: 70 | O7: 67.77 | P7: =O7*N7 -> 4743.9 | Q7: 25 | R7: 0 | S7: =R7*Q7 -> 0 | T7: 25 | U7: 0 | V7: =U7*T7 -> 0 | W7: 0 | X7: 0 | Y7: =X7*W7 -> 0 | Z7: 0 | AA7: 0 | AB7: =AA7*Z7 -> 0 | AC7: 0 | AD7: 0 | AE7: =AD7*AC7 -> 0 | AF7: 0 | AG7: 0 | AH7: =AG7*AF7 -> 0 | AI7: 0 | AJ7: 0 | AK7: =AJ7*AI7 -> 0 | AL7: 0 | AM7: 0 | AN7: =AM7*AL7 -> 0
A8: SUPRESSOR CRMC/H | B8: 56579 | C8: 0 | D8: 0 | E8: 0 | F8: 0 | G8: =F8*E8 -> 0 | H8: 0 | I8: 0 | J8: =I8*H8 -> 0 | K8: 1 | L8: 405.11 | M8: =L8*K8 -> 405.11 | N8: 1 | O8: 405.11 | P8: =O8*N8 -> 405.11 | Q8: 1 | R8: 0 | S8: =R8*Q8 -> 0 | T8: 1 | U8: 0 | V8: =U8*T8 -> 0 | W8: 0 | X8: 0 | Y8: =X8*W8 -> 0 | Z8: 0 | AA8: 0 | AB8: =AA8*Z8 -> 0 | AC8: 0 | AD8: 0 | AE8: =AD8*AC8 -> 0 | AF8: 0 | AG8: 0 | AH8: =AG8*AF8 -> 0 | AI8: 0 | AJ8: 0 | AK8: =AJ8*AI8 -> 0 | AL8: 0 | AM8: 0 | AN8: =AM8*AL8 -> 0
A9: COMPOSTO C-170 | C9: 0 | D9: 0 | E9: 0 | F9: 0 | G9: =F9*E9 -> 0 | H9: 0 | I9: 0 | J9: =I9*H9 -> 0 | K9: 5 | L9: 18.83 | M9: =L9*K9 -> 94.15 | N9: 5 | O9: 18.83 | P9: =O9*N9 -> 94.15 | Q9: 1 | R9: 0 | S9: =R9*Q9 -> 0 | T9: 1 | U9: 0 | V9: =U9*T9 -> 0 | W9: 0 | X9: 0 | Y9: =X9*W9 -> 0 | Z9: 0 | AA9: 0 | AB9: =AA9*Z9 -> 0 | AC9: 0 | AD9: 0 | AE9: =AD9*AC9 -> 0 | AF9: 0 | AG9: 0 | AH9: =AG9*AF9 -> 0 | AI9: 0 | AJ9: 0 | AK9: =AJ9*AI9 -> 0 | AL9: 0 | AM9: 0 | AN9: =AM9*AL9 -> 0
B10: 64964 | C10: 0 | D10: 0 | E10: 0 | F10: 0 | G10: =F10*E10 -> 0 | H10: 0 | I10: 0 | J10: =I10*H10 -> 0 | K10: 0 | L10: 0 | M10: =L10*K10 -> 0 | N10: 0 | O10: 0 | P10: =O10*N10 -> 0 | Q10: 0 | R10: 0 | S10: =R10*Q10 -> 0 | T10: 0 | U10: 0 | V10: =U10*T10 -> 0 | W10: 0 | X10: 0 | Y10: =X10*W10 -> 0 | Z10: 0 | AA10: 0 | AB10: =AA10*Z10 -> 0 | AC10: 0 | AD10: 0 | AE10: =AD10*AC10 -> 0 | AF10: 0 | AG10: 0 | AH10: =AG10*AF10 -> 0 | AI10: 0 | AJ10: 0 | AK10: =AJ10*AI10 -> 0 | AL10: 0 | AM10: 0 | AN10: =AM10*AL10 -> 0
C11: 0 | D11: 0 | E11: 0 | F11: 0 | G11: =F11*E11 -> 0 | H11: 0 | I11: 0 | J11: =I11*H11 -> 0 | K11: 0 | L11: 0 | M11: =L11*K11 -> 0 | N11: 0 | O11: 0 | P11: =O11*N11 -> 0 | Q11: 0 | R11: 0 | S11: =R11*Q11 -> 0 | T11: 0 | U11: 0 | V11: =U11*T11 -> 0 | W11: 0 | X11: 0 | Y11: =X11*W11 -> 0 | Z11: 0 | AA11: 0 | AB11: =AA11*Z11 -> 0 | AC11: 0 | AD11: 0 | AE11: =AD11*AC11 -> 0 | AF11: 0 | AG11: 0 | AH11: =AG11*AF11 -> 0 | AI11: 0 | AJ11: 0 | AK11: =AJ11*AI11 -> 0 | AL11: 0 | AM11: 0 | AN11: =AM11*AL11 -> 0
C12: 0 | D12: 0 | E12: 0 | F12: 0 | G12: =F12*E12 -> 0 | H12: 0 | I12: 0 | J12: =I12*H12 -> 0 | K12: 0 | L12: 0 | M12: =L12*K12 -> 0 | N12: 0 | O12: 0 | P12: =O12*N12 -> 0 | Q12: 0 | R12: 0 | S12: =R12*Q12 -> 0 | T12: 0 | U12: 0 | V12: =U12*T12 -> 0 | W12: 0 | X12: 0 | Y12: =X12*W12 -> 0 | Z12: 0 | AA12: 0 | AB12: =AA12*Z12 -> 0 | AC12: 0 | AD12: 0 | AE12: =AD12*AC12 -> 0 | AF12: 0 | AG12: 0 | AH12: =AG12*AF12 -> 0 | AI12: 0 | AJ12: 0 | AK12: =AJ12*AI12 -> 0 | AL12: 0 | AM12: 0 | AN12: =AM12*AL12 -> 0
C13: 0 | D13: 0 | E13: 0 | G13: =F13*E13 -> 0 | K13: 0 | L13: 0 | M13: =L13*K13 -> 0
F14: Total | G14: =SUM(G6:G13) -> 0 | I14: Total | J14: =SUM(J6:J13) -> 0 | L14: Total | M14: =SUM(M6:M13) -> 29778.51 | O14: Total | P14: =SUM(P6:P13) -> 29439.66 | R14: Total | S14: =SUM(S6:S13) -> 24196.5 | U14: Total | V14: =SUM(V6:V13) -> 24196.5 | X14: Total | Y14: =SUM(Y6:Y13) -> 0 | AA14: Total | AB14: =SUM(AB6:AB13) -> 0 | AD14: Total | AE14: =SUM(AE6:AE13) -> 0 | AG14: Total | AH14: =SUM(AH6:AH13) -> 0 | AJ14: Total | AK14: =SUM(AK6:AK13) -> 0 | AM14: Total | AN14: =SUM(AN6:AN13) -> 0

Sheet Linha 9
A2: Menu
A3: Linha 9
E5: 44562 | F5: 44562 | G5: 44562 | H5: 45323 | I5: 45323 | J5: 45323 | K5: 45352 | L5: 45352 | M5: 45352 | N5: 45383 | O5: 45383 | P5: 45383 | Q5: 45413 | R5: 45413 | S5: 45413 | T5: 45444 | U5: 45444 | V5: 45444 | W5: 45474 | X5: 45474 | Y5: 45474 | Z5: 45505 | AA5: 45505 | AB5: 45505 | AC5: 45536 | AD5: 45536 | AE5: 45536 | AF5: 45566 | AG5: 45566 | AH5: 45566 | AI5: 45597 | AJ5: 45597 | AK5: 45597 | AL5: 45627 | AM5: 45627 | AN5: 45627
A6: Produto | B6: ID | C6: Volume tanque / lts | D6: Concentração g/lt | E6: Consumo Kg/lt | F6: Custo/Kg | G6: Custo Total | H6: Consumo Kg/lt | I6: Custo/Kg | J6: Custo Total | K6: Consumo Kg/lt | L6: Custo Kg/lt | M6: Custo Total | N6: Consumo Kg/lt | O6: Custo/Kg | P6: Custo Total | Q6: Consumo Kg/lt | R6: Custo/Kg | S6: Custo Total | T6: Consumo Kg/lt | U6: Custo/Kg | V6: Custo Total | W6: Consumo Kg/lt | X6: Custo/Kg | Y6: Custo Total | Z6: Consumo Kg/lt | AA6: Custo/Kg | AB6: Custo Total | AC6: Consumo Kg/lt | AD6: Custo/Kg | AE6: Custo Total | AF6: Consumo Kg/lt | AG6: Custo/Kg | AH6: Custo Total | AI6: Consumo Kg/lt | AJ6: Custo/Kg | AK6: Custo Total | AL6: Consumo Kg/lt | AM6: Custo/Kg | AN6: Custo Total
B7: 0 | C7: 0 | D7: 0 | E7: 0 | F7: 0 | G7: =F7*E7 -> 0 | H7: 0 | I7: 0 | J7: =I7*H7 -> 0 | K7: 0 | L7: 0 | M7: =L7*K7 -> 0 | N7: 0 | O7: 0 | P7: =O7*N7 -> 0 | Q7: 0 | R7: 8 | S7: =R7*Q7 -> 0 | T7: 0 | U7: 9 | V7: =U7*T7 -> 0 | W7: 0 | X7: 10 | Y7: =X7*W7 -> 0 | Z7: 0 | AA7: 0 | AB7: =AA7*Z7 -> 0 | AC7: 0 | AD7: 0 | AE7: =AD7*AC7 -> 0 | AF7: 0 | AG7: 13 | AH7: =AG7*AF7 -> 0 | AI7: 0 | AJ7: 0 | AK7: =AJ7*AI7 -> 0 | AL7: 0 | AM7: 15 | AN7: =AM7*AL7 -> 0
B8: 0 | C8: 0 | D8: 0 | E8: 0 | F8: 0 | G8: =F8*E8 -> 0 | H8: 0 | I8: 0 | J8: =I8*H8 -> 0 | K8: 0 | L8: 0 | M8: =L8*K8 -> 0 | N8: 0 | O8: 0 | P8: =O8*N8 -> 0 | Q8: 0 | R8: 0 | S8: =R8*Q8 -> 0 | T8: 0 | U8: 0 | V8: =U8*T8 -> 0 | W8: 0 | X8: 0 | Y8: =X8*W8 -> 0 | Z8: 0 | AA8: 0 | AB8: =AA8*Z8 -> 0 | AC8: 0 | AD8: 0 | AE8: =AD8*AC8 -> 0 | AF8: 0 | AG8: 0 | AH8: =AG8*AF8 -> 0 | AI8: 0 | AJ8: 0 | AK8: =AJ8*AI8 -> 0 | AL8: 0 | AM8: 0 | AN8: =AM8*AL8 -> 0
B9: 0 | C9: 0 | D9: 0 | E9: 0 | F9: 0 | G9: =F9*E9 -> 0 | H9: 0 | I9: 0 | J9: =I9*H9 -> 0 | K9: 0 | L9: 0 | M9: =L9*K9 -> 0 | N9: 0 | O9: 0 | P9: =O9*N9 -> 0 | Q9: 0 | R9: 0 | S9: =R9*Q9 -> 0 | T9: 0 | U9: 0 | V9: =U9*T9 -> 0 | W9: 0 | X9: 0 | Y9: =X9*W9 -> 0 | Z9: 0 | AA9: 0 | AB9: =AA9*Z9 -> 0 | AC9: 0 | AD9: 0 | AE9: =AD9*AC9 -> 0 | AF9: 0 | AG9: 0 | AH9: =AG9*AF9 -> 0 | AI9: 0 | AJ9: 0 | AK9: =AJ9*AI9 -> 0 | AL9: 0 | AM9: 0 | AN9: =AM9*AL9 -> 0
B10: 0 | C10: 0 | D10: 0 | E10: 0 | F10: 0 | G10: =F10*E10 -> 0 | H10: 0 | I10: 0 | J10: =I10*H10 -> 0 | K10: 0 | L10: 0 | M10: =L10*K10 -> 0 | N10: 0 | O10: 0 | P10: =O10*N10 -> 0 | Q10: 0 | R10: 0 | S10: =R10*Q10 -> 0 | T10: 0 | U10: 0 | V10: =U10*T10 -> 0 | W10: 0 | X10: 0 | Y10: =X10*W10 -> 0 | Z10: 0 | AA10: 0 | AB10: =AA10*Z10 -> 0 | AC10: 0 | AD10: 0 | AE10: =AD10*AC10 -> 0 | AF10: 0 | AG10: 0 | AH10: =AG10*AF10 -> 0 | AI10: 0 | AJ10: 0 | AK10: =AJ10*AI10 -> 0 | AL10: 0 | AM10: 0 | AN10: =AM10*AL10 -> 0
B11: 0 | C11: 0 | D11: 0 | E11: 0 | F11: 0 | G11: =F11*E11 -> 0 | H11: 0 | I11: 0 | J11: =I11*H11 -> 0 | K11: 0 | L11: 0 | M11: =L11*K11 -> 0 | N11: 0 | O11: 0 | P11: =O11*N11 -> 0 | Q11: 0 | R11: 0 | S11: =R11*Q11 -> 0 | T11: 0 | U11: 0 | V11: =U11*T11 -> 0 | W11: 0 | X11: 0 | Y11: =X11*W11 -> 0 | Z11: 0 | AA11: 0 | AB11: =AA11*Z11 -> 0 | AC11: 0 | AD11: 0 | AE11: =AD11*AC11 -> 0 | AF11: 0 | AG11: 0 | AH11: =AG11*AF11 -> 0 | AI11: 0 | AJ11: 0 | AK11: =AJ11*AI11 -> 0 | AL11: 0 | AM11: 0 | AN11: =AM11*AL11 -> 0
B12: 0 | C12: 0 | D12: 0 | E12: 0 | F12: 0 | G12: =F12*E12 -> 0 | H12: 0 | I12: 0 | J12: =I12*H12 -> 0 | K12: 0 | L12: 0 | M12: =L12*K12 -> 0 | N12: 0 | O12: 0 | P12: =O12*N12 -> 0 | Q12: 0 | R12: 0 | S12: =R12*Q12 -> 0 | T12: 0 | U12: 0 | V12: =U12*T12 -> 0 | W12: 0 | X12: 0 | Y12: =X12*W12 -> 0 | Z12: 0 | AA12: 0 | AB12: =AA12*Z12 -> 0 | AC12: 0 | AD12: 0 | AE12: =AD12*AC12 -> 0 | AF12: 0 | AG12: 0 | AH12: =AG12*AF12 -> 0 | AI12: 0 | AJ12: 0 | AK12: =AJ12*AI12 -> 0 | AL12: 0 | AM12: 0 | AN12: =AM12*AL12 -> 0
E13: 0 | F13: 0 | G13: =F13*E13 -> 0 | H13: 0 | I13: 0 | J13: =I13*H13 -> 0 | K13: 0 | L13: 0 | M13: =L13*K13 -> 0 | N13: 0 | O13: 0 | P13: =O13*N13 -> 0 | Q13: 0 | R13: 0 | S13: =R13*Q13 -> 0 | T13: 0 | U13: 0 | V13: =U13*T13 -> 0 | W13: 0 | X13: 0 | Y13: =X13*W13 -> 0 | Z13: 0 | AA13: 0 | AB13: =AA13*Z13 -> 0 | AC13: 0 | AD13: 0 | AE13: =AD13*AC13 -> 0 | AF13: 0 | AG13: 0 | AH13: =AG13*AF13 -> 0 | AI13: 0 | AJ13: 0 | AK13: =AJ13*AI13 -> 0 | AL13: 0 | AM13: 0 | AN13: =AM13*AL13 -> 0
K14: 0
F15: Total | G15: =SUM(G7:G13) -> 0 | I15: Total | J15: =SUM(J7:J14) -> 0 | L15: Total | M15: =SUM(M7:M14) -> 0 | O15: Total | P15: =SUM(P7:P14) -> 0 | R15: Total | S15: =SUM(S7:S14) -> 0 | U15: Total | V15: =SUM(V7:V14) -> 0 | X15: Total | Y15: =SUM(Y7:Y14) -> 0 | AA15: Total | AB15: =SUM(AB7:AB14) -> 0 | AD15: Total | AE15: =SUM(AE7:AE14) -> 0 | AG15: Total | AH15: =SUM(AH7:AH14) -> 0 | AJ15: Total | AK15: =SUM(AK7:AK14) -> 0 | AM15: Total | AN15: =SUM(AN7:AN14) -> 0

Sheet Linha 10
A1: Menu
A2: Linha 10
D3: 45292 | E3: 45292 | F3: 45292 | G3: 45323 | H3: 45323 | I3: 45323 | J3: 45352 | K3: 45352 | L3: 45352 | M3: 45383 | N3: 45383 | O3: 45383 | P3: 45413 | Q3: 45413 | R3: 45413 | S3: 45444 | T3: 45444 | U3: 45444 | V3: 45474 | W3: 45474 | X3: 45474 | Y3: 45505 | Z3: 45505 | AA3: 45505 | AB3: 45536 | AC3: 45536 | AD3: 45536 | AE3: 45566 | AF3: 45566 | AG3: 45566 | AH3: 45597 | AI3: 45597 | AJ3: 45597 | AK3: 45627 | AL3: 45627 | AM3: 45627
A4: Produto | B4: Volume tanque / lts | C4: Concentração g/lt | D4: Consumo Kg/lt | E4: Custo/Kg | F4: Custo Total | G4: Consumo Kg/lt | H4: Custo/Kg | I4: Custo Total | J4: Consumo Kg/lt | K4: Custo/Kg | L4: Custo Total | M4: Consumo Kg/lt | N4: Custo/Kg | O4: Custo Total | P4: Consumo Kg/lt | Q4: Custo/Kg | R4: Custo Total | S4: Consumo Kg/lt | T4: Custo/Kg | U4: Custo Total | V4: Consumo Kg/lt | W4: Custo/Kg | X4: Custo Total | Y4: Consumo Kg/lt | Z4: Custo/Kg | AA4: Custo Total | AB4: Consumo Kg/lt | AC4: Custo/Kg | AD4: Custo Total | AE4: Consumo Kg/lt | AF4: Custo/Kg | AG4: Custo Total | AH4: Consumo Kg/lt | AI4: Custo/Kg | AJ4: Custo Total | AK4: Consumo Kg/lt | AL4: Custo/Kg | AM4: Custo Total
B5: 0 | C5: 0 | D5: 0 | E5: 0 | F5: =E5*D5 -> 0 | G5: 0 | H5: 0 | I5: =H5*G5 -> 0 | J5: 0 | K5: 0 | L5: =K5*J5 -> 0 | M5: 0 | N5: 0 | O5: =N5*M5 -> 0 | P5: 0 | Q5: 0 | R5: =Q5*P5 -> 0 | S5: 0 | T5: 0 | U5: =T5*S5 -> 0 | V5: 0 | W5: 0 | X5: =W5*V5 -> 0 | Y5: 0 | Z5: 0 | AA5: =Z5*Y5 -> 0 | AB5: 0 | AC5: 0 | AD5: =AC5*AB5 -> 0 | AE5: 0 | AF5: 0 | AG5: =AF5*AE5 -> 0 | AH5: 0 | AI5: 0 | AJ5: =AI5*AH5 -> 0 | AK5: 0 | AL5: 15 | AM5: =AL5*AK5 -> 0
B6: 0 | C6: 0 | D6: 0 | E6: 0 | F6: =E6*D6 -> 0 | G6: 0 | H6: 0 | I6: =H6*G6 -> 0 | J6: 0 | K6: 0 | L6: =K6*J6 -> 0 | M6: 0 | N6: 0 | O6: =N6*M6 -> 0 | P6: 0 | Q6: 0 | R6: =Q6*P6 -> 0 | S6: 0 | T6: 0 | U6: =T6*S6 -> 0 | V6: 0 | W6: 0 | X6: =W6*V6 -> 0 | Y6: 0 | Z6: 0 | AA6: =Z6*Y6 -> 0 | AB6: 0 | AC6: 0 | AD6: =AC6*AB6 -> 0 | AE6: 0 | AF6: 0 | AG6: =AF6*AE6 -> 0 | AH6: 0 | AI6: 0 | AJ6: =AI6*AH6 -> 0 | AK6: 0 | AL6: 0 | AM6: =AL6*AK6 -> 0
B7: 0 | C7: 0 | D7: 0 | E7: 0 | F7: =E7*D7 -> 0 | G7: 0 | H7: 0 | I7: =H7*G7 -> 0 | J7: 0 | K7: 0 | L7: =K7*J7 -> 0 | M7: 0 | N7: 0 | O7: =N7*M7 -> 0 | P7: 0 | Q7: 0 | R7: =Q7*P7 -> 0 | S7: 0 | T7: 0 | U7: =T7*S7 -> 0 | V7: 0 | W7: 0 | X7: =W7*V7 -> 0 | Y7: 0 | Z7: 0 | AA7: =Z7*Y7 -> 0 | AB7: 0 | AC7: 0 | AD7: =AC7*AB7 -> 0 | AE7: 0 | AF7: 0 | AG7: =AF7*AE7 -> 0 | AH7: 0 | AI7: 0 | AJ7: =AI7*AH7 -> 0 | AK7: 0 | AL7: 0 | AM7: =AL7*AK7 -> 0
B8: 0 | C8: 0 | D8: 0 | E8: 0 | F8: =E8*D8 -> 0 | G8: 0 | H8: 0 | I8: =H8*G8 -> 0 | J8: 0 | K8: 0 | L8: =K8*J8 -> 0 | M8: 0 | N8: 0 | O8: =N8*M8 -> 0 | P8: 0 | Q8: 0 | R8: =Q8*P8 -> 0 | S8: 0 | T8: 0 | U8: =T8*S8 -> 0 | V8: 0 | W8: 0 | X8: =W8*V8 -> 0 | Y8: 0 | Z8: 0 | AA8: =Z8*Y8 -> 0 | AB8: 0 | AC8: 0 | AD8: =AC8*AB8 -> 0 | AE8: 0 | AF8: 0 | AG8: =AF8*AE8 -> 0 | AH8: 0 | AI8: 0 | AJ8: =AI8*AH8 -> 0 | AK8: 0 | AL8: 0 | AM8: =AL8*AK8 -> 0
B9: 0 | C9: 0 | D9: 0 | E9: 0 | F9: =E9*D9 -> 0 | G9: 0 | H9: 0 | I9: =H9*G9 -> 0 | J9: 0 | K9: 0 | L9: =K9*J9 -> 0 | M9: 0 | N9: 0 | O9: =N9*M9 -> 0 | P9: 0 | Q9: 0 | R9: =Q9*P9 -> 0 | S9: 0 | T9: 0 | U9: =T9*S9 -> 0 | V9: 0 | W9: 0 | X9: =W9*V9 -> 0 | Y9: 0 | Z9: 0 | AA9: =Z9*Y9 -> 0 | AB9: 0 | AC9: 0 | AD9: =AC9*AB9 -> 0 | AE9: 0 | AF9: 0 | AG9: =AF9*AE9 -> 0 | AH9: 0 | AI9: 0 | AJ9: =AI9*AH9 -> 0 | AK9: 0 | AL9: 0 | AM9: =AL9*AK9 -> 0
B10: 0 | C10: 0 | D10: 0 | E10: 0 | F10: =E10*D10 -> 0 | G10: 0 | H10: 0 | I10: =H10*G10 -> 0 | J10: 0 | K10: 0 | L10: =K10*J10 -> 0 | M10: 0 | N10: 0 | O10: =N10*M10 -> 0 | P10: 0 | Q10: 0 | R10: =Q10*P10 -> 0 | S10: 0 | T10: 0 | U10: =T10*S10 -> 0 | V10: 0 | W10: 0 | X10: =W10*V10 -> 0 | Y10: 0 | Z10: 0 | AA10: =Z10*Y10 -> 0 | AB10: 0 | AC10: 0 | AD10: =AC10*AB10 -> 0 | AE10: 0 | AF10: 0 | AG10: =AF10*AE10 -> 0 | AH10: 0 | AI10: 0 | AJ10: =AI10*AH10 -> 0 | AK10: 0 | AL10: 0 | AM10: =AL10*AK10 -> 0
B11: 0 | C11: 0 | D11: 0 | E11: 0 | F11: =E11*D11 -> 0 | G11: 0 | H11: 0 | I11: =H11*G11 -> 0 | J11: 0 | K11: 0 | L11: =K11*J11 -> 0 | M11: 0 | N11: 0 | O11: =N11*M11 -> 0 | P11: 0 | Q11: 0 | R11: =Q11*P11 -> 0 | S11: 0 | T11: 0 | U11: =T11*S11 -> 0 | V11: 0 | W11: 0 | X11: =W11*V11 -> 0 | Y11: 0 | Z11: 0 | AA11: =Z11*Y11 -> 0 | AB11: 0 | AC11: 0 | AD11: =AC11*AB11 -> 0 | AE11: 0 | AF11: 0 | AG11: =AF11*AE11 -> 0 | AH11: 0 | AI11: 0 | AJ11: =AI11*AH11 -> 0 | AK11: 0 | AL11: 0 | AM11: =AL11*AK11 -> 0
F12: =E12*D12 -> 0
F13: =E13*D13 -> 0
F14: =E14*D14 -> 0
F15: =E15*D15 -> 0
F16: =E16*D16 -> 0
F17: =E17*D17 -> 0
F18: =E18*D18 -> 0
F19: =E19*D19 -> 0
E20: Total | F20: =SUM(F5:F19) -> 0 | H20: Total | I20: =SUM(I5:I19) -> 0 | K20: Total | L20: =SUM(L5:L19) -> 0 | N20: Total | O20: =SUM(O5:O19) -> 0 | Q20: Total | R20: =SUM(R5:R19) -> 0 | T20: Total | U20: =SUM(U5:U19) -> 0 | W20: Total | X20: =SUM(X5:X19) -> 0 | Z20: Total | AA20: =SUM(AA5:AA19) -> 0 | AC20: Total | AD20: =SUM(AD5:AD19) -> 0 | AF20: Total | AG20: =SUM(AG5:AG19) -> 0 | AI20: Total | AJ20: =SUM(AJ5:AJ19) -> 0 | AL20: Total | AM20: =SUM(AM5:AM19) -> 0

Sheet Linha 11
A2: Menu
A3: Linha 11
D5: 45292 | E5: 45292 | F5: 45292 | G5: 45323 | H5: 45323 | I5: 45323 | J5: 45352 | K5: 45352 | L5: 45352 | M5: 45383 | N5: 45383 | O5: 45383 | P5: 45413 | Q5: 45413 | R5: 45413 | S5: 45444 | T5: 45444 | U5: 45444 | V5: 45474 | W5: 45474 | X5: 45474 | Y5: 45505 | Z5: 45505 | AA5: 45505 | AB5: 45536 | AC5: 45536 | AD5: 45536 | AE5: 45566 | AF5: 45566 | AG5: 45566 | AH5: 45597 | AI5: 45597 | AJ5: 45597 | AK5: 45627 | AL5: 45627 | AM5: 45627
A6: Produto | B6: Volume tanque / lts | C6: Concentração g/lt | D6: Consumo Kg/lt | E6: Custo/Kg | F6: Custo Total | G6: Consumo Kg/lt | H6: Custo/Kg | I6: Custo Total | J6: Consumo Kg/lt | K6: Custo Kg/lt | L6: Custo Total | M6: Consumo Kg/lt | N6: Custo/Kg | O6: Custo Total | P6: Consumo Kg/lt | Q6: Custo/Kg | R6: Custo Total | S6: Consumo Kg/lt | T6: Custo/Kg | U6: Custo Total | V6: Consumo Kg/lt | W6: Custo/Kg | X6: Custo Total | Y6: Consumo Kg/lt | Z6: Custo/Kg | AA6: Custo Total | AB6: Consumo Kg/lt | AC6: Custo/Kg | AD6: Custo Total | AE6: Consumo Kg/lt | AF6: Custo/Kg | AG6: Custo Total | AH6: Consumo Kg/lt | AI6: Custo/Kg | AJ6: Custo Total | AK6: Consumo Kg/lt | AL6: Custo/Kg | AM6: Custo Total
B7: 0 | C7: 0 | D7: 0 | E7: 0 | F7: =E7*D7 -> 0 | G7: 0 | H7: 0 | I7: =H7*G7 -> 0 | J7: 0 | K7: 0 | L7: =K7*J7 -> 0 | M7: 0 | N7: 0 | O7: =N7*M7 -> 0 | P7: 0 | Q7: 0 | R7: =Q7*P7 -> 0 | S7: 0 | T7: 0 | U7: =T7*S7 -> 0 | V7: 0 | W7: 0 | X7: =W7*V7 -> 0 | Y7: 0 | Z7: 0 | AA7: =Z7*Y7 -> 0 | AB7: 0 | AC7: 0 | AD7: =AC7*AB7 -> 0 | AE7: 0 | AF7: 0 | AG7: =AF7*AE7 -> 0 | AH7: 0 | AI7: 0 | AJ7: =AI7*AH7 -> 0 | AK7: 0 | AL7: 11 | AM7: =AL7*AK7 -> 0
B8: 0 | C8: 0 | D8: 0 | E8: 0 | F8: =E8*D8 -> 0 | G8: 0 | H8: 0 | I8: =H8*G8 -> 0 | J8: 0 | K8: 0 | L8: =K8*J8 -> 0 | M8: 0 | N8: 0 | O8: =N8*M8 -> 0 | P8: 0 | Q8: 0 | R8: =Q8*P8 -> 0 | S8: 0 | T8: 0 | U8: =T8*S8 -> 0 | V8: 0 | W8: 0 | X8: =W8*V8 -> 0 | Y8: 0 | Z8: 0 | AA8: =Z8*Y8 -> 0 | AB8: 0 | AC8: 0 | AD8: =AC8*AB8 -> 0 | AE8: 0 | AF8: 0 | AG8: =AF8*AE8 -> 0 | AH8: 0 | AI8: 0 | AJ8: =AI8*AH8 -> 0 | AK8: 0 | AL8: 0 | AM8: =AL8*AK8 -> 0
B9: 0 | C9: 0 | D9: 0 | E9: 0 | F9: =E9*D9 -> 0 | G9: 0 | H9: 0 | I9: =H9*G9 -> 0 | J9: 0 | K9: 0 | L9: =K9*J9 -> 0 | M9: 0 | N9: 0 | O9: =N9*M9 -> 0 | P9: 0 | Q9: 0 | R9: =Q9*P9 -> 0 | S9: 0 | T9: 0 | U9: =T9*S9 -> 0 | V9: 0 | W9: 0 | X9: =W9*V9 -> 0 | Y9: 0 | Z9: 0 | AA9: =Z9*Y9 -> 0 | AB9: 0 | AC9: 0 | AD9: =AC9*AB9 -> 0 | AE9: 0 | AF9: 0 | AG9: =AF9*AE9 -> 0 | AH9: 0 | AI9: 0 | AJ9: =AI9*AH9 -> 0 | AK9: 0 | AL9: 0 | AM9: =AL9*AK9 -> 0
B10: 0 | C10: 0 | D10: 0 | E10: 0 | F10: =E10*D10 -> 0 | G10: 0 | H10: 0 | I10: =H10*G10 -> 0 | J10: 0 | K10: 0 | L10: =K10*J10 -> 0 | M10: 0 | N10: 0 | O10: =N10*M10 -> 0 | P10: 0 | Q10: 0 | R10: =Q10*P10 -> 0 | S10: 0 | T10: 0 | U10: =T10*S10 -> 0 | V10: 0 | W10: 0 | X10: =W10*V10 -> 0 | Y10: 0 | Z10: 0 | AA10: =Z10*Y10 -> 0 | AB10: 0 | AC10: 0 | AD10: =AC10*AB10 -> 0 | AE10: 0 | AF10: 0 | AG10: =AF10*AE10 -> 0 | AH10: 0 | AI10: 0 | AJ10: =AI10*AH10 -> 0 | AK10: 0 | AL10: 0 | AM10: =AL10*AK10 -> 0
B11: 0 | C11: 0 | D11: 0 | E11: 0 | F11: =E11*D11 -> 0 | G11: 0 | H11: 0 | I11: =H11*G11 -> 0 | J11: 0 | K11: 0 | L11: =K11*J11 -> 0 | M11: 0 | N11: 0 | O11: =N11*M11 -> 0 | P11: 0 | Q11: 0 | R11: =Q11*P11 -> 0 | S11: 0 | T11: 0 | U11: =T11*S11 -> 0 | V11: 0 | W11: 0 | X11: =W11*V11 -> 0 | Y11: 0 | Z11: 0 | AA11: =Z11*Y11 -> 0 | AB11: 0 | AC11: 0 | AD11: =AC11*AB11 -> 0 | AE11: 0 | AF11: 0 | AG11: =AF11*AE11 -> 0 | AH11: 0 | AI11: 0 | AJ11: =AI11*AH11 -> 0 | AK11: 0 | AL11: 0 | AM11: =AL11*AK11 -> 0
B12: 0 | C12: 0 | D12: 0 | E12: 0 | F12: =E12*D12 -> 0 | G12: 0 | H12: 0 | I12: =H12*G12 -> 0 | J12: 0 | K12: 0 | L12: =K12*J12 -> 0 | M12: 0 | N12: 0 | O12: =N12*M12 -> 0 | P12: 0 | Q12: 0 | R12: =Q12*P12 -> 0 | S12: 0 | T12: 0 | U12: =T12*S12 -> 0 | V12: 0 | W12: 0 | X12: =W12*V12 -> 0 | Y12: 0 | Z12: 0 | AA12: =Z12*Y12 -> 0 | AB12: 0 | AC12: 0 | AD12: =AC12*AB12 -> 0 | AE12: 0 | AF12: 0 | AG12: =AF12*AE12 -> 0 | AH12: 0 | AI12: 0 | AJ12: =AI12*AH12 -> 0 | AK12: 0 | AL12: 0 | AM12: =AL12*AK12 -> 0
B13: 0 | C13: 0 | D13: 0 | E13: 0 | F13: =E13*D13 -> 0 | G13: 0 | H13: 0 | I13: =H13*G13 -> 0 | J13: 0 | K13: 0 | L13: =K13*J13 -> 0 | M13: 0 | N13: 0 | O13: =N13*M13 -> 0 | P13: 0 | Q13: 0 | R13: =Q13*P13 -> 0 | S13: 0 | T13: 0 | U13: =T13*S13 -> 0 | V13: 0 | W13: 0 | X13: =W13*V13 -> 0 | Y13: 0 | Z13: 0 | AA13: =Z13*Y13 -> 0 | AB13: 0 | AC13: 0 | AD13: =AC13*AB13 -> 0 | AE13: 0 | AF13: 0 | AG13: =AF13*AE13 -> 0 | AH13: 0 | AI13: 0 | AJ13: =AI13*AH13 -> 0 | AK13: 0 | AL13: 0 | AM13: =AL13*AK13 -> 0
B14: 0 | C14: 0 | D14: 0
E15: Total | F15: =SUM(F7:F14) -> 0 | H15: Total | I15: =SUM(I7:I14) -> 0 | K15: Total | L15: =SUM(L7:L14) -> 0 | N15: Total | O15: =SUM(O7:O14) -> 0 | Q15: Total | R15: =SUM(R7:R14) -> 0 | T15: Total | U15: =SUM(U7:U14) -> 0 | W15: Total | X15: =SUM(X7:X14) -> 0 | Z15: Total | AA15: =SUM(AA7:AA14) -> 0 | AC15: Total | AD15: =SUM(AD7:AD14) -> 0 | AF15: Total | AG15: =SUM(AG7:AG14) -> 0 | AI15: Total | AJ15: =SUM(AJ7:AJ14) -> 0 | AL15: Total | AM15: =SUM(AM7:AM14) -> 0

Sheet Desplacante  
A2: Menu
A3: Desplacante
E4: 44562 | F4: 44562 | G4: 44562 | H4: 45323 | I4: 45323 | J4: 45323 | K4: 45352 | L4: 45352 | M4: 45352 | N4: 45383 | O4: 45383 | P4: 45383 | Q4: 45413 | R4: 45413 | S4: 45413 | T4: 45444 | U4: 45444 | V4: 45444 | W4: 45474 | X4: 45474 | Y4: 45474 | Z4: 45505 | AA4: 45505 | AB4: 45505 | AC4: 45536 | AD4: 45536 | AE4: 45536 | AF4: 45566 | AG4: 45566 | AH4: 45566 | AI4: 45597 | AJ4: 45597 | AK4: 45597 | AL4: 45627 | AM4: 45627 | AN4: 45627
A5: Produto | B5: ID | C5: Volume tanque / lts | D5: Concentração g/lt | E5: Consumo Kg/lt | F5: Custo/Kg | G5: Custo Total | H5: Consumo Kg/lt | I5: Custo/Kg | J5: Custo Total | K5: Consumo Kg/lt | L5: Custo Kg/lt | M5: Custo Total | N5: Consumo Kg/lt | O5: Custo/Kg | P5: Custo Total | Q5: Consumo Kg/lt | R5: Custo/Kg | S5: Custo Total | T5: Consumo Kg/lt | U5: Custo/Kg | V5: Custo Total | W5: Consumo Kg/lt | X5: Custo/Kg | Y5: Custo Total | Z5: Consumo Kg/lt | AA5: Custo/Kg | AB5: Custo Total | AC5: Consumo Kg/lt | AD5: Custo/Kg | AE5: Custo Total | AF5: Consumo Kg/lt | AG5: Custo/Kg | AH5: Custo Total | AI5: Consumo Kg/lt | AJ5: Custo/Kg | AK5: Custo Total | AL5: Consumo Kg/lt | AM5: Custo/Kg | AN5: Custo Total
B6: 0 | C6: 0 | D6: 0 | E6: 0 | F6: 0 | G6: =E6*F6 -> 0 | H6: 0 | I6: 0 | J6: =I6*H6 -> 0 | K6: 0 | L6: 0 | M6: =L6*K6 -> 0 | N6: 0 | O6: 0 | P6: =O6*N6 -> 0 | Q6: 0 | R6: 0 | S6: =R6*Q6 -> 0 | T6: 0 | U6: 0 | V6: =U6*T6 -> 0 | W6: 0 | X6: 0 | Y6: =X6*W6 -> 0 | Z6: 0 | AA6: 0 | AB6: =AA6*Z6 -> 0 | AC6: 0 | AD6: 0 | AE6: =AD6*AC6 -> 0 | AF6: 0 | AG6: 0 | AH6: =AG6*AF6 -> 0 | AI6: 0 | AJ6: 0 | AK6: =AJ6*AI6 -> 0 | AL6: 0 | AM6: 0 | AN6: =AM6*AL6 -> 0
B7: 0 | C7: 0 | D7: 0 | E7: 0 | F7: 0 | G7: =E7*F7 -> 0 | H7: 0 | I7: 0 | J7: =I7*H7 -> 0 | K7: 0 | L7: 0 | M7: =L7*K7 -> 0 | N7: 0 | O7: 0 | P7: =O7*N7 -> 0 | Q7: 0 | R7: 0 | S7: =R7*Q7 -> 0 | T7: 0 | U7: 0 | V7: =U7*T7 -> 0 | W7: 0 | X7: 0 | Y7: =X7*W7 -> 0 | Z7: 0 | AA7: 0 | AB7: =AA7*Z7 -> 0 | AC7: 0 | AD7: 0 | AE7: =AD7*AC7 -> 0 | AF7: 0 | AG7: 0 | AH7: =AG7*AF7 -> 0 | AI7: 0 | AJ7: 0 | AK7: =AJ7*AI7 -> 0 | AL7: 0 | AM7: 0 | AN7: =AM7*AL7 -> 0
B8: 0 | C8: 0 | D8: 0 | E8: 0 | F8: 0 | G8: =E8*F8 -> 0 | H8: 0 | I8: 0 | J8: =I8*H8 -> 0 | K8: 0 | L8: 0 | M8: =L8*K8 -> 0 | N8: 0 | O8: 0 | P8: =O8*N8 -> 0 | Q8: 0 | R8: 0 | S8: =R8*Q8 -> 0 | T8: 0 | U8: 0 | V8: =U8*T8 -> 0 | W8: 0 | X8: 0 | Y8: =X8*W8 -> 0 | Z8: 0 | AA8: 0 | AB8: =AA8*Z8 -> 0 | AC8: 0 | AD8: 0 | AE8: =AD8*AC8 -> 0 | AF8: 0 | AG8: 0 | AH8: =AG8*AF8 -> 0 | AI8: 0 | AJ8: 0 | AK8: =AJ8*AI8 -> 0 | AL8: 0 | AM8: 0 | AN8: =AM8*AL8 -> 0
B9: 0 | C9: 0 | D9: 0 | E9: 0 | F9: 0 | G9: =E9*F9 -> 0 | H9: 0 | I9: 0 | J9: =I9*H9 -> 0 | K9: 0 | L9: 0 | M9: =L9*K9 -> 0 | N9: 0 | O9: 0 | P9: =O9*N9 -> 0 | Q9: 0 | R9: 0 | S9: =R9*Q9 -> 0 | T9: 0 | U9: 0 | V9: =U9*T9 -> 0 | W9: 0 | X9: 0 | Y9: =X9*W9 -> 0 | Z9: 0 | AA9: 0 | AB9: =AA9*Z9 -> 0 | AC9: 0 | AD9: 0 | AE9: =AD9*AC9 -> 0 | AF9: 0 | AG9: 0 | AH9: =AG9*AF9 -> 0 | AI9: 0 | AJ9: 0 | AK9: =AJ9*AI9 -> 0 | AL9: 0 | AM9: 0 | AN9: =AM9*AL9 -> 0
B10: 0 | C10: 0 | D10: 0 | E10: 0 | F10: 0 | G10: =E10*F10 -> 0 | H10: 0 | I10: 0 | J10: =I10*H10 -> 0 | K10: 0 | L10: 0 | M10: =L10*K10 -> 0 | N10: 0 | O10: 0 | P10: =O10*N10 -> 0 | Q10: 0 | R10: 0 | S10: =R10*Q10 -> 0 | T10: 0 | U10: 0 | V10: =U10*T10 -> 0 | W10: 0 | X10: 0 | Y10: =X10*W10 -> 0 | Z10: 0 | AA10: 0 | AB10: =AA10*Z10 -> 0 | AC10: 0 | AD10: 0 | AE10: =AD10*AC10 -> 0 | AF10: 0 | AG10: 0 | AH10: =AG10*AF10 -> 0 | AI10: 0 | AJ10: 0 | AK10: =AJ10*AI10 -> 0 | AL10: 0 | AM10: 0 | AN10: =AM10*AL10 -> 0
B11: 0 | C11: 0 | D11: 0 | E11: 0 | F11: 0 | G11: =E11*F11 -> 0 | H11: 0 | I11: 0 | J11: =I11*H11 -> 0 | K11: 0 | L11: 0 | M11: =L11*K11 -> 0 | N11: 0 | O11: 0 | P11: =O11*N11 -> 0 | Q11: 0 | R11: 0 | S11: =R11*Q11 -> 0 | T11: 0 | U11: 0 | V11: =U11*T11 -> 0 | W11: 0 | X11: 0 | Y11: =X11*W11 -> 0 | Z11: 0 | AA11: 0 | AB11: =AA11*Z11 -> 0 | AC11: 0 | AD11: 0 | AE11: =AD11*AC11 -> 0 | AF11: 0 | AG11: 0 | AH11: =AG11*AF11 -> 0 | AI11: 0 | AJ11: 0 | AK11: =AJ11*AI11 -> 0 | AL11: 0 | AM11: 0 | AN11: =AM11*AL11 -> 0
B12: 0 | C12: 0 | D12: 0 | E12: 0 | F12: 0 | G12: =E12*F12 -> 0 | H12: 0 | I12: 0 | J12: =I12*H12 -> 0 | K12: 0 | L12: 0 | M12: =L12*K12 -> 0 | N12: 0 | O12: 0 | P12: =O12*N12 -> 0 | Q12: 0 | R12: 0 | S12: =R12*Q12 -> 0 | T12: 0 | U12: 0 | V12: =U12*T12 -> 0 | W12: 0 | X12: 0 | Y12: =X12*W12 -> 0 | Z12: 0 | AA12: 0 | AB12: =AA12*Z12 -> 0 | AC12: 0 | AD12: 0 | AE12: =AD12*AC12 -> 0 | AF12: 0 | AG12: 0 | AH12: =AG12*AF12 -> 0 | AI12: 0 | AJ12: 0 | AK12: =AJ12*AI12 -> 0 | AL12: 0 | AM12: 0 | AN12: =AM12*AL12 -> 0
