Workbook

Sheet Menu
A1: B

Sheet Resumo de Custo
A2: Menu | E2: Resumo de Custo | K2: =TODAY() -> 46114 | L2: =K3-K2 -> -108
K3: 46006
A4: Horas Trabalhadas
A5: 220
B6: Janeiro | L6: Fevereiro | V6: Março | AF6: Abril | AP6: Maio | AZ6: Junho | BJ6: Julho | BT6: Agosto | CD6: Setembro | CN6: Outubro | CX6: Novembro | DH6: Dezembro | DV6: Custo Total | EI6: Custo Produto Químico
A7: Linha | B7: Produto Químico | C7: M.O.D | D7: M.O.I | E7: Custo Variáveis | F7: Outros Custos | G7: Transporte | H7: Manutenção | I7: Investimentos | J7: Total | K7: Custo Hora | L7: Produto Químico | M7: M.O.D | N7: M.O.I | O7: Custo Variáveis | P7: Outros Custos | Q7: Transporte | R7: Manutenção | S7: Investimentos | T7: Total | U7: Custo Hora | V7: Produto Químico | W7: M.O.D | X7: M.O.I | Y7: Custo Variáveis | Z7: Outros Custos | AA7: Transporte | AB7: Manutenção | AC7: Investimentos | AD7: Total | AE7: Custo Hora | AF7: Produto Químico | AG7: M.O.D | AH7: M.O.I | AI7: Custo Variáveis | AJ7: Outros Custos | AK7: Transporte | AL7: Manutenção | AM7: Investimentos | AN7: Total | AO7: Custo Hora | AP7: Produto Químico | AQ7: M.O.D | AR7: M.O.I | AS7: Custo Variáveis | AT7: Outros Custos | AU7: Transporte | AV7: Manutenção | AW7: Investimentos | AX7: Total | AY7: Custo Hora | AZ7: Produto Químico | BA7: M.O.D | BB7: M.O.I | BC7: Custo Variáveis | BD7: Outros Custos | BE7: Transporte | BF7: Manutenção | BG7: Investimentos | BH7: Total | BI7: Custo Hora | BJ7: Produto Químico | BK7: M.O.D | BL7: M.O.I | BM7: Custo Variáveis | BN7: Outros Custos | BO7: Transporte | BP7: Manutenção | BQ7: Investimentos | BR7: Total | BS7: Custo Hora | BT7: Produto Químico | BU7: M.O.D | BV7: M.O.I | BW7: Custo Variáveis | BX7: Outros Custos | BY7: Transporte | BZ7: Manutenção | CA7: Investimentos | CB7: Total | CC7: Custo Hora | CD7: Produto Químico | CE7: M.O.D | CF7: M.O.I | CG7: Custo Variáveis | CH7: Outros Custos | CI7: Transporte | CJ7: Manutenção | CK7: Investimentos | CL7: Total | CM7: Custo Hora | CN7: Produto Químico | CO7: M.O.D | CP7: M.O.I | CQ7: Custo Variáveis | CR7: Outros Custos | CS7: Transporte | CT7: Manutenção | CU7: Investimentos | CV7: Total | CW7: Custo Hora | CX7: Produto Químico | CY7: M.O.D | CZ7: M.O.I | DA7: Custo Variáveis | DB7: Outros Custos | DC7: Transporte | DD7: Manutenção | DE7: Investimentos | DF7: Total | DG7: Custo Hora | DH7: Produto Químico | DI7: M.O.D | DJ7: M.O.I | DK7: Custo Variáveis | DL7: Outros Custos | DM7: Transporte | DN7: Manutenção | DO7: Investimentos | DP7: Total | DQ7: Custo Hora | DS7: Jan | DT7: Fev | DU7: Mar | DV7: Abr | DW7: Mai | DX7: Jun | DY7: Jul | DZ7: Ago | EA7: Set | EB7: Out | EC7: Nov | ED7: Dez | EF7: Jan | EG7: Fev | EH7: Mar | EI7: Abr | EJ7: Mai | EK7: Jun | EL7: Jul | EM7: Ago | EN7: Set | EO7: Out | EP7: Nov | EQ7: Dez
A8: Linha 1 Zn Alc. Aut | B8: ='Lnha 1 Zn Alc. Aut'!G15 -> 0 | C8: ='Resumo M.O'!C2 -> 5410.4181 | D8: ='Resumo M.O'!$C$13 -> 9143.3131 | E8: ='Resumo Custos Variáveis'!$E$21 -> 0 | F8: ='Outros Custos'!$C$31 -> 0 | G8: =Transporte!$C$20 -> 0 | H8: =Manutenção!$C$21 -> 0 | I8: =Investimentos!G10 -> 0 | J8: =SUM(B8:I8) -> 14553.731 | K8: =IF($L$2>=1,J8/$A$5,0) -> 0 | L8: ='Lnha 1 Zn Alc. Aut'!J15 -> 0 | M8: ='Resumo M.O'!D2 -> 5410.4181 | N8: ='Resumo M.O'!$D$13 -> 9143.3131 | O8: ='Resumo Custos Variáveis'!$F$21 -> 0 | P8: ='Outros Custos'!$D$31 -> 0 | Q8: =Transporte!$D$20 -> 0 | R8: =Manutenção!$D$21 -> 0 | S8: =I8 -> 0 | T8: =SUM(L8:S8) -> 14553.731 | U8: =IF($L$2>=1,T8/$A$5,0) -> 0 | V8: ='Lnha 1 Zn Alc. Aut'!M15 -> 0 | W8: ='Resumo M.O'!E2 -> 5410.4181 | X8: ='Resumo M.O'!$E$13 -> 9143.3131 | Y8: ='Resumo Custos Variáveis'!$G$21 -> 0 | Z8: ='Outros Custos'!$E$31 -> 0 | AA8: =Transporte!$E$20 -> 0 | AB8: =Manutenção!$E$21 -> 0 | AC8: =S8 -> 0 | AD8: =SUM(V8:AC8) -> 14553.731 | AE8: =IF($L$2>=1,AD8/$A$5,0) -> 0 | AF8: ='Lnha 1 Zn Alc. Aut'!P15 -> 0 | AG8: ='Resumo M.O'!F2 -> 5410.4181 | AH8: ='Resumo M.O'!$F$13 -> 9143.3131 | AI8: ='Resumo Custos Variáveis'!$H$21 -> 0 | AJ8: ='Outros Custos'!$F$31 -> 0 | AK8: =Transporte!$F$20 -> 0 | AL8: =Manutenção!$F$21 -> 0 | AM8: =AC8 -> 0 | AN8: =SUM(AF8:AM8) -> 14553.731 | AO8: =IF(L2>=1,AN8/$A$5,0) -> 0 | AP8: ='Lnha 1 Zn Alc. Aut'!S15 -> 0 | AQ8: ='Resumo M.O'!G2 -> 5410.4181 | AR8: ='Resumo M.O'!$G$13 -> 9143.3131 | AS8: ='Resumo Custos Variáveis'!$I$21 -> 0 | AT8: ='Outros Custos'!$G$31 -> 0 | AU8: =Transporte!$G$20 -> 0 | AV8: =Manutenção!$G$21 -> 0 | AW8: =AM8 -> 0 | AX8: =SUM(AP8:AW8) -> 14553.731 | AY8: =IF(L2>=1,AX8/$A$5,0) -> 0 | AZ8: ='Lnha 1 Zn Alc. Aut'!V15 -> 0 | BA8: ='Resumo M.O'!H2 -> 5410.4181 | BB8: ='Resumo M.O'!$H$13 -> 9143.3131 | BC8: ='Resumo Custos Variáveis'!$J$21 -> 0 | BD8: ='Outros Custos'!$H$31 -> 0 | BE8: =Transporte!$H$20 -> 0 | BF8: =Manutenção!$H$21 -> 0 | BG8: =AW8 -> 0 | BH8: =SUM(AZ8:BG8) -> 14553.731 | BI8: =IF(L2>=1,BH8/$A$5,0) -> 0 | BJ8: ='Lnha 1 Zn Alc. Aut'!Y15 -> 0 | BK8: ='Resumo M.O'!I2 -> 5410.4181 | BL8: ='Resumo M.O'!$I$13 -> 9143.3131 | BM8: ='Resumo Custos Variáveis'!$K$21 -> 0 | BN8: ='Outros Custos'!$I$31 -> 0 | BO8: =Transporte!$I$20 -> 0 | BP8: =Manutenção!$I$21 -> 0 | BQ8: =BG8 -> 0 | BR8: =SUM(BJ8:BQ8) -> 14553.731 | BS8: =IF(L2>=1,BR8/$A$5,0) -> 0 | BT8: ='Lnha 1 Zn Alc. Aut'!AB15 -> 0 | BU8: ='Resumo M.O'!J2 -> 5410.4181 | BV8: ='Resumo M.O'!$J$13 -> 9143.3131 | BW8: ='Resumo Custos Variáveis'!$L$21 -> 0 | BX8: ='Outros Custos'!$J$31 -> 0 | BY8: =Transporte!$J$20 -> 0 | BZ8: =Manutenção!$J$21 -> 0 | CA8: =BQ8 -> 0 | CB8: =SUM(BT8:CA8) -> 14553.731 | CC8: =IF(L2>=1,CB8/$A$5,0) -> 0 | CD8: ='Lnha 1 Zn Alc. Aut'!AE15 -> 0 | CE8: ='Resumo M.O'!K2 -> 5410.4181 | CF8: ='Resumo M.O'!$K$13 -> 9143.3131 | CG8: ='Resumo Custos Variáveis'!$M$21 -> 4328.5714 | CH8: ='Outros Custos'!$K$31 -> 2140 | CI8: =Transporte!$K$20 -> 0 | CJ8: =Manutenção!$K$21 -> 10000 | CK8: =CA8 -> 0 | CL8: =SUM(CD8:CK8) -> 31022.303 | CM8: =IF(L2>=1,CL8/$A$5,0) -> 0 | CN8: ='Lnha 1 Zn Alc. Aut'!AH15 -> 0 | CO8: ='Resumo M.O'!L2 -> 5410.4181 | CP8: ='Resumo M.O'!$L$13 -> 9143.3131 | CQ8: ='Resumo Custos Variáveis'!$N$21 -> 0 | CR8: ='Outros Custos'!$L$31 -> 0 | CS8: =Transporte!$L$20 -> 0 | CT8: =Manutenção!$L$21 -> 10000 | CU8: =CK8 -> 0 | CV8: =SUM(CN8:CU8) -> 24553.731 | CW8: =IF(L2>=1,CV8/$A$5,0) -> 0 | CX8: ='Lnha 1 Zn Alc. Aut'!AK15 -> 0 | CY8: ='Resumo M.O'!M2 -> 5410.4181 | CZ8: ='Resumo M.O'!$M$13 -> 9143.3131 | DA8: ='Resumo Custos Variáveis'!$O$21 -> 0 | DB8: ='Outros Custos'!$M$31 -> 0 | DC8: =Transporte!$M$20 -> 0 | DD8: =Manutenção!$M$21 -> 10000 | DE8: =CU8 -> 0 | DF8: =SUM(CX8:DE8) -> 24553.731 | DG8: =IF(L2>=1,DF8/$A$5,0) -> 0 | DH8: ='Lnha 1 Zn Alc. Aut'!AN15 -> 0 | DI8: ='Resumo M.O'!N2 -> 5410.4181 | DJ8: ='Resumo M.O'!$N$13 -> 9143.3131 | DK8: ='Resumo Custos Variáveis'!$P$21 -> 0 | DL8: ='Outros Custos'!$N$31 -> 0 | DM8: =Transporte!$N$20 -> 0 | DN8: =Manutenção!$N$21 -> 10000 | DO8: =DE8 -> 0 | DP8: =SUM(DH8:DO8) -> 24553.731 | DQ8: =IF(L2>=1,DP8/$A$5,0) -> 0 | DS8: =K8 -> 0 | DT8: =U8 -> 0 | DU8: =AE8 -> 0 | DV8: =AO8 -> 0 | DW8: =AY8 -> 0 | DX8: =BI8 -> 0 | DY8: =BS8 -> 0 | DZ8: =CC8 -> 0 | EA8: =CM8 -> 0 | EB8: =CW8 -> 0 | EC8: =DG8 -> 0 | ED8: =DQ8 -> 0 | EF8: =B8/$A$5 -> 0 | EG8: =L8/$A$5 -> 0 | EH8: =V8/$A$5 -> 0 | EI8: =AF8/$A$5 -> 0 | EJ8: =AP8/$A$5 -> 0 | EK8: =AZ8/$A$5 -> 0 | EL8: =BJ8/$A$5 -> 0 | EM8: =BT8/$A$5 -> 0 | EN8: =CD8/$A$5 -> 0 | EO8: =CN8/$A$5 -> 0 | EP8: =CX8/$A$5 -> 0 | EQ8: =DH8/$A$5 -> 0
A9: Linha 2 Zn Alc. Aut | B9: ='Linha 2 Zn Alc. Aut'!G16 -> 0 | C9: ='Resumo M.O'!C3 -> 5410.4043 | D9: ='Resumo M.O'!$C$13 -> 9143.3131 | E9: ='Resumo Custos Variáveis'!$E$21 -> 0 | F9: ='Outros Custos'!$C$31 -> 0 | G9: =Transporte!$C$20 -> 0 | H9: =Manutenção!$C$21 -> 0 | I9: =Investimentos!G15 -> 0 | J9: =SUM(B9:I9) -> 14553.717 | K9: =IF($L$2>=1,J9/$A$5,0) -> 0 | L9: ='Linha 2 Zn Alc. Aut'!J16 -> 0 | M9: ='Resumo M.O'!D3 -> 5410.4043 | N9: ='Resumo M.O'!$D$13 -> 9143.3131 | O9: ='Resumo Custos Variáveis'!$F$21 -> 0 | P9: ='Outros Custos'!$D$31 -> 0 | Q9: =Transporte!$D$20 -> 0 | R9: =Manutenção!$D$21 -> 0 | S9: =I9 -> 0 | T9: =SUM(L9:S9) -> 14553.717 | U9: =IF($L$2>=1,T9/$A$5,0) -> 0 | V9: ='Linha 2 Zn Alc. Aut'!M16 -> 0 | W9: ='Resumo M.O'!E3 -> 5410.4043 | X9: ='Resumo M.O'!$E$13 -> 9143.3131 | Y9: ='Resumo Custos Variáveis'!$G$21 -> 0 | Z9: ='Outros Custos'!$E$31 -> 0 | AA9: =Transporte!$E$20 -> 0 | AB9: =Manutenção!$E$21 -> 0 | AC9: =S9 -> 0 | AD9: =SUM(V9:AC9) -> 14553.717 | AE9: =IF($L$2>=1,AD9/$A$5,0) -> 0 | AF9: ='Linha 2 Zn Alc. Aut'!P16 -> 0 | AG9: ='Resumo M.O'!F3 -> 5410.4043 | AH9: ='Resumo M.O'!$F$13 -> 9143.3131 | AI9: ='Resumo Custos Variáveis'!$H$21 -> 0 | AJ9: ='Outros Custos'!$F$31 -> 0 | AK9: =Transporte!$F$20 -> 0 | AL9: =Manutenção!$F$21 -> 0 | AM9: =AC9 -> 0 | AN9: =SUM(AF9:AM9) -> 14553.717 | AO9: =IF(L2>=1,AN9/$A$5,0) -> 0 | AP9: ='Linha 2 Zn Alc. Aut'!S16 -> 0 | AQ9: ='Resumo M.O'!G3 -> 5410.4043 | AR9: ='Resumo M.O'!$G$13 -> 9143.3131 | AS9: ='Resumo Custos Variáveis'!$I$21 -> 0 | AT9: ='Outros Custos'!$G$31 -> 0 | AU9: =Transporte!$G$20 -> 0 | AV9: =Manutenção!$G$21 -> 0 | AW9: =AM9 -> 0 | AX9: =SUM(AP9:AW9) -> 14553.717 | AY9: =IF(L2>=1,AX9/$A$5,0) -> 0 | AZ9: ='Linha 2 Zn Alc. Aut'!V16 -> 0 | BA9: ='Resumo M.O'!H3 -> 5410.4043 | BB9: ='Resumo M.O'!$H$13 -> 9143.3131 | BC9: ='Resumo Custos Variáveis'!$J$21 -> 0 | BD9: ='Outros Custos'!$H$31 -> 0 | BE9: =Transporte!$H$20 -> 0 | BF9: =Manutenção!$H$21 -> 0 | BG9: =AW9 -> 0 | BH9: =SUM(AZ9:BG9) -> 14553.717 | BI9: =IF(L2>=1,BH9/$A$5,0) -> 0 | BJ9: ='Linha 2 Zn Alc. Aut'!Y16 -> 0 | BK9: ='Resumo M.O'!I3 -> 5410.4043 | BL9: ='Resumo M.O'!$I$13 -> 9143.3131 | BM9: ='Resumo Custos Variáveis'!$K$21 -> 0 | BN9: ='Outros Custos'!$I$31 -> 0 | BO9: =Transporte!$I$20 -> 0 | BP9: =Manutenção!$I$21 -> 0 | BQ9: =BG9 -> 0 | BR9: =SUM(BJ9:BQ9) -> 14553.717 | BS9: =IF(L2>=1,BR9/$A$5,0) -> 0 | BT9: ='Linha 2 Zn Alc. Aut'!AB16 -> 0 | BU9: ='Resumo M.O'!J3 -> 5410.4043 | BV9: ='Resumo M.O'!$J$13 -> 9143.3131 | BW9: ='Resumo Custos Variáveis'!$L$21 -> 0 | BX9: ='Outros Custos'!$J$31 -> 0 | BY9: =Transporte!$J$20 -> 0 | BZ9: =Manutenção!$J$21 -> 0 | CA9: =BQ9 -> 0 | CB9: =SUM(BT9:CA9) -> 14553.717 | CC9: =IF(L2>=1,CB9/$A$5,0) -> 0 | CD9: ='Linha 2 Zn Alc. Aut'!AE16 -> 0 | CE9: ='Resumo M.O'!K3 -> 5410.4043 | CF9: ='Resumo M.O'!$K$13 -> 9143.3131 | CG9: ='Resumo Custos Variáveis'!$M$21 -> 4328.5714 | CH9: ='Outros Custos'!$K$31 -> 2140 | CI9: =Transporte!$K$20 -> 0 | CJ9: =Manutenção!$K$21 -> 10000 | CK9: =CA9 -> 0 | CL9: =SUM(CD9:CK9) -> 31022.289 | CM9: =IF(L2>=1,CL9/$A$5,0) -> 0 | CN9: ='Linha 2 Zn Alc. Aut'!AH16 -> 0 | CO9: ='Resumo M.O'!L3 -> 5410.4043 | CP9: ='Resumo M.O'!$L$13 -> 9143.3131 | CQ9: ='Resumo Custos Variáveis'!$N$21 -> 0 | CR9: ='Outros Custos'!$L$31 -> 0 | CS9: =Transporte!$L$20 -> 0 | CT9: =Manutenção!$L$21 -> 10000 | CU9: =CK9 -> 0 | CV9: =SUM(CN9:CU9) -> 24553.717 | CW9: =IF(L2>=1,CV9/$A$5,0) -> 0 | CX9: ='Linha 2 Zn Alc. Aut'!AK16 -> 0 | CY9: ='Resumo M.O'!M3 -> 5410.4043 | CZ9: ='Resumo M.O'!$M$13 -> 9143.3131 | DA9: ='Resumo Custos Variáveis'!$O$21 -> 0 | DB9: ='Outros Custos'!$M$31 -> 0 | DC9: =Transporte!$M$20 -> 0 | DD9: =Manutenção!$M$21 -> 10000 | DE9: =CU9 -> 0 | DF9: =SUM(CX9:DE9) -> 24553.717 | DG9: =IF(L2>=1,DF9/$A$5,0) -> 0 | DH9: ='Linha 2 Zn Alc. Aut'!AN16 -> 0 | DI9: ='Resumo M.O'!N3 -> 5410.4043 | DJ9: ='Resumo M.O'!$N$13 -> 9143.3131 | DK9: ='Resumo Custos Variáveis'!$P$21 -> 0 | DL9: ='Outros Custos'!$N$31 -> 0 | DM9: =Transporte!$N$20 -> 0 | DN9: =Manutenção!$N$21 -> 10000 | DO9: =DE9 -> 0 | DP9: =SUM(DH9:DO9) -> 24553.717 | DQ9: =IF(L2>=1,DP9/$A$5,0) -> 0 | DS9: =K9 -> 0 | DT9: =U9 -> 0 | DU9: =AE9 -> 0 | DV9: =AO9 -> 0 | DW9: =AY9 -> 0 | DX9: =BI9 -> 0 | DY9: =BS9 -> 0 | DZ9: =CC9 -> 0 | EA9: =CM9 -> 0 | EB9: =CW9 -> 0 | EC9: =DG9 -> 0 | ED9: =DQ9 -> 0 | EF9: =B9/$A$5 -> 0 | EG9: =L9/$A$5 -> 0 | EH9: =V9/$A$5 -> 0 | EI9: =AF9/$A$5 -> 0 | EJ9: =AP9/$A$5 -> 0 | EK9: =AZ9/$A$5 -> 0 | EL9: =BJ9/$A$5 -> 0 | EM9: =BT9/$A$5 -> 0 | EN9: =CD9/$A$5 -> 0 | EO9: =CN9/$A$5 -> 0 | EP9: =CX9/$A$5 -> 0 | EQ9: =DH9/$A$5 -> 0
A10: Linha 3 Zn Alc. Aut | B10: ='Linha 3 Zn Alc. Aut'!G17 -> 0 | C10: ='Resumo M.O'!C4 -> 4028.0981 | D10: ='Resumo M.O'!$C$13 -> 9143.3131 | E10: ='Resumo Custos Variáveis'!$E$21 -> 0 | F10: ='Outros Custos'!$C$31 -> 0 | G10: =Transporte!$C$20 -> 0 | H10: =Manutenção!$C$21 -> 0 | I10: =Investimentos!G20 -> 0 | J10: =SUM(B10:I10) -> 13171.411 | K10: =IF($L$2>=1,J10/$A$5,0) -> 0 | L10: ='Linha 3 Zn Alc. Aut'!J17 -> 0 | M10: ='Resumo M.O'!D4 -> 4028.0981 | N10: ='Resumo M.O'!$D$13 -> 9143.3131 | O10: ='Resumo Custos Variáveis'!$F$21 -> 0 | P10: ='Outros Custos'!$D$31 -> 0 | Q10: =Transporte!$D$20 -> 0 | R10: =Manutenção!$D$21 -> 0 | S10: =I10 -> 0 | T10: =SUM(L10:S10) -> 13171.411 | U10: =IF($L$2>=1,T10/$A$5,0) -> 0 | V10: ='Linha 3 Zn Alc. Aut'!M17 -> 0 | W10: ='Resumo M.O'!E4 -> 4028.0981 | X10: ='Resumo M.O'!$E$13 -> 9143.3131 | Y10: ='Resumo Custos Variáveis'!$G$21 -> 0 | Z10: ='Outros Custos'!$E$31 -> 0 | AA10: =Transporte!$E$20 -> 0 | AB10: =Manutenção!$E$21 -> 0 | AC10: =S10 -> 0 | AD10: =SUM(V10:AC10) -> 13171.411 | AE10: =IF($L$2>=1,AD10/$A$5,0) -> 0 | AF10: ='Linha 3 Zn Alc. Aut'!P17 -> 0 | AG10: ='Resumo M.O'!F4 -> 4028.0981 | AH10: ='Resumo M.O'!$F$13 -> 9143.3131 | AI10: ='Resumo Custos Variáveis'!$H$21 -> 0 | AJ10: ='Outros Custos'!$F$31 -> 0 | AK10: =Transporte!$F$20 -> 0 | AL10: =Manutenção!$F$21 -> 0 | AM10: =AC10 -> 0 | AN10: =SUM(AF10:AM10) -> 13171.411 | AO10: =IF(L2>=1,AN10/$A$5,0) -> 0 | AP10: ='Linha 3 Zn Alc. Aut'!S17 -> 0 | AQ10: ='Resumo M.O'!G4 -> 4028.0981 | AR10: ='Resumo M.O'!$G$13 -> 9143.3131 | AS10: ='Resumo Custos Variáveis'!$I$21 -> 0 | AT10: ='Outros Custos'!$G$31 -> 0 | AU10: =Transporte!$G$20 -> 0 | AV10: =Manutenção!$G$21 -> 0 | AW10: =AM10 -> 0 | AX10: =SUM(AP10:AW10) -> 13171.411 | AY10: =IF(L2>=1,AX10/$A$5,0) -> 0 | AZ10: ='Linha 3 Zn Alc. Aut'!V17 -> 0 | BA10: ='Resumo M.O'!H4 -> 4028.0981 | BB10: ='Resumo M.O'!$H$13 -> 9143.3131 | BC10: ='Resumo Custos Variáveis'!$J$21 -> 0 | BD10: ='Outros Custos'!$H$31 -> 0 | BE10: =Transporte!$H$20 -> 0 | BF10: =Manutenção!$H$21 -> 0 | BG10: =AW10 -> 0 | BH10: =SUM(AZ10:BG10) -> 13171.411 | BI10: =IF(L2>=1,BH10/$A$5,0) -> 0 | BJ10: ='Linha 3 Zn Alc. Aut'!Y17 -> 0 | BK10: ='Resumo M.O'!I4 -> 4028.0981 | BL10: ='Resumo M.O'!$I$13 -> 9143.3131 | BM10: ='Resumo Custos Variáveis'!$K$21 -> 0 | BN10: ='Outros Custos'!$I$31 -> 0 | BO10: =Transporte!$I$20 -> 0 | BP10: =Manutenção!$I$21 -> 0 | BQ10: =BG10 -> 0 | BR10: =SUM(BJ10:BQ10) -> 13171.411 | BS10: =IF(L2>=1,BR10/$A$5,0) -> 0 | BT10: ='Linha 3 Zn Alc. Aut'!AB17 -> 0 | BU10: ='Resumo M.O'!J4 -> 4028.0981 | BV10: ='Resumo M.O'!$J$13 -> 9143.3131 | BW10: ='Resumo Custos Variáveis'!$L$21 -> 0 | BX10: ='Outros Custos'!$J$31 -> 0 | BY10: =Transporte!$J$20 -> 0 | BZ10: =Manutenção!$J$21 -> 0 | CA10: =BQ10 -> 0 | CB10: =SUM(BT10:CA10) -> 13171.411 | CC10: =IF(L2>=1,CB10/$A$5,0) -> 0 | CD10: ='Linha 3 Zn Alc. Aut'!AE17 -> 0 | CE10: ='Resumo M.O'!K4 -> 4028.0981 | CF10: ='Resumo M.O'!$K$13 -> 9143.3131 | CG10: ='Resumo Custos Variáveis'!$M$21 -> 4328.5714 | CH10: ='Outros Custos'!$K$31 -> 2140 | CI10: =Transporte!$K$20 -> 0 | CJ10: =Manutenção!$K$21 -> 10000 | CK10: =CA10 -> 0 | CL10: =SUM(CD10:CK10) -> 29639.983 | CM10: =IF(L2>=1,CL10/$A$5,0) -> 0 | CN10: ='Linha 3 Zn Alc. Aut'!AH17 -> 0 | CO10: ='Resumo M.O'!L4 -> 4028.0981 | CP10: ='Resumo M.O'!$L$13 -> 9143.3131 | CQ10: ='Resumo Custos Variáveis'!$N$21 -> 0 | CR10: ='Outros Custos'!$L$31 -> 0 | CS10: =Transporte!$L$20 -> 0 | CT10: =Manutenção!$L$21 -> 10000 | CU10: =CK10 -> 0 | CV10: =SUM(CN10:CU10) -> 23171.411 | CW10: =IF(L2>=1,CV10/$A$5,0) -> 0 | CX10: ='Linha 3 Zn Alc. Aut'!AK17 -> 0 | CY10: ='Resumo M.O'!M4 -> 4028.0981 | CZ10: ='Resumo M.O'!$M$13 -> 9143.3131 | DA10: ='Resumo Custos Variáveis'!$O$21 -> 0 | DB10: ='Outros Custos'!$M$31 -> 0 | DC10: =Transporte!$M$20 -> 0 | DD10: =Manutenção!$M$21 -> 10000 | DE10: =CU10 -> 0 | DF10: =SUM(CX10:DE10) -> 23171.411 | DG10: =IF(L2>=1,DF10/$A$5,0) -> 0 | DH10: ='Linha 3 Zn Alc. Aut'!AN17 -> 0 | DI10: ='Resumo M.O'!N4 -> 4028.0981 | DJ10: ='Resumo M.O'!$N$13 -> 9143.3131 | DK10: ='Resumo Custos Variáveis'!$P$21 -> 0 | DL10: ='Outros Custos'!$N$31 -> 0 | DM10: =Transporte!$N$20 -> 0 | DN10: =Manutenção!$N$21 -> 10000 | DO10: =DE10 -> 0 | DP10: =SUM(DH10:DO10) -> 23171.411 | DQ10: =IF(L2>=1,DP10/$A$5,0) -> 0 | DS10: =K10 -> 0 | DT10: =U10 -> 0 | DU10: =AE10 -> 0 | DV10: =AO10 -> 0 | DW10: =AY10 -> 0 | DX10: =BI10 -> 0 | DY10: =BS10 -> 0 | DZ10: =CC10 -> 0 | EA10: =CM10 -> 0 | EB10: =CW10 -> 0 | EC10: =DG10 -> 0 | ED10: =DQ10 -> 0 | EF10: =B10/$A$5 -> 0 | EG10: =L10/$A$5 -> 0 | EH10: =V10/$A$5 -> 0 | EI10: =AF10/$A$5 -> 0 | EJ10: =AP10/$A$5 -> 0 | EK10: =AZ10/$A$5 -> 0 | EL10: =BJ10/$A$5 -> 0 | EM10: =BT10/$A$5 -> 0 | EN10: =CD10/$A$5 -> 0 | EO10: =CN10/$A$5 -> 0 | EP10: =CX10/$A$5 -> 0 | EQ10: =DH10/$A$5 -> 0
A11: Linha 4 Zn Alc. Manual | B11: =+'Linha 4 Zn Alc. Manual'!G15 -> 0 | C11: ='Resumo M.O'!C5 -> 3961.4925 | D11: ='Resumo M.O'!$C$13 -> 9143.3131 | E11: ='Resumo Custos Variáveis'!$E$21 -> 0 | F11: ='Outros Custos'!$C$31 -> 0 | G11: =Transporte!$C$20 -> 0 | H11: =Manutenção!$C$21 -> 0 | I11: =Investimentos!G27 -> 0 | J11: =SUM(B11:I11) -> 13104.806 | K11: =IF($L$2>=1,J11/$A$5,0) -> 0 | L11: ='Linha 4 Zn Alc. Manual'!J15 -> 0 | M11: ='Resumo M.O'!D5 -> 3961.4925 | N11: ='Resumo M.O'!$D$13 -> 9143.3131 | O11: ='Resumo Custos Variáveis'!$F$21 -> 0 | P11: ='Outros Custos'!$D$31 -> 0 | Q11: =Transporte!$D$20 -> 0 | R11: =Manutenção!$D$21 -> 0 | S11: =I11 -> 0 | T11: =SUM(L11:S11) -> 13104.806 | U11: =IF($L$2>=1,T11/$A$5,0) -> 0 | V11: ='Linha 4 Zn Alc. Manual'!M15 -> 0 | W11: ='Resumo M.O'!E5 -> 3961.4925 | X11: ='Resumo M.O'!$E$13 -> 9143.3131 | Y11: ='Resumo Custos Variáveis'!$G$21 -> 0 | Z11: ='Outros Custos'!$E$31 -> 0 | AA11: =Transporte!$E$20 -> 0 | AB11: =Manutenção!$E$21 -> 0 | AC11: =S11 -> 0 | AD11: =SUM(V11:AC11) -> 13104.806 | AE11: =IF($L$2>=1,AD11/$A$5,0) -> 0 | AF11: ='Linha 4 Zn Alc. Manual'!P15 -> 0 | AG11: ='Resumo M.O'!F5 -> 3961.4925 | AH11: ='Resumo M.O'!$F$13 -> 9143.3131 | AI11: ='Resumo Custos Variáveis'!$H$21 -> 0 | AJ11: ='Outros Custos'!$F$31 -> 0 | AK11: =Transporte!$F$20 -> 0 | AL11: =Manutenção!$F$21 -> 0 | AM11: =AC11 -> 0 | AN11: =SUM(AF11:AM11) -> 13104.806 | AO11: =IF(L2>=1,AN11/$A$5,0) -> 0 | AP11: ='Linha 4 Zn Alc. Manual'!S15 -> 0 | AQ11: ='Resumo M.O'!G5 -> 3961.4925 | AR11: ='Resumo M.O'!$G$13 -> 9143.3131 | AS11: ='Resumo Custos Variáveis'!$I$21 -> 0 | AT11: ='Outros Custos'!$G$31 -> 0 | AU11: =Transporte!$G$20 -> 0 | AV11: =Manutenção!$G$21 -> 0 | AW11: =AM11 -> 0 | AX11: =SUM(AP11:AW11) -> 13104.806 | AY11: =IF(L2>=1,AX11/$A$5,0) -> 0 | AZ11: ='Linha 4 Zn Alc. Manual'!V15 -> 0 | BA11: ='Resumo M.O'!H5 -> 3961.4925 | BB11: ='Resumo M.O'!$H$13 -> 9143.3131 | BC11: ='Resumo Custos Variáveis'!$J$21 -> 0 | BD11: ='Outros Custos'!$H$31 -> 0 | BE11: =Transporte!$H$20 -> 0 | BF11: =Manutenção!$H$21 -> 0 | BG11: =AW11 -> 0 | BH11: =SUM(AZ11:BG11) -> 13104.806 | BI11: =IF(L2>=1,BH11/$A$5,0) -> 0 | BJ11: ='Linha 4 Zn Alc. Manual'!Y15 -> 0 | BK11: ='Resumo M.O'!I5 -> 3961.4925 | BL11: ='Resumo M.O'!$I$13 -> 9143.3131 | BM11: ='Resumo Custos Variáveis'!$K$21 -> 0 | BN11: ='Outros Custos'!$I$31 -> 0 | BO11: =Transporte!$I$20 -> 0 | BP11: =Manutenção!$I$21 -> 0 | BQ11: =BG11 -> 0 | BR11: =SUM(BJ11:BQ11) -> 13104.806 | BS11: =IF(L2>=1,BR11/$A$5,0) -> 0 | BT11: ='Linha 4 Zn Alc. Manual'!AB15 -> 0 | BU11: ='Resumo M.O'!J5 -> 3961.4925 | BV11: ='Resumo M.O'!$J$13 -> 9143.3131 | BW11: ='Resumo Custos Variáveis'!$L$21 -> 0 | BX11: ='Outros Custos'!$J$31 -> 0 | BY11: =Transporte!$J$20 -> 0 | BZ11: =Manutenção!$J$21 -> 0 | CA11: =BQ11 -> 0 | CB11: =SUM(BT11:CA11) -> 13104.806 | CC11: =IF(L2>=1,CB11/$A$5,0) -> 0 | CD11: ='Linha 4 Zn Alc. Manual'!AE15 -> 0 | CE11: ='Resumo M.O'!K5 -> 3961.4925 | CF11: ='Resumo M.O'!$K$13 -> 9143.3131 | CG11: ='Resumo Custos Variáveis'!$M$21 -> 4328.5714 | CH11: ='Outros Custos'!$K$31 -> 2140 | CI11: =Transporte!$K$20 -> 0 | CJ11: =Manutenção!$K$21 -> 10000 | CK11: =CA11 -> 0 | CL11: =SUM(CD11:CK11) -> 29573.377 | CM11: =IF(L2>=1,CL11/$A$5,0) -> 0 | CN11: ='Linha 4 Zn Alc. Manual'!AH15 -> 0 | CO11: ='Resumo M.O'!L5 -> 3961.4925 | CP11: ='Resumo M.O'!$L$13 -> 9143.3131 | CQ11: ='Resumo Custos Variáveis'!$N$21 -> 0 | CR11: ='Outros Custos'!$L$31 -> 0 | CS11: =Transporte!$L$20 -> 0 | CT11: =Manutenção!$L$21 -> 10000 | CU11: =CK11 -> 0 | CV11: =SUM(CN11:CU11) -> 23104.806 | CW11: =IF(L2>=1,CV11/$A$5,0) -> 0 | CX11: ='Linha 4 Zn Alc. Manual'!AK15 -> 0 | CY11: ='Resumo M.O'!M5 -> 3961.4925 | CZ11: ='Resumo M.O'!$M$13 -> 9143.3131 | DA11: ='Resumo Custos Variáveis'!$O$21 -> 0 | DB11: ='Outros Custos'!$M$31 -> 0 | DC11: =Transporte!$M$20 -> 0 | DD11: =Manutenção!$M$21 -> 10000 | DE11: =CU11 -> 0 | DF11: =SUM(CX11:DE11) -> 23104.806 | DG11: =IF(L2>=1,DF11/$A$5,0) -> 0 | DH11: ='Linha 4 Zn Alc. Manual'!AN15 -> 0 | DI11: ='Resumo M.O'!N5 -> 3961.4925 | DJ11: ='Resumo M.O'!$N$13 -> 9143.3131 | DK11: ='Resumo Custos Variáveis'!$P$21 -> 0 | DL11: ='Outros Custos'!$N$31 -> 0 | DM11: =Transporte!$N$20 -> 0 | DN11: =Manutenção!$N$21 -> 10000 | DO11: =DE11 -> 0 | DP11: =SUM(DH11:DO11) -> 23104.806 | DQ11: =IF(L2>=1,DP11/$A$5,0) -> 0 | DS11: =K11 -> 0 | DT11: =U11 -> 0 | DU11: =AE11 -> 0 | DV11: =AO11 -> 0 | DW11: =AY11 -> 0 | DX11: =BI11 -> 0 | DY11: =BS11 -> 0 | DZ11: =CC11 -> 0 | EA11: =CM11 -> 0 | EB11: =CW11 -> 0 | EC11: =DG11 -> 0 | ED11: =DQ11 -> 0 | EF11: =B11/$A$5 -> 0 | EG11: =L11/$A$5 -> 0 | EH11: =V11/$A$5 -> 0 | EI11: =AF11/$A$5 -> 0 | EJ11: =AP11/$A$5 -> 0 | EK11: =AZ11/$A$5 -> 0 | EL11: =BJ11/$A$5 -> 0 | EM11: =BT11/$A$5 -> 0 | EN11: =CD11/$A$5 -> 0 | EO11: =CN11/$A$5 -> 0 | EP11: =CX11/$A$5 -> 0 | EQ11: =DH11/$A$5 -> 0
A12: Linha 5 Zn Alc.Semi Aut | B12: ='Linha 5 Zn Alc. Semi Aut.'!G15 -> 0 | C12: ='Resumo M.O'!C6 -> 7491.4369 | D12: ='Resumo M.O'!$C$13 -> 9143.3131 | E12: ='Resumo Custos Variáveis'!$E$21 -> 0 | F12: ='Outros Custos'!$C$31 -> 0 | G12: =Transporte!$C$20 -> 0 | H12: =Manutenção!$C$21 -> 0 | I12: =Investimentos!G32 -> 0 | J12: =SUM(B12:I12) -> 16634.75 | K12: =IF($L$2>=1,J12/$A$5,0) -> 0 | L12: ='Linha 5 Zn Alc. Semi Aut.'!J15 -> 0 | M12: ='Resumo M.O'!D6 -> 7491.4369 | N12: ='Resumo M.O'!$D$13 -> 9143.3131 | O12: ='Resumo Custos Variáveis'!$F$21 -> 0 | P12: ='Outros Custos'!$D$31 -> 0 | Q12: =Transporte!$D$20 -> 0 | R12: =Manutenção!$D$21 -> 0 | S12: =I12 -> 0 | T12: =SUM(L12:S12) -> 16634.75 | U12: =IF($L$2>=1,T12/$A$5,0) -> 0 | V12: ='Linha 5 Zn Alc. Semi Aut.'!M15 -> 0 | W12: ='Resumo M.O'!E6 -> 7491.4369 | X12: ='Resumo M.O'!$E$13 -> 9143.3131 | Y12: ='Resumo Custos Variáveis'!$G$21 -> 0 | Z12: ='Outros Custos'!$E$31 -> 0 | AA12: =Transporte!$E$20 -> 0 | AB12: =Manutenção!$E$21 -> 0 | AC12: =S12 -> 0 | AD12: =SUM(V12:AC12) -> 16634.75 | AE12: =IF($L$2>=1,AD12/$A$5,0) -> 0 | AF12: ='Linha 5 Zn Alc. Semi Aut.'!P15 -> 0 | AG12: ='Resumo M.O'!F6 -> 7491.4369 | AH12: ='Resumo M.O'!$F$13 -> 9143.3131 | AI12: ='Resumo Custos Variáveis'!$H$21 -> 0 | AJ12: ='Outros Custos'!$F$31 -> 0 | AK12: =Transporte!$F$20 -> 0 | AL12: =Manutenção!$F$21 -> 0 | AM12: =AC12 -> 0 | AN12: =SUM(AF12:AM12) -> 16634.75 | AO12: =IF(L2>=1,AN12/$A$5,0) -> 0 | AP12: ='Linha 5 Zn Alc. Semi Aut.'!S15 -> 0 | AQ12: ='Resumo M.O'!G6 -> 7491.4369 | AR12: ='Resumo M.O'!$G$13 -> 9143.3131 | AS12: ='Resumo Custos Variáveis'!$I$21 -> 0 | AT12: ='Outros Custos'!$G$31 -> 0 | AU12: =Transporte!$G$20 -> 0 | AV12: =Manutenção!$G$21 -> 0 | AW12: =AM12 -> 0 | AX12: =SUM(AP12:AW12) -> 16634.75 | AY12: =IF(L2>=1,AX12/$A$5,0) -> 0 | AZ12: ='Linha 5 Zn Alc. Semi Aut.'!V15 -> 0 | BA12: ='Resumo M.O'!H6 -> 7491.4369 | BB12: ='Resumo M.O'!$H$13 -> 9143.3131 | BC12: ='Resumo Custos Variáveis'!$J$21 -> 0 | BD12: ='Outros Custos'!$H$31 -> 0 | BE12: =Transporte!$H$20 -> 0 | BF12: =Manutenção!$H$21 -> 0 | BG12: =AW12 -> 0 | BH12: =SUM(AZ12:BG12) -> 16634.75 | BI12: =IF(L$2>=1,BH12/$A$5,0) -> 0 | BJ12: ='Linha 5 Zn Alc. Semi Aut.'!Y15 -> 0 | BK12: ='Resumo M.O'!I6 -> 7491.4369 | BL12: ='Resumo M.O'!$I$13 -> 9143.3131 | BM12: ='Resumo Custos Variáveis'!$K$21 -> 0 | BN12: ='Outros Custos'!$I$31 -> 0 | BO12: =Transporte!$I$20 -> 0 | BP12: =Manutenção!$I$21 -> 0 | BQ12: =BG12 -> 0 | BR12: =SUM(BJ12:BQ12) -> 16634.75 | BS12: =IF(L$2>=1,BR12/$A$5,0) -> 0 | BT12: ='Linha 5 Zn Alc. Semi Aut.'!AB15 -> 0 | BU12: ='Resumo M.O'!J6 -> 7491.4369 | BV12: ='Resumo M.O'!$J$13 -> 9143.3131 | BW12: ='Resumo Custos Variáveis'!$L$21 -> 0 | BX12: ='Outros Custos'!$J$31 -> 0 | BY12: =Transporte!$J$20 -> 0 | BZ12: =Manutenção!$J$21 -> 0 | CA12: =BQ12 -> 0 | CB12: =SUM(BT12:CA12) -> 16634.75 | CC12: =IF(L$2>=1,CB12/$A$5,0) -> 0 | CD12: ='Linha 5 Zn Alc. Semi Aut.'!AE15 -> 0 | CE12: ='Resumo M.O'!K6 -> 3126.8886 | CF12: ='Resumo M.O'!$K$13 -> 9143.3131 | CG12: ='Resumo Custos Variáveis'!$M$21 -> 4328.5714 | CH12: ='Outros Custos'!$K$31 -> 2140 | CI12: =Transporte!$K$20 -> 0 | CJ12: =Manutenção!$K$21 -> 10000 | CK12: =CA12 -> 0 | CL12: =SUM(CD12:CK12) -> 28738.773 | CM12: =IF(L2>=1,CL12/$A$5,0) -> 0 | CN12: ='Linha 5 Zn Alc. Semi Aut.'!AH15 -> 0 | CO12: ='Resumo M.O'!L6 -> 3126.8886 | CP12: ='Resumo M.O'!$L$13 -> 9143.3131 | CQ12: ='Resumo Custos Variáveis'!$N$21 -> 0 | CR12: ='Outros Custos'!$L$31 -> 0 | CS12: =Transporte!$L$20 -> 0 | CT12: =Manutenção!$L$21 -> 10000 | CU12: =CK12 -> 0 | CV12: =SUM(CN12:CU12) -> 22270.202 | CW12: =IF(L$2>=1,CV12/$A$5,0) -> 0 | CX12: ='Linha 5 Zn Alc. Semi Aut.'!AK15 -> 0 | CY12: ='Resumo M.O'!M6 -> 3126.8886 | CZ12: ='Resumo M.O'!$M$13 -> 9143.3131 | DA12: ='Resumo Custos Variáveis'!$O$21 -> 0 | DB12: ='Outros Custos'!$M$31 -> 0 | DC12: =Transporte!$M$20 -> 0 | DD12: =Manutenção!$M$21 -> 10000 | DE12: =CU12 -> 0 | DF12: =SUM(CX12:DE12) -> 22270.202 | DG12: =IF(L$2>=1,DF12/$A$5,0) -> 0 | DH12: ='Linha 5 Zn Alc. Semi Aut.'!AN15 -> 0 | DI12: ='Resumo M.O'!N6 -> 3126.8886 | DJ12: ='Resumo M.O'!$N$13 -> 9143.3131 | DK12: ='Resumo Custos Variáveis'!$P$21 -> 0 | DL12: ='Outros Custos'!$N$31 -> 0 | DM12: =Transporte!$N$20 -> 0 | DN12: =Manutenção!$N$21 -> 10000 | DO12: =DE12 -> 0 | DP12: =SUM(DH12:DO12) -> 22270.202 | DQ12: =IF(L$2>=1,DP12/$A$5,0) -> 0 | DS12: =K12 -> 0 | DT12: =U12 -> 0 | DU12: =AE12 -> 0 | DV12: =AO12 -> 0 | DW12: =AY12 -> 0 | DX12: =BI12 -> 0 | DY12: =BS12 -> 0 | DZ12: =CC12 -> 0 | EA12: =CM12 -> 0 | EB12: =CW12 -> 0 | EC12: =DG12 -> 0 | ED12: =DQ12 -> 0 | EF12: =B12/$A$5 -> 0 | EG12: =L12/$A$5 -> 0 | EH12: =V12/$A$5 -> 0 | EI12: =AF12/$A$5 -> 0 | EJ12: =AP12/$A$5 -> 0 | EK12: =AZ12/$A$5 -> 0 | EL12: =BJ12/$A$5 -> 0 | EM12: =BT12/$A$5 -> 0 | EN12: =CD12/$A$5 -> 0 | EO12: =CN12/$A$5 -> 0 | EP12: =CX12/$A$5 -> 0 | EQ12: =DH12/$A$5 -> 0
A13: Linha 6 ZnNí Alc.Semi Aut | B13: ='Linha 6 ZnNí Semi Aut.'!G16 -> 0 | C13: ='Resumo M.O'!C7 -> 6872.2222 | D13: ='Resumo M.O'!$C$13 -> 9143.3131 | E13: ='Resumo Custos Variáveis'!$E$21 -> 0 | F13: ='Outros Custos'!$C$31 -> 0 | G13: =Transporte!$C$20 -> 0 | H13: =Manutenção!$C$21 -> 0 | I13: =Investimentos!G37 -> 0 | J13: =SUM(B13:I13) -> 16015.535 | K13: =IF($L$2>=1,J13/$A$5,0) -> 0 | L13: ='Linha 6 ZnNí Semi Aut.'!J16 -> 0 | M13: ='Resumo M.O'!D7 -> 6872.2222 | N13: ='Resumo M.O'!$D$13 -> 9143.3131 | O13: ='Resumo Custos Variáveis'!$F$21 -> 0 | P13: ='Outros Custos'!$D$31 -> 0 | Q13: =Transporte!$D$20 -> 0 | R13: =Manutenção!$D$21 -> 0 | S13: =I13 -> 0 | T13: =SUM(L13:S13) -> 16015.535 | U13: =IF($L$2>=1,T13/$A$5,0) -> 0 | V13: ='Linha 6 ZnNí Semi Aut.'!M16 -> 0 | W13: ='Resumo M.O'!E7 -> 6872.2222 | X13: ='Resumo M.O'!$E$13 -> 9143.3131 | Y13: ='Resumo Custos Variáveis'!$G$21 -> 0 | Z13: ='Outros Custos'!$E$31 -> 0 | AA13: =Transporte!$E$20 -> 0 | AB13: =Manutenção!$E$21 -> 0 | AC13: =S13 -> 0 | AD13: =SUM(V13:AC13) -> 16015.535 | AE13: =IF($L$2>=1,AD13/$A$5,0) -> 0 | AF13: ='Linha 6 ZnNí Semi Aut.'!P16 -> 0 | AG13: ='Resumo M.O'!F7 -> 6872.2222 | AH13: ='Resumo M.O'!$F$13 -> 9143.3131 | AI13: ='Resumo Custos Variáveis'!$H$21 -> 0 | AJ13: ='Outros Custos'!$F$31 -> 0 | AK13: =Transporte!$F$20 -> 0 | AL13: =Manutenção!$F$21 -> 0 | AM13: =AC13 -> 0 | AN13: =SUM(AF13:AM13) -> 16015.535 | AO13: =IF(L2>=1,AN13/$A$5,0) -> 0 | AP13: ='Linha 6 ZnNí Semi Aut.'!S16 -> 0 | AQ13: ='Resumo M.O'!G7 -> 6872.2222 | AR13: ='Resumo M.O'!$G$13 -> 9143.3131 | AS13: ='Resumo Custos Variáveis'!$I$21 -> 0 | AT13: ='Outros Custos'!$G$31 -> 0 | AU13: =Transporte!$G$20 -> 0 | AV13: =Manutenção!$G$21 -> 0 | AW13: =AM13 -> 0 | AX13: =SUM(AP13:AW13) -> 16015.535 | AY13: =IF(L2>=1,AX13/$A$5,0) -> 0 | AZ13: ='Linha 6 ZnNí Semi Aut.'!V16 -> 0 | BA13: ='Resumo M.O'!H7 -> 6872.2222 | BB13: ='Resumo M.O'!$H$13 -> 9143.3131 | BC13: ='Resumo Custos Variáveis'!$J$21 -> 0 | BD13: ='Outros Custos'!$H$31 -> 0 | BE13: =Transporte!$H$20 -> 0 | BF13: =Manutenção!$H$21 -> 0 | BG13: =AW13 -> 0 | BH13: =SUM(AZ13:BG13) -> 16015.535 | BI13: =IF(L$2>=1,BH13/$A$5,0) -> 0 | BJ13: ='Linha 6 ZnNí Semi Aut.'!Y16 -> 0 | BK13: ='Resumo M.O'!I7 -> 6872.2222 | BL13: ='Resumo M.O'!$I$13 -> 9143.3131 | BM13: ='Resumo Custos Variáveis'!$K$21 -> 0 | BN13: ='Outros Custos'!$I$31 -> 0 | BO13: =Transporte!$I$20 -> 0 | BP13: =Manutenção!$I$21 -> 0 | BQ13: =BG13 -> 0 | BR13: =SUM(BJ13:BQ13) -> 16015.535 | BS13: =IF(L$2>=1,BR13/$A$5,0) -> 0 | BT13: ='Linha 6 ZnNí Semi Aut.'!AB16 -> 0 | BU13: ='Resumo M.O'!J7 -> 6872.2222 | BV13: ='Resumo M.O'!$J$13 -> 9143.3131 | BW13: ='Resumo Custos Variáveis'!$L$21 -> 0 | BX13: ='Outros Custos'!$J$31 -> 0 | BY13: =Transporte!$J$20 -> 0 | BZ13: =Manutenção!$J$21 -> 0 | CA13: =BQ13 -> 0 | CB13: =SUM(BT13:CA13) -> 16015.535 | CC13: =IF(L$2>=1,CB13/$A$5,0) -> 0 | CD13: ='Linha 6 ZnNí Semi Aut.'!AE16 -> 40000 | CE13: ='Resumo M.O'!K7 -> 6047.5556 | CF13: ='Resumo M.O'!$K$13 -> 9143.3131 | CG13: ='Resumo Custos Variáveis'!$M$21 -> 4328.5714 | CH13: ='Outros Custos'!$K$31 -> 2140 | CI13: =Transporte!$K$20 -> 0 | CJ13: =Manutenção!$K$21 -> 10000 | CK13: =CA13 -> 0 | CL13: =SUM(CD13:CK13) -> 71659.44 | CM13: =IF(L2>=1,CL13/$A$5,0) -> 0 | CN13: ='Linha 6 ZnNí Semi Aut.'!AH16 -> 0 | CO13: ='Resumo M.O'!L7 -> 6047.5556 | CP13: ='Resumo M.O'!$L$13 -> 9143.3131 | CQ13: ='Resumo Custos Variáveis'!$N$21 -> 0 | CR13: ='Outros Custos'!$L$31 -> 0 | CS13: =Transporte!$L$20 -> 0 | CT13: =Manutenção!$L$21 -> 10000 | CU13: =CK13 -> 0 | CV13: =SUM(CN13:CU13) -> 25190.869 | CW13: =IF(L$2>=1,CV13/$A$5,0) -> 0 | CX13: ='Linha 6 ZnNí Semi Aut.'!AK16 -> 0 | CY13: ='Resumo M.O'!M7 -> 6047.5556 | CZ13: ='Resumo M.O'!$M$13 -> 9143.3131 | DA13: ='Resumo Custos Variáveis'!$O$21 -> 0 | DB13: ='Outros Custos'!$M$31 -> 0 | DC13: =Transporte!$M$20 -> 0 | DD13: =Manutenção!$M$21 -> 10000 | DE13: =CU13 -> 0 | DF13: =SUM(CX13:DE13) -> 25190.869 | DG13: =IF(L$2>=1,DF13/$A$5,0) -> 0 | DH13: ='Linha 6 ZnNí Semi Aut.'!AN16 -> 0 | DI13: ='Resumo M.O'!N7 -> 6047.5556 | DJ13: ='Resumo M.O'!$N$13 -> 9143.3131 | DK13: ='Resumo Custos Variáveis'!$P$21 -> 0 | DL13: ='Outros Custos'!$N$31 -> 0 | DM13: =Transporte!$N$20 -> 0 | DN13: =Manutenção!$N$21 -> 10000 | DO13: =DE13 -> 0 | DP13: =SUM(DH13:DO13) -> 25190.869 | DQ13: =IF(L$2>=1,DP13/$A$5,0) -> 0 | DS13: =K13 -> 0 | DT13: =U13 -> 0 | DU13: =AE13 -> 0 | DV13: =AO13 -> 0 | DW13: =AY13 -> 0 | DX13: =BI13 -> 0 | DY13: =BS13 -> 0 | DZ13: =CC13 -> 0 | EA13: =CM13 -> 0 | EB13: =CW13 -> 0 | EC13: =DG13 -> 0 | ED13: =DQ13 -> 0 | EF13: =B13/$A$5 -> 0 | EG13: =L13/$A$5 -> 0 | EH13: =V13/$A$5 -> 0 | EI13: =AF13/$A$5 -> 0 | EJ13: =AP13/$A$5 -> 0 | EK13: =AZ13/$A$5 -> 0 | EL13: =BJ13/$A$5 -> 0 | EM13: =BT13/$A$5 -> 0 | EN13: =CD13/$A$5 -> 181.81818 | EO13: =CN13/$A$5 -> 0 | EP13: =CX13/$A$5 -> 0 | EQ13: =DH13/$A$5 -> 0
A14: Linha 9 Pré-Trat. Fosfato Aut. | B14: ='Linha 9 Pré Trat. Fosfato Aut.'!G14 -> 0 | C14: ='Resumo M.O'!C8 -> 3023.7778 | D14: ='Resumo M.O'!$C$13 -> 9143.3131 | E14: ='Resumo Custos Variáveis'!$E$21 -> 0 | F14: ='Outros Custos'!$C$31 -> 0 | G14: =Transporte!$C$20 -> 0 | H14: =Manutenção!$C$21 -> 0 | I14: =Investimentos!G42 -> 0 | J14: =SUM(B14:I14) -> 12167.091 | K14: =IF($L$2>=1,J14/$A$5,0) -> 0 | L14: ='Linha 9 Pré Trat. Fosfato Aut.'!J14 -> 0 | M14: ='Resumo M.O'!D8 -> 3023.7778 | N14: ='Resumo M.O'!$D$13 -> 9143.3131 | O14: ='Resumo Custos Variáveis'!$F$21 -> 0 | P14: ='Outros Custos'!$D$31 -> 0 | Q14: =Transporte!$D$20 -> 0 | R14: =Manutenção!$D$21 -> 0 | S14: =I14 -> 0 | T14: =SUM(L14:S14) -> 12167.091 | U14: =IF($L$2>=1,T14/$A$5,0) -> 0 | V14: ='Linha 9 Pré Trat. Fosfato Aut.'!M14 -> 0 | W14: ='Resumo M.O'!E8 -> 3023.7778 | X14: ='Resumo M.O'!$E$13 -> 9143.3131 | Y14: ='Resumo Custos Variáveis'!$G$21 -> 0 | Z14: ='Outros Custos'!$E$31 -> 0 | AA14: =Transporte!$E$20 -> 0 | AB14: =Manutenção!$E$21 -> 0 | AC14: =S14 -> 0 | AD14: =SUM(V14:AC14) -> 12167.091 | AE14: =IF($L$2>=1,AD14/$A$5,0) -> 0 | AF14: ='Linha 9 Pré Trat. Fosfato Aut.'!P14 -> 0 | AG14: ='Resumo M.O'!F8 -> 3023.7778 | AH14: ='Resumo M.O'!$F$13 -> 9143.3131 | AI14: ='Resumo Custos Variáveis'!$H$21 -> 0 | AJ14: ='Outros Custos'!$F$31 -> 0 | AK14: =Transporte!$F$20 -> 0 | AL14: =Manutenção!$F$21 -> 0 | AM14: =AC14 -> 0 | AN14: =SUM(AF14:AM14) -> 12167.091 | AO14: =IF(L2>=1,AN14/$A$5,0) -> 0 | AP14: ='Linha 9 Pré Trat. Fosfato Aut.'!S14 -> 0 | AQ14: ='Resumo M.O'!G8 -> 3023.7778 | AR14: ='Resumo M.O'!$G$13 -> 9143.3131 | AS14: ='Resumo Custos Variáveis'!$I$21 -> 0 | AT14: ='Outros Custos'!$G$31 -> 0 | AU14: =Transporte!$G$20 -> 0 | AV14: =Manutenção!$G$21 -> 0 | AW14: =AM14 -> 0 | AX14: =SUM(AP14:AW14) -> 12167.091 | AY14: =IF(L2>=1,AX14/$A$5,0) -> 0 | AZ14: ='Linha 9 Pré Trat. Fosfato Aut.'!V14 -> 0 | BA14: ='Resumo M.O'!H8 -> 3023.7778 | BB14: ='Resumo M.O'!$H$13 -> 9143.3131 | BC14: ='Resumo Custos Variáveis'!$J$21 -> 0 | BD14: ='Outros Custos'!$H$31 -> 0 | BE14: =Transporte!$H$20 -> 0 | BF14: =Manutenção!$H$21 -> 0 | BG14: =AW14 -> 0 | BH14: =SUM(AZ14:BG14) -> 12167.091 | BI14: =IF(L$2>=1,BH14/$A$5,0) -> 0 | BJ14: ='Linha 9 Pré Trat. Fosfato Aut.'!Y14 -> 0 | BK14: ='Resumo M.O'!I8 -> 3023.7778 | BL14: ='Resumo M.O'!$I$13 -> 9143.3131 | BM14: ='Resumo Custos Variáveis'!$K$21 -> 0 | BN14: ='Outros Custos'!$I$31 -> 0 | BO14: =Transporte!$I$20 -> 0 | BP14: =Manutenção!$I$21 -> 0 | BQ14: =BG14 -> 0 | BR14: =SUM(BJ14:BQ14) -> 12167.091 | BS14: =IF(L$2>=1,BR14/$A$5,0) -> 0 | BT14: ='Linha 9 Pré Trat. Fosfato Aut.'!AB14 -> 0 | BU14: ='Resumo M.O'!J8 -> 3023.7778 | BV14: ='Resumo M.O'!$J$13 -> 9143.3131 | BW14: ='Resumo Custos Variáveis'!$L$21 -> 0 | BX14: ='Outros Custos'!$J$31 -> 0 | BY14: =Transporte!$J$20 -> 0 | BZ14: =Manutenção!$J$21 -> 0 | CA14: =BQ14 -> 0 | CB14: =SUM(BT14:CA14) -> 12167.091 | CC14: =IF(L$2>=1,CB14/$A$5,0) -> 0 | CD14: ='Linha 9 Pré Trat. Fosfato Aut.'!AE14 -> 0 | CE14: ='Resumo M.O'!K8 -> 3023.7778 | CF14: ='Resumo M.O'!$K$13 -> 9143.3131 | CG14: ='Resumo Custos Variáveis'!$M$21 -> 4328.5714 | CH14: ='Outros Custos'!$K$31 -> 2140 | CI14: =Transporte!$K$20 -> 0 | CJ14: =Manutenção!$K$21 -> 10000 | CK14: =CA14 -> 0 | CL14: =SUM(CD14:CK14) -> 28635.662 | CM14: =IF(L2>=1,CL14/$A$5,0) -> 0 | CN14: ='Linha 9 Pré Trat. Fosfato Aut.'!AH14 -> 0 | CO14: ='Resumo M.O'!L8 -> 3023.7778 | CP14: ='Resumo M.O'!$L$13 -> 9143.3131 | CQ14: ='Resumo Custos Variáveis'!$N$21 -> 0 | CR14: ='Outros Custos'!$L$31 -> 0 | CS14: =Transporte!$L$20 -> 0 | CT14: =Manutenção!$L$21 -> 10000 | CU14: =CK14 -> 0 | CV14: =SUM(CN14:CU14) -> 22167.091 | CW14: =IF(L$2>=1,CV14/$A$5,0) -> 0 | CX14: ='Linha 9 Pré Trat. Fosfato Aut.'!AK14 -> 0 | CY14: ='Resumo M.O'!M8 -> 3023.7778 | CZ14: ='Resumo M.O'!$M$13 -> 9143.3131 | DA14: ='Resumo Custos Variáveis'!$O$21 -> 0 | DB14: ='Outros Custos'!$M$31 -> 0 | DC14: =Transporte!$M$20 -> 0 | DD14: =Manutenção!$M$21 -> 10000 | DE14: =CU14 -> 0 | DF14: =SUM(CX14:DE14) -> 22167.091 | DG14: =IF(L$2>=1,DF14/$A$5,0) -> 0 | DH14: ='Linha 9 Pré Trat. Fosfato Aut.'!AN14 -> 0 | DI14: ='Resumo M.O'!N8 -> 3023.7778 | DJ14: ='Resumo M.O'!$N$13 -> 9143.3131 | DK14: ='Resumo Custos Variáveis'!$P$21 -> 0 | DL14: ='Outros Custos'!$N$31 -> 0 | DM14: =Transporte!$N$20 -> 0 | DN14: =Manutenção!$N$21 -> 10000 | DO14: =DE14 -> 0 | DP14: =SUM(DH14:DO14) -> 22167.091 | DQ14: =IF(L$2>=1,DP14/$A$5,0) -> 0 | DS14: =K14 -> 0 | DT14: =U14 -> 0 | DU14: =AE14 -> 0 | DV14: =AO14 -> 0 | DW14: =AY14 -> 0 | DX14: =BI14 -> 0 | DY14: =BS14 -> 0 | DZ14: =CC14 -> 0 | EA14: =CM14 -> 0 | EB14: =CW14 -> 0 | EC14: =DG14 -> 0 | ED14: =DQ14 -> 0 | EF14: =B14/$A$5 -> 0 | EG14: =L14/$A$5 -> 0 | EH14: =V14/$A$5 -> 0 | EI14: =AF14/$A$5 -> 0 | EJ14: =AP14/$A$5 -> 0 | EK14: =AZ14/$A$5 -> 0 | EL14: =BJ14/$A$5 -> 0 | EM14: =BT14/$A$5 -> 0 | EN14: =CD14/$A$5 -> 0 | EO14: =CN14/$A$5 -> 0 | EP14: =CX14/$A$5 -> 0 | EQ14: =DH14/$A$5 -> 0
A15: E.T.E | B15: 0 | C15: ='Resumo M.O'!C9 -> 0 | D15: 0 | E15: ='Resumo Custos Variáveis'!$E$21 -> 0 | F15: ='Outros Custos'!$C$31 -> 0 | G15: =Transporte!$C$20 -> 0 | H15: =Manutenção!$C$21 -> 0 | I15: 0 | J15: =SUM(B15:I15) -> 0 | K15: =IF($L$2>=1,J15/$A$5,0) -> 0 | L15: 0 | M15: ='Resumo M.O'!D9 -> 0 | N15: 0 | O15: ='Resumo Custos Variáveis'!$F$21 -> 0 | P15: ='Outros Custos'!$D$31 -> 0 | Q15: =Transporte!$D$20 -> 0 | R15: =Manutenção!$D$21 -> 0 | S15: =I15 -> 0 | T15: =SUM(L15:S15) -> 0 | U15: =IF($L$2>=1,T15/$A$5,0) -> 0 | V15: 0 | W15: ='Resumo M.O'!E9 -> 0 | X15: 0 | Y15: ='Resumo Custos Variáveis'!$G$21 -> 0 | Z15: ='Outros Custos'!$E$31 -> 0 | AA15: =Transporte!$E$20 -> 0 | AB15: =Manutenção!$E$21 -> 0 | AC15: =S15 -> 0 | AD15: =SUM(V15:AC15) -> 0 | AE15: =IF($L$2>=1,AD15/$A$5,0) -> 0 | AF15: 0 | AG15: ='Resumo M.O'!F9 -> 0 | AH15: 0 | AI15: ='Resumo Custos Variáveis'!$H$21 -> 0 | AJ15: ='Outros Custos'!$F$31 -> 0 | AK15: =Transporte!$F$20 -> 0 | AL15: =Manutenção!$F$21 -> 0 | AM15: =AC15 -> 0 | AN15: =SUM(AF15:AM15) -> 0 | AO15: =IF(L2>=1,AN15/$A$5,0) -> 0 | AP15: 0 | AQ15: ='Resumo M.O'!G9 -> 0 | AR15: 0 | AS15: ='Resumo Custos Variáveis'!$I$21 -> 0 | AT15: ='Outros Custos'!$G$31 -> 0 | AU15: =Transporte!$G$20 -> 0 | AV15: =Manutenção!$G$21 -> 0 | AW15: =AM15 -> 0 | AX15: =SUM(AP15:AW15) -> 0 | AY15: =IF(L2>=1,AX15/$A$5,0) -> 0 | AZ15: 0 | BA15: ='Resumo M.O'!H9 -> 0 | BB15: 0 | BC15: ='Resumo Custos Variáveis'!$J$21 -> 0 | BD15: ='Outros Custos'!$H$31 -> 0 | BE15: =Transporte!$H$20 -> 0 | BF15: =Manutenção!$H$21 -> 0 | BG15: =AW15 -> 0 | BH15: =SUM(AZ15:BG15) -> 0 | BI15: =IF(L$2>=1,BH15/$A$5,0) -> 0 | BJ15: 0 | BK15: ='Resumo M.O'!I9 -> 0 | BL15: 0 | BM15: ='Resumo Custos Variáveis'!$K$21 -> 0 | BN15: ='Outros Custos'!$I$31 -> 0 | BO15: =Transporte!$I$20 -> 0 | BP15: =Manutenção!$I$21 -> 0 | BQ15: =BG15 -> 0 | BR15: =SUM(BJ15:BQ15) -> 0 | BS15: =IF(L$2>=1,BR15/$A$5,0) -> 0 | BT15: 0 | BU15: ='Resumo M.O'!J9 -> 0 | BV15: 0 | BW15: ='Resumo Custos Variáveis'!$L$21 -> 0 | BX15: ='Outros Custos'!$J$31 -> 0 | BY15: =Transporte!$J$20 -> 0 | BZ15: =Manutenção!$J$21 -> 0 | CA15: =BQ15 -> 0 | CB15: =SUM(BT15:CA15) -> 0 | CC15: =IF(L$2>=1,CB15/$A$5,0) -> 0 | CD15: 0 | CE15: ='Resumo M.O'!K9 -> 0 | CF15: 0 | CG15: 0 | CH15: 0 | CI15: =Transporte!$K$20 -> 0 | CJ15: 0 | CK15: =CA15 -> 0 | CL15: =SUM(CD15:CK15) -> 0 | CM15: =IF(L4>=1,CL15/$A$5,0) -> 0 | CN15: 0 | CO15: ='Resumo M.O'!L9 -> 0 | CP15: 0 | CQ15: ='Resumo Custos Variáveis'!$N$21 -> 0 | CR15: ='Outros Custos'!$L$31 -> 0 | CS15: =Transporte!$L$20 -> 0 | CT15: 0 | CU15: =CK15 -> 0 | CV15: =SUM(CN15:CU15) -> 0 | CW15: =IF(L$2>=1,CV15/$A$5,0) -> 0 | CX15: 0 | CY15: ='Resumo M.O'!M9 -> 0 | CZ15: 0 | DA15: ='Resumo Custos Variáveis'!$O$21 -> 0 | DB15: ='Outros Custos'!$M$31 -> 0 | DC15: =Transporte!$M$20 -> 0 | DD15: 0 | DE15: =CU15 -> 0 | DF15: =SUM(CX15:DE15) -> 0 | DG15: =IF(L$2>=1,DF15/$A$5,0) -> 0 | DH15: 0 | DI15: ='Resumo M.O'!N9 -> 0 | DJ15: 0 | DK15: ='Resumo Custos Variáveis'!$P$21 -> 0 | DL15: ='Outros Custos'!$N$31 -> 0 | DM15: =Transporte!$N$20 -> 0 | DN15: 0 | DO15: =DE15 -> 0 | DP15: =SUM(DH15:DO15) -> 0 | DQ15: =IF(L$2>=1,DP15/$A$5,0) -> 0 | DS15: =K15 -> 0 | DT15: =U15 -> 0 | DU15: =AE15 -> 0 | DV15: =AO15 -> 0 | DW15: =AY15 -> 0 | DX15: =BI15 -> 0 | DY15: =BS15 -> 0 | DZ15: =CC15 -> 0 | EA15: =CM15 -> 0 | EB15: =CW15 -> 0 | EC15: =DG15 -> 0 | ED15: =DQ15 -> 0 | EF15: =B15/$A$5 -> 0 | EG15: =L15/$A$5 -> 0 | EH15: =V15/$A$5 -> 0 | EI15: =AF15/$A$5 -> 0 | EJ15: =AP15/$A$5 -> 0 | EK15: =AZ15/$A$5 -> 0 | EL15: =BJ15/$A$5 -> 0 | EM15: =BT15/$A$5 -> 0 | EN15: =CD15/$A$5 -> 0 | EO15: =CN15/$A$5 -> 0 | EP15: =CX15/$A$5 -> 0 | EQ15: =DH15/$A$5 -> 0

Sheet Peças por Hora Galvanoplastia
A2: Menu | C2: Peças por Hora Galvanoplastia
B5: Linha 1 Zn Alcalino Rotativo
B6: Área de 1 peça (dm²) | C6: Peso de 1 peça (Kg) | D6: Kg / Carga | E6: Peças/carga | F6: Area da Carga / Dm² | H6: Peso Especifico | I6: 7.1
B7: 2.3 | C7: 0.7 | D7: 30 | E7: =D7/C7 -> 42.857143 | F7: =(E7*B7)*F9 -> 492.85714 | H7: Equivalente Eletroquimico | I7: 1.2195
B8: Rendimento de corrente (%) | C8: Espessura (mm) | E8: Amperagem | F8: Número de Tambores
B9: 90 | C9: 4 | E9: =E11*F7 -> 246.42857 | F9: 5
B10: Peças por hora | C10: Kg por hora | E10: Densidade de Corrente | F10: Tempo de banho
B11: =(60/F11)*E7*F9 -> 414.06564 | C11: =(60/F11)*D7*F9 -> 289.84595 | E11: 0.5 | F11: =(60*C9*I6)/(I7*E11*B9) -> 31.050977
B13: Linha 2 Zn Alcalino Rotativo
B14: Área de 1 peça (dm²) | C14: Peso de 1 peça (Kg) | D14: Kg/ Carga | E14: Peças por carga | F14: Area da Carga / Dm² | H14: Peso Especifico | I14: 7.1
B15: 2.3 | C15: 0.7 | D15: 30 | E15: =D15/C15 -> 42.857143 | F15: =(B15*E15)*F17 -> 492.85714 | H15: Equivalente Eletroquimico | I15: 1.2195
B16: Rendimento de corrente (%) | C16: Espessura (mm) | E16: Amperagem | F16: Número de Tambores | H16: E Q
B17: 90 | C17: 4 | E17: =E19*F15 -> 246.42857 | F17: 5 | H17: 1.095
B18: Peças por hora | C18: Kg por hora | E18: Densidade de Corrente | F18: Tempo de banho
B19: =(60/F19)*(E15*F17) -> 414.06564 | C19: =(60/F19)*(D15*F17) -> 289.84595 | E19: 0.5 | F19: =(60*C17*I14)/(I15*E19*B17) -> 31.050977
B21: Linha 3 Zn Alcalino Automático
B22: Área de 1 peça (dm²) | C22: Peso de 1 peça (Kg) | D22: Kg/ Carga | E22: Peças por carga | F22: Area da Carga / Dm² | H22: Peso Especifico | I22: 7.1
B23: 2.3 | C23: 0.7 | D23: 30 | E23: =D23/C23 -> 42.857143 | F23: =(E23*B23)*F25 -> 591.42857 | H23: Equivalente Eletroquimico | I23: 1.2195
B24: Rendimento de corrente (%) | C24: Espessura (mm) | E24: Amperagem | F24: Número de Tambores | H24: E Q
B25: 90 | C25: 4 | E25: =E27*F23 -> 591.42857 | F25: 6 | H25: 1.186
B26: Peças por hora | C26: Kg por hora | E26: Densidade de Corrente | F26: Tempo de banho
B27: =(60/F27)*(E23*F25) -> 993.75755 | C27: =(60/F27)*(D23*F25) -> 695.63028 | E27: 1 | F27: =(60*C25*I22)/(I23*E27*B25) -> 15.525489
B29: Linha 4 ZnNí Alcalino Manual
B30: Área de 1 peça (dm²) | C30: Peso de 1 peça (Kg) | D30: Kg / Carga | E30: Peças/carga | F30: Area da Carga / Dm² | H30: Peso Especifico | I30: 7.1
B31: 2.3 | C31: 0.7 | D31: 30 | E31: =D31/C31 -> 42.857143 | F31: =B31*E31*F33 -> 394.28571 | H31: Equivalente Eletroquimico | I31: 1.2195
B32: Rendimento de corrente (%) | C32: Espessura (mm) | E32: Amperagem | F32: Número de Tambores
B33: 90 | C33: 4 | E33: =E35*F31 -> 394.28571 | F33: 4
B34: Peças por hora | C34: Kg por hora | E34: Densidade de Corrente | F34: Tempo de banho
B35: =(60/F35)*E31*F33 -> 662.50503 | C35: =(60/F35)*(D31*F33) -> 463.75352 | E35: 1 | F35: =(60*C33*I30)/(I31*E35*B33) -> 15.525489
B37: Linha 5 Zn Alcalino Semi Parado .
B38: Área de 1 peça (dm²) | C38: Peso de 1 peça (Kg) | D38: Kg / Carga | E38: Peças por carga | F38: Area da Carga / Dm² | H38: Peso Especifico | I38: 7.1
B39: 2.3 | C39: 0.7 | D39: 30 | E39: =D39/C39 -> 42.857143 | F39: =(E39*B39)*F41 -> 690 | H39: Equivalente Eletroquimico | I39: 1.2195
B40: Rendimento de corrente (%) | C40: Espessura (mm) | E40: Amperagem | F40: Número de Gancheira | H40: E Q
B41: 90 | C41: 4 | E41: =E43*F39 -> 690 | F41: 7 | H41: 1.095
B42: Peças por hora | C42: Kg por hora | E42: Densidade de Corrente | F42: Tempo de banho
B43: =(60/F43)*(E39*F41) -> 1159.3838 | C43: =(60/F43)*(D39*F41) -> 811.56866 | E43: 1 | F43: =(60*C41*I38)/(I39*E43*B41) -> 15.525489
B45: Linha 6 ZnNí Aut.
B46: Área de 1 peça (dm²) | C46: Peso de 1 peça (Kg) | D46: Kg / Carga | E46: Peças por carga | F46: Area da Carga / Dm² | H46: Peso Especifico | I46: 7.12
B47: 2.3 | C47: 0.7 | D47: 80 | E47: =D47/C47 -> 114.28571 | F47: =(E47*B47)*F49 -> 2102.8571 | H47: Equivalente Eletroquimico | I47: 1.22
B48: Rendimento de corrente (%) | C48: Espessura (mm) | E48: Amperagem | F48: Número de Gancheira | H48: E Q
B49: 90 | C49: 4 | E49: =E51*F47 -> 2102.8571 | F49: 8 | H49: 0.323
B50: Peças por hora | C50: Kg por hora | E50: Densidade de Corrente | F50: Tempo de banho
B51: =(60/F51)*(E47*F49) -> 3524.8796 | C51: =(60/F51)*(D47*F49) -> 2467.4157 | E51: 1 | F51: =(60*C49*I46)/(I47*E51*B49) -> 15.562842
B53: Linha 9 Pré Trat. Fosfato Aut.
B54: Área de 1 peça (dm²) | C54: Peso de 1 peça (Kg) | D54: Kg / Carga | E54: Peças por carga | F54: Area da Carga / Dm² | H54: pe
B55: 2.3 | C55: 0.7 | D55: 30 | E55: =D55/C55 -> 42.857143 | F55: =E55*B55*F57 -> 98.571429 | H55: 8.9
B56: Rendimento de corrente (%) | C56: Espessura (mm) | E56: Amperagem | F56: Número de Tambores | H56: E Q
B57: 89 | C57: 2 | E57: =E59*F55 -> 197.14286 | F57: 1 | H57: 1.095
B58: Peças por hora | C58: Kg por hora | E58: Densidade de Corrente | F58: Tempo de banho
B59: =(60/F59)*(E55*F57) -> 469.28571 | C59: =(60/F59)*(D55*F57) -> 328.5 | E59: 2 | F59: =(60*C57*H55)/(H57*E59*B57) -> 5.4794521
H62: pe
H63: 8.9
H64: E Q
H65: 1.095

Sheet Custo Galvanoplastia
A2: Menu | C2: Custo Por Peça Galvanoplastia
G6: Set
B8: Linha 1 | C8: Custo / Peça | D8: Custo/Kilo | E8: Custo/ Peça P.Q | F8: Custo/ Kilo P.Q | H8: Linha 1 | I8: Custo/ Total | K8: Prod. Químico | M8: Linha 1 | N8: % | O8: Peça | P8: Kilo
B9: Zn Alc. Aut | C9: =I9/'Peças por Hora Galvanoplastia'!B11 -> 0 | D9: =I9/'Peças por Hora Galvanoplastia'!C11 -> 0 | E9: =K9/'Peças por Hora Galvanoplastia'!B11 -> 0 | F9: =K9/'Peças por Hora Galvanoplastia'!C11 -> 0 | H9: Zn Alc. Aut | I9: =IF(J9=1,HLOOKUP(G6,'Resumo de Custo'!DS7:ED15,2,0),0) -> 0 | J9: 1 | K9: =IF(J9=1,HLOOKUP(G6,'Resumo de Custo'!EF7:EQ15,2,0),0) -> 0 | M9: Item | N9: 1 | O9: =C20 -> 0 | P9: =D20 -> 0
M10: Imposto Único | N10: 0.15 | O10: =O9*N10 -> 0 | P10: =P9*N10 -> 0
H18: Total | I18: =SUM(I9:I17) -> 0 | K18: =SUM(K9:K17) -> 0 | M18: Custo Liquido | O18: =SUM(O9:O17) -> 0 | P18: =SUM(P9:P17) -> 0
B20: Total | C20: =SUM(C9:C19) -> 0 | D20: =SUM(D9:D19) -> 0 | E20: =SUM(E9:E19) -> 0 | F20: =SUM(F9:F19) -> 0
B23: Linha 2 | C23: Custo / Peça | D23: Custo/Kilo | E23: Custo/ Peça P.Q | F23: Custo/ Kilo P.Q | H23: Linha 2 | I23: Custo/ Total | K23: Prod. Químico | M23: Linha 2 | N23: % | O23: Peça | P23: Kilo
B24: Zn Alc. Aut | C24: =I24/'Peças por Hora Galvanoplastia'!B19 -> 0 | D24: =I24/'Peças por Hora Galvanoplastia'!C19 -> 0 | E24: =K24/'Peças por Hora Galvanoplastia'!B19 -> 0 | F24: =K24/'Peças por Hora Galvanoplastia'!C19 -> 0 | H24: Zn Alc. Aut | I24: =IF(J24=1,HLOOKUP(G6,'Resumo de Custo'!DS7:ED15,3,0),0) -> 0 | J24: 1 | K24: =IF(J24=1,HLOOKUP(G6,'Resumo de Custo'!EF7:EQ15,3,0),0) -> 0 | M24: Item | N24: 1 | O24: =C35 -> 0 | P24: =D35 -> 0
M25: Imposto Único | N25: 0.15 | O25: =O24*N25 -> 0 | P25: =P24*N25 -> 0
H33: Total | I33: =SUM(I24:I32) -> 0 | K33: =SUM(K24:K32) -> 0 | M33: Custo Liquido | O33: =SUM(O24:O32) -> 0 | P33: =SUM(P24:P32) -> 0
B35: Total | C35: =SUM(C24:C34) -> 0 | D35: =SUM(D24:D34) -> 0 | E35: =SUM(E25:E34) -> 0 | F35: =SUM(F24:F34) -> 0
B38: Linha 3 | C38: Custo / Peça | D38: Custo/Kilo | E38: Custo/ Peça P.Q | F38: Custo/ Kilo P.Q | H38: Linha 3 | I38: Custo/ Total | K38: Prod. Químico | M38: Linha 3 | N38: % | O38: Peça | P38: Kilo
B39: Zn Alc. Aut | C39: =I39/'Peças por Hora Galvanoplastia'!B27 -> 0 | D39: =I39/'Peças por Hora Galvanoplastia'!C27 -> 0 | E39: =K39/'Peças por Hora Galvanoplastia'!B27 -> 0 | F39: =K39/'Peças por Hora Galvanoplastia'!C27 -> 0 | H39: Zn Alc. Aut | I39: =IF(J39=1,HLOOKUP(G6,'Resumo de Custo'!DS7:ED15,4,0),0) -> 0 | J39: 1 | K39: =IF(J39,HLOOKUP(G6,'Resumo de Custo'!EF7:EQ15,4,0),0) -> 0 | M39: Item | N39: 1 | O39: =C48 -> 0 | P39: =D48 -> 0
M40: Imposto Único | N40: 0.15 | O40: =O39*N40 -> 0 | P40: =P39*N40 -> 0
H47: Total | I47: =SUM(I39:I46) -> 0 | K47: =SUM(K39:K46) -> 0
B48: Total | C48: =SUM(C39:C47) -> 0 | D48: =SUM(D39:D47) -> 0 | E48: =SUM(E39:E47) -> 0 | F48: =SUM(F39:F47) -> 0 | M48: Custo Liquido | O48: =SUM(O39:O47) -> 0 | P48: =SUM(P39:P47) -> 0
B51: Linha 4 | C51: Custo / Peça | D51: Custo/Kilo | E51: Custo/ Peça P.Q | F51: Custo/ Kilo P.Q | H51: Linha 4 | I51: Custo/ Total | K51: Prod. Químico | M51: Linha 4 | N51: % | O51: Peça | P51: Kilo
B52: Zn Alc. Manual | C52: =I52/'Peças por Hora Galvanoplastia'!B35 -> 0 | D52: =I52/'Peças por Hora Galvanoplastia'!C35 -> 0 | E52: =K52/'Peças por Hora Galvanoplastia'!B35 -> 0 | F52: =K52/'Peças por Hora Galvanoplastia'!C35 -> 0 | H52: Zn Alc. Manual | I52: =IF(J52=1,HLOOKUP(G6,'Resumo de Custo'!DS7:ED15,5,0),0) -> 0 | J52: 1 | K52: =IF(J52=1,HLOOKUP(G6,'Resumo de Custo'!EF7:EQ15,5,0),0) -> 0 | M52: Item | N52: 1 | O52: =C61 -> 0 | P52: =D61 -> 0
M53: Imposto Único | N53: 0.15 | O53: =O52*N53 -> 0 | P53: =P52*N53 -> 0
H60: Total | I60: =SUM(I52:I59) -> 0 | K60: =SUM(K52:K59) -> 0
B61: Total | C61: =SUM(C52:C60) -> 0 | D61: =SUM(D52:D60) -> 0 | E61: =SUM(E52:E60) -> 0 | F61: =SUM(F52:F60) -> 0 | M61: Custo Liquido | O61: =SUM(O52:O60) -> 0 | P61: =SUM(P52:P60) -> 0
B64: Linha 5 | C64: Custo / Peça | D64: Custo/Kilo | E64: Custo/ Peça P.Q | F64: Custo/ Kilo P.Q | H64: Linha 5 | I64: Custo/ Total | K64: Prod. Químico | M64: Linha 5 | N64: % | O64: Peça | P64: Kilo
B65: Zn Alc. Semi Aut. | C65: =I65/'Peças por Hora Galvanoplastia'!B43 -> 0 | D65: =I65/'Peças por Hora Galvanoplastia'!C43 -> 0 | E65: =K65/'Peças por Hora Galvanoplastia'!B43 -> 0 | F65: =K65/'Peças por Hora Galvanoplastia'!C43 -> 0 | H65: Zn Alc. Semi Aut. | I65: =IF(J65=1,HLOOKUP(G6,'Resumo de Custo'!DS7:ED15,6,0),0) -> 0 | J65: 1 | K65: =IF(J65=1,HLOOKUP(G6,'Resumo de Custo'!EF7:EQ15,6,0),0) -> 0 | M65: Item | N65: 1 | O65: =C74 -> 0 | P65: =D74 -> 0
M66: Imposto Único | N66: 0.15 | O66: =O65*N66 -> 0 | P66: =P65*N66 -> 0
H73: Total | I73: =SUM(I65:I72) -> 0 | K73: =SUM(K65:K72) -> 0
B74: Total | C74: =SUM(C65:C73) -> 0 | D74: =SUM(D65:D73) -> 0 | E74: =SUM(E65:E73) -> 0 | F74: =SUM(F65:F73) -> 0 | M74: Custo Liquido | O74: =SUM(O65:O73) -> 0 | P74: =SUM(P65:P73) -> 0
B77: Linha 6 | C77: Custo / Peça | D77: Custo/Kilo | E77: Custo/ Peça P.Q | F77: Custo/ Kilo P.Q | H77: Linha 6 | I77: Custo/ Total | K77: Prod. Químico | M77: Linha 6 | N77: % | O77: Peça | P77: Kilo
B78: Zn Ní. Semi Aut. | C78: =I78/'Peças por Hora Galvanoplastia'!B51 -> 0 | D78: =I78/'Peças por Hora Galvanoplastia'!C51 -> 0 | E78: =K78/'Peças por Hora Galvanoplastia'!B51 -> 0.051581388 | F78: =K78/'Peças por Hora Galvanoplastia'!C51 -> 0.073687697 | H78: Zn Ní. Semi Aut. | I78: =IF(J78=1,HLOOKUP(G6,'Resumo de Custo'!DS7:ED15,7,0),0) -> 0 | J78: 1 | K78: =IF(J78=1,HLOOKUP(G6,'Resumo de Custo'!EF7:EQ15,7,0),0) -> 181.81818 | M78: Item | N78: 1 | O78: =C87 -> 0 | P78: =D87 -> 0
M79: Imposto Único | N79: 0.15 | O79: =O78*N79 -> 0 | P79: =P78*N79 -> 0
H86: Total | I86: =SUM(I78:I85) -> 0 | K86: =SUM(K78:K85) -> 181.81818
B87: Total | C87: =SUM(C78:C86) -> 0 | D87: =SUM(D78:D86) -> 0 | E87: =SUM(E78:E86) -> 0.051581388 | F87: =SUM(F78:F86) -> 0.073687697 | M87: Custo Liquido | O87: =SUM(O78:O86) -> 0 | P87: =SUM(P78:P86) -> 0
B90: Linha 9 | C90: Custo / Peça | D90: Custo/Kilo | E90: Custo/ Peça P.Q | F90: Custo/ Kilo P.Q | H90: Linha 9 | I90: Custo/ Total | K90: Prod. Químico | M90: Linha 9 | N90: % | O90: Peça | P90: Kilo
B91: Pré Trat. Fosfato | C91: =I91/'Peças por Hora Galvanoplastia'!B59 -> 0 | D91: =I91/'Peças por Hora Galvanoplastia'!C59 -> 0 | E91: =K91/'Peças por Hora Galvanoplastia'!B59 -> 0 | F91: =K91/'Peças por Hora Galvanoplastia'!C59 -> 0 | H91: Pré Trat. Fosfato | I91: =IF(J91=1,HLOOKUP(G6,'Resumo de Custo'!DS7:ED15,8,0),0) -> 0 | J91: 1 | K91: =IF(J91=1,HLOOKUP(G6,'Resumo de Custo'!EF7:EQ15,8,0),0) -> 0 | M91: Item | N91: 1 | O91: =C100 -> 0 | P91: =D100 -> 0
M92: Imposto Único | N92: 0.15 | O92: =O91*N92 -> 0 | P92: =P91*N92 -> 0
H99: Total | I99: =SUM(I91:I98) -> 0 | K99: =SUM(K91:K98) -> 0
A100: Jan | B100: Total | C100: =SUM(C91:C99) -> 0 | D100: =SUM(D91:D99) -> 0 | E100: =SUM(E91:E99) -> 0 | F100: =SUM(F91:F99) -> 0 | M100: Custo Liquido | O100: =SUM(O91:O99) -> 0 | P100: =SUM(P91:P99) -> 0
A101: Fev
A102: Mar
A103: Abr
A104: Mai
A105: Jun
A106: Jul
A107: Ago
A108: Set
A109: Out
A110: Nov
A111: Dez

Sheet Lnha 1 Zn Alc. Aut
A2: Menu
A3: Zn/Alcalino Rotativo Aut
E5: 45292 | F5: 45292 | G5: 45292 | H5: 45323 | I5: 45323 | J5: 45323 | K5: 45352 | L5: 45352 | M5: 45352 | N5: 45383 | O5: 45383 | P5: 45383 | Q5: 45413 | R5: 45413 | S5: 45413 | T5: 45444 | U5: 45444 | V5: 45444 | W5: 45474 | X5: 45474 | Y5: 45474 | Z5: 45505 | AA5: 45505 | AB5: 45505 | AC5: 45536 | AD5: 45536 | AE5: 45536 | AF5: 45566 | AG5: 45566 | AH5: 45566 | AI5: 45597 | AJ5: 45597 | AK5: 45597 | AL5: 45627 | AM5: 45627 | AN5: 45627
A6: Produto | B6: ID | C6: Volume tanque / lts | D6: Concentração g/lt | E6: Consumo Kg/lt | F6: Custo/Kg | G6: Custo Total | H6: Consumo Kg/lt | I6: Custo/Kg | J6: Custo Total | K6: Consumo Kg/lt | L6: Custo Kg/lt | M6: Custo Total | N6: Consumo Kg/lt | O6: Custo/Kg | P6: Custo Total | Q6: Consumo Kg/lt | R6: Custo/Kg | S6: Custo Total | T6: Consumo Kg/lt | U6: Custo/Kg | V6: Custo Total | W6: Consumo Kg/lt | X6: Custo/Kg | Y6: Custo Total | Z6: Consumo Kg/lt | AA6: Custo/Kg | AB6: Custo Total | AC6: Consumo Kg/lt | AD6: Custo/Kg | AE6: Custo Total | AF6: Consumo Kg/lt | AG6: Custo/Kg | AH6: Custo Total | AI6: Consumo Kg/lt | AJ6: Custo/Kg | AK6: Custo Total | AL6: Consumo Kg/lt | AM6: Custo/Kg | AN6: Custo Total
A7: Composto C-40 (soda cáustica) | C7: 5000 | D7: 0 | E7: 0 | F7: 0 | G7: =F7*E7 -> 0 | H7: 0 | I7: 0 | J7: =I7*H7 -> 0 | K7: 0 | L7: 0 | M7: =L7*K7 -> 0 | N7: 0 | O7: 0 | P7: =O7*N7 -> 0 | Q7: 0 | R7: 0 | S7: =R7*Q7 -> 0 | T7: 0 | U7: 0 | V7: =U7*T7 -> 0 | W7: 0 | X7: 0 | Y7: =X7*W7 -> 0 | Z7: 0 | AA7: 0 | AB7: =AA7*Z7 -> 0 | AC7: 200 | AD7: 0 | AE7: =AD7*AC7 -> 0 | AF7: 0 | AG7: 0 | AH7: =AG7*AF7 -> 0 | AI7: 0 | AJ7: 0 | AK7: =AJ7*AI7 -> 0 | AL7: 0 | AM7: 0 | AN7: =AM7*AL7 -> 0
A8: Zincoat Plus Carrier | D8: 0 | E8: 0 | F8: 0 | G8: =F8*E8 -> 0 | H8: 0 | I8: 0 | J8: =I8*H8 -> 0 | K8: 0 | L8: 0 | M8: =L8*K8 -> 0 | N8: 0 | O8: 0 | P8: =O8*N8 -> 0 | Q8: 0 | R8: 0 | S8: =R8*Q8 -> 0 | T8: 0 | U8: 0 | V8: =U8*T8 -> 0 | W8: 0 | X8: 0 | Y8: =X8*W8 -> 0 | Z8: 0 | AA8: 0 | AB8: =AA8*Z8 -> 0 | AC8: 100 | AD8: 0 | AE8: =AD8*AC8 -> 0 | AF8: 0 | AG8: 0 | AH8: =AG8*AF8 -> 0 | AI8: 0 | AJ8: 0 | AK8: =AJ8*AI8 -> 0 | AL8: 0 | AM8: 0 | AN8: =AM8*AL8 -> 0
A9: Zincoat Plus Brightener | D9: 0 | E9: 0 | F9: 0 | G9: =F9*E9 -> 0 | H9: 0 | I9: 0 | J9: =I9*H9 -> 0 | K9: 0 | L9: 0 | M9: =L9*K9 -> 0 | N9: 0 | O9: 0 | P9: =O9*N9 -> 0 | Q9: 0 | R9: 0 | S9: =R9*Q9 -> 0 | T9: 0 | U9: 0 | V9: =U9*T9 -> 0 | W9: 0 | X9: 0 | Y9: =X9*W9 -> 0 | Z9: 0 | AA9: 0 | AB9: =AA9*Z9 -> 0 | AC9: 100 | AD9: 0 | AE9: =AD9*AC9 -> 0 | AF9: 0 | AG9: 0 | AH9: =AG9*AF9 -> 0 | AI9: 0 | AJ9: 0 | AK9: =AJ9*AI9 -> 0 | AL9: 0 | AM9: 0 | AN9: =AM9*AL9 -> 0
A10: Spectra Matte 255 | C10: 300 | D10: 0 | E10: 0 | F10: 0 | G10: =F10*E10 -> 0 | H10: 0 | I10: 0 | J10: =I10*H10 -> 0 | K10: 0 | L10: 0 | M10: =L10*K10 -> 0 | N10: 0 | O10: 0 | P10: =O10*N10 -> 0 | Q10: 0 | R10: 0 | S10: =R10*Q10 -> 0 | T10: 0 | U10: 0 | V10: =U10*T10 -> 0 | W10: 0 | X10: 0 | Y10: =X10*W10 -> 0 | Z10: 0 | AA10: 0 | AB10: =AA10*Z10 -> 0 | AC10: 25 | AD10: 0 | AE10: =AD10*AC10 -> 0 | AF10: 0 | AG10: 0 | AH10: =AG10*AF10 -> 0 | AI10: 0 | AJ10: 0 | AK10: =AJ10*AI10 -> 0 | AL10: 0 | AM10: 0 | AN10: =AM10*AL10 -> 0
A11: Active MC-20 | C11: 300 | D11: 0 | E11: 0 | F11: 0 | G11: =F11*E11 -> 0 | H11: 0 | I11: 0 | J11: =I11*H11 -> 0 | K11: 0 | L11: 0 | M11: =L11*K11 -> 0 | N11: 0 | O11: 0 | P11: =O11*N11 -> 0 | Q11: 0 | R11: 0 | S11: =R11*Q11 -> 0 | T11: 0 | U11: 0 | V11: =U11*T11 -> 0 | W11: 0 | X11: 0 | Y11: =X11*W11 -> 0 | Z11: 0 | AA11: 0 | AB11: =AA11*Z11 -> 0 | AC11: 25 | AD11: 0 | AE11: =AD11*AC11 -> 0 | AF11: 0 | AG11: 0 | AH11: =AG11*AF11 -> 0 | AI11: 0 | AJ11: 0 | AK11: =AJ11*AI11 -> 0 | AL11: 0 | AM11: 0 | AN11: =AM11*AL11 -> 0
A12: Metal Clean FE 01 | C12: 500 | D12: 0 | E12: 0 | F12: 0 | G12: =F12*E12 -> 0 | H12: 0 | I12: 0 | J12: =I12*H12 -> 0 | K12: 0 | L12: 0 | M12: =L12*K12 -> 0 | N12: 0 | O12: 0 | P12: =O12*N12 -> 0 | Q12: 0 | R12: 0 | S12: =R12*Q12 -> 0 | T12: 0 | U12: 0 | V12: =U12*T12 -> 0 | W12: 0 | X12: 0 | Y12: =X12*W12 -> 0 | Z12: 0 | AA12: 0 | AB12: =AA12*Z12 -> 0 | AC12: 25 | AD12: 0 | AE12: =AD12*AC12 -> 0 | AF12: 0 | AG12: 0 | AH12: =AG12*AF12 -> 0 | AI12: 0 | AJ12: 0 | AK12: =AJ12*AI12 -> 0 | AL12: 0 | AM12: 0 | AN12: =AM12*AL12 -> 0
A13: Anodo | C13: 0 | D13: 0 | E13: 0 | F13: 0 | G13: =F13*E13 -> 0 | H13: 0 | I13: 0 | J13: =I13*H13 -> 0 | K13: 0 | L13: 0 | M13: =L13*K13 -> 0 | N13: 0 | O13: 0 | P13: =O13*N13 -> 0 | Q13: 0 | R13: 0 | S13: =R13*Q13 -> 0 | T13: 0 | U13: 0 | V13: =U13*T13 -> 0 | W13: 0 | X13: 0 | Y13: =X13*W13 -> 0 | Z13: 0 | AA13: 0 | AB13: =AA13*Z13 -> 0 | AC13: 200 | AD13: 0 | AE13: =AD13*AC13 -> 0 | AF13: 0 | AG13: 0 | AH13: =AG13*AF13 -> 0 | AI13: 0 | AJ13: 0 | AK13: =AJ13*AI13 -> 0 | AL13: 0 | AM13: 0 | AN13: =AM13*AL13 -> 0
C14: 0 | D14: 0 | E14: 0
F15: Total | G15: =SUM(G7:G14) -> 0 | I15: Total | J15: =SUM(J7:J14) -> 0 | L15: Total | M15: =SUM(M7:M14) -> 0 | O15: Total | P15: =SUM(P7:P14) -> 0 | R15: Total | S15: =SUM(S7:S14) -> 0 | U15: Total | V15: =SUM(V7:V14) -> 0 | X15: Total | Y15: =SUM(Y7:Y14) -> 0 | AA15: Total | AB15: =SUM(AB7:AB14) -> 0 | AD15: Total | AE15: =SUM(AE7:AE14) -> 0 | AG15: Total | AH15: =SUM(AH7:AH14) -> 0 | AJ15: Total | AK15: =SUM(AK7:AK14) -> 0 | AM15: Total | AN15: =SUM(AN7:AN14) -> 0

Sheet Linha 2 Zn Alc. Aut
A2: Menu
A3: Zn/Alcalino Rotativo Aut
E5: 45292 | F5: 45292 | G5: 45292 | H5: 45323 | I5: 45323 | J5: 45323 | K5: 45352 | L5: 45352 | M5: 45352 | N5: 45383 | O5: 45383 | P5: 45383 | Q5: 45413 | R5: 45413 | S5: 45413 | T5: 45444 | U5: 45444 | V5: 45444 | W5: 45474 | X5: 45474 | Y5: 45474 | Z5: 45505 | AA5: 45505 | AB5: 45505 | AC5: 45536 | AD5: 45536 | AE5: 45536 | AF5: 45566 | AG5: 45566 | AH5: 45566 | AI5: 45597 | AJ5: 45597 | AK5: 45597 | AL5: 45627 | AM5: 45627 | AN5: 45627
A6: Produto | B6: ID | C6: Volume tanque / lts | D6: Concentração /% | E6: Consumo Kg/lt | F6: Custo/Kg | G6: Custo Total | H6: Consumo Kg/lt | I6: Custo/Kg | J6: Custo Total | K6: Consumo Kg/lt | L6: Custo Kg/lt | M6: Custo Total | N6: Consumo Kg/lt | O6: Custo/Kg | P6: Custo Total | Q6: Consumo Kg/lt | R6: Custo/Kg | S6: Custo Total | T6: Consumo Kg/lt | U6: Custo/Kg | V6: Custo Total | W6: Consumo Kg/lt | X6: Custo/Kg | Y6: Custo Total | Z6: Consumo Kg/lt | AA6: Custo/Kg | AB6: Custo Total | AC6: Consumo Kg/lt | AD6: Custo/Kg | AE6: Custo Total | AF6: Consumo Kg/lt | AG6: Custo/Kg | AH6: Custo Total | AI6: Consumo Kg/lt | AJ6: Custo/Kg | AK6: Custo Total | AL6: Consumo Kg/lt | AM6: Custo/Kg | AN6: Custo Total
A7: Composto C-40 (soda cáustica) | C7: 5000 | D7: 0 | E7: 0 | F7: 0 | G7: =F7*E7 -> 0 | H7: 0 | I7: 0 | J7: =I7*H7 -> 0 | K7: 0 | L7: 0 | M7: =L7*K7 -> 0 | N7: 0 | O7: 0 | P7: =O7*N7 -> 0 | Q7: 0 | R7: 0 | S7: =R7*Q7 -> 0 | T7: 0 | U7: 1 | V7: =U7*T7 -> 0 | W7: 0 | X7: 0 | Y7: =X7*W7 -> 0 | Z7: 0 | AA7: 0 | AB7: =AA7*Z7 -> 0 | AC7: 200 | AD7: 0 | AE7: =AD7*AC7 -> 0 | AF7: 0 | AG7: 0 | AH7: =AG7*AF7 -> 0 | AI7: 0 | AJ7: 0 | AK7: =AJ7*AI7 -> 0 | AL7: 0 | AM7: 0 | AN7: =AM7*AL7 -> 0
A8: Zincoat Plus Carrier | D8: 0 | E8: 0 | F8: 0 | G8: =F8*E8 -> 0 | H8: 0 | I8: 0 | J8: =I8*H8 -> 0 | K8: 0 | L8: 0 | M8: =L8*K8 -> 0 | N8: 0 | O8: 0 | P8: =O8*N8 -> 0 | Q8: 0 | R8: 0 | S8: =R8*Q8 -> 0 | T8: 0 | U8: 0 | V8: =U8*T8 -> 0 | W8: 0 | X8: 0 | Y8: =X8*W8 -> 0 | Z8: 0 | AA8: 0 | AB8: =AA8*Z8 -> 0 | AC8: 100 | AD8: 0 | AE8: =AD8*AC8 -> 0 | AF8: 0 | AG8: 0 | AH8: =AG8*AF8 -> 0 | AI8: 0 | AJ8: 0 | AK8: =AJ8*AI8 -> 0 | AL8: 0 | AM8: 0 | AN8: =AM8*AL8 -> 0
A9: Zincoat Plus Brightener | D9: 0 | E9: 0 | F9: 0 | G9: =F9*E9 -> 0 | H9: 0 | I9: 0 | J9: =I9*H9 -> 0 | K9: 0 | L9: 0 | M9: =L9*K9 -> 0 | N9: 0 | O9: 0 | P9: =O9*N9 -> 0 | Q9: 0 | R9: 0 | S9: =R9*Q9 -> 0 | T9: 0 | U9: 0 | V9: =U9*T9 -> 0 | W9: 0 | X9: 0 | Y9: =X9*W9 -> 0 | Z9: 0 | AA9: 0 | AB9: =AA9*Z9 -> 0 | AC9: 100 | AD9: 0 | AE9: =AD9*AC9 -> 0 | AF9: 0 | AG9: 0 | AH9: =AG9*AF9 -> 0 | AI9: 0 | AJ9: 0 | AK9: =AJ9*AI9 -> 0 | AL9: 0 | AM9: 0 | AN9: =AM9*AL9 -> 0
A10: Spectra Matte 255 | C10: 300 | D10: 0 | E10: 0 | F10: 0 | G10: =F10*E10 -> 0 | H10: 0 | I10: 0 | J10: =I10*H10 -> 0 | K10: 0 | L10: 0 | M10: =L10*K10 -> 0 | N10: 0 | O10: 0 | P10: =O10*N10 -> 0 | Q10: 0 | R10: 0 | S10: =R10*Q10 -> 0 | T10: 0 | U10: 0 | V10: =U10*T10 -> 0 | W10: 0 | X10: 0 | Y10: =X10*W10 -> 0 | Z10: 0 | AA10: 0 | AB10: =AA10*Z10 -> 0 | AC10: 25 | AD10: 0 | AE10: =AD10*AC10 -> 0 | AF10: 0 | AG10: 0 | AH10: =AG10*AF10 -> 0 | AI10: 0 | AJ10: 0 | AK10: =AJ10*AI10 -> 0 | AL10: 0 | AM10: 0 | AN10: =AM10*AL10 -> 0
A11: Active MC-20 | C11: 300 | D11: 0 | E11: 0 | F11: 0 | G11: =F11*E11 -> 0 | H11: 0 | I11: 0 | J11: =I11*H11 -> 0 | K11: 0 | L11: 0 | M11: =L11*K11 -> 0 | N11: 0 | O11: 0 | P11: =O11*N11 -> 0 | Q11: 0 | R11: 0 | S11: =R11*Q11 -> 0 | T11: 0 | U11: 1 | V11: =U11*T11 -> 0 | W11: 0 | X11: 0 | Y11: =X11*W11 -> 0 | Z11: 0 | AA11: 0 | AB11: =AA11*Z11 -> 0 | AC11: 25 | AD11: 0 | AE11: =AD11*AC11 -> 0 | AF11: 0 | AG11: 0 | AH11: =AG11*AF11 -> 0 | AI11: 0 | AJ11: 0 | AK11: =AJ11*AI11 -> 0 | AL11: 0 | AM11: 0 | AN11: =AM11*AL11 -> 0
A12: Desengraxante Eletrolitico | C12: 600 | D12: 0 | E12: 0 | F12: 0 | G12: =F12*E12 -> 0 | H12: 0 | I12: 0 | J12: =I12*H12 -> 0 | K12: 0 | L12: 0 | M12: =L12*K12 -> 0 | N12: 0 | O12: 0 | P12: =O12*N12 -> 0 | Q12: 0 | R12: 0 | S12: =R12*Q12 -> 0 | T12: 0 | U12: 0 | V12: =U12*T12 -> 0 | W12: 0 | X12: 0 | Y12: =X12*W12 -> 0 | Z12: 0 | AA12: 0 | AB12: =AA12*Z12 -> 0 | AC12: 25 | AD12: 0 | AE12: =AD12*AC12 -> 0 | AF12: 0 | AG12: 0 | AH12: =AG12*AF12 -> 0 | AI12: 0 | AJ12: 0 | AK12: =AJ12*AI12 -> 0 | AL12: 0 | AM12: 0 | AN12: =AM12*AL12 -> 0
A13: Anodo | C13: 0 | D13: 0 | E13: 0 | F13: 0 | G13: =F13*E13 -> 0 | H13: 0 | I13: 0 | J13: =I13*H13 -> 0 | K13: 0 | L13: 0 | M13: =L13*K13 -> 0 | N13: 0 | O13: 0 | P13: =O13*N13 -> 0 | Q13: 0 | R13: 0 | S13: =R13*Q13 -> 0 | T13: 0 | U13: 0 | V13: =U13*T13 -> 0 | W13: 0 | X13: 0 | Y13: =X13*W13 -> 0 | Z13: 0 | AA13: 0 | AB13: =AA13*Z13 -> 0 | AC13: 200 | AD13: 0 | AE13: =AD13*AC13 -> 0 | AF13: 0 | AG13: 0 | AH13: =AG13*AF13 -> 0 | AI13: 0 | AJ13: 0 | AK13: =AJ13*AI13 -> 0 | AL13: 0 | AM13: 0 | AN13: =AM13*AL13 -> 0
C14: 0 | D14: 0 | E14: 0 | F14: 0 | G14: =F14*E14 -> 0 | H14: 0 | I14: 0 | J14: =I14*H14 -> 0 | K14: 0 | L14: 0 | M14: =L14*K14 -> 0 | N14: 0 | O14: 0 | P14: =O14*N14 -> 0 | Q14: 0 | R14: 0 | S14: =R14*Q14 -> 0 | T14: 0 | U14: 0 | V14: =U14*T14 -> 0 | W14: 0 | X14: 0 | Y14: =X14*W14 -> 0 | Z14: 0 | AA14: 0 | AB14: =AA14*Z14 -> 0 | AC14: 0 | AD14: 0 | AE14: =AD14*AC14 -> 0 | AF14: 0 | AG14: 0 | AH14: =AG14*AF14 -> 0 | AI14: 0 | AJ14: 0 | AK14: =AJ14*AI14 -> 0 | AL14: 0 | AM14: 0 | AN14: =AM14*AL14 -> 0
C15: 0 | D15: 0 | E15: 0 | F15: 0 | G15: =F15*E15 -> 0 | H15: 0 | I15: 0 | J15: =I15*H15 -> 0 | K15: 0 | L15: 0 | M15: =L15*K15 -> 0 | N15: 0 | O15: 0 | P15: =O15*N15 -> 0 | Q15: 0 | R15: 0 | S15: =R15*Q15 -> 0 | T15: 0 | U15: 0 | V15: =U15*T15 -> 0 | W15: 0 | X15: 0 | Y15: =X15*W15 -> 0 | Z15: 0 | AA15: 0 | AB15: =AA15*Z15 -> 0 | AC15: 0 | AD15: 0 | AE15: =AD15*AC15 -> 0 | AF15: 0 | AG15: 0 | AH15: =AG15*AF15 -> 0 | AI15: 0 | AJ15: 0 | AK15: =AJ15*AI15 -> 0 | AL15: 0 | AM15: 0 | AN15: =AM15*AL15 -> 0
F16: Total | G16: =SUM(G7:G15) -> 0 | I16: Total | J16: =SUM(J7:J15) -> 0 | L16: Total | M16: =SUM(M7:M15) -> 0 | O16: Total | P16: =SUM(P7:P15) -> 0 | R16: Total | S16: =SUM(S7:S15) -> 0 | U16: Total | V16: =SUM(V7:V15) -> 0 | X16: Total | Y16: =SUM(Y7:Y15) -> 0 | AA16: Total | AB16: =SUM(AB7:AB15) -> 0 | AD16: Total | AE16: =SUM(AE7:AE15) -> 0 | AG16: Total | AH16: =SUM(AH7:AH15) -> 0 | AJ16: Total | AK16: =SUM(AK7:AK15) -> 0 | AM16: Total | AN16: =SUM(AN7:AN15) -> 0

Sheet Linha 3 Zn Alc. Aut
A2: Menu
A3: Zn/Alcalino Rotativo Aut
E5: 45292 | F5: 45292 | G5: 45292 | H5: 45323 | I5: 45323 | J5: 45323 | K5: 45352 | L5: 45352 | M5: 45352 | N5: 45383 | O5: 45383 | P5: 45383 | Q5: 45413 | R5: 45413 | S5: 45413 | T5: 45444 | U5: 45444 | V5: 45444 | W5: 45474 | X5: 45474 | Y5: 45474 | Z5: 45505 | AA5: 45505 | AB5: 45505 | AC5: 45536 | AD5: 45536 | AE5: 45536 | AF5: 45566 | AG5: 45566 | AH5: 45566 | AI5: 45597 | AJ5: 45597 | AK5: 45597 | AL5: 45627 | AM5: 45627 | AN5: 45627
A6: Produto | B6: ID | C6: Volume tanque / lts | D6: Concentração g/lt | E6: Consumo Kg/lt | F6: Custo/Kg | G6: Custo Total | H6: Consumo Kg/lt | I6: Custo/Kg | J6: Custo Total | K6: Consumo Kg/lt | L6: Custo Kg/lt | M6: Custo Total | N6: Consumo Kg/lt | O6: Custo/Kg | P6: Custo Total | Q6: Consumo Kg/lt | R6: Custo/Kg | S6: Custo Total | T6: Consumo Kg/lt | U6: Custo/Kg | V6: Custo Total | W6: Consumo Kg/lt | X6: Custo/Kg | Y6: Custo Total | Z6: Consumo Kg/lt | AA6: Custo/Kg | AB6: Custo Total | AC6: Consumo Kg/lt | AD6: Custo/Kg | AE6: Custo Total | AF6: Consumo Kg/lt | AG6: Custo/Kg | AH6: Custo Total | AI6: Consumo Kg/lt | AJ6: Custo/Kg | AK6: Custo Total | AL6: Consumo Kg/lt | AM6: Custo/Kg | AN6: Custo Total
A7: Composto C-40 (soda cáustica) | C7: 5000 | D7: 0 | E7: 0 | F7: 0 | G7: =F7*E7 -> 0 | H7: 0 | I7: 0 | J7: =I7*H7 -> 0 | K7: 0 | L7: 0 | M7: =L7*K7 -> 0 | N7: 0 | O7: 0 | P7: =O7*N7 -> 0 | Q7: 0 | R7: 0 | S7: =R7*Q7 -> 0 | T7: 0 | U7: 0 | V7: =U7*T7 -> 0 | W7: 0 | X7: 0 | Y7: =X7*W7 -> 0 | Z7: 0 | AA7: 0 | AB7: =AA7*Z7 -> 0 | AC7: 200 | AD7: 0 | AE7: =AD7*AC7 -> 0 | AF7: 0 | AG7: 0 | AH7: =AG7*AF7 -> 0 | AI7: 0 | AJ7: 0 | AK7: =AJ7*AI7 -> 0 | AL7: 0 | AM7: 0 | AN7: =AM7*AL7 -> 0
A8: Zincoat Plus Carrier | D8: 0 | E8: 0 | F8: 0 | G8: =F8*E8 -> 0 | H8: 0 | I8: 0 | J8: =I8*H8 -> 0 | K8: 0 | L8: 0 | M8: =L8*K8 -> 0 | N8: 0 | O8: 0 | P8: =O8*N8 -> 0 | Q8: 0 | R8: 0 | S8: =R8*Q8 -> 0 | T8: 0 | U8: 0 | V8: =U8*T8 -> 0 | W8: 0 | X8: 0 | Y8: =X8*W8 -> 0 | Z8: 0 | AA8: 0 | AB8: =AA8*Z8 -> 0 | AC8: 100 | AD8: 0 | AE8: =AD8*AC8 -> 0 | AF8: 0 | AG8: 0 | AH8: =AG8*AF8 -> 0 | AI8: 0 | AJ8: 0 | AK8: =AJ8*AI8 -> 0 | AL8: 0 | AM8: 0 | AN8: =AM8*AL8 -> 0
A9: Zincoat Plus Brightener | D9: 0 | E9: 0 | F9: 0 | G9: =F9*E9 -> 0 | H9: 0 | I9: 0 | J9: =I9*H9 -> 0 | K9: 0 | L9: 0 | M9: =L9*K9 -> 0 | N9: 0 | O9: 0 | P9: =O9*N9 -> 0 | Q9: 0 | R9: 0 | S9: =R9*Q9 -> 0 | T9: 0 | U9: 0 | V9: =U9*T9 -> 0 | W9: 0 | X9: 0 | Y9: =X9*W9 -> 0 | Z9: 0 | AA9: 0 | AB9: =AA9*Z9 -> 0 | AC9: 100 | AD9: 0 | AE9: =AD9*AC9 -> 0 | AF9: 0 | AG9: 0 | AH9: =AG9*AF9 -> 0 | AI9: 0 | AJ9: 0 | AK9: =AJ9*AI9 -> 0 | AL9: 0 | AM9: 0 | AN9: =AM9*AL9 -> 0
A10: Metal Clean FE 01 | C10: 300 | D10: 0 | E10: 0 | F10: 0 | G10: =F10*E10 -> 0 | H10: 0 | I10: 0 | J10: =I10*H10 -> 0 | K10: 0 | L10: 0 | M10: =L10*K10 -> 0 | N10: 0 | O10: 0 | P10: =O10*N10 -> 0 | Q10: 0 | R10: 0 | S10: =R10*Q10 -> 0 | T10: 0 | U10: 0 | V10: =U10*T10 -> 0 | W10: 0 | X10: 0 | Y10: =X10*W10 -> 0 | Z10: 0 | AA10: 0 | AB10: =AA10*Z10 -> 0 | AC10: 25 | AD10: 0 | AE10: =AD10*AC10 -> 0 | AF10: 0 | AG10: 0 | AH10: =AG10*AF10 -> 0 | AI10: 0 | AJ10: 0 | AK10: =AJ10*AI10 -> 0 | AL10: 0 | AM10: 0 | AN10: =AM10*AL10 -> 0
A11: Metal Clean FE 01 | C11: 300 | D11: 0 | E11: 0 | F11: 0 | G11: =F11*E11 -> 0 | H11: 0 | I11: 0 | J11: =I11*H11 -> 0 | K11: 0 | L11: 0 | M11: =L11*K11 -> 0 | N11: 0 | O11: 0 | P11: =O11*N11 -> 0 | Q11: 0 | R11: 0 | S11: =R11*Q11 -> 0 | T11: 0 | U11: 0 | V11: =U11*T11 -> 0 | W11: 0 | X11: 0 | Y11: =X11*W11 -> 0 | Z11: 0 | AA11: 0 | AB11: =AA11*Z11 -> 0 | AC11: 25 | AD11: 0 | AE11: =AD11*AC11 -> 0 | AF11: 0 | AG11: 0 | AH11: =AG11*AF11 -> 0 | AI11: 0 | AJ11: 0 | AK11: =AJ11*AI11 -> 0 | AL11: 0 | AM11: 0 | AN11: =AM11*AL11 -> 0
A12: Desengraxante Eletrolitico | C12: 300 | D12: 0 | E12: 0 | F12: 0 | G12: =F12*E12 -> 0 | H12: 0 | I12: 0 | J12: =I12*H12 -> 0 | K12: 0 | L12: 0 | M12: =L12*K12 -> 0 | N12: 0 | O12: 0 | P12: =O12*N12 -> 0 | Q12: 0 | R12: 0 | S12: =R12*Q12 -> 0 | T12: 0 | U12: 0 | V12: =U12*T12 -> 0 | W12: 0 | X12: 0 | Y12: =X12*W12 -> 0 | Z12: 0 | AA12: 0 | AB12: =AA12*Z12 -> 0 | AC12: 25 | AD12: 0 | AE12: =AD12*AC12 -> 0 | AF12: 0 | AG12: 0 | AH12: =AG12*AF12 -> 0 | AI12: 0 | AJ12: 0 | AK12: =AJ12*AI12 -> 0 | AL12: 0 | AM12: 0 | AN12: =AM12*AL12 -> 0
A13: Ácido Cloridrico | C13: 300 | D13: 0 | E13: 0 | F13: 0 | G13: =F13*E13 -> 0 | H13: 0 | I13: 0 | J13: =I13*H13 -> 0 | K13: 0 | L13: 0 | M13: =L13*K13 -> 0 | N13: 0 | O13: 0 | P13: =O13*N13 -> 0 | Q13: 0 | R13: 0 | S13: =R13*Q13 -> 0 | T13: 0 | U13: 0 | V13: =U13*T13 -> 0 | W13: 0 | X13: 0 | Y13: =X13*W13 -> 0 | Z13: 0 | AA13: 0 | AB13: =AA13*Z13 -> 0 | AC13: 25 | AD13: 0 | AE13: =AD13*AC13 -> 0 | AF13: 0 | AG13: 0 | AH13: =AG13*AF13 -> 0 | AI13: 0 | AJ13: 0 | AK13: =AJ13*AI13 -> 0 | AL13: 0 | AM13: 0 | AN13: =AM13*AL13 -> 0
A14: Spectra Matte 255 | C14: 300 | D14: 0 | E14: 0 | F14: 0 | G14: =F14*E14 -> 0 | H14: 0 | I14: 0 | J14: =I14*H14 -> 0 | K14: 0 | L14: 0 | M14: =L14*K14 -> 0 | N14: 0 | O14: 0 | P14: =O14*N14 -> 0 | Q14: 0 | R14: 0 | S14: =R14*Q14 -> 0 | T14: 0 | U14: 0 | V14: =U14*T14 -> 0 | W14: 0 | X14: 0 | Y14: =X14*W14 -> 0 | Z14: 0 | AA14: 0 | AB14: =AA14*Z14 -> 0 | AC14: 25 | AD14: 0 | AE14: =AD14*AC14 -> 0 | AF14: 0 | AG14: 0 | AH14: =AG14*AF14 -> 0 | AI14: 0 | AJ14: 0 | AK14: =AJ14*AI14 -> 0 | AL14: 0 | AM14: 0 | AN14: =AM14*AL14 -> 0
A15: Active MC-20 | C15: 300 | D15: 0 | E15: 0 | F15: 0 | G15: =F15*E15 -> 0 | H15: 0 | I15: 0 | J15: =I15*H15 -> 0 | K15: 0 | L15: 0 | M15: =L15*K15 -> 0 | N15: 0 | O15: 0 | P15: =O15*N15 -> 0 | Q15: 0 | R15: 0 | S15: =R15*Q15 -> 0 | T15: 0 | U15: 0 | V15: =U15*T15 -> 0 | W15: 0 | X15: 0 | Y15: =X15*W15 -> 0 | Z15: 0 | AA15: 0 | AB15: =AA15*Z15 -> 0 | AC15: 25 | AD15: 0 | AE15: =AD15*AC15 -> 0 | AF15: 0 | AG15: 0 | AH15: =AG15*AF15 -> 0 | AI15: 0 | AJ15: 0 | AK15: =AJ15*AI15 -> 0 | AL15: 0 | AM15: 0 | AN15: =AM15*AL15 -> 0
A16: Anodo | D16: 0 | E16: 0 | F16: 0 | G16: =F16*E16 -> 0 | H16: 0 | I16: 0 | J16: =I16*H16 -> 0 | K16: 0 | L16: 0 | M16: =L16*K16 -> 0 | N16: 0 | O16: 0 | P16: =O16*N16 -> 0 | Q16: 0 | R16: 0 | S16: =R16*Q16 -> 0 | T16: 0 | U16: 0 | V16: =U16*T16 -> 0 | W16: 0 | X16: 0 | Y16: =X16*W16 -> 0 | Z16: 0 | AA16: 0 | AB16: =AA16*Z16 -> 0 | AC16: 200 | AD16: 0 | AE16: =AD16*AC16 -> 0 | AF16: 0 | AG16: 0 | AH16: =AG16*AF16 -> 0 | AI16: 0 | AJ16: 0 | AK16: =AJ16*AI16 -> 0 | AL16: 0 | AM16: 0 | AN16: =AM16*AL16 -> 0
F17: Total | G17: =SUM(G7:G16) -> 0 | I17: Total | J17: =SUM(J7:J16) -> 0 | L17: Total | M17: =SUM(M7:M16) -> 0 | O17: Total | P17: =SUM(P7:P16) -> 0 | R17: Total | S17: =SUM(S7:S16) -> 0 | U17: Total | V17: =SUM(V7:V16) -> 0 | X17: Total | Y17: =SUM(Y7:Y16) -> 0 | AA17: Total | AB17: =SUM(AB7:AB16) -> 0 | AD17: Total | AE17: =SUM(AE7:AE16) -> 0 | AG17: Total | AH17: =SUM(AH7:AH16) -> 0 | AJ17: Total | AK17: =SUM(AK7:AK16) -> 0 | AM17: Total | AN17: =SUM(AN7:AN16) -> 0

Sheet Linha 4 Zn Alc. Manual
A2: Menu
A3: Zn/Alcalino Rotativo Manu.
E5: 45292 | F5: 45292 | G5: 45292 | H5: 45323 | I5: 45323 | J5: 45323 | K5: 45352 | L5: 45352 | M5: 45352 | N5: 45383 | O5: 45383 | P5: 45383 | Q5: 45413 | R5: 45413 | S5: 45413 | T5: 45444 | U5: 45444 | V5: 45444 | W5: 45474 | X5: 45474 | Y5: 45474 | Z5: 45505 | AA5: 45505 | AB5: 45505 | AC5: 45536 | AD5: 45536 | AE5: 45536 | AF5: 45566 | AG5: 45566 | AH5: 45566 | AI5: 45597 | AJ5: 45597 | AK5: 45597 | AL5: 45627 | AM5: 45627 | AN5: 45627
A6: Produto | B6: ID | C6: Volume tanque / lts | D6: Concentração g/lt | E6: Consumo Kg/lt | F6: Custo/Kg | G6: Custo Total | H6: Consumo Kg/lt | I6: Custo/Kg | J6: Custo Total | K6: Consumo Kg/lt | L6: Custo Kg/lt | M6: Custo Total | N6: Consumo Kg/lt | O6: Custo/Kg | P6: Custo Total | Q6: Consumo Kg/lt | R6: Custo/Kg | S6: Custo Total | T6: Consumo Kg/lt | U6: Custo/Kg | V6: Custo Total | W6: Consumo Kg/lt | X6: Custo/Kg | Y6: Custo Total | Z6: Consumo Kg/lt | AA6: Custo/Kg | AB6: Custo Total | AC6: Consumo Kg/lt | AD6: Custo/Kg | AE6: Custo Total | AF6: Consumo Kg/lt | AG6: Custo/Kg | AH6: Custo Total | AI6: Consumo Kg/lt | AJ6: Custo/Kg | AK6: Custo Total | AL6: Consumo Kg/lt | AM6: Custo/Kg | AN6: Custo Total
A7: Composto C-40 | C7: 2600 | D7: 0 | E7: 0 | F7: 0 | G7: =F7*E7 -> 0 | H7: 0 | I7: 0 | J7: =I7*H7 -> 0 | K7: 0 | L7: 0 | M7: =L7*K7 -> 0 | N7: 0 | O7: 0 | P7: =O7*N7 -> 0 | Q7: 0 | R7: 0 | S7: =R7*Q7 -> 0 | T7: 0 | U7: 0 | V7: =U7*T7 -> 0 | W7: 0 | X7: 0 | Y7: =X7*W7 -> 0 | Z7: 0 | AA7: 0 | AB7: =AA7*Z7 -> 0 | AC7: 100 | AD7: 0 | AE7: =AD7*AC7 -> 0 | AF7: 0 | AG7: 0 | AH7: =AG7*AF7 -> 0 | AI7: 0 | AJ7: 0 | AK7: =AJ7*AI7 -> 0 | AL7: 0 | AM7: 5 | AN7: =AM7*AL7 -> 0
A8: Zincoat Premium Make Up | D8: 0 | E8: 0 | F8: 0 | G8: =F8*E8 -> 0 | H8: 0 | I8: 0 | J8: =I8*H8 -> 0 | K8: 0 | L8: 0 | M8: =L8*K8 -> 0 | N8: 0 | O8: 0 | P8: =O8*N8 -> 0 | Q8: 0 | R8: 0 | S8: =R8*Q8 -> 0 | T8: 0 | U8: 0 | V8: =U8*T8 -> 0 | W8: 0 | X8: 0 | Y8: =X8*W8 -> 0 | Z8: 0 | AA8: 0 | AB8: =AA8*Z8 -> 0 | AC8: 50 | AD8: 0 | AE8: =AD8*AC8 -> 0 | AF8: 0 | AG8: 0 | AH8: =AG8*AF8 -> 0 | AI8: 0 | AJ8: 0 | AK8: =AJ8*AI8 -> 0 | AL8: 0 | AM8: 0 | AN8: =AM8*AL8 -> 0
A9: Zincoat Premium Replenisher | D9: 0 | E9: 0 | F9: 0 | G9: =F9*E9 -> 0 | H9: 0 | I9: 0 | J9: =I9*H9 -> 0 | K9: 0 | L9: 0 | M9: =L9*K9 -> 0 | N9: 0 | O9: 0 | P9: =O9*N9 -> 0 | Q9: 0 | R9: 0 | S9: =R9*Q9 -> 0 | T9: 0 | U9: 0 | V9: =U9*T9 -> 0 | W9: 0 | X9: 0 | Y9: =X9*W9 -> 0 | Z9: 0 | AA9: 0 | AB9: =AA9*Z9 -> 0 | AC9: 50 | AD9: 0 | AE9: =AD9*AC9 -> 0 | AF9: 0 | AG9: 0 | AH9: =AG9*AF9 -> 0 | AI9: 0 | AJ9: 0 | AK9: =AJ9*AI9 -> 0 | AL9: 0 | AM9: 0 | AN9: =AM9*AL9 -> 0
A10: Spectra Silver ZNI | C10: 440 | D10: 0 | E10: 0 | F10: 0 | G10: =F10*E10 -> 0 | H10: 0 | I10: 0 | J10: =I10*H10 -> 0 | K10: 0 | L10: 0 | M10: =L10*K10 -> 0 | N10: 0 | O10: 0 | P10: =O10*N10 -> 0 | Q10: 0 | R10: 0 | S10: =R10*Q10 -> 0 | T10: 0 | U10: 0 | V10: =U10*T10 -> 0 | W10: 0 | X10: 0 | Y10: =X10*W10 -> 0 | Z10: 0 | AA10: 0 | AB10: =AA10*Z10 -> 0 | AC10: 0 | AD10: 0 | AE10: =AD10*AC10 -> 0 | AF10: 0 | AG10: 0 | AH10: =AG10*AF10 -> 0 | AI10: 0 | AJ10: 0 | AK10: =AJ10*AI10 -> 0 | AL10: 0 | AM10: 0 | AN10: =AM10*AL10 -> 0
A11: Spectra Seal 050 | C11: 240 | D11: 0 | E11: 0 | F11: 0 | G11: =F11*E11 -> 0 | H11: 0 | I11: 0 | J11: =I11*H11 -> 0 | K11: 0 | L11: 0 | M11: =L11*K11 -> 0 | N11: 0 | O11: 0 | P11: =O11*N11 -> 0 | Q11: 0 | R11: 0 | S11: =R11*Q11 -> 0 | T11: 0 | U11: 0 | V11: =U11*T11 -> 0 | W11: 0 | X11: 0 | Y11: =X11*W11 -> 0 | Z11: 0 | AA11: 0 | AB11: =AA11*Z11 -> 0 | AC11: 0 | AD11: 0 | AE11: =AD11*AC11 -> 0 | AF11: 0 | AG11: 0 | AH11: =AG11*AF11 -> 0 | AI11: 0 | AJ11: 0 | AK11: =AJ11*AI11 -> 0 | AL11: 0 | AM11: 0 | AN11: =AM11*AL11 -> 0
A12: Anodo | C12: 0 | D12: 0 | E12: 0 | F12: 0 | G12: =F12*E12 -> 0 | H12: 0 | I12: 0 | J12: =I12*H12 -> 0 | K12: 0 | L12: 0 | M12: =L12*K12 -> 0 | N12: 0 | O12: 0 | P12: =O12*N12 -> 0 | Q12: 0 | R12: 0 | S12: =R12*Q12 -> 0 | T12: 0 | U12: 0 | V12: =U12*T12 -> 0 | W12: 0 | X12: 0 | Y12: =X12*W12 -> 0 | Z12: 0 | AA12: 0 | AB12: =AA12*Z12 -> 0 | AC12: 25 | AD12: 0 | AE12: =AD12*AC12 -> 0 | AF12: 0 | AG12: 0 | AH12: =AG12*AF12 -> 0 | AI12: 0 | AJ12: 0 | AK12: =AJ12*AI12 -> 0 | AL12: 0 | AM12: 0 | AN12: =AM12*AL12 -> 0
C13: 0 | D13: 0 | E13: 0 | F13: 0 | G13: =F13*E13 -> 0 | H13: 0 | I13: 0 | J13: =I13*H13 -> 0 | K13: 0 | L13: 0 | M13: =L13*K13 -> 0 | N13: 0 | O13: 0 | P13: =O13*N13 -> 0 | Q13: 0 | R13: 0 | S13: =R13*Q13 -> 0 | T13: 0 | U13: 0 | V13: =U13*T13 -> 0 | W13: 0 | X13: 0 | Y13: =X13*W13 -> 0 | Z13: 0 | AA13: 0 | AB13: =AA13*Z13 -> 0 | AC13: 0 | AD13: 0 | AE13: =AD13*AC13 -> 0 | AF13: 0 | AG13: 0 | AH13: =AG13*AF13 -> 0 | AI13: 0 | AJ13: 0 | AK13: =AJ13*AI13 -> 0 | AL13: 0 | AM13: 0 | AN13: =AM13*AL13 -> 0
C14: 0 | D14: 0 | E14: 0 | F14: 0 | G14: =F14*E14 -> 0 | H14: 0 | I14: 0 | J14: =I14*H14 -> 0 | K14: 0 | L14: 0 | M14: =L14*K14 -> 0 | N14: 0 | O14: 0 | P14: =O14*N14 -> 0 | Q14: 0 | R14: 0 | S14: =R14*Q14 -> 0 | T14: 0 | U14: 0 | V14: =U14*T14 -> 0 | W14: 0 | X14: 0 | Y14: =X14*W14 -> 0 | Z14: 0 | AA14: 0 | AB14: =AA14*Z14 -> 0 | AC14: 0 | AD14: 0 | AE14: =AD14*AC14 -> 0 | AF14: 0 | AG14: 0 | AH14: =AG14*AF14 -> 0 | AI14: 0 | AJ14: 0 | AK14: =AJ14*AI14 -> 0 | AL14: 0 | AM14: 0 | AN14: =AM14*AL14 -> 0
F15: Total | G15: =SUM(G7:G14) -> 0 | I15: Total | J15: =SUM(J7:J14) -> 0 | L15: Total | M15: =SUM(M7:M14) -> 0 | O15: Total | P15: =SUM(P7:P14) -> 0 | R15: Total | S15: =SUM(S7:S14) -> 0 | U15: Total | V15: =SUM(V7:V14) -> 0 | X15: Total | Y15: =SUM(Y7:Y14) -> 0 | AA15: Total | AB15: =SUM(AB7:AB14) -> 0 | AD15: Total | AE15: =SUM(AE7:AE14) -> 0 | AG15: Total | AH15: =SUM(AH7:AH14) -> 0 | AJ15: Total | AK15: =SUM(AK7:AK14) -> 0 | AM15: Total | AN15: =SUM(AN7:AN14) -> 0

Sheet Linha 5 Zn Alc. Semi Aut.
A2: Menu
A3: Zn/Alcalino Parado Semi Aut.
E5: 45292 | F5: 45292 | G5: 45292 | H5: 45323 | I5: 45323 | J5: 45323 | K5: 45352 | L5: 45352 | M5: 45352 | N5: 45383 | O5: 45383 | P5: 45383 | Q5: 45413 | R5: 45413 | S5: 45413 | T5: 45444 | U5: 45444 | V5: 45444 | W5: 45474 | X5: 45474 | Y5: 45474 | Z5: 45505 | AA5: 45505 | AB5: 45505 | AC5: 45536 | AD5: 45536 | AE5: 45536 | AF5: 45566 | AG5: 45566 | AH5: 45566 | AI5: 45597 | AJ5: 45597 | AK5: 45597 | AL5: 45627 | AM5: 45627 | AN5: 45627
A6: Produto | B6: ID | C6: Volume tanque / lts | D6: Concentração g/lt | E6: Consumo Kg/lt | F6: Custo/Kg | G6: Custo Total | H6: Consumo Kg/lt | I6: Custo/Kg | J6: Custo Total | K6: Consumo Kg/lt | L6: Custo Kg/lt | M6: Custo Total | N6: Consumo Kg/lt | O6: Custo/Kg | P6: Custo Total | Q6: Consumo Kg/lt | R6: Custo/Kg | S6: Custo Total | T6: Consumo Kg/lt | U6: Custo/Kg | V6: Custo Total | W6: Consumo Kg/lt | X6: Custo/Kg | Y6: Custo Total | Z6: Consumo Kg/lt | AA6: Custo/Kg | AB6: Custo Total | AC6: Consumo Kg/lt | AD6: Custo/Kg | AE6: Custo Total | AF6: Consumo Kg/lt | AG6: Custo/Kg | AH6: Custo Total | AI6: Consumo Kg/lt | AJ6: Custo/Kg | AK6: Custo Total | AL6: Consumo Kg/lt | AM6: Custo/Kg | AN6: Custo Total
A7: Composto C-40 | C7: 6000 | D7: 0 | E7: 0 | F7: 5 | G7: =F7*E7 -> 0 | H7: 0 | I7: 0 | J7: =I7*H7 -> 0 | K7: 0 | L7: 0 | M7: =L7*K7 -> 0 | N7: 0 | O7: 0 | P7: =O7*N7 -> 0 | Q7: 0 | R7: 0 | S7: =R7*Q7 -> 0 | T7: 0 | U7: 0 | V7: =U7*T7 -> 0 | W7: 0 | X7: 0 | Y7: =X7*W7 -> 0 | Z7: 0 | AA7: 0 | AB7: =AA7*Z7 -> 0 | AC7: 50 | AD7: 0 | AE7: =AD7*AC7 -> 0 | AF7: 0 | AG7: 0 | AH7: =AG7*AF7 -> 0 | AI7: 0 | AJ7: 0 | AK7: =AJ7*AI7 -> 0 | AL7: 0 | AM7: 15 | AN7: =AM7*AL7 -> 0
A8: Zincoat Plus Carrier | D8: 0 | E8: 0 | F8: 0 | G8: =F8*E8 -> 0 | H8: 0 | I8: 0 | J8: =I8*H8 -> 0 | K8: 0 | L8: 0 | M8: =L8*K8 -> 0 | N8: 0 | O8: 0 | P8: =O8*N8 -> 0 | Q8: 0 | R8: 0 | S8: =R8*Q8 -> 0 | T8: 0 | U8: 0 | V8: =U8*T8 -> 0 | W8: 0 | X8: 0 | Y8: =X8*W8 -> 0 | Z8: 0 | AA8: 0 | AB8: =AA8*Z8 -> 0 | AC8: 25 | AD8: 0 | AE8: =AD8*AC8 -> 0 | AF8: 0 | AG8: 0 | AH8: =AG8*AF8 -> 0 | AI8: 0 | AJ8: 0 | AK8: =AJ8*AI8 -> 0 | AL8: 0 | AM8: 0 | AN8: =AM8*AL8 -> 0
A9: Zicoat Plus Brightener | D9: 0 | E9: 0 | F9: 0 | G9: =F9*E9 -> 0 | H9: 0 | I9: 0 | J9: =I9*H9 -> 0 | K9: 0 | L9: 0 | M9: =L9*K9 -> 0 | N9: 0 | O9: 0 | P9: =O9*N9 -> 0 | Q9: 0 | R9: 0 | S9: =R9*Q9 -> 0 | T9: 0 | U9: 0 | V9: =U9*T9 -> 0 | W9: 0 | X9: 0 | Y9: =X9*W9 -> 0 | Z9: 0 | AA9: 0 | AB9: =AA9*Z9 -> 0 | AC9: 25 | AD9: 0 | AE9: =AD9*AC9 -> 0 | AF9: 0 | AG9: 0 | AH9: =AG9*AF9 -> 0 | AI9: 0 | AJ9: 0 | AK9: =AJ9*AI9 -> 0 | AL9: 0 | AM9: 0 | AN9: =AM9*AL9 -> 0
A10: Spectra Mate 255 | C10: 900 | D10: 0 | E10: 0 | F10: 0 | G10: =F10*E10 -> 0 | H10: 0 | I10: 0 | J10: =I10*H10 -> 0 | K10: 0 | L10: 0 | M10: =L10*K10 -> 0 | N10: 0 | O10: 0 | P10: =O10*N10 -> 0 | Q10: 0 | R10: 0 | S10: =R10*Q10 -> 0 | T10: 0 | U10: 0 | V10: =U10*T10 -> 0 | W10: 0 | X10: 0 | Y10: =X10*W10 -> 0 | Z10: 0 | AA10: 0 | AB10: =AA10*Z10 -> 0 | AC10: 25 | AD10: 0 | AE10: =AD10*AC10 -> 0 | AF10: 0 | AG10: 0 | AH10: =AG10*AF10 -> 0 | AI10: 0 | AJ10: 0 | AK10: =AJ10*AI10 -> 0 | AL10: 0 | AM10: 0 | AN10: =AM10*AL10 -> 0
A11: Ácido Nítrico Active MC-20 | C11: 900 | D11: 0 | E11: 0 | F11: 0 | G11: =F11*E11 -> 0 | H11: 0 | I11: 0 | J11: =I11*H11 -> 0 | K11: 0 | L11: 0 | M11: =L11*K11 -> 0 | N11: 0 | O11: 0 | P11: =O11*N11 -> 0 | Q11: 0 | R11: 0 | S11: =R11*Q11 -> 0 | T11: 0 | U11: 0 | V11: =U11*T11 -> 0 | W11: 0 | X11: 0 | Y11: =X11*W11 -> 0 | Z11: 0 | AA11: 0 | AB11: =AA11*Z11 -> 0 | AC11: 25 | AD11: 0 | AE11: =AD11*AC11 -> 0 | AF11: 0 | AG11: 0 | AH11: =AG11*AF11 -> 0 | AI11: 0 | AJ11: 0 | AK11: =AJ11*AI11 -> 0 | AL11: 0 | AM11: 0 | AN11: =AM11*AL11 -> 0
A12: Metal Clean FE LT | C12: 1500 | D12: 0 | E12: 0 | F12: 0 | G12: =F12*E12 -> 0 | H12: 0 | I12: 0 | J12: =I12*H12 -> 0 | K12: 0 | L12: 0 | M12: =L12*K12 -> 0 | N12: 0 | O12: 0 | P12: =O12*N12 -> 0 | Q12: 0 | R12: 0 | S12: =R12*Q12 -> 0 | T12: 0 | U12: 0 | V12: =U12*T12 -> 0 | W12: 0 | X12: 0 | Y12: =X12*W12 -> 0 | Z12: 0 | AA12: 0 | AB12: =AA12*Z12 -> 0 | AC12: 25 | AD12: 0 | AE12: =AD12*AC12 -> 0 | AF12: 0 | AG12: 0 | AH12: =AG12*AF12 -> 0 | AI12: 0 | AJ12: 0 | AK12: =AJ12*AI12 -> 0 | AL12: 0 | AM12: 0 | AN12: =AM12*AL12 -> 0
A13: Metal Clean FE 01 | C13: 750 | D13: 0 | E13: 0 | F13: 0 | G13: =F13*E13 -> 0 | H13: 0 | I13: 0 | J13: =I13*H13 -> 0 | K13: 0 | L13: 0 | M13: =L13*K13 -> 0 | N13: 0 | O13: 0 | P13: =O13*N13 -> 0 | Q13: 0 | R13: 0 | S13: =R13*Q13 -> 0 | T13: 0 | U13: 0 | V13: =U13*T13 -> 0 | W13: 0 | X13: 0 | Y13: =X13*W13 -> 0 | Z13: 0 | AA13: 0 | AB13: =AA13*Z13 -> 0 | AC13: 0 | AD13: 0 | AE13: =AD13*AC13 -> 0 | AF13: 0 | AG13: 0 | AH13: =AG13*AF13 -> 0 | AI13: 0 | AJ13: 0 | AK13: =AJ13*AI13 -> 0 | AL13: 0 | AM13: 0 | AN13: =AM13*AL13 -> 0
A14: Anodo | D14: 0 | E14: 0 | F14: 0 | G14: =F14*E14 -> 0 | H14: 0 | I14: 0 | J14: =I14*H14 -> 0 | K14: 0 | L14: 0 | M14: =L14*K14 -> 0 | N14: 0 | O14: 0 | P14: =O14*N14 -> 0 | Q14: 0 | R14: 0 | S14: =R14*Q14 -> 0 | T14: 0 | U14: 0 | V14: =U14*T14 -> 0 | W14: 0 | X14: 0 | Y14: =X14*W14 -> 0 | Z14: 0 | AA14: 0 | AB14: =AA14*Z14 -> 0 | AC14: 50 | AD14: 0 | AE14: =AD14*AC14 -> 0 | AF14: 0 | AG14: 0 | AH14: =AG14*AF14 -> 0 | AI14: 0 | AJ14: 0 | AK14: =AJ14*AI14 -> 0 | AL14: 0 | AM14: 0 | AN14: =AM14*AL14 -> 0
F15: Total | G15: =SUM(G7:G14) -> 0 | I15: Total | J15: =SUM(J7:J14) -> 0 | L15: Total | M15: =SUM(M7:M14) -> 0 | O15: Total | P15: =SUM(P7:P14) -> 0 | R15: Total | S15: =SUM(S7:S14) -> 0 | U15: Total | V15: =SUM(V7:V14) -> 0 | X15: Total | Y15: =SUM(Y7:Y14) -> 0 | AA15: Total | AB15: =SUM(AB7:AB14) -> 0 | AD15: Total | AE15: =SUM(AE7:AE14) -> 0 | AG15: Total | AH15: =SUM(AH7:AH14) -> 0 | AJ15: Total | AK15: =SUM(AK7:AK14) -> 0 | AM15: Total | AN15: =SUM(AN7:AN14) -> 0
O21: .

Sheet Linha 6 ZnNí Semi Aut.
A2: Menu
A3: Zn/Ní Parado Semi Aut.
E5: 45292 | F5: 45292 | G5: 45292 | H5: 45323 | I5: 45323 | J5: 45323 | K5: 45352 | L5: 45352 | M5: 45352 | N5: 45383 | O5: 45383 | P5: 45383 | Q5: 45413 | R5: 45413 | S5: 45413 | T5: 45444 | U5: 45444 | V5: 45444 | W5: 45474 | X5: 45474 | Y5: 45474 | Z5: 45505 | AA5: 45505 | AB5: 45505 | AC5: 45536 | AD5: 45536 | AE5: 45536 | AF5: 45566 | AG5: 45566 | AH5: 45566 | AI5: 45597 | AJ5: 45597 | AK5: 45597 | AL5: 45627 | AM5: 45627 | AN5: 45627
A6: Produto | B6: ID | C6: Volume tanque / lts | D6: Concentração g/lt | E6: Consumo Kg/lt | F6: Custo/Kg | G6: Custo Total | H6: Consumo Kg/lt | I6: Custo/Kg | J6: Custo Total | K6: Consumo Kg/lt | L6: Custo Kg/lt | M6: Custo Total | N6: Consumo Kg/lt | O6: Custo/Kg | P6: Custo Total | Q6: Consumo Kg/lt | R6: Custo/Kg | S6: Custo Total | T6: Consumo Kg/lt | U6: Custo/Kg | V6: Custo Total | W6: Consumo Kg/lt | X6: Custo/Kg | Y6: Custo Total | Z6: Consumo Kg/lt | AA6: Custo/Kg | AB6: Custo Total | AC6: Consumo Kg/lt | AD6: Custo/Kg | AE6: Custo Total | AF6: Consumo Kg/lt | AG6: Custo/Kg | AH6: Custo Total | AI6: Consumo Kg/lt | AJ6: Custo/Kg | AK6: Custo Total | AL6: Consumo Kg/lt | AM6: Custo/Kg | AN6: Custo Total
A7: Composto C-40 | C7: 8400 | D7: 0 | E7: 0 | F7: 0 | G7: =F7*E7 -> 0 | H7: 0 | I7: 0 | J7: =I7*H7 -> 0 | K7: 0 | L7: 0 | M7: =L7*K7 -> 0 | N7: 0 | O7: 0 | P7: =O7*N7 -> 0 | Q7: 0 | R7: 0 | S7: =R7*Q7 -> 0 | T7: 0 | U7: 0 | V7: =U7*T7 -> 0 | W7: 0 | X7: 0 | Y7: =X7*W7 -> 0 | Z7: 0 | AA7: 0 | AB7: =AA7*Z7 -> 0 | AC7: 200 | AD7: 200 | AE7: =AD7*AC7 -> 40000 | AF7: 0 | AG7: 0 | AH7: =AG7*AF7 -> 0 | AI7: 0 | AJ7: 0 | AK7: =AJ7*AI7 -> 0 | AL7: 0 | AM7: 0 | AN7: =AM7*AL7 -> 0
A8: Zincoat Premium Make Up | D8: 0 | E8: 0 | F8: 0 | G8: =F8*E8 -> 0 | H8: 0 | I8: 0 | J8: =I8*H8 -> 0 | K8: 0 | L8: 0 | M8: =L8*K8 -> 0 | N8: 0 | O8: 0 | P8: =O8*N8 -> 0 | Q8: 0 | R8: 0 | S8: =R8*Q8 -> 0 | T8: 0 | U8: 0 | V8: =U8*T8 -> 0 | W8: 0 | X8: 0 | Y8: =X8*W8 -> 0 | Z8: 0 | AA8: 0 | AB8: =AA8*Z8 -> 0 | AC8: 150 | AD8: 0 | AE8: =AD8*AC8 -> 0 | AF8: 0 | AG8: 0 | AH8: =AG8*AF8 -> 0 | AI8: 0 | AJ8: 0 | AK8: =AJ8*AI8 -> 0 | AL8: 0 | AM8: 0 | AN8: =AM8*AL8 -> 0
A9: Zncoat Premium Replenisher | D9: 0 | E9: 0 | F9: 0 | G9: =F9*E9 -> 0 | H9: 0 | I9: 0 | J9: =I9*H9 -> 0 | K9: 0 | L9: 0 | M9: =L9*K9 -> 0 | N9: 0 | O9: 0 | P9: =O9*N9 -> 0 | Q9: 0 | R9: 0 | S9: =R9*Q9 -> 0 | T9: 0 | U9: 0 | V9: =U9*T9 -> 0 | W9: 0 | X9: 0 | Y9: =X9*W9 -> 0 | Z9: 0 | AA9: 0 | AB9: =AA9*Z9 -> 0 | AC9: 150 | AD9: 0 | AE9: =AD9*AC9 -> 0 | AF9: 0 | AG9: 0 | AH9: =AG9*AF9 -> 0 | AI9: 0 | AJ9: 0 | AK9: =AJ9*AI9 -> 0 | AL9: 0 | AM9: 0 | AN9: =AM9*AL9 -> 0
A10: Spectra Seal 050 | C10: 850 | D10: 0 | E10: 0 | F10: 0 | G10: =F10*E10 -> 0 | H10: 0 | I10: 0 | J10: =I10*H10 -> 0 | K10: 0 | L10: 0 | M10: =L10*K10 -> 0 | N10: 0 | O10: 0 | P10: =O10*N10 -> 0 | Q10: 0 | R10: 0 | S10: =R10*Q10 -> 0 | T10: 0 | U10: 0 | V10: =U10*T10 -> 0 | W10: 0 | X10: 0 | Y10: =X10*W10 -> 0 | Z10: 0 | AA10: 0 | AB10: =AA10*Z10 -> 0 | AC10: 0 | AD10: 0 | AE10: =AD10*AC10 -> 0 | AF10: 0 | AG10: 0 | AH10: =AG10*AF10 -> 0 | AI10: 0 | AJ10: 0 | AK10: =AJ10*AI10 -> 0 | AL10: 0 | AM10: 0 | AN10: =AM10*AL10 -> 0
A11: Spectra Silver ZNI | C11: 850 | D11: 0 | E11: 0 | F11: 0 | G11: =F11*E11 -> 0 | H11: 0 | I11: 0 | J11: =I11*H11 -> 0 | K11: 0 | L11: 0 | M11: =L11*K11 -> 0 | N11: 0 | O11: 0 | P11: 0 | Q11: 0 | R11: 0 | S11: =R11*Q11 -> 0 | T11: 0 | U11: 0 | V11: =U11*T11 -> 0 | W11: 0 | X11: 0 | Y11: =X11*W11 -> 0 | Z11: 0 | AA11: 0 | AB11: =AA11*Z11 -> 0 | AC11: 0 | AD11: 0 | AE11: =AD11*AC11 -> 0 | AF11: 0 | AG11: 0 | AH11: =AG11*AF11 -> 0 | AI11: 0 | AJ11: 0 | AK11: =AJ11*AI11 -> 0 | AL11: 0 | AM11: 0 | AN11: =AM11*AL11 -> 0
A12: Metal Clean FE LT | C12: 2040 | D12: 0 | E12: 0 | F12: 0 | G12: =F12*E12 -> 0 | H12: 0 | I12: 0 | J12: =I12*H12 -> 0 | K12: 0 | L12: 0 | M12: =L12*K12 -> 0 | N12: 0 | O12: 0 | P12: =O12*N12 -> 0 | Q12: 0 | R12: 0 | S12: =R12*Q12 -> 0 | T12: 0 | U12: 0 | V12: =U12*T12 -> 0 | W12: 0 | X12: 0 | Y12: =X12*W12 -> 0 | Z12: 0 | AA12: 0 | AB12: =AA12*Z12 -> 0 | AC12: 0 | AD12: 0 | AE12: =AD12*AC12 -> 0 | AF12: 0 | AG12: 0 | AH12: =AG12*AF12 -> 0 | AI12: 0 | AJ12: 0 | AK12: =AJ12*AI12 -> 0 | AL12: 0 | AM12: 0 | AN12: =AM12*AL12 -> 0
A13: Ácido Cloridrico | C13: 850 | D13: 0 | E13: 0 | F13: 0 | G13: =F13*E13 -> 0 | H13: 0 | I13: 0 | J13: =I13*H13 -> 0 | K13: 0 | L13: 0 | M13: =L13*K13 -> 0 | N13: 0 | O13: 0 | P13: =O13*N13 -> 0 | Q13: 0 | R13: 0 | S13: =R13*Q13 -> 0 | T13: 0 | U13: 0 | V13: =U13*T13 -> 0 | W13: 0 | X13: 0 | Y13: =X13*W13 -> 0 | Z13: 0 | AA13: 0 | AB13: =AA13*Z13 -> 0 | AC13: 0 | AD13: 0 | AE13: =AD13*AC13 -> 0 | AF13: 0 | AG13: 0 | AH13: =AG13*AF13 -> 0 | AI13: 0 | AJ13: 0 | AK13: =AJ13*AI13 -> 0 | AL13: 0 | AM13: 0 | AN13: =AM13*AL13 -> 0
A14: Metal Clean FT 13 A | C14: 850 | D14: 0 | E14: 0 | F14: 0 | G14: =F14*E14 -> 0 | H14: 0 | I14: 0 | J14: =I14*H14 -> 0 | K14: 0 | L14: 0 | M14: =L14*K14 -> 0 | N14: 0 | O14: 0 | P14: =O14*N14 -> 0 | Q14: 0 | R14: 0 | S14: =R14*Q14 -> 0 | T14: 0 | U14: 0 | V14: =U14*T14 -> 0 | W14: 0 | X14: 0 | Y14: =X14*W14 -> 0 | Z14: 0 | AA14: 0 | AB14: =AA14*Z14 -> 0 | AC14: 0 | AD14: 0 | AE14: =AD14*AC14 -> 0 | AF14: 0 | AG14: 0 | AH14: =AG14*AF14 -> 0 | AI14: 0 | AJ14: 0 | AK14: =AJ14*AI14 -> 0 | AL14: 0 | AM14: 0 | AN14: =AM14*AL14 -> 0
A15: Anodo | D15: 0 | E15: 0 | F15: 0 | G15: =F15*E15 -> 0 | H15: 0 | I15: 0 | J15: =I15*H15 -> 0 | K15: 0 | L15: 0 | M15: =L15*K15 -> 0 | N15: 0 | O15: 0 | P15: =O15*N15 -> 0 | Q15: 0 | R15: 0 | S15: =R15*Q15 -> 0 | T15: 0 | U15: 0 | V15: =U15*T15 -> 0 | W15: 0 | X15: 0 | Y15: =X15*W15 -> 0 | Z15: 0 | AA15: 0 | AB15: =AA15*Z15 -> 0 | AC15: 50 | AD15: 0 | AE15: =AD15*AC15 -> 0 | AF15: 0 | AG15: 0 | AH15: =AG15*AF15 -> 0 | AI15: 0 | AJ15: 0 | AK15: =AJ15*AI15 -> 0 | AL15: 0 | AM15: 0 | AN15: =AM15*AL15 -> 0
F16: Total | G16: =SUM(G7:G14) -> 0 | I16: Total | J16: =SUM(J7:J14) -> 0 | L16: Total | M16: =SUM(M7:M14) -> 0 | O16: Total | P16: =SUM(P7:P14) -> 0 | R16: Total | S16: =SUM(S7:S14) -> 0 | U16: Total | V16: =SUM(V7:V14) -> 0 | X16: Total | Y16: =SUM(Y7:Y14) -> 0 | AA16: Total | AB16: =SUM(AB7:AB14) -> 0 | AD16: Total | AE16: =SUM(AE7:AE14) -> 40000 | AG16: Total | AH16: =SUM(AH7:AH14) -> 0 | AJ16: Total | AK16: =SUM(AK7:AK14) -> 0 | AM16: Total | AN16: =SUM(AN7:AN14) -> 0

Sheet Linha 9 Pré Trat. Fosfato Aut.
A2: Menu
A3: Pré-Trtamento/Fosfato Aut.
E4: 45292 | F4: 45292 | G4: 45292 | H4: 45323 | I4: 45323 | J4: 45323 | K4: 45352 | L4: 45352 | M4: 45352 | N4: 45383 | O4: 45383 | P4: 45383 | Q4: 45413 | R4: 45413 | S4: 45413 | T4: 45444 | U4: 45444 | V4: 45444 | W4: 45474 | X4: 45474 | Y4: 45474 | Z4: 45505 | AA4: 45505 | AB4: 45505 | AC4: 45536 | AD4: 45536 | AE4: 45536 | AF4: 45566 | AG4: 45566 | AH4: 45566 | AI4: 45597 | AJ4: 45597 | AK4: 45597 | AL4: 45627 | AM4: 45627 | AN4: 45627
A5: Produto | B5: ID | C5: Volume tanque / lts | D5: Concentração g/lt | E5: Consumo Kg/lt | F5: Custo/Kg | G5: Custo Total | H5: Consumo Kg/lt | I5: Custo/Kg | J5: Custo Total | K5: Consumo Kg/lt | L5: CustoKg/lt | M5: Custo Total | N5: Consumo Kg/lt | O5: Custo/Kg | P5: Custo Total | Q5: Consumo Kg/lt | R5: Custo/Kg | S5: Custo Total | T5: Consumo Kg/lt | U5: Custo/Kg | V5: Custo Total | W5: Consumo Kg/lt | X5: Custo/Kg | Y5: Custo Total | Z5: Consumo Kg/lt | AA5: Custo/Kg | AB5: Custo Total | AC5: Consumo Kg/lt | AD5: Custo/Kg | AE5: Custo Total | AF5: Consumo Kg/lt | AG5: Custo/Kg | AH5: Custo Total | AI5: Consumo Kg/lt | AJ5: Custo/Kg | AK5: Custo Total | AL5: Consumo Kg/lt | AM5: Custo/Kg | AN5: Custo Total
A6: Metal Clean FE LT | C6: 2300 | D6: 0 | E6: 0 | F6: 0 | G6: =F6*E6 -> 0 | H6: 0 | I6: 0 | J6: =I6*H6 -> 0 | K6: 0 | L6: 0 | M6: =L6*K6 -> 0 | N6: 0 | O6: 0 | P6: =O6*N6 -> 0 | Q6: 0 | R6: 0 | S6: =R6*Q6 -> 0 | T6: 0 | U6: 0 | V6: =U6*T6 -> 0 | W6: 0 | X6: 0 | Y6: =X6*W6 -> 0 | Z6: 0 | AA6: 0 | AB6: =AA6*Z6 -> 0 | AC6: 0 | AD6: 0 | AE6: =AD6*AC6 -> 0 | AF6: 0 | AG6: 0 | AH6: =AG6*AF6 -> 0 | AI6: 0 | AJ6: 0 | AK6: =AJ6*AI6 -> 0 | AL6: 0 | AM6: 0 | AN6: =AM6*AL6 -> 0
A7: Ácido Decapante 1 | C7: 1000 | D7: 0 | E7: 0 | F7: 0 | G7: =F7*E7 -> 0 | H7: 0 | I7: 0 | J7: =I7*H7 -> 0 | K7: 0 | L7: 0 | M7: =L7*K7 -> 0 | N7: 0 | O7: 0 | P7: =O7*N7 -> 0 | Q7: 0 | R7: 0 | S7: =R7*Q7 -> 0 | T7: 0 | U7: 0 | V7: =U7*T7 -> 0 | W7: 0 | X7: 0 | Y7: =X7*W7 -> 0 | Z7: 0 | AA7: 0 | AB7: =AA7*Z7 -> 0 | AC7: 0 | AD7: 0 | AE7: =AD7*AC7 -> 0 | AF7: 0 | AG7: 0 | AH7: =AG7*AF7 -> 0 | AI7: 0 | AJ7: 0 | AK7: =AJ7*AI7 -> 0 | AL7: 0 | AM7: 0 | AN7: =AM7*AL7 -> 0
A8: Ácido Decapante 2 | C8: 1000 | D8: 0 | E8: 0 | F8: 0 | G8: =F8*E8 -> 0 | H8: 0 | I8: 0 | J8: =I8*H8 -> 0 | K8: 0 | L8: 0 | M8: =L8*K8 -> 0 | N8: 0 | O8: 0 | P8: =O8*N8 -> 0 | Q8: 0 | R8: 0 | S8: =R8*Q8 -> 0 | T8: 0 | U8: 0 | V8: =U8*T8 -> 0 | W8: 0 | X8: 0 | Y8: =X8*W8 -> 0 | Z8: 0 | AA8: 0 | AB8: =AA8*Z8 -> 0 | AC8: 0 | AD8: 0 | AE8: =AD8*AC8 -> 0 | AF8: 0 | AG8: 0 | AH8: =AG8*AF8 -> 0 | AI8: 0 | AJ8: 0 | AK8: =AJ8*AI8 -> 0 | AL8: 0 | AM8: 0 | AN8: =AM8*AL8 -> 0
A9: Refimador 1 | C9: 1000 | D9: 0 | E9: 0 | F9: 0 | G9: =F9*E9 -> 0 | H9: 0 | I9: 0 | J9: =I9*H9 -> 0 | K9: 0 | L9: 0 | M9: =L9*K9 -> 0 | N9: 0 | O9: 0 | P9: =O9*N9 -> 0 | Q9: 0 | R9: 0 | S9: =R9*Q9 -> 0 | T9: 0 | U9: 0 | V9: =U9*T9 -> 0 | W9: 0 | X9: 0 | Y9: =X9*W9 -> 0 | Z9: 0 | AA9: 0 | AB9: =AA9*Z9 -> 0 | AC9: 0 | AD9: 0 | AE9: =AD9*AC9 -> 0 | AF9: 0 | AG9: 0 | AH9: =AG9*AF9 -> 0 | AI9: 0 | AJ9: 0 | AK9: =AJ9*AI9 -> 0 | AL9: 0 | AM9: 0 | AN9: =AM9*AL9 -> 0
A10: Fosfato 1 | C10: 1000 | D10: 0 | E10: 0 | F10: 0 | G10: =F10*E10 -> 0 | H10: 0 | I10: 0 | J10: =I10*H10 -> 0 | K10: 0 | L10: 0 | M10: =L10*K10 -> 0 | N10: 0 | O10: 0 | P10: =O10*N10 -> 0 | Q10: 0 | R10: 0 | S10: =R10*Q10 -> 0 | T10: 0 | U10: 0 | V10: =U10*T10 -> 0 | W10: 0 | X10: 0 | Y10: =X10*W10 -> 0 | Z10: 0 | AA10: 0 | AB10: =AA10*Z10 -> 0 | AC10: 0 | AD10: 0 | AE10: =AD10*AC10 -> 0 | AF10: 0 | AG10: 0 | AH10: =AG10*AF10 -> 0 | AI10: 0 | AJ10: 0 | AK10: =AJ10*AI10 -> 0 | AL10: 0 | AM10: 0 | AN10: =AM10*AL10 -> 0
A11: Refimador 2 | C11: 1000 | D11: 0 | E11: 0 | F11: 0 | G11: =F11*E11 -> 0 | H11: 0 | I11: 0 | J11: =I11*H11 -> 0 | K11: 0 | L11: 0 | M11: =L11*K11 -> 0 | N11: 0 | O11: 0 | P11: =O11*N11 -> 0 | Q11: 0 | R11: 0 | S11: =R11*Q11 -> 0 | T11: 0 | U11: 0 | V11: =U11*T11 -> 0 | W11: 0 | X11: 0 | Y11: =X11*W11 -> 0 | Z11: 0 | AA11: 0 | AB11: =AA11*Z11 -> 0 | AC11: 0 | AD11: 0 | AE11: =AD11*AC11 -> 0 | AF11: 0 | AG11: 0 | AH11: =AG11*AF11 -> 0 | AI11: 0 | AJ11: 0 | AK11: =AJ11*AI11 -> 0 | AL11: 0 | AM11: 0 | AN11: =AM11*AL11 -> 0
A12: Fosfato 2 | C12: 1000 | D12: 0 | E12: 0 | F12: 0 | G12: =F12*E12 -> 0 | H12: 0 | I12: 0 | J12: =I12*H12 -> 0 | K12: 0 | L12: 0 | M12: =L12*K12 -> 0 | N12: 0 | O12: 0 | P12: =O12*N12 -> 0 | Q12: 0 | R12: 0 | S12: =R12*Q12 -> 0 | T12: 0 | U12: 0 | V12: =U12*T12 -> 0 | W12: 0 | X12: 0 | Y12: =X12*W12 -> 0 | Z12: 0 | AA12: 0 | AB12: =AA12*Z12 -> 0 | AC12: 0 | AD12: 0 | AE12: =AD12*AC12 -> 0 | AF12: 0 | AG12: 0 | AH12: =AG12*AF12 -> 0 | AI12: 0 | AJ12: 0 | AK12: =AJ12*AI12 -> 0 | AL12: 0 | AM12: 0 | AN12: =AM12*AL12 -> 0
A13: Neutralizador | C13: 1000 | D13: 0 | E13: 0 | F13: 0 | G13: =F13*E13 -> 0 | H13: 0 | I13: 0 | J13: =I13*H13 -> 0 | K13: 0 | L13: 0 | M13: =L13*K13 -> 0 | N13: 0 | O13: 0 | P13: =O13*N13 -> 0 | Q13: 0 | R13: 0 | S13: =R13*Q13 -> 0 | T13: 0 | U13: 0 | V13: =U13*T13 -> 0 | W13: 0 | X13: 0 | Y13: =X13*W13 -> 0 | Z13: 0 | AA13: 0 | AB13: =AA13*Z13 -> 0 | AC13: 0 | AD13: 0 | AE13: =AD13*AC13 -> 0 | AF13: 0 | AG13: 0 | AH13: =AG13*AF13 -> 0 | AI13: 0 | AJ13: 0 | AK13: =AJ13*AI13 -> 0 | AL13: 0 | AM13: 0 | AN13: =AM13*AL13 -> 0
F14: Total | G14: =+SUM(G6:G13) -> 0 | I14: Total | J14: =SUM(J6:J13) -> 0 | L14: Total | M14: =SUM(M6:M13) -> 0 | O14: Total | P14: =SUM(P6:P13) -> 0 | R14: Total | S14: =SUM(S6:S13) -> 0 | U14: Total | V14: =SUM(V6:V13) -> 0 | X14: Total | Y14: =SUM(Y6:Y13) -> 0 | AA14: Total | AB14: =SUM(AB6:AB13) -> 0 | AD14: Total | AE14: =SUM(AE6:AE13) -> 0 | AG14: Total | AH14: =SUM(AH6:AH13) -> 0 | AJ14: Total | AK14: =SUM(AK6:AK13) -> 0 | AM14: Total | AN14: =SUM(AN6:AN13) -> 0

Sheet E.T.E
A2: Menu
A3: E.T.E
E4: 44562 | F4: 44562 | G4: 44562 | H4: 45323 | I4: 45323 | J4: 45323 | K4: 45352 | L4: 45352 | M4: 45352 | N4: 45383 | O4: 45383 | P4: 45383 | Q4: 45413 | R4: 45413 | S4: 45413 | T4: 45444 | U4: 45444 | V4: 45444 | W4: 45474 | X4: 45474 | Y4: 45474 | Z4: 45505 | AA4: 45505 | AB4: 45505 | AC4: 45536 | AD4: 45536 | AE4: 45536 | AF4: 45566 | AG4: 45566 | AH4: 45566 | AI4: 45597 | AJ4: 45597 | AK4: 45597 | AL4: 45627 | AM4: 45627 | AN4: 45627
A5: Produto | B5: ID | C5: Volume tanque / lts | D5: Concentração g/lt | E5: Consumo Kg/lt | F5: Custo/Kg | G5: Custo Total | H5: Consumo Kg/lt | I5: Custo/Kg | J5: Custo Total | K5: Consumo Kg/lt | L5: Custo Kg/lt | M5: Custo Total | N5: Consumo Kg/lt | O5: Custo/Kg | P5: Custo Total | Q5: Consumo Kg/lt | R5: Custo/Kg | S5: Custo Total | T5: Consumo Kg/lt | U5: Custo/Kg | V5: Custo Total | W5: Consumo Kg/lt | X5: Custo/Kg | Y5: Custo Total | Z5: Consumo Kg/lt | AA5: Custo/Kg | AB5: Custo Total | AC5: Consumo Kg/lt | AD5: Custo/Kg | AE5: Custo Total | AF5: Consumo Kg/lt | AG5: Custo/Kg | AH5: Custo Total | AI5: Consumo Kg/lt | AJ5: Custo/Kg | AK5: Custo Total | AL5: Consumo Kg/lt | AM5: Custo/Kg | AN5: Custo Total
A6: Soda 50% | B6: 0 | C6: 0 | D6: 0 | E6: 0 | F6: 0 | G6: =E6*F6 -> 0 | H6: 0 | I6: 0 | J6: =I6*H6 -> 0 | K6: 0 | L6: 0 | M6: =L6*K6 -> 0 | N6: 0 | O6: 0 | P6: =O6*N6 -> 0 | Q6: 0 | R6: 0 | S6: =R6*Q6 -> 0 | T6: 0 | U6: 0 | V6: =U6*T6 -> 0 | W6: 0 | X6: 0 | Y6: =X6*W6 -> 0 | Z6: 0 | AA6: 0 | AB6: =AA6*Z6 -> 0 | AC6: 0 | AD6: 0 | AE6: =AD6*AC6 -> 0 | AF6: 0 | AG6: 0 | AH6: =AG6*AF6 -> 0 | AI6: 0 | AJ6: 0 | AK6: =AJ6*AI6 -> 0 | AL6: 0 | AM6: 0 | AN6: =AM6*AL6 -> 0
A7: Ácido Cloridrico | B7: 0 | C7: 0 | D7: 0 | E7: 0 | F7: 0 | G7: =E7*F7 -> 0 | H7: 0 | I7: 0 | J7: =I7*H7 -> 0 | K7: 0 | L7: 0 | M7: =L7*K7 -> 0 | N7: 0 | O7: 0 | P7: =O7*N7 -> 0 | Q7: 0 | R7: 0 | S7: =R7*Q7 -> 0 | T7: 0 | U7: 0 | V7: =U7*T7 -> 0 | W7: 0 | X7: 0 | Y7: =X7*W7 -> 0 | Z7: 0 | AA7: 0 | AB7: =AA7*Z7 -> 0 | AC7: 0 | AD7: 0 | AE7: =AD7*AC7 -> 0 | AF7: 0 | AG7: 0 | AH7: =AG7*AF7 -> 0 | AI7: 0 | AJ7: 0 | AK7: =AJ7*AI7 -> 0 | AL7: 0 | AM7: 0 | AN7: =AM7*AL7 -> 0
A8: Metabissulfito de Sódio | B8: 0 | C8: 0 | D8: 0 | E8: 0 | F8: 0 | G8: =E8*F8 -> 0 | H8: 0 | I8: 0 | J8: =I8*H8 -> 0 | K8: 0 | L8: 0 | M8: =L8*K8 -> 0 | N8: 0 | O8: 0 | P8: =O8*N8 -> 0 | Q8: 0 | R8: 0 | S8: =R8*Q8 -> 0 | T8: 0 | U8: 0 | V8: =U8*T8 -> 0 | W8: 0 | X8: 0 | Y8: =X8*W8 -> 0 | Z8: 0 | AA8: 0 | AB8: =AA8*Z8 -> 0 | AC8: 0 | AD8: 0 | AE8: =AD8*AC8 -> 0 | AF8: 0 | AG8: 0 | AH8: =AG8*AF8 -> 0 | AI8: 0 | AJ8: 0 | AK8: =AJ8*AI8 -> 0 | AL8: 0 | AM8: 0 | AN8: =AM8*AL8 -> 0
A9: Carbonato de Calcio | B9: 0 | C9: 0 | D9: 0 | E9: 0 | F9: 0 | G9: =E9*F9 -> 0 | H9: 0 | I9: 0 | J9: =I9*H9 -> 0 | K9: 0 | L9: 0 | M9: =L9*K9 -> 0 | N9: 0 | O9: 0 | P9: =O9*N9 -> 0 | Q9: 0 | R9: 0 | S9: =R9*Q9 -> 0 | T9: 0 | U9: 0 | V9: =U9*T9 -> 0 | W9: 0 | X9: 0 | Y9: =X9*W9 -> 0 | Z9: 0 | AA9: 0 | AB9: =AA9*Z9 -> 0 | AC9: 0 | AD9: 0 | AE9: =AD9*AC9 -> 0 | AF9: 0 | AG9: 0 | AH9: =AG9*AF9 -> 0 | AI9: 0 | AJ9: 0 | AK9: =AJ9*AI9 -> 0 | AL9: 0 | AM9: 0 | AN9: =AM9*AL9 -> 0
A10: Anti espumante | B10: 0 | C10: 0 | D10: 0 | E10: 0 | F10: 0 | G10: =E10*F10 -> 0 | H10: 0 | I10: 0 | J10: =I10*H10 -> 0 | K10: 0 | L10: 0 | M10: =L10*K10 -> 0 | N10: 0 | O10: 0 | P10: =O10*N10 -> 0 | Q10: 0 | R10: 0 | S10: =R10*Q10 -> 0 | T10: 0 | U10: 0 | V10: =U10*T10 -> 0 | W10: 0 | X10: 0 | Y10: =X10*W10 -> 0 | Z10: 0 | AA10: 0 | AB10: =AA10*Z10 -> 0 | AC10: 0 | AD10: 0 | AE10: =AD10*AC10 -> 0 | AF10: 0 | AG10: 0 | AH10: =AG10*AF10 -> 0 | AI10: 0 | AJ10: 0 | AK10: =AJ10*AI10 -> 0 | AL10: 0 | AM10: 0 | AN10: =AM10*AL10 -> 0
A11: Polieletrólito | B11: 0 | C11: 0 | D11: 0 | E11: 0 | F11: 0 | G11: =E11*F11 -> 0 | H11: 0 | I11: 0 | J11: =I11*H11 -> 0 | K11: 0 | L11: 0 | M11: =L11*K11 -> 0 | N11: 0 | O11: 0 | P11: =O11*N11 -> 0 | Q11: 0 | R11: 0 | S11: =R11*Q11 -> 0 | T11: 0 | U11: 0 | V11: =U11*T11 -> 0 | W11: 0 | X11: 0 | Y11: =X11*W11 -> 0 | Z11: 0 | AA11: 0 | AB11: =AA11*Z11 -> 0 | AC11: 0 | AD11: 0 | AE11: =AD11*AC11 -> 0 | AF11: 0 | AG11: 0 | AH11: =AG11*AF11 -> 0 | AI11: 0 | AJ11: 0 | AK11: =AJ11*AI11 -> 0 | AL11: 0 | AM11: 0 | AN11: =AM11*AL11 -> 0
B12: 0 | C12: 0 | D12: 0 | E12: 0 | F12: 0 | G12: =E12*F12 -> 0 | H12: 0 | I12: 0 | J12: =I12*H12 -> 0 | K12: 0 | L12: 0 | M12: =L12*K12 -> 0 | N12: 0 | O12: 0 | P12: =O12*N12 -> 0 | Q12: 0 | R12: 0 | S12: =R12*Q12 -> 0 | T12: 0 | U12: 0 | V12: =U12*T12 -> 0 | W12: 0 | X12: 0 | Y12: =X12*W12 -> 0 | Z12: 0 | AA12: 0 | AB12: =AA12*Z12 -> 0 | AC12: 0 | AD12: 0 | AE12: =AD12*AC12 -> 0 | AF12: 0 | AG12: 0 | AH12: =AG12*AF12 -> 0 | AI12: 0 | AJ12: 0 | AK12: =AJ12*AI12 -> 0 | AL12: 0 | AM12: 0 | AN12: =AM12*AL12 -> 0
B13: 0 | C13: 0 | D13: 0 | E13: 0 | F13: 0 | G13: =E13*F13 -> 0 | H13: 0 | I13: 0 | J13: =I13*H13 -> 0 | K13: 0 | L13: 0 | M13: =L13*K13 -> 0 | N13: 0 | O13: 0 | P13: =O13*N13 -> 0 | Q13: 0 | R13: 0 | S13: =R13*Q13 -> 0 | T13: 0 | U13: 0 | V13: =U13*T13 -> 0 | W13: 0 | X13: 0 | Y13: =X13*W13 -> 0 | Z13: 0 | AA13: 0 | AB13: =AA13*Z13 -> 0 | AC13: 0 | AD13: 0 | AE13: =AD13*AC13 -> 0 | AF13: 0 | AG13: 0 | AH13: =AG13*AF13 -> 0 | AI13: 0 | AJ13: 0 | AK13: =AJ13*AI13 -> 0 | AL13: 0 | AM13: 0 | AN13: =AM13*AL13 -> 0
F14: Total | G14: =SUM(G6:G13) -> 0 | I14: Total | J14: =SUM(J6:J13) -> 0 | L14: Total | M14: =SUM(M6:M13) -> 0 | O14: Total | P14: =SUM(P6:P13) -> 0 | R14: Total | S14: =SUM(S6:S13) -> 0 | U14: Total | V14: =SUM(V6:V13) -> 0 | X14: Total | Y14: =SUM(Y6:Y13) -> 0 | AA14: Total | AB14: =SUM(AB6:AB13) -> 0 | AD14: Total | AE14: =SUM(AE6:AE13) -> 0 | AG14: Total | AH14: =SUM(AH6:AH13) -> 0 | AJ14: Total | AK14: =SUM(AK6:AK13) -> 0 | AM14: Total | AN14: =SUM(AN6:AN13) -> 0

Sheet Transporte
A2: Menu
A3: Transporte
C4: Jan Custo Total | D4: Fev Custo Total | E4: Mar Custo Total | F4: Abr Custo Total | G4: Mai Custo Total | H4: Jun Custo Total | I4: Jul Custo Total | J4: Ago Custo Total | K4: Set Custo Total | L4: Out Custo Total | M4: Nov Custo Total | N4: Dez Custo Total
A5: Produto | B5: Mês
C6: 0 | D6: 0 | E6: 0 | F6: 0 | G6: 0 | H6: 0 | I6: 0 | J6: 0 | K6: 0 | L6: 0 | M6: 0 | N6: 0
C7: 0 | D7: 0 | E7: 0 | F7: 0 | G7: 0 | H7: 0 | I7: 0 | J7: 0 | K7: 0 | L7: 0 | M7: 0 | N7: 0
C8: 0 | D8: 0 | E8: 0 | F8: 0 | G8: 0 | H8: 0 | I8: 0 | J8: 0 | K8: 0 | L8: 0 | M8: 0 | N8: 0
C9: 0 | D9: 0 | E9: 0 | F9: 0 | G9: 0 | H9: 0 | I9: 0 | J9: 0 | K9: 0 | L9: 0 | M9: 0 | N9: 0
C10: 0 | D10: 0 | E10: 0 | F10: 0 | G10: 0 | H10: 0 | I10: 0 | J10: 0 | K10: 0 | L10: 0 | M10: 0 | N10: 0
C11: 0 | D11: 0 | E11: 0 | F11: 0 | G11: 0 | H11: 0 | I11: 0 | J11: 0 | K11: 0 | L11: 0 | M11: 0 | N11: 0
C12: 0 | D12: 0 | E12: 0 | F12: 0 | G12: 0 | H12: 0 | I12: 0 | J12: 0 | K12: 0 | L12: 0 | M12: 0 | N12: 0
C13: 0 | D13: 0 | E13: 0 | F13: 0 | G13: 0 | H13: 0 | I13: 0 | J13: 0 | K13: 0 | L13: 0 | M13: 0 | N13: 0
C14: 0 | D14: 0 | E14: 0 | F14: 0 | G14: 0 | H14: 0 | I14: 0 | J14: 0 | K14: 0 | L14: 0 | M14: 0 | N14: 0
C15: 0 | D15: 0 | E15: 0 | F15: 0 | G15: 0 | H15: 0 | I15: 0 | J15: 0 | K15: 0 | L15: 0 | M15: 0 | N15: 0
C16: 0 | D16: 0 | E16: 0 | F16: 0 | G16: 0 | H16: 0 | I16: 0 | J16: 0 | K16: 0 | L16: 0 | M16: 0 | N16: 0
C17: 0 | D17: 0 | E17: 0 | F17: 0 | G17: 0 | H17: 0 | I17: 0 | J17: 0 | K17: 0 | L17: 0 | M17: 0 | N17: 0
C18: 0 | D18: 0 | E18: 0 | F18: 0 | G18: 0 | H18: 0 | I18: 0 | J18: 0 | K18: 0 | L18: 0 | M18: 0 | N18: 0
C19: 0 | D19: =SUM(D6:D18) -> 0 | E19: 0 | F19: 0 | G19: 0 | H19: 0 | I19: 0 | J19: 0 | K19: 0 | L19: 0 | M19: 0 | N19: 0
A20: Total | C20: =SUM(C6:C19) -> 0 | D20: =SUM(D19) -> 0 | E20: =SUM(E6:E19) -> 0 | F20: =SUM(F6:F19) -> 0 | G20: =SUM(G6:G19) -> 0 | H20: =SUM(H6:H19) -> 0 | I20: =SUM(I6:I19) -> 0 | J20: =SUM(J6:J19) -> 0 | K20: =SUM(K6:K19) -> 0 | L20: =SUM(L6:L19) -> 0 | ... N20: =SUM(N6:N19) -> 0

Sheet Manutenção
A2: Menu | C2: 7
A3: Manutenção
A5: Produto | B5: Mês | C5: Jan Custo Total | D5: Fev Custo Total | E5: Mar Custo Total | F5: Abr Custo Total | G5: Mai Custo Total | H5: Jun Custo Total | I5: Jul Custo Total | J5: Ago Custo Total | K5: Set Custo Total | L5: Out Custo Total | M5: Nov Custo Total | N5: Dez Custo Total
A7: Invest. Gerais | C7: 0 | D7: 0 | E7: 0 | F7: 0 | G7: 0 | H7: 0 | I7: 0 | J7: 0 | K7: 70000 | L7: 70000 | M7: 70000 | N7: 70000
C8: 0 | D8: 0 | E8: 0 | F8: 0 | G8: 0 | H8: 0 | I8: 0 | J8: 0 | K8: 0 | L8: 0 | M8: 0 | N8: 0
C9: 0 | D9: 0 | E9: 0 | F9: 0 | G9: 0 | H9: 0 | I9: 0 | J9: 0 | K9: 0 | L9: 0 | M9: 0 | N9: 0
C10: 0 | D10: 0 | E10: 0 | F10: 0 | G10: 0 | H10: 0 | I10: 0 | J10: 0 | K10: 0 | L10: 0 | M10: 0 | N10: 0
C11: 0 | D11: 0 | E11: 0 | F11: 0 | G11: 0 | H11: 0 | I11: 0 | J11: 0 | K11: 0 | L11: 0 | M11: 0 | N11: 0
C12: 0 | D12: 0 | E12: 0 | F12: 0 | G12: 0 | H12: 0 | I12: 0 | J12: 0 | K12: 0 | L12: 0 | M12: 0 | N12: 0
C13: 0 | D13: 0 | E13: 0 | F13: 0 | G13: 0 | H13: 0 | I13: 0 | J13: 0 | K13: 0 | L13: 0 | M13: 0 | N13: 0
C14: 0 | D14: 0 | E14: 0 | F14: 0 | G14: 0 | H14: 0 | I14: 0 | J14: 0 | K14: 0 | L14: 0 | M14: 0 | N14: 0
C15: 0 | D15: 0 | E15: 0 | F15: 0 | G15: 0 | H15: 0 | I15: 0 | J15: 0 | K15: 0 | L15: 0 | M15: 0 | N15: 0
C16: 0 | D16: 0 | E16: 0 | F16: 0 | G16: 0 | H16: 0 | I16: 0 | J16: 0 | K16: 0 | L16: 0 | M16: 0 | N16: 0
C17: 0 | D17: 0 | E17: 0 | F17: 0 | G17: 0 | H17: 0 | I17: 0 | J17: 0 | K17: 0 | L17: 0 | M17: 0 | N17: 0
C18: 0 | D18: 0 | E18: 0 | F18: 0 | G18: 0 | H18: 0 | I18: 0 | J18: 0 | K18: 0 | L18: 0 | M18: 0 | N18: 0
C19: 0 | D19: 0 | E19: 0 | F19: 0 | G19: 0 | H19: 0 | I19: 0 | J19: 0 | K19: 0 | L19: 0 | M19: 0 | N19: 0
C20: 0 | D20: 0 | E20: 0 | F20: 0 | G20: 0 | H20: 0 | I20: 0 | J20: 0 | K20: 0 | L20: 0 | M20: 0 | N20: 0
C21: =SUM(C6:C20)/C2 -> 0 | D21: =SUM(D6:D20)/C2 -> 0 | E21: =SUM(E6:E20)/C2 -> 0 | F21: =SUM(F6:F20)/C2 -> 0 | G21: =SUM(G6:G20)/C2 -> 0 | H21: =SUM(H6:H20)/C2 -> 0 | I21: =SUM(I6:I20)/C2 -> 0 | J21: =SUM(J6:J20)/C2 -> 0 | K21: =SUM(K6:K20)/C2 -> 10000 | L21: =SUM(L6:L20)/C2 -> 10000 | M21: =SUM(M6:M20)/C2 -> 10000 | N21: =SUM(N6:N20)/C2 -> 10000

Sheet Outros Custos
A2: Menu | B2: 7
A3: Outros Custos
A5: Produto | B5: Data | C5: Janeiro | D5: Fevereiro | E5: Março | F5: Abril | G5: Maio | H5: Junho | I5: Julho | J5: Agosto | K5: Setembro | L5: Outubro | M5: Novembro | N5: Dezembro
A6: EPI | C6: 0 | D6: 0 | E6: 0 | F6: 0 | G6: 0 | H6: 0 | I6: 0 | J6: 0 | K6: 2500 | L6: 0 | M6: 0 | N6: 0
A7: Prod.Manut.Corretiva | C7: 0 | D7: 0 | E7: 0 | F7: 0 | G7: 0 | H7: 0 | I7: 0 | J7: 0 | K7: 5000 | L7: 0 | M7: 0 | N7: 0
A8: Vale Refeição | C8: 0 | D8: 0 | E8: 0 | F8: 0 | G8: 0 | H8: 0 | I8: 0 | J8: 0 | K8: 5280 | L8: 0 | M8: 0 | N8: 0
A9: Material de Escritório | C9: 0 | D9: 0 | E9: 0 | F9: 0 | G9: 0 | H9: 0 | I9: 0 | J9: 0 | K9: 1000 | L9: 0 | M9: 0 | N9: 0
A10: Equip. para Lab. (Reagentes,Vidrarias,Calibração) | C10: 0 | D10: 0 | E10: 0 | F10: 0 | G10: 0 | H10: 0 | I10: 0 | J10: 0 | K10: 200 | L10: 0 | M10: 0 | N10: 0
A11: Custo ADM | C11: 0 | D11: 0 | E11: 0 | F11: 0 | G11: 0 | H11: 0 | I11: 0 | J11: 0 | K11: 0 | L11: 0 | M11: 0 | N11: 0
A12: Alimentação | C12: 0 | D12: 0 | E12: 0 | F12: 0 | G12: 0 | H12: 0 | I12: 0 | J12: 0 | K12: 1000 | L12: 0 | M12: 0 | N12: 0
C13: 0 | D13: 0 | E13: 0 | F13: 0 | G13: 0 | H13: 0 | I13: 0 | J13: 0 | K13: 0 | L13: 0 | M13: 0 | N13: 0
C14: 0 | D14: 0 | E14: 0 | F14: 0 | G14: 0 | H14: 0 | I14: 0 | J14: 0 | K14: 0 | L14: 0 | M14: 0 | N14: 0
C15: 0 | D15: 0 | E15: 0 | F15: 0 | G15: 0 | H15: 0 | I15: 0 | J15: 0 | K15: 0 | L15: 0 | M15: 0 | N15: 0
C16: 0 | D16: 0 | E16: 0 | F16: 0 | G16: 0 | H16: 0 | I16: 0 | J16: 0 | K16: 0 | L16: 0 | M16: 0 | N16: 0
C17: 0 | D17: 0 | E17: 0 | F17: 0 | G17: 0 | H17: 0 | I17: 0 | J17: 0 | K17: 0 | L17: 0 | M17: 0 | N17: 0
C18: 0 | D18: 0 | E18: 0 | F18: 0 | G18: 0 | H18: 0 | I18: 0 | J18: 0 | K18: 0 | L18: 0 | M18: 0 | N18: 0
C19: 0 | D19: 0 | E19: 0 | F19: 0 | G19: 0 | H19: 0 | I19: 0 | J19: 0 | K19: 0 | L19: 0 | M19: 0 | N19: 0
C20: 0 | D20: 0 | E20: 0 | F20: 0 | G20: 0 | H20: 0 | I20: 0 | J20: 0 | K20: 0 | L20: 0 | M20: 0 | N20: 0
C21: 0 | D21: 0 | E21: 0 | F21: 0 | G21: 0 | H21: 0 | I21: 0 | J21: 0 | K21: 0 | L21: 0 | M21: 0 | N21: 0
C22: 0 | D22: 0 | E22: 0 | F22: 0 | G22: 0 | H22: 0 | I22: 0 | J22: 0 | K22: 0 | L22: 0 | M22: 0 | N22: 0
C23: 0 | D23: 0 | E23: 0 | F23: 0 | G23: 0 | H23: 0 | I23: 0 | J23: 0 | K23: 0 | L23: 0 | M23: 0 | N23: 0
C24: 0 | D24: 0 | E24: 0 | F24: 0 | G24: 0 | H24: 0 | I24: 0 | J24: 0 | K24: 0 | L24: 0 | M24: 0 | N24: 0
... C30: 0 | D30: 0 | E30: 0 | F30: 0 | G30: 0 | H30: 0 | I30: 0 | J30: 0 | K30: 0 | L30: 0 | M30: 0 | N30: 0
A31: Soma | C31: =SUM(C6:C30)/B2 -> 0 | D31: =SUM(D6:D30)/B2 -> 0 | E31: =SUM(E6:E30)/B2 -> 0 | F31: =SUM(F6:F30)/B2 -> 0 | G31: =SUM(G6:G30)/B2 -> 0 | H31: =SUM(H6:H30)/B2 -> 0 | I31: =SUM(I6:I30)/B2 -> 0 | J31: =SUM(J6:J30)/B2 -> 0 | K31: =SUM(K6:K30)/B2 -> 2140 | L31: =SUM(L6:L30)/B2 -> 0 | M31: =SUM(M6:M30)/B2 -> 0 | N31: =SUM(N6:N30)/B2 -> 0

Sheet M.O
B1: Salario Minimo | C1: 1412 | D1: 2160
A2: Menu | E2: Mão de Obra
A4: 220 | B4: Hrs Trab | AA4: 220 | AB4: Hrs Trab | AY4: 220 | AZ4: Hrs Trab | BV4: 220 | BW4: Hrs Trab | CN4: 220 | CO4: Hrs Trab | DF4: 220 | DG4: Hrs Trab | DX4: 220 | DY4: Hrs Trab | EP4: 220 | EQ4: Hrs Trab | FH4: 220 | FI4: Hrs Trab | FZ4: 220 | GA4: Hrs Trab | GR4: 220 | GS4: Hrs Trab | HJ4: 220 | HK4: Hrs Trab
B5: Mês | D5: Janeiro | E5: INSS | F5: FGTS | G5: Férias | H5: 1/3 Férias | I5: 13° | J5: Total | K5: Hrs Extra | L5: Hrs Extra | M5: Hrs Extra | N5: Hrs Extra | O5: Hrs Extra | P5: Total Extra | Q5: Total Extra | R5: Total Extra | S5: Total Extra | T5: Total Extra | U5: Hrs Extra Mês | V5: Por fora | W5: Insalubridade | X5: Total Geral | Z5: Mês | AB5: Fevereiro | AC5: INSS | AD5: FGTS | AE5: Férias | AF5: 1/3 Férias | AG5: 13° | AH5: Total | AI5: Hrs Extra | AJ5: Hrs Extra | AK5: Hrs Extra | AL5: Hrs Extra | AM5: Hrs Extra | AN5: Total Extra | AO5: Total Extra | AP5: Total Extra | AQ5: Total Extra | AR5: Total Extra | AS5: Hrs Extra Mês | AT5: Por fora | AU5: Insalubridade | AV5: Total Geral | AX5: Mês | AZ5: Março | BA5: INSS | BB5: FGTS | BC5: Férias | BD5: 1/3 Férias | BE5: 13° | BF5: Total | BG5: Hrs Extra | BH5: Hrs Extra | BI5: Hrs Extra | BJ5: Hrs Extra | BK5: Hrs Extra | BL5: Total Extra | BM5: Total Extra | BN5: Total Extra | BO5: Total Extra | BP5: Total Extra | BQ5: Hrs Extra Mês | BR5: Por fora | BS5: Insalubridade | BT5: Total Geral | BV5: Mês | BX5: Abril | BY5: INSS | BZ5: FGTS | CA5: Férias | CB5: 1/3 Férias | CC5: 13° | CD5: Total | CE5: Hrs Extra | CF5: Hrs Extra | CG5: Hrs Extra | CH5: Hrs Extra | CI5: Hrs Extra | CJ5: Total Extra | CK5: Total Extra | CL5: Total Extra | CM5: Total Extra | CN5: Total Extra | CO5: Hrs Extra Mês | CP5: Por fora | CQ5: Insalubridade | CR5: Total Geral | CT5: Mês | CV5: Maio | CW5: INSS | CX5: FGTS | CY5: Férias | CZ5: 1/3 Férias | DA5: 13° | DB5: Total | DC5: Hrs Extra | DD5: Hrs Extra | DE5: Hrs Extra | DF5: Hrs Extra | DG5: Hrs Extra | DH5: Total Extra | DI5: Total Extra | DJ5: Total Extra | DK5: Total Extra | DL5: Total Extra | DM5: Hrs Extra Mês | DN5: Por fora | DO5: Insalubridade | DP5: Total Geral | DR5: Mês | DT5: Junhp | DU5: INSS | DV5: FGTS | DW5: Férias | DX5: 1/3 Férias | DY5: 13° | DZ5: Total | EA5: Hrs Extra | EB5: Hrs Extra | EC5: Hrs Extra | ED5: Hrs Extra | EE5: Hrs Extra | EF5: Total Extra | EG5: Total Extra | EH5: Total Extra | EI5: Total Extra | EJ5: Total Extra | EK5: Hrs Extra Mês | EL5: Por fora | EM5: Insalubridade | EN5: Total Geral | EP5: Mês | ER5: Julho | ES5: INSS | ET5: FGTS | EU5: Férias | EV5: 1/3 Férias | EW5: 13° | EX5: Total | EY5: Hrs Extra | EZ5: Hrs Extra | FA5: Hrs Extra | FB5: Hrs Extra | FC5: Hrs Extra | FD5: Total Extra | FE5: Total Extra | FF5: Total Extra | FG5: Total Extra | FH5: Total Extra | FI5: Hrs Extra Mês | FJ5: Por fora | FK5: Insalubridade | FL5: Total Geral | FN5: Mês | FP5: Agosto | FQ5: INSS | FR5: FGTS | FS5: Férias | FT5: 1/3 Férias | FU5: 13° | FV5: Total | FW5: Hrs Extra | FX5: Hrs Extra | FY5: Hrs Extra | FZ5: Hrs Extra | GA5: Hrs Extra | GB5: Total Extra | GC5: Total Extra | GD5: Total Extra | GE5: Total Extra | GF5: Total Extra | GG5: Hrs Extra Mês | GH5: Por fora | GI5: Insalubridade | GJ5: Total Geral | GL5: Mês | GN5: Setembro | GO5: INSS | GP5: FGTS | GQ5: Férias | GR5: 1/3 Férias | GS5: 13° | GT5: Total | GU5: Hrs Extra | GV5: Hrs Extra | GW5: Hrs Extra | GX5: Hrs Extra | GY5: Hrs Extra | GZ5: Total Extra | HA5: Total Extra | HB5: Total Extra | HC5: Total Extra | HD5: Total Extra | HE5: Hrs Extra Mês | HF5: Por fora | HG5: Insalubridade | HH5: Total Geral | HJ5: Mês | HL5: Outubro | HM5: INSS | HN5: FGTS | HO5: Férias | HP5: 1/3 Férias | HQ5: 13° | HR5: Total | HS5: Hrs Extra | HT5: Hrs Extra | HU5: Hrs Extra | HV5: Hrs Extra | HW5: Hrs Extra | HX5: Total Extra | HY5: Total Extra | HZ5: Total Extra | IA5: Total Extra | IB5: Total Extra | IC5: Hrs Extra Mês | ID5: Por fora | IE5: Insalubridade | IF5: Total Geral | IH5: Mês | IJ5: Novembro | IK5: INSS | IL5: FGTS | IM5: Férias | IN5: 1/3 Férias | IO5: 13° | IP5: Total | IQ5: Hrs Extra | IR5: Hrs Extra | IS5: Hrs Extra | IT5: Hrs Extra | IU5: Hrs Extra | IV5: Total Extra | IW5: Total Extra | IX5: Total Extra | IY5: Total Extra | IZ5: Total Extra | JA5: Hrs Extra Mês | JB5: Por fora | JC5: Insalubridade | JD5: Total Geral | JF5: Mês | JH5: Dezembro | JI5: INSS | JJ5: FGTS | JK5: Férias | JL5: 1/3 Férias | JM5: 13° | JN5: Total | JO5: Hrs Extra | JP5: Hrs Extra | JQ5: Hrs Extra | JR5: Hrs Extra | JS5: Hrs Extra | JT5: Total Extra | JU5: Total Extra | JV5: Total Extra | JW5: Total Extra | JX5: Total Extra | JY5: Hrs Extra Mês | JZ5: Por fora | KA5: Insalubridade | KB5: Total Geral
B6: Funcionário | C6: Sal/Hora | D6: Salario Mensal | E6: 0.1 | F6: 0.08 | G6: 12 | H6: 3 | I6: 12 | J6: - | K6: 0.5 | L6: 0.6 | M6: 0.8 | N6: 1 | O6: 1.5 | P6: 1.5 | Q6: 1.6 | R6: 1.8 | S6: 2 | T6: 2.5 | U6: - | V6: - | W6: 0.2 | X6: - | Z6: Funcionário | AA6: Sal/Hora | AB6: Salario Mensal | AC6: 0.1 | AD6: 0.08 | AE6: 12 | AF6: 3 | AG6: 12 | AH6: - | AI6: 0.5 | AJ6: 0.6 | AK6: 0.8 | AL6: 1 | AM6: 1.5 | AN6: 1.5 | AO6: 1.6 | AP6: 1.8 | AQ6: 2 | AR6: 2.5 | AS6: - | AT6: - | AU6: 0.2 | AV6: - | AX6: Funcionário | AY6: Sal/Hora | AZ6: Salario Mensal | BA6: 0.1 | BB6: 0.08 | BC6: 12 | BD6: 3 | BE6: 12 | BF6: - | BG6: 0.5 | BH6: 0.6 | BI6: 0.8 | BJ6: 1 | BK6: 1.5 | BL6: 1.5 | BM6: 1.6 | BN6: 1.8 | BO6: 2 | BP6: 2.5 | BQ6: - | BR6: - | BS6: 0.2 | BT6: - | BV6: Funcionário | BW6: Sal/Hora | BX6: Salario Mensal | BY6: 0.1 | BZ6: 0.08 | CA6: 12 | CB6: 3 | CC6: 12 | CD6: - | CE6: 0.5 | CF6: 0.6 | CG6: 0.8 | CH6: 1 | CI6: 1.5 | CJ6: 1.5 | CK6: 1.6 | CL6: 1.8 | CM6: 2 | CN6: 2.5 | CO6: - | CP6: - | CQ6: 0.2 | CR6: - | CT6: Funcionário | CU6: Sal/Hora | CV6: Salario Mensal | CW6: 0.1 | CX6: 0.08 | CY6: 12 | CZ6: 3 | DA6: 12 | DB6: - | DC6: 0.5 | DD6: 0.6 | DE6: 0.8 | DF6: 1 | DG6: 1.5 | DH6: 1.5 | DI6: 1.6 | DJ6: 1.8 | DK6: 2 | DL6: 2.5 | DM6: - | DN6: - | DO6: 0.2 | DP6: - | DR6: Funcionário | DS6: Sal/Hora | DT6: Salario Mensal | DU6: 0.1 | DV6: 0.08 | DW6: 12 | DX6: 3 | DY6: 12 | DZ6: - | EA6: 0.5 | EB6: 0.6 | EC6: 0.8 | ED6: 1 | EE6: 1.5 | EF6: 1.5 | EG6: 1.6 | EH6: 1.8 | EI6: 2 | EJ6: 2.5 | EK6: - | EL6: - | EM6: 0.2 | EN6: - | EP6: Funcionário | EQ6: Sal/Hora | ER6: Salario Mensal | ES6: 0.1 | ET6: 0.08 | EU6: 12 | EV6: 3 | EW6: 12 | EX6: - | EY6: 0.5 | EZ6: 0.6 | FA6: 0.8 | FB6: 1 | FC6: 1.5 | FD6: 1.5 | FE6: 1.6 | FF6: 1.8 | FG6: 2 | FH6: 2.5 | FI6: - | FJ6: - | FK6: 0.2 | FL6: - | FN6: Funcionário | FO6: Sal/Hora | FP6: Salario Mensal | FQ6: 0.1 | FR6: 0.08 | FS6: 12 | FT6: 3 | FU6: 12 | FV6: - | FW6: 0.5 | FX6: 0.6 | FY6: 0.8 | FZ6: 1 | GA6: 1.5 | GB6: 1.5 | GC6: 1.6 | GD6: 1.8 | GE6: 2 | GF6: 2.5 | GG6: - | GH6: - | GI6: 0.2 | GJ6: - | GL6: Funcionário | GM6: Sal/Hora | GN6: Salario Mensal | GO6: 0.1 | GP6: 0.08 | GQ6: 12 | GR6: 3 | GS6: 12 | GT6: - | GU6: 0.5 | GV6: 0.6 | GW6: 0.8 | GX6: 1 | GY6: 1.5 | GZ6: 1.5 | HA6: 1.6 | HB6: 1.8 | HC6: 2 | HD6: 2.5 | HE6: - | HF6: - | HG6: 0.2 | HH6: - | HJ6: Funcionário | HK6: Sal/Hora | HL6: Salario Mensal | HM6: 0.1 | HN6: 0.08 | HO6: 12 | HP6: 3 | HQ6: 12 | HR6: - | HS6: 0.5 | HT6: 0.6 | HU6: 0.8 | HV6: 1 | HW6: 1.5 | HX6: 1.5 | HY6: 1.6 | HZ6: 1.8 | IA6: 2 | IB6: 2.5 | IC6: - | ID6: - | IE6: 0.2 | IF6: - | IH6: Funcionário | II6: Sal/Hora | IJ6: Salario Mensal | IK6: 0.1 | IL6: 0.08 | IM6: 12 | IN6: 3 | IO6: 12 | IP6: - | IQ6: 0.5 | IR6: 0.6 | IS6: 0.8 | IT6: 1 | IU6: 1.5 | IV6: 1.5 | IW6: 1.6 | IX6: 1.8 | IY6: 2 | IZ6: 2.5 | JA6: - | JB6: - | JC6: 0.2 | JD6: - | JF6: Funcionário | JG6: Sal/Hora | JH6: Salario Mensal | JI6: 0.1 | JJ6: 0.08 | JK6: 12 | JL6: 3 | JM6: 12 | JN6: - | JO6: 0.5 | JP6: 0.6 | JQ6: 0.8 | JR6: 1 | JS6: 1.5 | JT6: 1.5 | JU6: 1.6 | JV6: 1.8 | JW6: 2 | JX6: 2.5 | JY6: - | JZ6: - | KA6: 0.2 | KB6: -
E7: Linha 1 Zn Alc.Aut | AC7: Linha 1 Zn Alc.Aut | BA7: Linha 1 Zn Alc.Aut | BY7: Linha 1 Zn Alc.Aut | CW7: Linha 1 Zn Alc.Aut | DU7: Linha 1 Zn Alc.Aut | ES7: Linha 1 Zn Alc.Aut | FQ7: Linha 1 Zn Alc.Aut | GO7: Linha 1 Zn Alc.Aut | HM7: Linha 1 Zn Alc.Aut | IK7: Linha 1 Zn Alc.Aut | JI7: Linha 1 Zn Alc.Aut
A8: 0 | B8: Josiel Op. B | C8: =D8/$AY$4 -> 11.928591 | D8: 2624.29 | E8: =D8*E$6 -> 262.429 | F8: =D8*F$6 -> 209.9432 | G8: =D8/G$6 -> 218.69083 | H8: =G8/H$6 -> 72.896944 | I8: =D8/I$6 -> 218.69083 | J8: =SUM(D8:I8) -> 3606.9408 | P8: =((C8*P$6)+(C8*E$6)+(C8*F$6))*K8 -> 0 | Q8: =((C8*Q6)+(C8*E6)+(C8*F6))*L8 -> 0 | R8: =((C8*R$6)+(C8*E$6)+(C8*F$6))*M8 -> 0 | S8: =((C8*S$6)+(C8*E$6)+(C8*F$6))*N8 -> 0 | T8: =((C8*T$6)+(C8*E$6)+(C8*F$6))*O8 -> 0 | U8: =SUM(P8:T8) -> 0 | V8: 0 | W8: =IF(A8=1,($C$1*$W$6),0) -> 0 | X8: =J8+U8+V8+W8 -> 3606.9408 | Y8: 0 | Z8: Josiel Op. B | AA8: =AB8/$AY$4 -> 11.928591 | AB8: 2624.29 | AC8: =AB8*AC$6 -> 262.429 | AD8: =AB8*AD$6 -> 209.9432 | AE8: =AB8/AE$6 -> 218.69083 | AF8: =AE8/AF$6 -> 72.896944 | AG8: =AB8/AG$6 -> 218.69083 | AH8: =SUM(AB8:AG8) -> 3606.9408 | AN8: =((AA8*AN$6)+(AA8*AC$6)+(AA8*AD$6))*AI8 -> 0 | AO8: =((AA8*AO6)+(AA8*AC6)+(AA8*AD6))*AJ8 -> 0 | AP8: =((AA8*AP$6)+(AA8*AC$6)+(AA8*AD$6))*AK8 -> 0 | AQ8: =((AA8*AQ$6)+(AA8*AC$6)+(AA8*AD$6))*AL8 -> 0 | AR8: =((AA8*AR$6)+(AA8*AC$6)+(AA8*AD$6))*AM8 -> 0 | AS8: =SUM(AN8:AR8) -> 0 | AT8: 0 | AU8: =IF(Y8=1,($C$1*$W$6),0) -> 0 | AV8: =AH8+AS8+AT8+AU8 -> 3606.9408 | AW8: 0 | AX8: Josiel Op. B | AY8: =AZ8/$AY$4 -> 11.928591 | AZ8: 2624.29 | BA8: =AZ8*BA$6 -> 262.429 | BB8: =AZ8*BB$6 -> 209.9432 | BC8: =AZ8/BC$6 -> 218.69083 | BD8: =BC8/BD$6 -> 72.896944 | BE8: =AZ8/BE$6 -> 218.69083 | BF8: =SUM(AZ8:BE8) -> 3606.9408 | BL8: =((AY8*BL$6)+(AY8*BA$6)+(AY8*BB$6))*BG8 -> 0 | BM8: =((AY8*BM6)+(AY8*BA6)+(AY8*BB6))*BH8 -> 0 | BN8: =((AY8*BN$6)+(AY8*BA$6)+(AY8*BB$6))*BI8 -> 0 | BO8: =((AY8*BO$6)+(AY8*BA$6)+(AY8*BB$6))*BJ8 -> 0 | BP8: =((AY8*BP$6)+(AY8*BA$6)+(AY8*BB$6))*BK8 -> 0 | BQ8: =SUM(BL8:BP8) -> 0 | BR8: 0 | BS8: =IF(AW8=1,($C$1*$W$6),0) -> 0 | BT8: =BF8+BQ8+BR8+BS8 -> 3606.9408 | BU8: 0 | BV8: Josiel Op. B | BW8: =BX8/$AY$4 -> 11.928591 | BX8: 2624.29 | BY8: =BX8*BY$6 -> 262.429 | BZ8: =BX8*BZ$6 -> 209.9432 | CA8: =BX8/CA$6 -> 218.69083 | CB8: =CA8/CB$6 -> 72.896944 | CC8: =BX8/CC$6 -> 218.69083 | CD8: =SUM(BX8:CC8) -> 3606.9408 | CJ8: =((BW8*CJ$6)+(BW8*BY$6)+(BW8*BZ$6))*CE8 -> 0 | CK8: =((BW8*CK6)+(BW8*BY6)+(BW8*BZ6))*CF8 -> 0 | CL8: =((BW8*CL$6)+(BW8*BY$6)+(BW8*BZ$6))*CG8 -> 0 | CM8: =((BW8*CM$6)+(BW8*BY$6)+(BW8*BZ$6))*CH8 -> 0 | CN8: =((BW8*CN$6)+(BW8*BY$6)+(BW8*BZ$6))*CI8 -> 0 | CO8: =SUM(CJ8:CN8) -> 0 | CP8: 0 | CQ8: =IF(BU8=1,($C$1*$W$6),0) -> 0 | CR8: =CD8+CO8+CP8+CQ8 -> 3606.9408 | CS8: 0 | CT8: Josiel Op. B | CU8: =CV8/$AY$4 -> 11.928591 | CV8: 2624.29 | CW8: =CV8*CW$6 -> 262.429 | CX8: =CV8*CX$6 -> 209.9432 | CY8: =CV8/CY$6 -> 218.69083 | CZ8: =CY8/CZ$6 -> 72.896944 | DA8: =CV8/DA$6 -> 218.69083 | DB8: =SUM(CV8:DA8) -> 3606.9408 | DH8: =((CU8*DH$6)+(CU8*CW$6)+(CU8*CX$6))*DC8 -> 0 | DI8: =((CU8*DI6)+(CU8*CW6)+(CU8*CX6))*DD8 -> 0 | DJ8: =((CU8*DJ$6)+(CU8*CW$6)+(CU8*CX$6))*DE8 -> 0 | DK8: =((CU8*DK$6)+(CU8*CW$6)+(CU8*CX$6))*DF8 -> 0 | DL8: =((CU8*DL$6)+(CU8*CW$6)+(CU8*CX$6))*DG8 -> 0 | DM8: =SUM(DH8:DL8) -> 0 | DN8: 0 | DO8: =IF(CS8=1,($C$1*$W$6),0) -> 0 | DP8: =DB8+DM8+DN8+DO8 -> 3606.9408 | DQ8: 0 | DR8: Josiel Op. B | DS8: =DT8/$AY$4 -> 11.928591 | DT8: 2624.29 | DU8: =DT8*DU$6 -> 262.429 | DV8: =DT8*DV$6 -> 209.9432 | DW8: =DT8/DW$6 -> 218.69083 | DX8: =DW8/DX$6 -> 72.896944 | DY8: =DT8/DY$6 -> 218.69083 | DZ8: =SUM(DT8:DY8) -> 3606.9408 | EF8: =((DS8*EF$6)+(DS8*DU$6)+(DS8*DV$6))*EA8 -> 0 | EG8: =((DS8*EG6)+(DS8*DU6)+(DS8*DV6))*EB8 -> 0 | EH8: =((DS8*EH$6)+(DS8*DU$6)+(DS8*DV$6))*EC8 -> 0 | EI8: =((DS8*EI$6)+(DS8*DU$6)+(DS8*DV$6))*ED8 -> 0 | EJ8: =((DS8*EJ$6)+(DS8*DU$6)+(DS8*DV$6))*EE8 -> 0 | EK8: =SUM(EF8:EJ8) -> 0 | EL8: 0 | EM8: =IF(DQ8=1,($C$1*$W$6),0) -> 0 | EN8: =DZ8+EK8+EL8+EM8 -> 3606.9408 | EO8: 0 | EP8: Josiel Op. B | EQ8: =ER8/$AY$4 -> 11.928591 | ER8: 2624.29 | ES8: =ER8*ES$6 -> 262.429 | ET8: =ER8*ET$6 -> 209.9432 | EU8: =ER8/EU$6 -> 218.69083 | EV8: =EU8/EV$6 -> 72.896944 | EW8: =ER8/EW$6 -> 218.69083 | EX8: =SUM(ER8:EW8) -> 3606.9408 | FD8: =((EQ8*FD$6)+(EQ8*ES$6)+(EQ8*ET$6))*EY8 -> 0 | FE8: =((EQ8*FE6)+(EQ8*ES6)+(EQ8*ET6))*EZ8 -> 0 | FF8: =((EQ8*FF$6)+(EQ8*ES$6)+(EQ8*ET$6))*FA8 -> 0 | FG8: =((EQ8*FG$6)+(EQ8*ES$6)+(EQ8*ET$6))*FB8 -> 0 | FH8: =((EQ8*FH$6)+(EQ8*ES$6)+(EQ8*ET$6))*FC8 -> 0 | FI8: =SUM(FD8:FH8) -> 0 | FJ8: 0 | FK8: =IF(EO8=1,($C$1*$W$6),0) -> 0 | FL8: =EX8+FI8+FJ8+FK8 -> 3606.9408 | FM8: 0 | FN8: Josiel Op. B | FO8: =FP8/$AY$4 -> 11.928591 | FP8: 2624.29 | FQ8: =FP8*FQ$6 -> 262.429 | FR8: =FP8*FR$6 -> 209.9432 | FS8: =FP8/FS$6 -> 218.69083 | FT8: =FS8/FT$6 -> 72.896944 | FU8: =FP8/FU$6 -> 218.69083 | FV8: =SUM(FP8:FU8) -> 3606.9408 | GB8: =((FO8*GB$6)+(FO8*FQ$6)+(FO8*FR$6))*FW8 -> 0 | GC8: =((FO8*GC6)+(FO8*FQ6)+(FO8*FR6))*FX8 -> 0 | GD8: =((FO8*GD$6)+(FO8*FQ$6)+(FO8*FR$6))*FY8 -> 0 | GE8: =((FO8*GE$6)+(FO8*FQ$6)+(FO8*FR$6))*FZ8 -> 0 | GF8: =((FO8*GF$6)+(FO8*FQ$6)+(FO8*FR$6))*GA8 -> 0 | GG8: =SUM(GB8:GF8) -> 0 | GH8: 0 | GI8: =IF(FM8=1,($C$1*$W$6),0) -> 0 | GJ8: =FV8+GG8+GH8+GI8 -> 3606.9408 | GK8: 0 | GL8: Josiel Op. B | GM8: =GN8/$AY$4 -> 11.928591 | GN8: 2624.29 | GO8: =GN8*GO$6 -> 262.429 | GP8: =GN8*GP$6 -> 209.9432 | GQ8: =GN8/GQ$6 -> 218.69083 | GR8: =GQ8/GR$6 -> 72.896944 | GS8: =GN8/GS$6 -> 218.69083 | GT8: =SUM(GN8:GS8) -> 3606.9408 | GZ8: =((GM8*GZ$6)+(GM8*GO$6)+(GM8*GP$6))*GU8 -> 0 | HA8: =((GM8*HA6)+(GM8*GO6)+(GM8*GP6))*GV8 -> 0 | HB8: =((GM8*HB$6)+(GM8*GO$6)+(GM8*GP$6))*GW8 -> 0 | HC8: =((GM8*HC$6)+(GM8*GO$6)+(GM8*GP$6))*GX8 -> 0 | HD8: =((GM8*HD$6)+(GM8*GO$6)+(GM8*GP$6))*GY8 -> 0 | HE8: =SUM(GZ8:HD8) -> 0 | HF8: 0 | HG8: =IF(GK8=1,($C$1*$W$6),0) -> 0 | HH8: =GT8+HE8+HF8+HG8 -> 3606.9408 | HI8: 0 | HJ8: Josiel Op. B | HK8: =HL8/$AY$4 -> 11.928591 | HL8: 2624.29 | HM8: =HL8*HM$6 -> 262.429 | HN8: =HL8*HN$6 -> 209.9432 | HO8: =HL8/HO$6 -> 218.69083 | HP8: =HO8/HP$6 -> 72.896944 | HQ8: =HL8/HQ$6 -> 218.69083 | HR8: =SUM(HL8:HQ8) -> 3606.9408 | HX8: =((HK8*HX$6)+(HK8*HM$6)+(HK8*HN$6))*HS8 -> 0 | HY8: =((HK8*HY6)+(HK8*HM6)+(HK8*HN6))*HT8 -> 0 | HZ8: =((HK8*HZ$6)+(HK8*HM$6)+(HK8*HN$6))*HU8 -> 0 | IA8: =((HK8*IA$6)+(HK8*HM$6)+(HK8*HN$6))*HV8 -> 0 | IB8: =((HK8*IB$6)+(HK8*HM$6)+(HK8*HN$6))*HW8 -> 0 | IC8: =SUM(HX8:IB8) -> 0 | ID8: 0 | IE8: =IF(HI8=1,($C$1*$W$6),0) -> 0 | IF8: =HR8+IC8+ID8+IE8 -> 3606.9408 | IG8: 0 | IH8: Josiel Op. B | II8: =IJ8/$AY$4 -> 11.928591 | IJ8: 2624.29 | IK8: =IJ8*IK$6 -> 262.429 | IL8: =IJ8*IL$6 -> 209.9432 | IM8: =IJ8/IM$6 -> 218.69083 | IN8: =IM8/IN$6 -> 72.896944 | IO8: =IJ8/IO$6 -> 218.69083 | IP8: =SUM(IJ8:IO8) -> 3606.9408 | IV8: =((II8*IV$6)+(II8*IK$6)+(II8*IL$6))*IQ8 -> 0 | IW8: =((II8*IW6)+(II8*IK6)+(II8*IL6))*IR8 -> 0 | IX8: =((II8*IX$6)+(II8*IK$6)+(II8*IL$6))*IS8 -> 0 | IY8: =((II8*IY$6)+(II8*IK$6)+(II8*IL$6))*IT8 -> 0 | IZ8: =((II8*IZ$6)+(II8*IK$6)+(II8*IL$6))*IU8 -> 0 | JA8: =SUM(IV8:IZ8) -> 0 | JB8: 0 | JC8: =IF(IG8=1,($C$1*$W$6),0) -> 0 | JD8: =IP8+JA8+JB8+JC8 -> 3606.9408 | JE8: 0 | JF8: Josiel Op. B | JG8: =JH8/$AY$4 -> 11.928591 | JH8: 2624.29 | JI8: =JH8*JI$6 -> 262.429 | JJ8: =JH8*JJ$6 -> 209.9432 | JK8: =JH8/JK$6 -> 218.69083 | JL8: =JK8/JL$6 -> 72.896944 | JM8: =JH8/JM$6 -> 218.69083 | JN8: =SUM(JH8:JM8) -> 3606.9408 | JT8: =((JG8*JT$6)+(JG8*JI$6)+(JG8*JJ$6))*JO8 -> 0 | JU8: =((JG8*JU6)+(JG8*JI6)+(JG8*JJ6))*JP8 -> 0 | JV8: =((JG8*JV$6)+(JG8*JI$6)+(JG8*JJ$6))*JQ8 -> 0 | JW8: =((JG8*JW$6)+(JG8*JI$6)+(JG8*JJ$6))*JR8 -> 0 | JX8: =((JG8*JX$6)+(JG8*JI$6)+(JG8*JJ$6))*JS8 -> 0 | JY8: =SUM(JT8:JX8) -> 0 | JZ8: 0 | KA8: =IF(JE8=1,($C$1*$W$6),0) -> 0 | KB8: =JN8+JY8+JZ8+KA8 -> 3606.9408
A9: 0 | B9: Claudio Operador A | C9: =D9/$AY$4 -> 5.9643182 | D9: 1312.15 | E9: =D9*E$6 -> 131.215 | F9: =D9*F$6 -> 104.972 | G9: =D9/G$6 -> 109.34583 | H9: =G9/H$6 -> 36.448611 | I9: =D9/I$6 -> 109.34583 | J9: =SUM(D9:I9) -> 1803.4773 | P9: =((C9*P$6)+(C9*E$6)+(C9*F$6))*K9 -> 0 | Q9: =((C9*Q$6)+(C9*E$6)+(C9*F$6))*L9 -> 0 | R9: =((C9*R$6)+(C9*E$6)+(C9*F$6))*M9 -> 0 | S9: =((C9*S$6)+(C9*E$6)+(C9*F$6))*N9 -> 0 | T9: =((C9*T$6)+(C9*E$6)+(C9*F$6))*O9 -> 0 | U9: =SUM(P9:T9) -> 0 | V9: 0 | W9: =IF(A9=1,($C$1*$W$6),0) -> 0 | X9: =J9+U9+V9+W9 -> 1803.4773 | Y9: 0 | Z9: Claudio Operador A | AA9: =AB9/$AY$4 -> 5.9643182 | AB9: 1312.15 | AC9: =AB9*AC$6 -> 131.215 | AD9: =AB9*AD$6 -> 104.972 | AE9: =AB9/AE$6 -> 109.34583 | AF9: =AE9/AF$6 -> 36.448611 | AG9: =AB9/AG$6 -> 109.34583 | AH9: =SUM(AB9:AG9) -> 1803.4773 | AN9: =((AA9*AN$6)+(AA9*AC$6)+(AA9*AD$6))*AI9 -> 0 | AO9: =((AA9*AO$6)+(AA9*AC$6)+(AA9*AD$6))*AJ9 -> 0 | AP9: =((AA9*AP$6)+(AA9*AC$6)+(AA9*AD$6))*AK9 -> 0 | AQ9: =((AA9*AQ$6)+(AA9*AC$6)+(AA9*AD$6))*AL9 -> 0 | AR9: =((AA9*AR$6)+(AA9*AC$6)+(AA9*AD$6))*AM9 -> 0 | AS9: =SUM(AN9:AR9) -> 0 | AT9: 0 | AU9: =IF(Y9=1,($C$1*$W$6),0) -> 0 | AV9: =AH9+AS9+AT9+AU9 -> 1803.4773 | AW9: 0 | AX9: Claudio Operador A | AY9: =AZ9/$AY$4 -> 5.9643182 | AZ9: 1312.15 | BA9: =AZ9*BA$6 -> 131.215 | BB9: =AZ9*BB$6 -> 104.972 | BC9: =AZ9/BC$6 -> 109.34583 | BD9: =BC9/BD$6 -> 36.448611 | BE9: =AZ9/BE$6 -> 109.34583 | BF9: =SUM(AZ9:BE9) -> 1803.4773 | BL9: =((AY9*BL$6)+(AY9*BA$6)+(AY9*BB$6))*BG9 -> 0 | BM9: =((AY9*BM$6)+(AY9*BA$6)+(AY9*BB$6))*BH9 -> 0 | BN9: =((AY9*BN$6)+(AY9*BA$6)+(AY9*BB$6))*BI9 -> 0 | BO9: =((AY9*BO$6)+(AY9*BA$6)+(AY9*BB$6))*BJ9 -> 0 | BP9: =((AY9*BP$6)+(AY9*BA$6)+(AY9*BB$6))*BK9 -> 0 | BQ9: =SUM(BL9:BP9) -> 0 | BR9: 0 | BS9: =IF(AW9=1,($C$1*$W$6),0) -> 0 | BT9: =BF9+BQ9+BR9+BS9 -> 1803.4773 | BU9: 0 | BV9: Claudio Operador A | BW9: =BX9/$AY$4 -> 5.9643182 | BX9: 1312.15 | BY9: =BX9*BY$6 -> 131.215 | BZ9: =BX9*BZ$6 -> 104.972 | CA9: =BX9/CA$6 -> 109.34583 | CB9: =CA9/CB$6 -> 36.448611 | CC9: =BX9/CC$6 -> 109.34583 | CD9: =SUM(BX9:CC9) -> 1803.4773 | CJ9: =((BW9*CJ$6)+(BW9*BY$6)+(BW9*BZ$6))*CE9 -> 0 | CK9: =((BW9*CK$6)+(BW9*BY$6)+(BW9*BZ$6))*CF9 -> 0 | CL9: =((BW9*CL$6)+(BW9*BY$6)+(BW9*BZ$6))*CG9 -> 0 | CM9: =((BW9*CM$6)+(BW9*BY$6)+(BW9*BZ$6))*CH9 -> 0 | CN9: =((BW9*CN$6)+(BW9*BY$6)+(BW9*BZ$6))*CI9 -> 0 | CO9: =SUM(CJ9:CN9) -> 0 | CP9: 0 | CQ9: =IF(BU9=1,($C$1*$W$6),0) -> 0 | CR9: =CD9+CO9+CP9+CQ9 -> 1803.4773 | CS9: 0 | CT9: Claudio Operador A | CU9: =CV9/$AY$4 -> 5.9643182 | CV9: 1312.15 | CW9: =CV9*CW$6 -> 131.215 | CX9: =CV9*CX$6 -> 104.972 | CY9: =CV9/CY$6 -> 109.34583 | CZ9: =CY9/CZ$6 -> 36.448611 | DA9: =CV9/DA$6 -> 109.34583 | DB9: =SUM(CV9:DA9) -> 1803.4773 | DH9: =((CU9*DH$6)+(CU9*CW$6)+(CU9*CX$6))*DC9 -> 0 | DI9: =((CU9*DI$6)+(CU9*CW$6)+(CU9*CX$6))*DD9 -> 0 | DJ9: =((CU9*DJ$6)+(CU9*CW$6)+(CU9*CX$6))*DE9 -> 0 | DK9: =((CU9*DK$6)+(CU9*CW$6)+(CU9*CX$6))*DF9 -> 0 | DL9: =((CU9*DL$6)+(CU9*CW$6)+(CU9*CX$6))*DG9 -> 0 | DM9: =SUM(DH9:DL9) -> 0 | DN9: 0 | DO9: =IF(CS9=1,($C$1*$W$6),0) -> 0 | DP9: =DB9+DM9+DN9+DO9 -> 1803.4773 | DQ9: 0 | DR9: Claudio Operador A | DS9: =DT9/$AY$4 -> 5.9643182 | DT9: 1312.15 | DU9: =DT9*DU$6 -> 131.215 | DV9: =DT9*DV$6 -> 104.972 | DW9: =DT9/DW$6 -> 109.34583 | DX9: =DW9/DX$6 -> 36.448611 | DY9: =DT9/DY$6 -> 109.34583 | DZ9: =SUM(DT9:DY9) -> 1803.4773 | EF9: =((DS9*EF$6)+(DS9*DU$6)+(DS9*DV$6))*EA9 -> 0 | EG9: =((DS9*EG$6)+(DS9*DU$6)+(DS9*DV$6))*EB9 -> 0 | EH9: =((DS9*EH$6)+(DS9*DU$6)+(DS9*DV$6))*EC9 -> 0 | EI9: =((DS9*EI$6)+(DS9*DU$6)+(DS9*DV$6))*ED9 -> 0 | EJ9: =((DS9*EJ$6)+(DS9*DU$6)+(DS9*DV$6))*EE9 -> 0 | EK9: =SUM(EF9:EJ9) -> 0 | EL9: 0 | EM9: =IF(DQ9=1,($C$1*$W$6),0) -> 0 | EN9: =DZ9+EK9+EL9+EM9 -> 1803.4773 | EO9: 0 | EP9: Claudio Operador A | EQ9: =ER9/$AY$4 -> 5.9643182 | ER9: 1312.15 | ES9: =ER9*ES$6 -> 131.215 | ET9: =ER9*ET$6 -> 104.972 | EU9: =ER9/EU$6 -> 109.34583 | EV9: =EU9/EV$6 -> 36.448611 | EW9: =ER9/EW$6 -> 109.34583 | EX9: =SUM(ER9:EW9) -> 1803.4773 | FD9: =((EQ9*FD$6)+(EQ9*ES$6)+(EQ9*ET$6))*EY9 -> 0 | FE9: =((EQ9*FE$6)+(EQ9*ES$6)+(EQ9*ET$6))*EZ9 -> 0 | FF9: =((EQ9*FF$6)+(EQ9*ES$6)+(EQ9*ET$6))*FA9 -> 0 | FG9: =((EQ9*FG$6)+(EQ9*ES$6)+(EQ9*ET$6))*FB9 -> 0 | FH9: =((EQ9*FH$6)+(EQ9*ES$6)+(EQ9*ET$6))*FC9 -> 0 | FI9: =SUM(FD9:FH9) -> 0 | FJ9: 0 | FK9: =IF(EO9=1,($C$1*$W$6),0) -> 0 | FL9: =EX9+FI9+FJ9+FK9 -> 1803.4773 | FM9: 0 | FN9: Claudio Operador A | FO9: =FP9/$AY$4 -> 5.9643182 | FP9: 1312.15 | FQ9: =FP9*FQ$6 -> 131.215 | FR9: =FP9*FR$6 -> 104.972 | FS9: =FP9/FS$6 -> 109.34583 | FT9: =FS9/FT$6 -> 36.448611 | FU9: =FP9/FU$6 -> 109.34583 | FV9: =SUM(FP9:FU9) -> 1803.4773 | GB9: =((FO9*GB$6)+(FO9*FQ$6)+(FO9*FR$6))*FW9 -> 0 | GC9: =((FO9*GC$6)+(FO9*FQ$6)+(FO9*FR$6))*FX9 -> 0 | GD9: =((FO9*GD$6)+(FO9*FQ$6)+(FO9*FR$6))*FY9 -> 0 | GE9: =((FO9*GE$6)+(FO9*FQ$6)+(FO9*FR$6))*FZ9 -> 0 | GF9: =((FO9*GF$6)+(FO9*FQ$6)+(FO9*FR$6))*GA9 -> 0 | GG9: =SUM(GB9:GF9) -> 0 | GH9: 0 | GI9: =IF(FM9=1,($C$1*$W$6),0) -> 0 | GJ9: =FV9+GG9+GH9+GI9 -> 1803.4773 | GK9: 0 | GL9: Claudio Operador A | GM9: =GN9/$AY$4 -> 5.9643182 | GN9: 1312.15 | GO9: =GN9*GO$6 -> 131.215 | GP9: =GN9*GP$6 -> 104.972 | GQ9: =GN9/GQ$6 -> 109.34583 | GR9: =GQ9/GR$6 -> 36.448611 | GS9: =GN9/GS$6 -> 109.34583 | GT9: =SUM(GN9:GS9) -> 1803.4773 | GZ9: =((GM9*GZ$6)+(GM9*GO$6)+(GM9*GP$6))*GU9 -> 0 | HA9: =((GM9*HA$6)+(GM9*GO$6)+(GM9*GP$6))*GV9 -> 0 | HB9: =((GM9*HB$6)+(GM9*GO$6)+(GM9*GP$6))*GW9 -> 0 | HC9: =((GM9*HC$6)+(GM9*GO$6)+(GM9*GP$6))*GX9 -> 0 | HD9: =((GM9*HD$6)+(GM9*GO$6)+(GM9*GP$6))*GY9 -> 0 | HE9: =SUM(GZ9:HD9) -> 0 | HF9: 0 | HG9: =IF(GK9=1,($C$1*$W$6),0) -> 0 | HH9: =GT9+HE9+HF9+HG9 -> 1803.4773 | HI9: 0 | HJ9: Claudio Operador A | HK9: =HL9/$AY$4 -> 5.9643182 | HL9: 1312.15 | HM9: =HL9*HM$6 -> 131.215 | HN9: =HL9*HN$6 -> 104.972 | HO9: =HL9/HO$6 -> 109.34583 | HP9: =HO9/HP$6 -> 36.448611 | HQ9: =HL9/HQ$6 -> 109.34583 | HR9: =SUM(HL9:HQ9) -> 1803.4773 | HX9: =((HK9*HX$6)+(HK9*HM$6)+(HK9*HN$6))*HS9 -> 0 | HY9: =((HK9*HY$6)+(HK9*HM$6)+(HK9*HN$6))*HT9 -> 0 | HZ9: =((HK9*HZ$6)+(HK9*HM$6)+(HK9*HN$6))*HU9 -> 0 | IA9: =((HK9*IA$6)+(HK9*HM$6)+(HK9*HN$6))*HV9 -> 0 | IB9: =((HK9*IB$6)+(HK9*HM$6)+(HK9*HN$6))*HW9 -> 0 | IC9: =SUM(HX9:IB9) -> 0 | ID9: 0 | IE9: =IF(HI9=1,($C$1*$W$6),0) -> 0 | IF9: =HR9+IC9+ID9+IE9 -> 1803.4773 | IG9: 0 | IH9: Claudio Operador A | II9: =IJ9/$AY$4 -> 5.9643182 | IJ9: 1312.15 | IK9: =IJ9*IK$6 -> 131.215 | IL9: =IJ9*IL$6 -> 104.972 | IM9: =IJ9/IM$6 -> 109.34583 | IN9: =IM9/IN$6 -> 36.448611 | IO9: =IJ9/IO$6 -> 109.34583 | IP9: =SUM(IJ9:IO9) -> 1803.4773 | IV9: =((II9*IV$6)+(II9*IK$6)+(II9*IL$6))*IQ9 -> 0 | IW9: =((II9*IW$6)+(II9*IK$6)+(II9*IL$6))*IR9 -> 0 | IX9: =((II9*IX$6)+(II9*IK$6)+(II9*IL$6))*IS9 -> 0 | IY9: =((II9*IY$6)+(II9*IK$6)+(II9*IL$6))*IT9 -> 0 | IZ9: =((II9*IZ$6)+(II9*IK$6)+(II9*IL$6))*IU9 -> 0 | JA9: =SUM(IV9:IZ9) -> 0 | JB9: 0 | JC9: =IF(IG9=1,($C$1*$W$6),0) -> 0 | JD9: =IP9+JA9+JB9+JC9 -> 1803.4773 | JE9: 0 | JF9: Claudio Operador A | JG9: =JH9/$AY$4 -> 5.9643182 | JH9: 1312.15 | JI9: =JH9*JI$6 -> 131.215 | JJ9: =JH9*JJ$6 -> 104.972 | JK9: =JH9/JK$6 -> 109.34583 | JL9: =JK9/JL$6 -> 36.448611 | JM9: =JH9/JM$6 -> 109.34583 | JN9: =SUM(JH9:JM9) -> 1803.4773 | JT9: =((JG9*JT$6)+(JG9*JI$6)+(JG9*JJ$6))*JO9 -> 0 | JU9: =((JG9*JU$6)+(JG9*JI$6)+(JG9*JJ$6))*JP9 -> 0 | JV9: =((JG9*JV$6)+(JG9*JI$6)+(JG9*JJ$6))*JQ9 -> 0 | JW9: =((JG9*JW$6)+(JG9*JI$6)+(JG9*JJ$6))*JR9 -> 0 | JX9: =((JG9*JX$6)+(JG9*JI$6)+(JG9*JJ$6))*JS9 -> 0 | JY9: =SUM(JT9:JX9) -> 0 | JZ9: 0 | KA9: =IF(JE9=1,($C$1*$W$6),0) -> 0 | KB9: =JN9+JY9+JZ9+KA9 -> 1803.4773
A10: 0 | C10: =D10/$AY$4 -> 0 | D10: 0 | E10: =D10*E$6 -> 0 | F10: =D10*F$6 -> 0 | G10: =D10/G$6 -> 0 | H10: =G10/H$6 -> 0 | I10: =D10/I$6 -> 0 | J10: =SUM(D10:I10) -> 0 | P10: =((C10*P$6)+(C10*E$6)+(C10*F$6))*K10 -> 0 | Q10: =((C10*Q$6)+(C10*E$6)+(C10*F$6))*L10 -> 0 | R10: =((C10*R$6)+(C10*F$6)+(C10*E$6))*M10 -> 0 | S10: =((C10*S$6)+(C10*E$6)+(C10*F$6))*N10 -> 0 | T10: =((C10*T$6)+(C10*E$6)+(C10*F$6))*O10 -> 0 | U10: =SUM(P10:T10) -> 0 | V10: 0 | W10: =IF(A10=1,($C$1*$W$6),0) -> 0 | X10: =J10+U10+V10+W10 -> 0 | Y10: 0 | AA10: =AB10/$AY$4 -> 0 | AB10: 0 | AC10: =AB10*AC$6 -> 0 | AD10: =AB10*AD$6 -> 0 | AE10: =AB10/AE$6 -> 0 | AF10: =AE10/AF$6 -> 0 | AG10: =AB10/AG$6 -> 0 | AH10: =SUM(AB10:AG10) -> 0 | AN10: =((AA10*AN$6)+(AA10*AC$6)+(AA10*AD$6))*AI10 -> 0 | AO10: =((AA10*AO$6)+(AA10*AC$6)+(AA10*AD$6))*AJ10 -> 0 | AP10: =((AA10*AP$6)+(AA10*AD$6)+(AA10*AC$6))*AK10 -> 0 | AQ10: =((AA10*AQ$6)+(AA10*AC$6)+(AA10*AD$6))*AL10 -> 0 | AR10: =((AA10*AR$6)+(AA10*AC$6)+(AA10*AD$6))*AM10 -> 0 | AS10: =SUM(AN10:AR10) -> 0 | AT10: 0 | AU10: =IF(Y10=1,($C$1*$W$6),0) -> 0 | AV10: =AH10+AS10+AT10+AU10 -> 0 | AW10: 0 | AY10: =AZ10/$AY$4 -> 0 | AZ10: 0 | BA10: =AZ10*BA$6 -> 0 | BB10: =AZ10*BB$6 -> 0 | BC10: =AZ10/BC$6 -> 0 | BD10: =BC10/BD$6 -> 0 | BE10: =AZ10/BE$6 -> 0 | BF10: =SUM(AZ10:BE10) -> 0 | BL10: =((AY10*BL$6)+(AY10*BA$6)+(AY10*BB$6))*BG10 -> 0 | BM10: =((AY10*BM$6)+(AY10*BA$6)+(AY10*BB$6))*BH10 -> 0 | BN10: =((AY10*BN$6)+(AY10*BB$6)+(AY10*BA$6))*BI10 -> 0 | BO10: =((AY10*BO$6)+(AY10*BA$6)+(AY10*BB$6))*BJ10 -> 0 | BP10: =((AY10*BP$6)+(AY10*BA$6)+(AY10*BB$6))*BK10 -> 0 | BQ10: =SUM(BL10:BP10) -> 0 | BR10: 0 | BS10: =IF(AW10=1,($C$1*$W$6),0) -> 0 | BT10: =BF10+BQ10+BR10+BS10 -> 0 | BU10: 0 | BW10: =BX10/$AY$4 -> 0 | BX10: 0 | BY10: =BX10*BY$6 -> 0 | BZ10: =BX10*BZ$6 -> 0 | CA10: =BX10/CA$6 -> 0 | CB10: =CA10/CB$6 -> 0 | CC10: =BX10/CC$6 -> 0 | CD10: =SUM(BX10:CC10) -> 0 | CJ10: =((BW10*CJ$6)+(BW10*BY$6)+(BW10*BZ$6))*CE10 -> 0 | CK10: =((BW10*CK$6)+(BW10*BY$6)+(BW10*BZ$6))*CF10 -> 0 | CL10: =((BW10*CL$6)+(BW10*BZ$6)+(BW10*BY$6))*CG10 -> 0 | CM10: =((BW10*CM$6)+(BW10*BY$6)+(BW10*BZ$6))*CH10 -> 0 | CN10: =((BW10*CN$6)+(BW10*BY$6)+(BW10*BZ$6))*CI10 -> 0 | CO10: =SUM(CJ10:CN10) -> 0 | CP10: 0 | CQ10: =IF(BU10=1,($C$1*$W$6),0) -> 0 | CR10: =CD10+CO10+CP10+CQ10 -> 0 | CS10: 0 | CU10: =CV10/$AY$4 -> 0 | CV10: 0 | CW10: =CV10*CW$6 -> 0 | CX10: =CV10*CX$6 -> 0 | CY10: =CV10/CY$6 -> 0 | CZ10: =CY10/CZ$6 -> 0 | DA10: =CV10/DA$6 -> 0 | DB10: =SUM(CV10:DA10) -> 0 | DH10: =((CU10*DH$6)+(CU10*CW$6)+(CU10*CX$6))*DC10 -> 0 | DI10: =((CU10*DI$6)+(CU10*CW$6)+(CU10*CX$6))*DD10 -> 0 | DJ10: =((CU10*DJ$6)+(CU10*CX$6)+(CU10*CW$6))*DE10 -> 0 | DK10: =((CU10*DK$6)+(CU10*CW$6)+(CU10*CX$6))*DF10 -> 0 | DL10: =((CU10*DL$6)+(CU10*CW$6)+(CU10*CX$6))*DG10 -> 0 | DM10: =SUM(DH10:DL10) -> 0 | DN10: 0 | DO10: =IF(CS10=1,($C$1*$W$6),0) -> 0 | DP10: =DB10+DM10+DN10+DO10 -> 0 | DQ10: 0 | DS10: =DT10/$AY$4 -> 0 | DT10: 0 | DU10: =DT10*DU$6 -> 0 | DV10: =DT10*DV$6 -> 0 | DW10: =DT10/DW$6 -> 0 | DX10: =DW10/DX$6 -> 0 | DY10: =DT10/DY$6 -> 0 | DZ10: =SUM(DT10:DY10) -> 0 | EF10: =((DS10*EF$6)+(DS10*DU$6)+(DS10*DV$6))*EA10 -> 0 | EG10: =((DS10*EG$6)+(DS10*DU$6)+(DS10*DV$6))*EB10 -> 0 | EH10: =((DS10*EH$6)+(DS10*DV$6)+(DS10*DU$6))*EC10 -> 0 | EI10: =((DS10*EI$6)+(DS10*DU$6)+(DS10*DV$6))*ED10 -> 0 | EJ10: =((DS10*EJ$6)+(DS10*DU$6)+(DS10*DV$6))*EE10 -> 0 | EK10: =SUM(EF10:EJ10) -> 0 | EL10: 0 | EM10: =IF(DQ10=1,($C$1*$W$6),0) -> 0 | EN10: =DZ10+EK10+EL10+EM10 -> 0 | EO10: 0 | EQ10: =ER10/$AY$4 -> 0 | ER10: 0 | ES10: =ER10*ES$6 -> 0 | ET10: =ER10*ET$6 -> 0 | EU10: =ER10/EU$6 -> 0 | EV10: =EU10/EV$6 -> 0 | EW10: =ER10/EW$6 -> 0 | EX10: =SUM(ER10:EW10) -> 0 | FD10: =((EQ10*FD$6)+(EQ10*ES$6)+(EQ10*ET$6))*EY10 -> 0 | FE10: =((EQ10*FE$6)+(EQ10*ES$6)+(EQ10*ET$6))*EZ10 -> 0 | FF10: =((EQ10*FF$6)+(EQ10*ET$6)+(EQ10*ES$6))*FA10 -> 0 | FG10: =((EQ10*FG$6)+(EQ10*ES$6)+(EQ10*ET$6))*FB10 -> 0 | FH10: =((EQ10*FH$6)+(EQ10*ES$6)+(EQ10*ET$6))*FC10 -> 0 | FI10: =SUM(FD10:FH10) -> 0 | FJ10: 0 | FK10: =IF(EO10=1,($C$1*$W$6),0) -> 0 | FL10: =EX10+FI10+FJ10+FK10 -> 0 | FM10: 0 | FO10: =FP10/$AY$4 -> 0 | FP10: 0 | FQ10: =FP10*FQ$6 -> 0 | FR10: =FP10*FR$6 -> 0 | FS10: =FP10/FS$6 -> 0 | FT10: =FS10/FT$6 -> 0 | FU10: =FP10/FU$6 -> 0 | FV10: =SUM(FP10:FU10) -> 0 | GB10: =((FO10*GB$6)+(FO10*FQ$6)+(FO10*FR$6))*FW10 -> 0 | GC10: =((FO10*GC$6)+(FO10*FQ$6)+(FO10*FR$6))*FX10 -> 0 | GD10: =((FO10*GD$6)+(FO10*FR$6)+(FO10*FQ$6))*FY10 -> 0 | GE10: =((FO10*GE$6)+(FO10*FQ$6)+(FO10*FR$6))*FZ10 -> 0 | GF10: =((FO10*GF$6)+(FO10*FQ$6)+(FO10*FR$6))*GA10 -> 0 | GG10: =SUM(GB10:GF10) -> 0 | GH10: 0 | GI10: =IF(FM10=1,($C$1*$W$6),0) -> 0 | GJ10: =FV10+GG10+GH10+GI10 -> 0 | GK10: 0 | GM10: =GN10/$AY$4 -> 0 | GN10: 0 | GO10: =GN10*GO$6 -> 0 | GP10: =GN10*GP$6 -> 0 | GQ10: =GN10/GQ$6 -> 0 | GR10: =GQ10/GR$6 -> 0 | GS10: =GN10/GS$6 -> 0 | GT10: =SUM(GN10:GS10) -> 0 | GZ10: =((GM10*GZ$6)+(GM10*GO$6)+(GM10*GP$6))*GU10 -> 0 | HA10: =((GM10*HA$6)+(GM10*GO$6)+(GM10*GP$6))*GV10 -> 0 | HB10: =((GM10*HB$6)+(GM10*GP$6)+(GM10*GO$6))*GW10 -> 0 | HC10: =((GM10*HC$6)+(GM10*GO$6)+(GM10*GP$6))*GX10 -> 0 | HD10: =((GM10*HD$6)+(GM10*GO$6)+(GM10*GP$6))*GY10 -> 0 | HE10: =SUM(GZ10:HD10) -> 0 | HF10: 0 | HG10: =IF(GK10=1,($C$1*$W$6),0) -> 0 | HH10: =GT10+HE10+HF10+HG10 -> 0 | HI10: 0 | HK10: =HL10/$AY$4 -> 0 | HL10: 0 | HM10: =HL10*HM$6 -> 0 | HN10: =HL10*HN$6 -> 0 | HO10: =HL10/HO$6 -> 0 | HP10: =HO10/HP$6 -> 0 | HQ10: =HL10/HQ$6 -> 0 | HR10: =SUM(HL10:HQ10) -> 0 | HX10: =((HK10*HX$6)+(HK10*HM$6)+(HK10*HN$6))*HS10 -> 0 | HY10: =((HK10*HY$6)+(HK10*HM$6)+(HK10*HN$6))*HT10 -> 0 | HZ10: =((HK10*HZ$6)+(HK10*HN$6)+(HK10*HM$6))*HU10 -> 0 | IA10: =((HK10*IA$6)+(HK10*HM$6)+(HK10*HN$6))*HV10 -> 0 | IB10: =((HK10*IB$6)+(HK10*HM$6)+(HK10*HN$6))*HW10 -> 0 | IC10: =SUM(HX10:IB10) -> 0 | ID10: 0 | IE10: =IF(HI10=1,($C$1*$W$6),0) -> 0 | IF10: =HR10+IC10+ID10+IE10 -> 0 | IG10: 0 | II10: =IJ10/$AY$4 -> 0 | IJ10: 0 | IK10: =IJ10*IK$6 -> 0 | IL10: =IJ10*IL$6 -> 0 | IM10: =IJ10/IM$6 -> 0 | IN10: =IM10/IN$6 -> 0 | IO10: =IJ10/IO$6 -> 0 | IP10: =SUM(IJ10:IO10) -> 0 | IV10: =((II10*IV$6)+(II10*IK$6)+(II10*IL$6))*IQ10 -> 0 | IW10: =((II10*IW$6)+(II10*IK$6)+(II10*IL$6))*IR10 -> 0 | IX10: =((II10*IX$6)+(II10*IL$6)+(II10*IK$6))*IS10 -> 0 | IY10: =((II10*IY$6)+(II10*IK$6)+(II10*IL$6))*IT10 -> 0 | IZ10: =((II10*IZ$6)+(II10*IK$6)+(II10*IL$6))*IU10 -> 0 | JA10: =SUM(IV10:IZ10) -> 0 | JB10: 0 | JC10: =IF(IG10=1,($C$1*$W$6),0) -> 0 | JD10: =IP10+JA10+JB10+JC10 -> 0 | JE10: 0 | JG10: =JH10/$AY$4 -> 0 | JH10: 0 | JI10: =JH10*JI$6 -> 0 | JJ10: =JH10*JJ$6 -> 0 | JK10: =JH10/JK$6 -> 0 | JL10: =JK10/JL$6 -> 0 | JM10: =JH10/JM$6 -> 0 | JN10: =SUM(JH10:JM10) -> 0 | JT10: =((JG10*JT$6)+(JG10*JI$6)+(JG10*JJ$6))*JO10 -> 0 | JU10: =((JG10*JU$6)+(JG10*JI$6)+(JG10*JJ$6))*JP10 -> 0 | JV10: =((JG10*JV$6)+(JG10*JJ$6)+(JG10*JI$6))*JQ10 -> 0 | JW10: =((JG10*JW$6)+(JG10*JI$6)+(JG10*JJ$6))*JR10 -> 0 | JX10: =((JG10*JX$6)+(JG10*JI$6)+(JG10*JJ$6))*JS10 -> 0 | JY10: =SUM(JT10:JX10) -> 0 | JZ10: 0 | KA10: =IF(JE10=1,($C$1*$W$6),0) -> 0 | KB10: =JN10+JY10+JZ10+KA10 -> 0
W11: Total | X11: =SUM(X8:X10) -> 5410.4181 | AU11: Total | AV11: =SUM(AV8:AV10) -> 5410.4181 | BS11: Total | BT11: =SUM(BT8:BT10) -> 5410.4181 | CQ11: Total | CR11: =SUM(CR8:CR10) -> 5410.4181 | DO11: Total | DP11: =SUM(DP8:DP10) -> 5410.4181 | EM11: Total | EN11: =SUM(EN8:EN10) -> 5410.4181 | FK11: Total | FL11: =SUM(FL8:FL10) -> 5410.4181 | GI11: Total | GJ11: =SUM(GJ8:GJ10) -> 5410.4181 | HG11: Total | HH11: =SUM(HH8:HH10) -> 5410.4181 | IE11: Total | IF11: =SUM(IF8:IF10) -> 5410.4181 | JC11: Total | JD11: =SUM(JD8:JD10) -> 5410.4181 | KA11: Total | KB11: =SUM(KB8:KB10) -> 5410.4181
B12: Funcionário | C12: Sal/Hora | D12: Salario Mensal | E12: 0.1 | F12: 0.08 | G12: 12 | H12: 3 | I12: 12 | J12: - | K12: 0.5 | L12: 0.6 | M12: 0.8 | N12: 1 | O12: 1.5 | P12: 1.5 | Q12: 1.6 | R12: 1.8 | S12: 2 | T12: 2.5 | U12: - | V12: - | W12: 0.2 | X12: - | Z12: Funcionário | AA12: Sal/Hora | AB12: Salario Mensal | AC12: 0.1 | AD12: 0.08 | AE12: 12 | AF12: 3 | AG12: 12 | AH12: - | AI12: 0.5 | AJ12: 0.6 | AK12: 0.8 | AL12: 1 | AM12: 1.5 | AN12: 1.5 | AO12: 1.6 | AP12: 1.8 | AQ12: 2 | AR12: 2.5 | AS12: - | AT12: - | AU12: 0.2 | AV12: - | AX12: Funcionário | AY12: Sal/Hora | AZ12: Salario Mensal | BA12: 0.1 | BB12: 0.08 | BC12: 12 | BD12: 3 | BE12: 12 | BF12: - | BG12: 0.5 | BH12: 0.6 | BI12: 0.8 | BJ12: 1 | BK12: 1.5 | BL12: 1.5 | BM12: 1.6 | BN12: 1.8 | BO12: 2 | BP12: 2.5 | BQ12: - | BR12: - | BS12: 0.2 | BT12: - | BV12: Funcionário | BW12: Sal/Hora | BX12: Salario Mensal | BY12: 0.1 | BZ12: 0.08 | CA12: 12 | CB12: 3 | CC12: 12 | CD12: - | CE12: 0.5 | CF12: 0.6 | CG12: 0.8 | CH12: 1 | CI12: 1.5 | CJ12: 1.5 | CK12: 1.6 | CL12: 1.8 | CM12: 2 | CN12: 2.5 | CO12: - | CP12: - | CQ12: 0.2 | CR12: - | CT12: Funcionário | CU12: Sal/Hora | CV12: Salario Mensal | CW12: 0.1 | CX12: 0.08 | CY12: 12 | CZ12: 3 | DA12: 12 | DB12: - | DC12: 0.5 | DD12: 0.6 | DE12: 0.8 | DF12: 1 | DG12: 1.5 | DH12: 1.5 | DI12: 1.6 | DJ12: 1.8 | DK12: 2 | DL12: 2.5 | DM12: - | DN12: - | DO12: 0.2 | DP12: - | DR12: Funcionário | DS12: Sal/Hora | DT12: Salario Mensal | DU12: 0.1 | DV12: 0.08 | DW12: 12 | DX12: 3 | DY12: 12 | DZ12: - | EA12: 0.5 | EB12: 0.6 | EC12: 0.8 | ED12: 1 | EE12: 1.5 | EF12: 1.5 | EG12: 1.6 | EH12: 1.8 | EI12: 2 | EJ12: 2.5 | EK12: - | EL12: - | EM12: 0.2 | EN12: - | EP12: Funcionário | EQ12: Sal/Hora | ER12: Salario Mensal | ES12: 0.1 | ET12: 0.08 | EU12: 12 | EV12: 3 | EW12: 12 | EX12: - | EY12: 0.5 | EZ12: 0.6 | FA12: 0.8 | FB12: 1 | FC12: 1.5 | FD12: 1.5 | FE12: 1.6 | FF12: 1.8 | FG12: 2 | FH12: 2.5 | FI12: - | FJ12: - | FK12: 0.2 | FL12: - | FN12: Funcionário | FO12: Sal/Hora | FP12: Salario Mensal | FQ12: 0.1 | FR12: 0.08 | FS12: 12 | FT12: 3 | FU12: 12 | FV12: - | FW12: 0.5 | FX12: 0.6 | FY12: 0.8 | FZ12: 1 | GA12: 1.5 | GB12: 1.5 | GC12: 1.6 | GD12: 1.8 | GE12: 2 | GF12: 2.5 | GG12: - | GH12: - | GI12: 0.2 | GJ12: - | GL12: Funcionário | GM12: Sal/Hora | GN12: Salario Mensal | GO12: 0.1 | GP12: 0.08 | GQ12: 12 | GR12: 3 | GS12: 12 | GT12: - | GU12: 0.5 | GV12: 0.6 | GW12: 0.8 | GX12: 1 | GY12: 1.5 | GZ12: 1.5 | HA12: 1.6 | HB12: 1.8 | HC12: 2 | HD12: 2.5 | HE12: - | HF12: - | HG12: 0.2 | HH12: - | HJ12: Funcionário | HK12: Sal/Hora | HL12: Salario Mensal | HM12: 0.1 | HN12: 0.08 | HO12: 12 | HP12: 3 | HQ12: 12 | HR12: - | HS12: 0.5 | HT12: 0.6 | HU12: 0.8 | HV12: 1 | HW12: 1.5 | HX12: 1.5 | HY12: 1.6 | HZ12: 1.8 | IA12: 2 | IB12: 2.5 | IC12: - | ID12: - | IE12: 0.2 | IF12: - | IH12: Funcionário | II12: Sal/Hora | IJ12: Salario Mensal | IK12: 0.1 | IL12: 0.08 | IM12: 12 | IN12: 3 | IO12: 12 | IP12: - | IQ12: 0.5 | IR12: 0.6 | IS12: 0.8 | IT12: 1 | IU12: 1.5 | IV12: 1.5 | IW12: 1.6 | IX12: 1.8 | IY12: 2 | IZ12: 2.5 | JA12: - | JB12: - | JC12: 0.2 | JD12: - | JF12: Funcionário | JG12: Sal/Hora | JH12: Salario Mensal | JI12: 0.1 | JJ12: 0.08 | JK12: 12 | JL12: 3 | JM12: 12 | JN12: - | JO12: 0.5 | JP12: 0.6 | JQ12: 0.8 | JR12: 1 | JS12: 1.5 | JT12: 1.5 | JU12: 1.6 | JV12: 1.8 | JW12: 2 | JX12: 2.5 | JY12: - | JZ12: - | KA12: 0.2 | KB12: -
E13: Linha 2 Zn Alc.Aut | AC13: Linha 2 Zn Alc.Aut | BA13: Linha 2 Zn Alc.Aut | BY13: Linha 2 Zn Alc.Aut | CW13: Linha 2 Zn Alc.Aut | DU13: Linha 2 Zn Alc.Aut | ES13: Linha 2 Zn Alc.Aut | FQ13: Linha 2 Zn Alc.Aut | GO13: Linha 2 Zn Alc.Aut | HM13: Linha 2 Zn Alc.Aut | IK13: Linha 2 Zn Alc.Aut | JI13: Linha 2 Zn Alc.Aut
A14: 0 | B14: Valdeir Op. A | C14: =D14/$AY$4 -> 11.928591 | D14: 2624.29 | E14: =D14*E$12 -> 262.429 | F14: =D14*F$12 -> 209.9432 | G14: =D14/G$12 -> 218.69083 | H14: =G14/H$12 -> 72.896944 | I14: =D14/I$12 -> 218.69083 | J14: =SUM(D14:I14) -> 3606.9408 | P14: =((C14*P$12)+(C14*E$12)+(C14*F$12))*K14 -> 0 | Q14: =((C14*Q$12)+(C14*E$12)+(C14*F$12))*L14 -> 0 | R14: =((C14*R$12)+(C14*E$12)+(C14*F$12))*M14 -> 0 | S14: =((C14*S$6)+(C14*E$6)+(C14*F$6))*N14 -> 0 | T14: =((C14*T$12)+(C14*E$12)+(C14*F$12))*O14 -> 0 | U14: =SUM(P14:T14) -> 0 | V14: 0 | W14: =IF(A14=1,($C$1*$W$6),0) -> 0 | X14: =J14+U14+V14+W14 -> 3606.9408 | Y14: 0 | Z14: Valdeir Op. A | AA14: =AB14/$AY$4 -> 11.928591 | AB14: 2624.29 | AC14: =AB14*AC$12 -> 262.429 | AD14: =AB14*AD$12 -> 209.9432 | AE14: =AB14/AE$12 -> 218.69083 | AF14: =AE14/AF$12 -> 72.896944 | AG14: =AB14/AG$12 -> 218.69083 | AH14: =SUM(AB14:AG14) -> 3606.9408 | AN14: =((AA14*AN$12)+(AA14*AC$12)+(AA14*AD$12))*AI14 -> 0 | AO14: =((AA14*AO$12)+(AA14*AC$12)+(AA14*AD$12))*AJ14 -> 0 | AP14: =((AA14*AP$12)+(AA14*AC$12)+(AA14*AD$12))*AK14 -> 0 | AQ14: =((AA14*AQ$6)+(AA14*AC$6)+(AA14*AD$6))*AL14 -> 0 | AR14: =((AA14*AR$12)+(AA14*AC$12)+(AA14*AD$12))*AM14 -> 0 | AS14: =SUM(AN14:AR14) -> 0 | AT14: 0 | AU14: =IF(Y14=1,($C$1*$W$6),0) -> 0 | AV14: =AH14+AS14+AT14+AU14 -> 3606.9408 | AW14: 0 | AX14: Valdeir Op. A | AY14: =AZ14/$AY$4 -> 11.928591 | AZ14: 2624.29 | BA14: =AZ14*BA$12 -> 262.429 | BB14: =AZ14*BB$12 -> 209.9432 | BC14: =AZ14/BC$12 -> 218.69083 | BD14: =BC14/BD$12 -> 72.896944 | BE14: =AZ14/BE$12 -> 218.69083 | BF14: =SUM(AZ14:BE14) -> 3606.9408 | BL14: =((AY14*BL$12)+(AY14*BA$12)+(AY14*BB$12))*BG14 -> 0 | BM14: =((AY14*BM$12)+(AY14*BA$12)+(AY14*BB$12))*BH14 -> 0 | BN14: =((AY14*BN$12)+(AY14*BA$12)+(AY14*BB$12))*BI14 -> 0 | BO14: =((AY14*BO$6)+(AY14*BA$6)+(AY14*BB$6))*BJ14 -> 0 | BP14: =((AY14*BP$12)+(AY14*BA$12)+(AY14*BB$12))*BK14 -> 0 | BQ14: =SUM(BL14:BP14) -> 0 | BR14: 0 | BS14: =IF(AW14=1,($C$1*$W$6),0) -> 0 | BT14: =BF14+BQ14+BR14+BS14 -> 3606.9408 | BU14: 0 | BV14: Valdeir Op. A | BW14: =BX14/$AY$4 -> 11.928591 | BX14: 2624.29 | BY14: =BX14*BY$12 -> 262.429 | BZ14: =BX14*BZ$12 -> 209.9432 | CA14: =BX14/CA$12 -> 218.69083 | CB14: =CA14/CB$12 -> 72.896944 | CC14: =BX14/CC$12 -> 218.69083 | CD14: =SUM(BX14:CC14) -> 3606.9408 | CJ14: =((BW14*CJ$12)+(BW14*BY$12)+(BW14*BZ$12))*CE14 -> 0 | CK14: =((BW14*CK$12)+(BW14*BY$12)+(BW14*BZ$12))*CF14 -> 0 | CL14: =((BW14*CL$12)+(BW14*BY$12)+(BW14*BZ$12))*CG14 -> 0 | CM14: =((BW14*CM$6)+(BW14*BY$6)+(BW14*BZ$6))*CH14 -> 0 | CN14: =((BW14*CN$12)+(BW14*BY$12)+(BW14*BZ$12))*CI14 -> 0 | CO14: =SUM(CJ14:CN14) -> 0 | CP14: 0 | CQ14: =IF(BU14=1,($C$1*$W$6),0) -> 0 | CR14: =CD14+CO14+CP14+CQ14 -> 3606.9408 | CS14: 0 | CT14: Valdeir Op. A | CU14: =CV14/$AY$4 -> 11.928591 | CV14: 2624.29 | CW14: =CV14*CW$12 -> 262.429 | CX14: =CV14*CX$12 -> 209.9432 | CY14: =CV14/CY$12 -> 218.69083 | CZ14: =CY14/CZ$12 -> 72.896944 | DA14: =CV14/DA$12 -> 218.69083 | DB14: =SUM(CV14:DA14) -> 3606.9408 | DH14: =((CU14*DH$12)+(CU14*CW$12)+(CU14*CX$12))*DC14 -> 0 | DI14: =((CU14*DI$12)+(CU14*CW$12)+(CU14*CX$12))*DD14 -> 0 | DJ14: =((CU14*DJ$12)+(CU14*CW$12)+(CU14*CX$12))*DE14 -> 0 | DK14: =((CU14*DK$6)+(CU14*CW$6)+(CU14*CX$6))*DF14 -> 0 | DL14: =((CU14*DL$12)+(CU14*CW$12)+(CU14*CX$12))*DG14 -> 0 | DM14: =SUM(DH14:DL14) -> 0 | DN14: 0 | DO14: =IF(CS14=1,($C$1*$W$6),0) -> 0 | DP14: =DB14+DM14+DN14+DO14 -> 3606.9408 | DQ14: 0 | DR14: Valdeir Op. A | DS14: =DT14/$AY$4 -> 11.928591 | DT14: 2624.29 | DU14: =DT14*DU$12 -> 262.429 | DV14: =DT14*DV$12 -> 209.9432 | DW14: =DT14/DW$12 -> 218.69083 | DX14: =DW14/DX$12 -> 72.896944 | DY14: =DT14/DY$12 -> 218.69083 | DZ14: =SUM(DT14:DY14) -> 3606.9408 | EF14: =((DS14*EF$12)+(DS14*DU$12)+(DS14*DV$12))*EA14 -> 0 | EG14: =((DS14*EG$12)+(DS14*DU$12)+(DS14*DV$12))*EB14 -> 0 | EH14: =((DS14*EH$12)+(DS14*DU$12)+(DS14*DV$12))*EC14 -> 0 | EI14: =((DS14*EI$6)+(DS14*DU$6)+(DS14*DV$6))*ED14 -> 0 | EJ14: =((DS14*EJ$12)+(DS14*DU$12)+(DS14*DV$12))*EE14 -> 0 | EK14: =SUM(EF14:EJ14) -> 0 | EL14: 0 | EM14: =IF(DQ14=1,($C$1*$W$6),0) -> 0 | EN14: =DZ14+EK14+EL14+EM14 -> 3606.9408 | EO14: 0 | EP14: Valdeir Op. A | EQ14: =ER14/$AY$4 -> 11.928591 | ER14: 2624.29 | ES14: =ER14*ES$12 -> 262.429 | ET14: =ER14*ET$12 -> 209.9432 | EU14: =ER14/EU$12 -> 218.69083 | EV14: =EU14/EV$12 -> 72.896944 | EW14: =ER14/EW$12 -> 218.69083 | EX14: =SUM(ER14:EW14) -> 3606.9408 | FD14: =((EQ14*FD$12)+(EQ14*ES$12)+(EQ14*ET$12))*EY14 -> 0 | FE14: =((EQ14*FE$12)+(EQ14*ES$12)+(EQ14*ET$12))*EZ14 -> 0 | FF14: =((EQ14*FF$12)+(EQ14*ES$12)+(EQ14*ET$12))*FA14 -> 0 | FG14: =((EQ14*FG$6)+(EQ14*ES$6)+(EQ14*ET$6))*FB14 -> 0 | FH14: =((EQ14*FH$12)+(EQ14*ES$12)+(EQ14*ET$12))*FC14 -> 0 | FI14: =SUM(FD14:FH14) -> 0 | FJ14: 0 | FK14: =IF(EO14=1,($C$1*$W$6),0) -> 0 | FL14: =EX14+FI14+FJ14+FK14 -> 3606.9408 | FM14: 0 | FN14: Valdeir Op. A | FO14: =FP14/$AY$4 -> 11.928591 | FP14: 2624.29 | FQ14: =FP14*FQ$12 -> 262.429 | FR14: =FP14*FR$12 -> 209.9432 | FS14: =FP14/FS$12 -> 218.69083 | FT14: =FS14/FT$12 -> 72.896944 | FU14: =FP14/FU$12 -> 218.69083 | FV14: =SUM(FP14:FU14) -> 3606.9408 | GB14: =((FO14*GB$12)+(FO14*FQ$12)+(FO14*FR$12))*FW14 -> 0 | GC14: =((FO14*GC$12)+(FO14*FQ$12)+(FO14*FR$12))*FX14 -> 0 | GD14: =((FO14*GD$12)+(FO14*FQ$12)+(FO14*FR$12))*FY14 -> 0 | GE14: =((FO14*GE$6)+(FO14*FQ$6)+(FO14*FR$6))*FZ14 -> 0 | GF14: =((FO14*GF$12)+(FO14*FQ$12)+(FO14*FR$12))*GA14 -> 0 | GG14: =SUM(GB14:GF14) -> 0 | GH14: 0 | GI14: =IF(FM14=1,($C$1*$W$6),0) -> 0 | GJ14: =FV14+GG14+GH14+GI14 -> 3606.9408 | GK14: 0 | GL14: Valdeir Op. A | GM14: =GN14/$AY$4 -> 11.928591 | GN14: 2624.29 | GO14: =GN14*GO$12 -> 262.429 | GP14: =GN14*GP$12 -> 209.9432 | GQ14: =GN14/GQ$12 -> 218.69083 | GR14: =GQ14/GR$12 -> 72.896944 | GS14: =GN14/GS$12 -> 218.69083 | GT14: =SUM(GN14:GS14) -> 3606.9408 | GZ14: =((GM14*GZ$12)+(GM14*GO$12)+(GM14*GP$12))*GU14 -> 0 | HA14: =((GM14*HA$12)+(GM14*GO$12)+(GM14*GP$12))*GV14 -> 0 | HB14: =((GM14*HB$12)+(GM14*GO$12)+(GM14*GP$12))*GW14 -> 0 | HC14: =((GM14*HC$6)+(GM14*GO$6)+(GM14*GP$6))*GX14 -> 0 | HD14: =((GM14*HD$12)+(GM14*GO$12)+(GM14*GP$12))*GY14 -> 0 | HE14: =SUM(GZ14:HD14) -> 0 | HF14: 0 | HG14: =IF(GK14=1,($C$1*$W$6),0) -> 0 | HH14: =GT14+HE14+HF14+HG14 -> 3606.9408 | HI14: 0 | HJ14: Valdeir Op. A | HK14: =HL14/$AY$4 -> 11.928591 | HL14: 2624.29 | HM14: =HL14*HM$12 -> 262.429 | HN14: =HL14*HN$12 -> 209.9432 | HO14: =HL14/HO$12 -> 218.69083 | HP14: =HO14/HP$12 -> 72.896944 | HQ14: =HL14/HQ$12 -> 218.69083 | HR14: =SUM(HL14:HQ14) -> 3606.9408 | HX14: =((HK14*HX$12)+(HK14*HM$12)+(HK14*HN$12))*HS14 -> 0 | HY14: =((HK14*HY$12)+(HK14*HM$12)+(HK14*HN$12))*HT14 -> 0 | HZ14: =((HK14*HZ$12)+(HK14*HM$12)+(HK14*HN$12))*HU14 -> 0 | IA14: =((HK14*IA$6)+(HK14*HM$6)+(HK14*HN$6))*HV14 -> 0 | IB14: =((HK14*IB$12)+(HK14*HM$12)+(HK14*HN$12))*HW14 -> 0 | IC14: =SUM(HX14:IB14) -> 0 | ID14: 0 | IE14: =IF(HI14=1,($C$1*$W$6),0) -> 0 | IF14: =HR14+IC14+ID14+IE14 -> 3606.9408 | IG14: 0 | IH14: Valdeir Op. A | II14: =IJ14/$AY$4 -> 11.928591 | IJ14: 2624.29 | IK14: =IJ14*IK$12 -> 262.429 | IL14: =IJ14*IL$12 -> 209.9432 | IM14: =IJ14/IM$12 -> 218.69083 | IN14: =IM14/IN$12 -> 72.896944 | IO14: =IJ14/IO$12 -> 218.69083 | IP14: =SUM(IJ14:IO14) -> 3606.9408 | IV14: =((II14*IV$12)+(II14*IK$12)+(II14*IL$12))*IQ14 -> 0 | IW14: =((II14*IW$12)+(II14*IK$12)+(II14*IL$12))*IR14 -> 0 | IX14: =((II14*IX$12)+(II14*IK$12)+(II14*IL$12))*IS14 -> 0 | IY14: =((II14*IY$6)+(II14*IK$6)+(II14*IL$6))*IT14 -> 0 | IZ14: =((II14*IZ$12)+(II14*IK$12)+(II14*IL$12))*IU14 -> 0 | JA14: =SUM(IV14:IZ14) -> 0 | JB14: 0 | JC14: =IF(IG14=1,($C$1*$W$6),0) -> 0 | JD14: =IP14+JA14+JB14+JC14 -> 3606.9408 | JE14: 0 | JF14: Valdeir Op. A | JG14: =JH14/$AY$4 -> 11.928591 | JH14: 2624.29 | JI14: =JH14*JI$12 -> 262.429 | JJ14: =JH14*JJ$12 -> 209.9432 | JK14: =JH14/JK$12 -> 218.69083 | JL14: =JK14/JL$12 -> 72.896944 | JM14: =JH14/JM$12 -> 218.69083 | JN14: =SUM(JH14:JM14) -> 3606.9408 | JT14: =((JG14*JT$12)+(JG14*JI$12)+(JG14*JJ$12))*JO14 -> 0 | JU14: =((JG14*JU$12)+(JG14*JI$12)+(JG14*JJ$12))*JP14 -> 0 | JV14: =((JG14*JV$12)+(JG14*JI$12)+(JG14*JJ$12))*JQ14 -> 0 | JW14: =((JG14*JW$6)+(JG14*JI$6)+(JG14*JJ$6))*JR14 -> 0 | JX14: =((JG14*JX$12)+(JG14*JI$12)+(JG14*JJ$12))*JS14 -> 0 | JY14: =SUM(JT14:JX14) -> 0 | JZ14: 0 | KA14: =IF(JE14=1,($C$1*$W$6),0) -> 0 | KB14: =JN14+JY14+JZ14+KA14 -> 3606.9408
A15: 0 | B15: Claudio Operador A | C15: =D15/$AY$4 -> 5.9642727 | D15: 1312.14 | E15: =D15*E$12 -> 131.214 | F15: =D15*F$12 -> 104.9712 | G15: =D15/G$12 -> 109.345 | H15: =G15/H$12 -> 36.448333 | I15: =D15/I$12 -> 109.345 | J15: =SUM(D15:I15) -> 1803.4635 | P15: =((C15*P$12)+(C15*E$12)+(C15*F$12))*K15 -> 0 | Q15: =((C15*Q$12)+(C15*E$12)+(C15*F$12))*L15 -> 0 | R15: =((C15*R$12)+(C15*E$12)+(C15*F$12))*M15 -> 0 | S15: =((C15*S$6)+(C15*E$6)+(C15*F$6))*N15 -> 0 | T15: =((C15*T$12)+(C15*E$12)+(C15*F$12))*O15 -> 0 | U15: =SUM(P15:T15) -> 0 | V15: 0 | W15: =IF(A15=1,($C$1*$W$6),0) -> 0 | X15: =J15+U15+V15+W15 -> 1803.4635 | Y15: 0 | Z15: Claudio Operador A | AA15: =AB15/$AY$4 -> 5.9642727 | AB15: 1312.14 | AC15: =AB15*AC$12 -> 131.214 | AD15: =AB15*AD$12 -> 104.9712 | AE15: =AB15/AE$12 -> 109.345 | AF15: =AE15/AF$12 -> 36.448333 | AG15: =AB15/AG$12 -> 109.345 | AH15: =SUM(AB15:AG15) -> 1803.4635 | AN15: =((AA15*AN$12)+(AA15*AC$12)+(AA15*AD$12))*AI15 -> 0 | AO15: =((AA15*AO$12)+(AA15*AC$12)+(AA15*AD$12))*AJ15 -> 0 | AP15: =((AA15*AP$12)+(AA15*AC$12)+(AA15*AD$12))*AK15 -> 0 | AQ15: =((AA15*AQ$6)+(AA15*AC$6)+(AA15*AD$6))*AL15 -> 0 | AR15: =((AA15*AR$12)+(AA15*AC$12)+(AA15*AD$12))*AM15 -> 0 | AS15: =SUM(AN15:AR15) -> 0 | AT15: 0 | AU15: =IF(Y15=1,($C$1*$W$6),0) -> 0 | AV15: =AH15+AS15+AT15+AU15 -> 1803.4635 | AW15: 0 | AX15: Claudio Operador A | AY15: =AZ15/$AY$4 -> 5.9642727 | AZ15: 1312.14 | BA15: =AZ15*BA$12 -> 131.214 | BB15: =AZ15*BB$12 -> 104.9712 | BC15: =AZ15/BC$12 -> 109.345 | BD15: =BC15/BD$12 -> 36.448333 | BE15: =AZ15/BE$12 -> 109.345 | BF15: =SUM(AZ15:BE15) -> 1803.4635 | BL15: =((AY15*BL$12)+(AY15*BA$12)+(AY15*BB$12))*BG15 -> 0 | BM15: =((AY15*BM$12)+(AY15*BA$12)+(AY15*BB$12))*BH15 -> 0 | BN15: =((AY15*BN$12)+(AY15*BA$12)+(AY15*BB$12))*BI15 -> 0 | BO15: =((AY15*BO$6)+(AY15*BA$6)+(AY15*BB$6))*BJ15 -> 0 | BP15: =((AY15*BP$12)+(AY15*BA$12)+(AY15*BB$12))*BK15 -> 0 | BQ15: =SUM(BL15:BP15) -> 0 | BR15: 0 | BS15: =IF(AW15=1,($C$1*$W$6),0) -> 0 | BT15: =BF15+BQ15+BR15+BS15 -> 1803.4635 | BU15: 0 | BV15: Claudio Operador A | BW15: =BX15/$AY$4 -> 5.9642727 | BX15: 1312.14 | BY15: =BX15*BY$12 -> 131.214 | BZ15: =BX15*BZ$12 -> 104.9712 | CA15: =BX15/CA$12 -> 109.345 | CB15: =CA15/CB$12 -> 36.448333 | CC15: =BX15/CC$12 -> 109.345 | CD15: =SUM(BX15:CC15) -> 1803.4635 | CJ15: =((BW15*CJ$12)+(BW15*BY$12)+(BW15*BZ$12))*CE15 -> 0 | CK15: =((BW15*CK$12)+(BW15*BY$12)+(BW15*BZ$12))*CF15 -> 0 | CL15: =((BW15*CL$12)+(BW15*BY$12)+(BW15*BZ$12))*CG15 -> 0 | CM15: =((BW15*CM$6)+(BW15*BY$6)+(BW15*BZ$6))*CH15 -> 0 | CN15: =((BW15*CN$12)+(BW15*BY$12)+(BW15*BZ$12))*CI15 -> 0 | CO15: =SUM(CJ15:CN15) -> 0 | CP15: 0 | CQ15: =IF(BU15=1,($C$1*$W$6),0) -> 0 | CR15: =CD15+CO15+CP15+CQ15 -> 1803.4635 | CS15: 0 | CT15: Claudio Operador A | CU15: =CV15/$AY$4 -> 5.9642727 | CV15: 1312.14 | CW15: =CV15*CW$12 -> 131.214 | CX15: =CV15*CX$12 -> 104.9712 | CY15: =CV15/CY$12 -> 109.345 | CZ15: =CY15/CZ$12 -> 36.448333 | DA15: =CV15/DA$12 -> 109.345 | DB15: =SUM(CV15:DA15) -> 1803.4635 | DH15: =((CU15*DH$12)+(CU15*CW$12)+(CU15*CX$12))*DC15 -> 0 | DI15: =((CU15*DI$12)+(CU15*CW$12)+(CU15*CX$12))*DD15 -> 0 | DJ15: =((CU15*DJ$12)+(CU15*CW$12)+(CU15*CX$12))*DE15 -> 0 | DK15: =((CU15*DK$6)+(CU15*CW$6)+(CU15*CX$6))*DF15 -> 0 | DL15: =((CU15*DL$12)+(CU15*CW$12)+(CU15*CX$12))*DG15 -> 0 | DM15: =SUM(DH15:DL15) -> 0 | DN15: 0 | DO15: =IF(CS15=1,($C$1*$W$6),0) -> 0 | DP15: =DB15+DM15+DN15+DO15 -> 1803.4635 | DQ15: 0 | DR15: Claudio Operador A | DS15: =DT15/$AY$4 -> 5.9642727 | DT15: 1312.14 | DU15: =DT15*DU$12 -> 131.214 | DV15: =DT15*DV$12 -> 104.9712 | DW15: =DT15/DW$12 -> 109.345 | DX15: =DW15/DX$12 -> 36.448333 | DY15: =DT15/DY$12 -> 109.345 | DZ15: =SUM(DT15:DY15) -> 1803.4635 | EF15: =((DS15*EF$12)+(DS15*DU$12)+(DS15*DV$12))*EA15 -> 0 | EG15: =((DS15*EG$12)+(DS15*DU$12)+(DS15*DV$12))*EB15 -> 0 | EH15: =((DS15*EH$12)+(DS15*DU$12)+(DS15*DV$12))*EC15 -> 0 | EI15: =((DS15*EI$6)+(DS15*DU$6)+(DS15*DV$6))*ED15 -> 0 | EJ15: =((DS15*EJ$12)+(DS15*DU$12)+(DS15*DV$12))*EE15 -> 0 | EK15: =SUM(EF15:EJ15) -> 0 | EL15: 0 | EM15: =IF(DQ15=1,($C$1*$W$6),0) -> 0 | EN15: =DZ15+EK15+EL15+EM15 -> 1803.4635 | EO15: 0 | EP15: Claudio Operador A | EQ15: =ER15/$AY$4 -> 5.9642727 | ER15: 1312.14 | ES15: =ER15*ES$12 -> 131.214 | ET15: =ER15*ET$12 -> 104.9712 | EU15: =ER15/EU$12 -> 109.345 | EV15: =EU15/EV$12 -> 36.448333 | EW15: =ER15/EW$12 -> 109.345 | EX15: =SUM(ER15:EW15) -> 1803.4635 | FD15: =((EQ15*FD$12)+(EQ15*ES$12)+(EQ15*ET$12))*EY15 -> 0 | FE15: =((EQ15*FE$12)+(EQ15*ES$12)+(EQ15*ET$12))*EZ15 -> 0 | FF15: =((EQ15*FF$12)+(EQ15*ES$12)+(EQ15*ET$12))*FA15 -> 0 | FG15: =((EQ15*FG$6)+(EQ15*ES$6)+(EQ15*ET$6))*FB15 -> 0 | FH15: =((EQ15*FH$12)+(EQ15*ES$12)+(EQ15*ET$12))*FC15 -> 0 | FI15: =SUM(FD15:FH15) -> 0 | FJ15: 0 | FK15: =IF(EO15=1,($C$1*$W$6),0) -> 0 | FL15: =EX15+FI15+FJ15+FK15 -> 1803.4635 | FM15: 0 | FN15: Claudio Operador A | FO15: =FP15/$AY$4 -> 5.9642727 | FP15: 1312.14 | FQ15: =FP15*FQ$12 -> 131.214 | FR15: =FP15*FR$12 -> 104.9712 | FS15: =FP15/FS$12 -> 109.345 | FT15: =FS15/FT$12 -> 36.448333 | FU15: =FP15/FU$12 -> 109.345 | FV15: =SUM(FP15:FU15) -> 1803.4635 | GB15: =((FO15*GB$12)+(FO15*FQ$12)+(FO15*FR$12))*FW15 -> 0 | GC15: =((FO15*GC$12)+(FO15*FQ$12)+(FO15*FR$12))*FX15 -> 0 | GD15: =((FO15*GD$12)+(FO15*FQ$12)+(FO15*FR$12))*FY15 -> 0 | GE15: =((FO15*GE$6)+(FO15*FQ$6)+(FO15*FR$6))*FZ15 -> 0 | GF15: =((FO15*GF$12)+(FO15*FQ$12)+(FO15*FR$12))*GA15 -> 0 | GG15: =SUM(GB15:GF15) -> 0 | GH15: 0 | GI15: =IF(FM15=1,($C$1*$W$6),0) -> 0 | GJ15: =FV15+GG15+GH15+GI15 -> 1803.4635 | GK15: 0 | GL15: Claudio Operador A | GM15: =GN15/$AY$4 -> 5.9642727 | GN15: 1312.14 | GO15: =GN15*GO$12 -> 131.214 | GP15: =GN15*GP$12 -> 104.9712 | GQ15: =GN15/GQ$12 -> 109.345 | GR15: =GQ15/GR$12 -> 36.448333 | GS15: =GN15/GS$12 -> 109.345 | GT15: =SUM(GN15:GS15) -> 1803.4635 | GZ15: =((GM15*GZ$12)+(GM15*GO$12)+(GM15*GP$12))*GU15 -> 0 | HA15: =((GM15*HA$12)+(GM15*GO$12)+(GM15*GP$12))*GV15 -> 0 | HB15: =((GM15*HB$12)+(GM15*GO$12)+(GM15*GP$12))*GW15 -> 0 | HC15: =((GM15*HC$6)+(GM15*GO$6)+(GM15*GP$6))*GX15 -> 0 | HD15: =((GM15*HD$12)+(GM15*GO$12)+(GM15*GP$12))*GY15 -> 0 | HE15: =SUM(GZ15:HD15) -> 0 | HF15: 0 | HG15: =IF(GK15=1,($C$1*$W$6),0) -> 0 | HH15: =GT15+HE15+HF15+HG15 -> 1803.4635 | HI15: 0 | HJ15: Claudio Operador A | HK15: =HL15/$AY$4 -> 5.9642727 | HL15: 1312.14 | HM15: =HL15*HM$12 -> 131.214 | HN15: =HL15*HN$12 -> 104.9712 | HO15: =HL15/HO$12 -> 109.345 | HP15: =HO15/HP$12 -> 36.448333 | HQ15: =HL15/HQ$12 -> 109.345 | HR15: =SUM(HL15:HQ15) -> 1803.4635 | HX15: =((HK15*HX$12)+(HK15*HM$12)+(HK15*HN$12))*HS15 -> 0 | HY15: =((HK15*HY$12)+(HK15*HM$12)+(HK15*HN$12))*HT15 -> 0 | HZ15: =((HK15*HZ$12)+(HK15*HM$12)+(HK15*HN$12))*HU15 -> 0 | IA15: =((HK15*IA$6)+(HK15*HM$6)+(HK15*HN$6))*HV15 -> 0 | IB15: =((HK15*IB$12)+(HK15*HM$12)+(HK15*HN$12))*HW15 -> 0 | IC15: =SUM(HX15:IB15) -> 0 | ID15: 0 | IE15: =IF(HI15=1,($C$1*$W$6),0) -> 0 | IF15: =HR15+IC15+ID15+IE15 -> 1803.4635 | IG15: 0 | IH15: Claudio Operador A | II15: =IJ15/$AY$4 -> 5.9642727 | IJ15: 1312.14 | IK15: =IJ15*IK$12 -> 131.214 | IL15: =IJ15*IL$12 -> 104.9712 | IM15: =IJ15/IM$12 -> 109.345 | IN15: =IM15/IN$12 -> 36.448333 | IO15: =IJ15/IO$12 -> 109.345 | IP15: =SUM(IJ15:IO15) -> 1803.4635 | IV15: =((II15*IV$12)+(II15*IK$12)+(II15*IL$12))*IQ15 -> 0 | IW15: =((II15*IW$12)+(II15*IK$12)+(II15*IL$12))*IR15 -> 0 | IX15: =((II15*IX$12)+(II15*IK$12)+(II15*IL$12))*IS15 -> 0 | IY15: =((II15*IY$6)+(II15*IK$6)+(II15*IL$6))*IT15 -> 0 | IZ15: =((II15*IZ$12)+(II15*IK$12)+(II15*IL$12))*IU15 -> 0 | JA15: =SUM(IV15:IZ15) -> 0 | JB15: 0 | JC15: =IF(IG15=1,($C$1*$W$6),0) -> 0 | JD15: =IP15+JA15+JB15+JC15 -> 1803.4635 | JE15: 0 | JF15: Claudio Operador A | JG15: =JH15/$AY$4 -> 5.9642727 | JH15: 1312.14 | JI15: =JH15*JI$12 -> 131.214 | JJ15: =JH15*JJ$12 -> 104.9712 | JK15: =JH15/JK$12 -> 109.345 | JL15: =JK15/JL$12 -> 36.448333 | JM15: =JH15/JM$12 -> 109.345 | JN15: =SUM(JH15:JM15) -> 1803.4635 | JT15: =((JG15*JT$12)+(JG15*JI$12)+(JG15*JJ$12))*JO15 -> 0 | JU15: =((JG15*JU$12)+(JG15*JI$12)+(JG15*JJ$12))*JP15 -> 0 | JV15: =((JG15*JV$12)+(JG15*JI$12)+(JG15*JJ$12))*JQ15 -> 0 | JW15: =((JG15*JW$6)+(JG15*JI$6)+(JG15*JJ$6))*JR15 -> 0 | JX15: =((JG15*JX$12)+(JG15*JI$12)+(JG15*JJ$12))*JS15 -> 0 | JY15: =SUM(JT15:JX15) -> 0 | JZ15: 0 | KA15: =IF(JE15=1,($C$1*$W$6),0) -> 0 | KB15: =JN15+JY15+JZ15+KA15 -> 1803.4635
A16: 0 | C16: =D16/$AY$4 -> 0 | D16: 0 | E16: =D16*E$12 -> 0 | F16: =D16*F$12 -> 0 | G16: =D16/G$12 -> 0 | H16: =G16/H$12 -> 0 | I16: =D16/I$12 -> 0 | J16: =SUM(D16:I16) -> 0 | P16: =((C16*P$12)+(C16*E$12)+(C16*F$12))*K16 -> 0 | Q16: =((C16*Q$12)+(C16*E$12)+(C16*F$12))*L16 -> 0 | R16: =((C16*R$12)+(C16*E$12)+(C16*F$12))*M16 -> 0 | S16: =((C16*S$6)+(C16*E$6)+(C16*F$6))*N16 -> 0 | T16: =((C16*T$12)+(C16*E$12)+(C16*F$12))*O16 -> 0 | U16: =SUM(P16:T16) -> 0 | V16: 0 | W16: =IF(A16=1,($C$1*$W$6),0) -> 0 | X16: =J16+U16+V16+W16 -> 0 | Y16: 0 | AA16: =AB16/$AY$4 -> 0 | AB16: 0 | AC16: =AB16*AC$12 -> 0 | AD16: =AB16*AD$12 -> 0 | AE16: =AB16/AE$12 -> 0 | AF16: =AE16/AF$12 -> 0 | AG16: =AB16/AG$12 -> 0 | AH16: =SUM(AB16:AG16) -> 0 | AN16: =((AA16*AN$12)+(AA16*AC$12)+(AA16*AD$12))*AI16 -> 0 | AO16: =((AA16*AO$12)+(AA16*AC$12)+(AA16*AD$12))*AJ16 -> 0 | AP16: =((AA16*AP$12)+(AA16*AC$12)+(AA16*AD$12))*AK16 -> 0 | AQ16: =((AA16*AQ$6)+(AA16*AC$6)+(AA16*AD$6))*AL16 -> 0 | AR16: =((AA16*AR$12)+(AA16*AC$12)+(AA16*AD$12))*AM16 -> 0 | AS16: =SUM(AN16:AR16) -> 0 | AT16: 0 | AU16: =IF(Y16=1,($C$1*$W$6),0) -> 0 | AV16: =AH16+AS16+AT16+AU16 -> 0 | AW16: 0 | AY16: =AZ16/$AY$4 -> 0 | AZ16: 0 | BA16: =AZ16*BA$12 -> 0 | BB16: =AZ16*BB$12 -> 0 | BC16: =AZ16/BC$12 -> 0 | BD16: =BC16/BD$12 -> 0 | BE16: =AZ16/BE$12 -> 0 | BF16: =SUM(AZ16:BE16) -> 0 | BL16: =((AY16*BL$12)+(AY16*BA$12)+(AY16*BB$12))*BG16 -> 0 | BM16: =((AY16*BM$12)+(AY16*BA$12)+(AY16*BB$12))*BH16 -> 0 | BN16: =((AY16*BN$12)+(AY16*BA$12)+(AY16*BB$12))*BI16 -> 0 | BO16: =((AY16*BO$6)+(AY16*BA$6)+(AY16*BB$6))*BJ16 -> 0 | BP16: =((AY16*BP$12)+(AY16*BA$12)+(AY16*BB$12))*BK16 -> 0 | BQ16: =SUM(BL16:BP16) -> 0 | BR16: 0 | BS16: =IF(AW16=1,($C$1*$W$6),0) -> 0 | BT16: =BF16+BQ16+BR16+BS16 -> 0 | BU16: 0 | BW16: =BX16/$AY$4 -> 0 | BX16: 0 | BY16: =BX16*BY$12 -> 0 | BZ16: =BX16*BZ$12 -> 0 | CA16: =BX16/CA$12 -> 0 | CB16: =CA16/CB$12 -> 0 | CC16: =BX16/CC$12 -> 0 | CD16: =SUM(BX16:CC16) -> 0 | CJ16: =((BW16*CJ$12)+(BW16*BY$12)+(BW16*BZ$12))*CE16 -> 0 | CK16: =((BW16*CK$12)+(BW16*BY$12)+(BW16*BZ$12))*CF16 -> 0 | CL16: =((BW16*CL$12)+(BW16*BY$12)+(BW16*BZ$12))*CG16 -> 0 | CM16: =((BW16*CM$6)+(BW16*BY$6)+(BW16*BZ$6))*CH16 -> 0 | CN16: =((BW16*CN$12)+(BW16*BY$12)+(BW16*BZ$12))*CI16 -> 0 | CO16: =SUM(CJ16:CN16) -> 0 | CP16: 0 | CQ16: =IF(BU16=1,($C$1*$W$6),0) -> 0 | CR16: =CD16+CO16+CP16+CQ16 -> 0 | CS16: 0 | CU16: =CV16/$AY$4 -> 0 | CV16: 0 | CW16: =CV16*CW$12 -> 0 | CX16: =CV16*CX$12 -> 0 | CY16: =CV16/CY$12 -> 0 | CZ16: =CY16/CZ$12 -> 0 | DA16: =CV16/DA$12 -> 0 | DB16: =SUM(CV16:DA16) -> 0 | DH16: =((CU16*DH$12)+(CU16*CW$12)+(CU16*CX$12))*DC16 -> 0 | DI16: =((CU16*DI$12)+(CU16*CW$12)+(CU16*CX$12))*DD16 -> 0 | DJ16: =((CU16*DJ$12)+(CU16*CW$12)+(CU16*CX$12))*DE16 -> 0 | DK16: =((CU16*DK$6)+(CU16*CW$6)+(CU16*CX$6))*DF16 -> 0 | DL16: =((CU16*DL$12)+(CU16*CW$12)+(CU16*CX$12))*DG16 -> 0 | DM16: =SUM(DH16:DL16) -> 0 | DN16: 0 | DO16: =IF(CS16=1,($C$1*$W$6),0) -> 0 | DP16: =DB16+DM16+DN16+DO16 -> 0 | DQ16: 0 | DS16: =DT16/$AY$4 -> 0 | DT16: 0 | DU16: =DT16*DU$12 -> 0 | DV16: =DT16*DV$12 -> 0 | DW16: =DT16/DW$12 -> 0 | DX16: =DW16/DX$12 -> 0 | DY16: =DT16/DY$12 -> 0 | DZ16: =SUM(DT16:DY16) -> 0 | EF16: =((DS16*EF$12)+(DS16*DU$12)+(DS16*DV$12))*EA16 -> 0 | EG16: =((DS16*EG$12)+(DS16*DU$12)+(DS16*DV$12))*EB16 -> 0 | EH16: =((DS16*EH$12)+(DS16*DU$12)+(DS16*DV$12))*EC16 -> 0 | EI16: =((DS16*EI$6)+(DS16*DU$6)+(DS16*DV$6))*ED16 -> 0 | EJ16: =((DS16*EJ$12)+(DS16*DU$12)+(DS16*DV$12))*EE16 -> 0 | EK16: =SUM(EF16:EJ16) -> 0 | EL16: 0 | EM16: =IF(DQ16=1,($C$1*$W$6),0) -> 0 | EN16: =DZ16+EK16+EL16+EM16 -> 0 | EO16: 0 | EQ16: =ER16/$AY$4 -> 0 | ER16: 0 | ES16: =ER16*ES$12 -> 0 | ET16: =ER16*ET$12 -> 0 | EU16: =ER16/EU$12 -> 0 | EV16: =EU16/EV$12 -> 0 | EW16: =ER16/EW$12 -> 0 | EX16: =SUM(ER16:EW16) -> 0 | FD16: =((EQ16*FD$12)+(EQ16*ES$12)+(EQ16*ET$12))*EY16 -> 0 | FE16: =((EQ16*FE$12)+(EQ16*ES$12)+(EQ16*ET$12))*EZ16 -> 0 | FF16: =((EQ16*FF$12)+(EQ16*ES$12)+(EQ16*ET$12))*FA16 -> 0 | FG16: =((EQ16*FG$6)+(EQ16*ES$6)+(EQ16*ET$6))*FB16 -> 0 | FH16: =((EQ16*FH$12)+(EQ16*ES$12)+(EQ16*ET$12))*FC16 -> 0 | FI16: =SUM(FD16:FH16) -> 0 | FJ16: 0 | FK16: =IF(EO16=1,($C$1*$W$6),0) -> 0 | FL16: =EX16+FI16+FJ16+FK16 -> 0 | FM16: 0 | FO16: =FP16/$AY$4 -> 0 | FP16: 0 | FQ16: =FP16*FQ$12 -> 0 | FR16: =FP16*FR$12 -> 0 | FS16: =FP16/FS$12 -> 0 | FT16: =FS16/FT$12 -> 0 | FU16: =FP16/FU$12 -> 0 | FV16: =SUM(FP16:FU16) -> 0 | GB16: =((FO16*GB$12)+(FO16*FQ$12)+(FO16*FR$12))*FW16 -> 0 | GC16: =((FO16*GC$12)+(FO16*FQ$12)+(FO16*FR$12))*FX16 -> 0 | GD16: =((FO16*GD$12)+(FO16*FQ$12)+(FO16*FR$12))*FY16 -> 0 | GE16: =((FO16*GE$6)+(FO16*FQ$6)+(FO16*FR$6))*FZ16 -> 0 | GF16: =((FO16*GF$12)+(FO16*FQ$12)+(FO16*FR$12))*GA16 -> 0 | GG16: =SUM(GB16:GF16) -> 0 | GH16: 0 | GI16: =IF(FM16=1,($C$1*$W$6),0) -> 0 | GJ16: =FV16+GG16+GH16+GI16 -> 0 | GK16: 0 | GM16: =GN16/$AY$4 -> 0 | GN16: 0 | GO16: =GN16*GO$12 -> 0 | GP16: =GN16*GP$12 -> 0 | GQ16: =GN16/GQ$12 -> 0 | GR16: =GQ16/GR$12 -> 0 | GS16: =GN16/GS$12 -> 0 | GT16: =SUM(GN16:GS16) -> 0 | GZ16: =((GM16*GZ$12)+(GM16*GO$12)+(GM16*GP$12))*GU16 -> 0 | HA16: =((GM16*HA$12)+(GM16*GO$12)+(GM16*GP$12))*GV16 -> 0 | HB16: =((GM16*HB$12)+(GM16*GO$12)+(GM16*GP$12))*GW16 -> 0 | HC16: =((GM16*HC$6)+(GM16*GO$6)+(GM16*GP$6))*GX16 -> 0 | HD16: =((GM16*HD$12)+(GM16*GO$12)+(GM16*GP$12))*GY16 -> 0 | HE16: =SUM(GZ16:HD16) -> 0 | HF16: 0 | HG16: =IF(GK16=1,($C$1*$W$6),0) -> 0 | HH16: =GT16+HE16+HF16+HG16 -> 0 | HI16: 0 | HK16: =HL16/$AY$4 -> 0 | HL16: 0 | HM16: =HL16*HM$12 -> 0 | HN16: =HL16*HN$12 -> 0 | HO16: =HL16/HO$12 -> 0 | HP16: =HO16/HP$12 -> 0 | HQ16: =HL16/HQ$12 -> 0 | HR16: =SUM(HL16:HQ16) -> 0 | HX16: =((HK16*HX$12)+(HK16*HM$12)+(HK16*HN$12))*HS16 -> 0 | HY16: =((HK16*HY$12)+(HK16*HM$12)+(HK16*HN$12))*HT16 -> 0 | HZ16: =((HK16*HZ$12)+(HK16*HM$12)+(HK16*HN$12))*HU16 -> 0 | IA16: =((HK16*IA$6)+(HK16*HM$6)+(HK16*HN$6))*HV16 -> 0 | IB16: =((HK16*IB$12)+(HK16*HM$12)+(HK16*HN$12))*HW16 -> 0 | IC16: =SUM(HX16:IB16) -> 0 | ID16: 0 | IE16: =IF(HI16=1,($C$1*$W$6),0) -> 0 | IF16: =HR16+IC16+ID16+IE16 -> 0 | IG16: 0 | II16: =IJ16/$AY$4 -> 0 | IJ16: 0 | IK16: =IJ16*IK$12 -> 0 | IL16: =IJ16*IL$12 -> 0 | IM16: =IJ16/IM$12 -> 0 | IN16: =IM16/IN$12 -> 0 | IO16: =IJ16/IO$12 -> 0 | IP16: =SUM(IJ16:IO16) -> 0 | IV16: =((II16*IV$12)+(II16*IK$12)+(II16*IL$12))*IQ16 -> 0 | IW16: =((II16*IW$12)+(II16*IK$12)+(II16*IL$12))*IR16 -> 0 | IX16: =((II16*IX$12)+(II16*IK$12)+(II16*IL$12))*IS16 -> 0 | IY16: =((II16*IY$6)+(II16*IK$6)+(II16*IL$6))*IT16 -> 0 | IZ16: =((II16*IZ$12)+(II16*IK$12)+(II16*IL$12))*IU16 -> 0 | JA16: =SUM(IV16:IZ16) -> 0 | JB16: 0 | JC16: =IF(IG16=1,($C$1*$W$6),0) -> 0 | JD16: =IP16+JA16+JB16+JC16 -> 0 | JE16: 0 | JG16: =JH16/$AY$4 -> 0 | JH16: 0 | JI16: =JH16*JI$12 -> 0 | JJ16: =JH16*JJ$12 -> 0 | JK16: =JH16/JK$12 -> 0 | JL16: =JK16/JL$12 -> 0 | JM16: =JH16/JM$12 -> 0 | JN16: =SUM(JH16:JM16) -> 0 | JT16: =((JG16*JT$12)+(JG16*JI$12)+(JG16*JJ$12))*JO16 -> 0 | JU16: =((JG16*JU$12)+(JG16*JI$12)+(JG16*JJ$12))*JP16 -> 0 | JV16: =((JG16*JV$12)+(JG16*JI$12)+(JG16*JJ$12))*JQ16 -> 0 | JW16: =((JG16*JW$6)+(JG16*JI$6)+(JG16*JJ$6))*JR16 -> 0 | JX16: =((JG16*JX$12)+(JG16*JI$12)+(JG16*JJ$12))*JS16 -> 0 | JY16: =SUM(JT16:JX16) -> 0 | JZ16: 0 | KA16: =IF(JE16=1,($C$1*$W$6),0) -> 0 | KB16: =JN16+JY16+JZ16+KA16 -> 0
A17: 0 | C17: =D17/$AY$4 -> 0 | D17: 0 | E17: =D17*E$12 -> 0 | F17: =D17*F$12 -> 0 | G17: =D17/G$12 -> 0 | H17: =G17/H$12 -> 0 | I17: =D17/I$12 -> 0 | J17: =SUM(D17:I17) -> 0 | P17: =((C17*P$12)+(C17*E$12)+(C17*F$12))*K17 -> 0 | Q17: =((C17*Q$12)+(C17*E$12)+(C17*F$12))*L17 -> 0 | R17: =((C17*R$12)+(C17*E$12)+(C17*F$12))*M17 -> 0 | S17: =((C17*S$6)+(C17*E$6)+(C17*F$6))*N17 -> 0 | T17: =((C17*T$12)+(C17*E$12)+(C17*F$12))*O17 -> 0 | U17: =SUM(P17:T17) -> 0 | V17: 0 | W17: =IF(A17=1,($C$1*$W$6),0) -> 0 | X17: =J17+U17+V17+W17 -> 0 | Y17: 0 | AA17: =AB17/$AY$4 -> 0 | AB17: 0 | AC17: =AB17*AC$12 -> 0 | AD17: =AB17*AD$12 -> 0 | AE17: =AB17/AE$12 -> 0 | AF17: =AE17/AF$12 -> 0 | AG17: =AB17/AG$12 -> 0 | AH17: =SUM(AB17:AG17) -> 0 | AN17: =((AA17*AN$12)+(AA17*AC$12)+(AA17*AD$12))*AI17 -> 0 | AO17: =((AA17*AO$12)+(AA17*AC$12)+(AA17*AD$12))*AJ17 -> 0 | AP17: =((AA17*AP$12)+(AA17*AC$12)+(AA17*AD$12))*AK17 -> 0 | AQ17: =((AA17*AQ$6)+(AA17*AC$6)+(AA17*AD$6))*AL17 -> 0 | AR17: =((AA17*AR$12)+(AA17*AC$12)+(AA17*AD$12))*AM17 -> 0 | AS17: =SUM(AN17:AR17) -> 0 | AT17: 0 | AU17: =IF(Y17=1,($C$1*$W$6),0) -> 0 | AV17: =AH17+AS17+AT17+AU17 -> 0 | AW17: 0 | AY17: =AZ17/$AY$4 -> 0 | AZ17: 0 | BA17: =AZ17*BA$12 -> 0 | BB17: =AZ17*BB$12 -> 0 | BC17: =AZ17/BC$12 -> 0 | BD17: =BC17/BD$12 -> 0 | BE17: =AZ17/BE$12 -> 0 | BF17: =SUM(AZ17:BE17) -> 0 | BL17: =((AY17*BL$12)+(AY17*BA$12)+(AY17*BB$12))*BG17 -> 0 | BM17: =((AY17*BM$12)+(AY17*BA$12)+(AY17*BB$12))*BH17 -> 0 | BN17: =((AY17*BN$12)+(AY17*BA$12)+(AY17*BB$12))*BI17 -> 0 | BO17: =((AY17*BO$6)+(AY17*BA$6)+(AY17*BB$6))*BJ17 -> 0 | BP17: =((AY17*BP$12)+(AY17*BA$12)+(AY17*BB$12))*BK17 -> 0 | BQ17: =SUM(BL17:BP17) -> 0 | BR17: 0 | BS17: =IF(AW17=1,($C$1*$W$6),0) -> 0 | BT17: =BF17+BQ17+BR17+BS17 -> 0 | BU17: 0 | BW17: =BX17/$AY$4 -> 0 | BX17: 0 | BY17: =BX17*BY$12 -> 0 | BZ17: =BX17*BZ$12 -> 0 | CA17: =BX17/CA$12 -> 0 | CB17: =CA17/CB$12 -> 0 | CC17: =BX17/CC$12 -> 0 | CD17: =SUM(BX17:CC17) -> 0 | CJ17: =((BW17*CJ$12)+(BW17*BY$12)+(BW17*BZ$12))*CE17 -> 0 | CK17: =((BW17*CK$12)+(BW17*BY$12)+(BW17*BZ$12))*CF17 -> 0 | CL17: =((BW17*CL$12)+(BW17*BY$12)+(BW17*BZ$12))*CG17 -> 0 | CM17: =((BW17*CM$6)+(BW17*BY$6)+(BW17*BZ$6))*CH17 -> 0 | CN17: =((BW17*CN$12)+(BW17*BY$12)+(BW17*BZ$12))*CI17 -> 0 | CO17: =SUM(CJ17:CN17) -> 0 | CP17: 0 | CQ17: =IF(BU17=1,($C$1*$W$6),0) -> 0 | CR17: =CD17+CO17+CP17+CQ17 -> 0 | CS17: 0 | CU17: =CV17/$AY$4 -> 0 | CV17: 0 | CW17: =CV17*CW$12 -> 0 | CX17: =CV17*CX$12 -> 0 | CY17: =CV17/CY$12 -> 0 | CZ17: =CY17/CZ$12 -> 0 | DA17: =CV17/DA$12 -> 0 | DB17: =SUM(CV17:DA17) -> 0 | DH17: =((CU17*DH$12)+(CU17*CW$12)+(CU17*CX$12))*DC17 -> 0 | DI17: =((CU17*DI$12)+(CU17*CW$12)+(CU17*CX$12))*DD17 -> 0 | DJ17: =((CU17*DJ$12)+(CU17*CW$12)+(CU17*CX$12))*DE17 -> 0 | DK17: =((CU17*DK$6)+(CU17*CW$6)+(CU17*CX$6))*DF17 -> 0 | DL17: =((CU17*DL$12)+(CU17*CW$12)+(CU17*CX$12))*DG17 -> 0 | DM17: =SUM(DH17:DL17) -> 0 | DN17: 0 | DO17: =IF(CS17=1,($C$1*$W$6),0) -> 0 | DP17: =DB17+DM17+DN17+DO17 -> 0 | DQ17: 0 | DS17: =DT17/$AY$4 -> 0 | DT17: 0 | DU17: =DT17*DU$12 -> 0 | DV17: =DT17*DV$12 -> 0 | DW17: =DT17/DW$12 -> 0 | DX17: =DW17/DX$12 -> 0 | DY17: =DT17/DY$12 -> 0 | DZ17: =SUM(DT17:DY17) -> 0 | EF17: =((DS17*EF$12)+(DS17*DU$12)+(DS17*DV$12))*EA17 -> 0 | EG17: =((DS17*EG$12)+(DS17*DU$12)+(DS17*DV$12))*EB17 -> 0 | EH17: =((DS17*EH$12)+(DS17*DU$12)+(DS17*DV$12))*EC17 -> 0 | EI17: =((DS17*EI$6)+(DS17*DU$6)+(DS17*DV$6))*ED17 -> 0 | EJ17: =((DS17*EJ$12)+(DS17*DU$12)+(DS17*DV$12))*EE17 -> 0 | EK17: =SUM(EF17:EJ17) -> 0 | EL17: 0 | EM17: =IF(DQ17=1,($C$1*$W$6),0) -> 0 | EN17: =DZ17+EK17+EL17+EM17 -> 0 | EO17: 0 | EQ17: =ER17/$AY$4 -> 0 | ER17: 0 | ES17: =ER17*ES$12 -> 0 | ET17: =ER17*ET$12 -> 0 | EU17: =ER17/EU$12 -> 0 | EV17: =EU17/EV$12 -> 0 | EW17: =ER17/EW$12 -> 0 | EX17: =SUM(ER17:EW17) -> 0 | FD17: =((EQ17*FD$12)+(EQ17*ES$12)+(EQ17*ET$12))*EY17 -> 0 | FE17: =((EQ17*FE$12)+(EQ17*ES$12)+(EQ17*ET$12))*EZ17 -> 0 | FF17: =((EQ17*FF$12)+(EQ17*ES$12)+(EQ17*ET$12))*FA17 -> 0 | FG17: =((EQ17*FG$6)+(EQ17*ES$6)+(EQ17*ET$6))*FB17 -> 0 | FH17: =((EQ17*FH$12)+(EQ17*ES$12)+(EQ17*ET$12))*FC17 -> 0 | FI17: =SUM(FD17:FH17) -> 0 | FJ17: 0 | FK17: =IF(EO17=1,($C$1*$W$6),0) -> 0 | FL17: =EX17+FI17+FJ17+FK17 -> 0 | FM17: 0 | FO17: =FP17/$AY$4 -> 0 | FP17: 0 | FQ17: =FP17*FQ$12 -> 0 | FR17: =FP17*FR$12 -> 0 | FS17: =FP17/FS$12 -> 0 | FT17: =FS17/FT$12 -> 0 | FU17: =FP17/FU$12 -> 0 | FV17: =SUM(FP17:FU17) -> 0 | GB17: =((FO17*GB$12)+(FO17*FQ$12)+(FO17*FR$12))*FW17 -> 0 | GC17: =((FO17*GC$12)+(FO17*FQ$12)+(FO17*FR$12))*FX17 -> 0 | GD17: =((FO17*GD$12)+(FO17*FQ$12)+(FO17*FR$12))*FY17 -> 0 | GE17: =((FO17*GE$6)+(FO17*FQ$6)+(FO17*FR$6))*FZ17 -> 0 | GF17: =((FO17*GF$12)+(FO17*FQ$12)+(FO17*FR$12))*GA17 -> 0 | GG17: =SUM(GB17:GF17) -> 0 | GH17: 0 | GI17: =IF(FM17=1,($C$1*$W$6),0) -> 0 | GJ17: =FV17+GG17+GH17+GI17 -> 0 | GK17: 0 | GM17: =GN17/$AY$4 -> 0 | GN17: 0 | GO17: =GN17*GO$12 -> 0 | GP17: =GN17*GP$12 -> 0 | GQ17: =GN17/GQ$12 -> 0 | GR17: =GQ17/GR$12 -> 0 | GS17: =GN17/GS$12 -> 0 | GT17: =SUM(GN17:GS17) -> 0 | GZ17: =((GM17*GZ$12)+(GM17*GO$12)+(GM17*GP$12))*GU17 -> 0 | HA17: =((GM17*HA$12)+(GM17*GO$12)+(GM17*GP$12))*GV17 -> 0 | HB17: =((GM17*HB$12)+(GM17*GO$12)+(GM17*GP$12))*GW17 -> 0 | HC17: =((GM17*HC$6)+(GM17*GO$6)+(GM17*GP$6))*GX17 -> 0 | HD17: =((GM17*HD$12)+(GM17*GO$12)+(GM17*GP$12))*GY17 -> 0 | HE17: =SUM(GZ17:HD17) -> 0 | HF17: 0 | HG17: =IF(GK17=1,($C$1*$W$6),0) -> 0 | HH17: =GT17+HE17+HF17+HG17 -> 0 | HI17: 0 | HK17: =HL17/$AY$4 -> 0 | HL17: 0 | HM17: =HL17*HM$12 -> 0 | HN17: =HL17*HN$12 -> 0 | HO17: =HL17/HO$12 -> 0 | HP17: =HO17/HP$12 -> 0 | HQ17: =HL17/HQ$12 -> 0 | HR17: =SUM(HL17:HQ17) -> 0 | HX17: =((HK17*HX$12)+(HK17*HM$12)+(HK17*HN$12))*HS17 -> 0 | HY17: =((HK17*HY$12)+(HK17*HM$12)+(HK17*HN$12))*HT17 -> 0 | HZ17: =((HK17*HZ$12)+(HK17*HM$12)+(HK17*HN$12))*HU17 -> 0 | IA17: =((HK17*IA$6)+(HK17*HM$6)+(HK17*HN$6))*HV17 -> 0 | IB17: =((HK17*IB$12)+(HK17*HM$12)+(HK17*HN$12))*HW17 -> 0 | IC17: =SUM(HX17:IB17) -> 0 | ID17: 0 | IE17: =IF(HI17=1,($C$1*$W$6),0) -> 0 | IF17: =HR17+IC17+ID17+IE17 -> 0 | IG17: 0 | II17: =IJ17/$AY$4 -> 0 | IJ17: 0 | IK17: =IJ17*IK$12 -> 0 | IL17: =IJ17*IL$12 -> 0 | IM17: =IJ17/IM$12 -> 0 | IN17: =IM17/IN$12 -> 0 | IO17: =IJ17/IO$12 -> 0 | IP17: =SUM(IJ17:IO17) -> 0 | IV17: =((II17*IV$12)+(II17*IK$12)+(II17*IL$12))*IQ17 -> 0 | IW17: =((II17*IW$12)+(II17*IK$12)+(II17*IL$12))*IR17 -> 0 | IX17: =((II17*IX$12)+(II17*IK$12)+(II17*IL$12))*IS17 -> 0 | IY17: =((II17*IY$6)+(II17*IK$6)+(II17*IL$6))*IT17 -> 0 | IZ17: =((II17*IZ$12)+(II17*IK$12)+(II17*IL$12))*IU17 -> 0 | JA17: =SUM(IV17:IZ17) -> 0 | JB17: 0 | JC17: =IF(IG17=1,($C$1*$W$6),0) -> 0 | JD17: =IP17+JA17+JB17+JC17 -> 0 | JE17: 0 | JG17: =JH17/$AY$4 -> 0 | JH17: 0 | JI17: =JH17*JI$12 -> 0 | JJ17: =JH17*JJ$12 -> 0 | JK17: =JH17/JK$12 -> 0 | JL17: =JK17/JL$12 -> 0 | JM17: =JH17/JM$12 -> 0 | JN17: =SUM(JH17:JM17) -> 0 | JT17: =((JG17*JT$12)+(JG17*JI$12)+(JG17*JJ$12))*JO17 -> 0 | JU17: =((JG17*JU$12)+(JG17*JI$12)+(JG17*JJ$12))*JP17 -> 0 | JV17: =((JG17*JV$12)+(JG17*JI$12)+(JG17*JJ$12))*JQ17 -> 0 | JW17: =((JG17*JW$6)+(JG17*JI$6)+(JG17*JJ$6))*JR17 -> 0 | JX17: =((JG17*JX$12)+(JG17*JI$12)+(JG17*JJ$12))*JS17 -> 0 | JY17: =SUM(JT17:JX17) -> 0 | JZ17: 0 | KA17: =IF(JE17=1,($C$1*$W$6),0) -> 0 | KB17: =JN17+JY17+JZ17+KA17 -> 0
A18: 0 | C18: =D18/$AY$4 -> 0 | D18: 0 | E18: =D18*E$12 -> 0 | F18: =D18*F$12 -> 0 | G18: =D18/G$12 -> 0 | H18: =G18/H$12 -> 0 | I18: =D18/I$12 -> 0 | J18: =SUM(D18:I18) -> 0 | P18: =((C18*P$12)+(C18*E$12)+(C18*F$12))*K18 -> 0 | Q18: =((C18*Q$12)+(C18*E$12)+(C18*F$12))*L18 -> 0 | R18: =((C18*R$12)+(C18*E$12)+(C18*F$12))*M18 -> 0 | S18: =((C18*S$6)+(C18*E$6)+(C18*F$6))*N18 -> 0 | T18: =((C18*T$12)+(C18*E$12)+(C18*F$12))*O18 -> 0 | U18: =SUM(P18:T18) -> 0 | V18: 0 | W18: =IF(A18=1,($C$1*$W$6),0) -> 0 | X18: =J18+U18+V18+W18 -> 0 | Y18: 0 | AA18: =AB18/$AY$4 -> 0 | AB18: 0 | AC18: =AB18*AC$12 -> 0 | AD18: =AB18*AD$12 -> 0 | AE18: =AB18/AE$12 -> 0 | AF18: =AE18/AF$12 -> 0 | AG18: =AB18/AG$12 -> 0 | AH18: =SUM(AB18:AG18) -> 0 | AN18: =((AA18*AN$12)+(AA18*AC$12)+(AA18*AD$12))*AI18 -> 0 | AO18: =((AA18*AO$12)+(AA18*AC$12)+(AA18*AD$12))*AJ18 -> 0 | AP18: =((AA18*AP$12)+(AA18*AC$12)+(AA18*AD$12))*AK18 -> 0 | AQ18: =((AA18*AQ$6)+(AA18*AC$6)+(AA18*AD$6))*AL18 -> 0 | AR18: =((AA18*AR$12)+(AA18*AC$12)+(AA18*AD$12))*AM18 -> 0 | AS18: =SUM(AN18:AR18) -> 0 | AT18: 0 | AU18: =IF(Y18=1,($C$1*$W$6),0) -> 0 | AV18: =AH18+AS18+AT18+AU18 -> 0 | AW18: 0 | AY18: =AZ18/$AY$4 -> 0 | AZ18: 0 | BA18: =AZ18*BA$12 -> 0 | BB18: =AZ18*BB$12 -> 0 | BC18: =AZ18/BC$12 -> 0 | BD18: =BC18/BD$12 -> 0 | BE18: =AZ18/BE$12 -> 0 | BF18: =SUM(AZ18:BE18) -> 0 | BL18: =((AY18*BL$12)+(AY18*BA$12)+(AY18*BB$12))*BG18 -> 0 | BM18: =((AY18*BM$12)+(AY18*BA$12)+(AY18*BB$12))*BH18 -> 0 | BN18: =((AY18*BN$12)+(AY18*BA$12)+(AY18*BB$12))*BI18 -> 0 | BO18: =((AY18*BO$6)+(AY18*BA$6)+(AY18*BB$6))*BJ18 -> 0 | BP18: =((AY18*BP$12)+(AY18*BA$12)+(AY18*BB$12))*BK18 -> 0 | BQ18: =SUM(BL18:BP18) -> 0 | BR18: 0 | BS18: =IF(AW18=1,($C$1*$W$6),0) -> 0 | BT18: =BF18+BQ18+BR18+BS18 -> 0 | BU18: 0 | BW18: =BX18/$AY$4 -> 0 | BX18: 0 | BY18: =BX18*BY$12 -> 0 | BZ18: =BX18*BZ$12 -> 0 | CA18: =BX18/CA$12 -> 0 | CB18: =CA18/CB$12 -> 0 | CC18: =BX18/CC$12 -> 0 | CD18: =SUM(BX18:CC18) -> 0 | CJ18: =((BW18*CJ$12)+(BW18*BY$12)+(BW18*BZ$12))*CE18 -> 0 | CK18: =((BW18*CK$12)+(BW18*BY$12)+(BW18*BZ$12))*CF18 -> 0 | CL18: =((BW18*CL$12)+(BW18*BY$12)+(BW18*BZ$12))*CG18 -> 0 | CM18: =((BW18*CM$6)+(BW18*BY$6)+(BW18*BZ$6))*CH18 -> 0 | CN18: =((BW18*CN$12)+(BW18*BY$12)+(BW18*BZ$12))*CI18 -> 0 | CO18: =SUM(CJ18:CN18) -> 0 | CP18: 0 | CQ18: =IF(BU18=1,($C$1*$W$6),0) -> 0 | CR18: =CD18+CO18+CP18+CQ18 -> 0 | CS18: 0 | CU18: =CV18/$AY$4 -> 0 | CV18: 0 | CW18: =CV18*CW$12 -> 0 | CX18: =CV18*CX$12 -> 0 | CY18: =CV18/CY$12 -> 0 | CZ18: =CY18/CZ$12 -> 0 | DA18: =CV18/DA$12 -> 0 | DB18: =SUM(CV18:DA18) -> 0 | DH18: =((CU18*DH$12)+(CU18*CW$12)+(CU18*CX$12))*DC18 -> 0 | DI18: =((CU18*DI$12)+(CU18*CW$12)+(CU18*CX$12))*DD18 -> 0 | DJ18: =((CU18*DJ$12)+(CU18*CW$12)+(CU18*CX$12))*DE18 -> 0 | DK18: =((CU18*DK$6)+(CU18*CW$6)+(CU18*CX$6))*DF18 -> 0 | DL18: =((CU18*DL$12)+(CU18*CW$12)+(CU18*CX$12))*DG18 -> 0 | DM18: =SUM(DH18:DL18) -> 0 | DN18: 0 | DO18: =IF(CS18=1,($C$1*$W$6),0) -> 0 | DP18: =DB18+DM18+DN18+DO18 -> 0 | DQ18: 0 | DS18: =DT18/$AY$4 -> 0 | DT18: 0 | DU18: =DT18*DU$12 -> 0 | DV18: =DT18*DV$12 -> 0 | DW18: =DT18/DW$12 -> 0 | DX18: =DW18/DX$12 -> 0 | DY18: =DT18/DY$12 -> 0 | DZ18: =SUM(DT18:DY18) -> 0 | EF18: =((DS18*EF$12)+(DS18*DU$12)+(DS18*DV$12))*EA18 -> 0 | EG18: =((DS18*EG$12)+(DS18*DU$12)+(DS18*DV$12))*EB18 -> 0 | EH18: =((DS18*EH$12)+(DS18*DU$12)+(DS18*DV$12))*EC18 -> 0 | EI18: =((DS18*EI$6)+(DS18*DU$6)+(DS18*DV$6))*ED18 -> 0 | EJ18: =((DS18*EJ$12)+(DS18*DU$12)+(DS18*DV$12))*EE18 -> 0 | EK18: =SUM(EF18:EJ18) -> 0 | EL18: 0 | EM18: =IF(DQ18=1,($C$1*$W$6),0) -> 0 | EN18: =DZ18+EK18+EL18+EM18 -> 0 | EO18: 0 | EQ18: =ER18/$AY$4 -> 0 | ER18: 0 | ES18: =ER18*ES$12 -> 0 | ET18: =ER18*ET$12 -> 0 | EU18: =ER18/EU$12 -> 0 | EV18: =EU18/EV$12 -> 0 | EW18: =ER18/EW$12 -> 0 | EX18: =SUM(ER18:EW18) -> 0 | FD18: =((EQ18*FD$12)+(EQ18*ES$12)+(EQ18*ET$12))*EY18 -> 0 | FE18: =((EQ18*FE$12)+(EQ18*ES$12)+(EQ18*ET$12))*EZ18 -> 0 | FF18: =((EQ18*FF$12)+(EQ18*ES$12)+(EQ18*ET$12))*FA18 -> 0 | FG18: =((EQ18*FG$6)+(EQ18*ES$6)+(EQ18*ET$6))*FB18 -> 0 | FH18: =((EQ18*FH$12)+(EQ18*ES$12)+(EQ18*ET$12))*FC18 -> 0 | FI18: =SUM(FD18:FH18) -> 0 | FJ18: 0 | FK18: =IF(EO18=1,($C$1*$W$6),0) -> 0 | FL18: =EX18+FI18+FJ18+FK18 -> 0 | FM18: 0 | FO18: =FP18/$AY$4 -> 0 | FP18: 0 | FQ18: =FP18*FQ$12 -> 0 | FR18: =FP18*FR$12 -> 0 | FS18: =FP18/FS$12 -> 0 | FT18: =FS18/FT$12 -> 0 | FU18: =FP18/FU$12 -> 0 | FV18: =SUM(FP18:FU18) -> 0 | GB18: =((FO18*GB$12)+(FO18*FQ$12)+(FO18*FR$12))*FW18 -> 0 | GC18: =((FO18*GC$12)+(FO18*FQ$12)+(FO18*FR$12))*FX18 -> 0 | GD18: =((FO18*GD$12)+(FO18*FQ$12)+(FO18*FR$12))*FY18 -> 0 | GE18: =((FO18*GE$6)+(FO18*FQ$6)+(FO18*FR$6))*FZ18 -> 0 | GF18: =((FO18*GF$12)+(FO18*FQ$12)+(FO18*FR$12))*GA18 -> 0 | GG18: =SUM(GB18:GF18) -> 0 | GH18: 0 | GI18: =IF(FM18=1,($C$1*$W$6),0) -> 0 | GJ18: =FV18+GG18+GH18+GI18 -> 0 | GK18: 0 | GM18: =GN18/$AY$4 -> 0 | GN18: 0 | GO18: =GN18*GO$12 -> 0 | GP18: =GN18*GP$12 -> 0 | GQ18: =GN18/GQ$12 -> 0 | GR18: =GQ18/GR$12 -> 0 | GS18: =GN18/GS$12 -> 0 | GT18: =SUM(GN18:GS18) -> 0 | GZ18: =((GM18*GZ$12)+(GM18*GO$12)+(GM18*GP$12))*GU18 -> 0 | HA18: =((GM18*HA$12)+(GM18*GO$12)+(GM18*GP$12))*GV18 -> 0 | HB18: =((GM18*HB$12)+(GM18*GO$12)+(GM18*GP$12))*GW18 -> 0 | HC18: =((GM18*HC$6)+(GM18*GO$6)+(GM18*GP$6))*GX18 -> 0 | HD18: =((GM18*HD$12)+(GM18*GO$12)+(GM18*GP$12))*GY18 -> 0 | HE18: =SUM(GZ18:HD18) -> 0 | HF18: 0 | HG18: =IF(GK18=1,($C$1*$W$6),0) -> 0 | HH18: =GT18+HE18+HF18+HG18 -> 0 | HI18: 0 | HK18: =HL18/$AY$4 -> 0 | HL18: 0 | HM18: =HL18*HM$12 -> 0 | HN18: =HL18*HN$12 -> 0 | HO18: =HL18/HO$12 -> 0 | HP18: =HO18/HP$12 -> 0 | HQ18: =HL18/HQ$12 -> 0 | HR18: =SUM(HL18:HQ18) -> 0 | HX18: =((HK18*HX$12)+(HK18*HM$12)+(HK18*HN$12))*HS18 -> 0 | HY18: =((HK18*HY$12)+(HK18*HM$12)+(HK18*HN$12))*HT18 -> 0 | HZ18: =((HK18*HZ$12)+(HK18*HM$12)+(HK18*HN$12))*HU18 -> 0 | IA18: =((HK18*IA$6)+(HK18*HM$6)+(HK18*HN$6))*HV18 -> 0 | IB18: =((HK18*IB$12)+(HK18*HM$12)+(HK18*HN$12))*HW18 -> 0 | IC18: =SUM(HX18:IB18) -> 0 | ID18: 0 | IE18: =IF(HI18=1,($C$1*$W$6),0) -> 0 | IF18: =HR18+IC18+ID18+IE18 -> 0 | IG18: 0 | II18: =IJ18/$AY$4 -> 0 | IJ18: 0 | IK18: =IJ18*IK$12 -> 0 | IL18: =IJ18*IL$12 -> 0 | IM18: =IJ18/IM$12 -> 0 | IN18: =IM18/IN$12 -> 0 | IO18: =IJ18/IO$12 -> 0 | IP18: =SUM(IJ18:IO18) -> 0 | IV18: =((II18*IV$12)+(II18*IK$12)+(II18*IL$12))*IQ18 -> 0 | IW18: =((II18*IW$12)+(II18*IK$12)+(II18*IL$12))*IR18 -> 0 | IX18: =((II18*IX$12)+(II18*IK$12)+(II18*IL$12))*IS18 -> 0 | IY18: =((II18*IY$6)+(II18*IK$6)+(II18*IL$6))*IT18 -> 0 | IZ18: =((II18*IZ$12)+(II18*IK$12)+(II18*IL$12))*IU18 -> 0 | JA18: =SUM(IV18:IZ18) -> 0 | JB18: 0 | JC18: =IF(IG18=1,($C$1*$W$6),0) -> 0 | JD18: =IP18+JA18+JB18+JC18 -> 0 | JE18: 0 | JG18: =JH18/$AY$4 -> 0 | JH18: 0 | JI18: =JH18*JI$12 -> 0 | JJ18: =JH18*JJ$12 -> 0 | JK18: =JH18/JK$12 -> 0 | JL18: =JK18/JL$12 -> 0 | JM18: =JH18/JM$12 -> 0 | JN18: =SUM(JH18:JM18) -> 0 | JT18: =((JG18*JT$12)+(JG18*JI$12)+(JG18*JJ$12))*JO18 -> 0 | JU18: =((JG18*JU$12)+(JG18*JI$12)+(JG18*JJ$12))*JP18 -> 0 | JV18: =((JG18*JV$12)+(JG18*JI$12)+(JG18*JJ$12))*JQ18 -> 0 | JW18: =((JG18*JW$6)+(JG18*JI$6)+(JG18*JJ$6))*JR18 -> 0 | JX18: =((JG18*JX$12)+(JG18*JI$12)+(JG18*JJ$12))*JS18 -> 0 | JY18: =SUM(JT18:JX18) -> 0 | JZ18: 0 | KA18: =IF(JE18=1,($C$1*$W$6),0) -> 0 | KB18: =JN18+JY18+JZ18+KA18 -> 0
A19: 0 | C19: =D19/$AY$4 -> 0 | D19: 0 | E19: =D19*E$12 -> 0 | F19: =D19*F$12 -> 0 | G19: =D19/G$12 -> 0 | H19: =G19/H$12 -> 0 | I19: =D19/I$12 -> 0 | J19: =SUM(D19:I19) -> 0 | P19: =((C19*P$12)+(C19*E$12)+(C19*F$12))*K19 -> 0 | Q19: =((C19*Q$12)+(C19*E$12)+(C19*F$12))*L19 -> 0 | R19: =((C19*R$12)+(C19*E$12)+(C19*F$12))*M19 -> 0 | S19: =((C19*S$6)+(C19*E$6)+(C19*F$6))*N19 -> 0 | T19: =((C19*T$12)+(C19*E$12)+(C19*F$12))*O19 -> 0 | U19: =SUM(P19:T19) -> 0 | V19: 0 | W19: =IF(A19=1,($C$1*$W$6),0) -> 0 | X19: =J19+U19+V19+W19 -> 0 | Y19: 0 | AA19: =AB19/$AY$4 -> 0 | AB19: 0 | AC19: =AB19*AC$12 -> 0 | AD19: =AB19*AD$12 -> 0 | AE19: =AB19/AE$12 -> 0 | AF19: =AE19/AF$12 -> 0 | AG19: =AB19/AG$12 -> 0 | AH19: =SUM(AB19:AG19) -> 0 | AN19: =((AA19*AN$12)+(AA19*AC$12)+(AA19*AD$12))*AI19 -> 0 | AO19: =((AA19*AO$12)+(AA19*AC$12)+(AA19*AD$12))*AJ19 -> 0 | AP19: =((AA19*AP$12)+(AA19*AC$12)+(AA19*AD$12))*AK19 -> 0 | AQ19: =((AA19*AQ$6)+(AA19*AC$6)+(AA19*AD$6))*AL19 -> 0 | AR19: =((AA19*AR$12)+(AA19*AC$12)+(AA19*AD$12))*AM19 -> 0 | AS19: =SUM(AN19:AR19) -> 0 | AT19: 0 | AU19: =IF(Y19=1,($C$1*$W$6),0) -> 0 | AV19: =AH19+AS19+AT19+AU19 -> 0 | AW19: 0 | AY19: =AZ19/$AY$4 -> 0 | AZ19: 0 | BA19: =AZ19*BA$12 -> 0 | BB19: =AZ19*BB$12 -> 0 | BC19: =AZ19/BC$12 -> 0 | BD19: =BC19/BD$12 -> 0 | BE19: =AZ19/BE$12 -> 0 | BF19: =SUM(AZ19:BE19) -> 0 | BL19: =((AY19*BL$12)+(AY19*BA$12)+(AY19*BB$12))*BG19 -> 0 | BM19: =((AY19*BM$12)+(AY19*BA$12)+(AY19*BB$12))*BH19 -> 0 | BN19: =((AY19*BN$12)+(AY19*BA$12)+(AY19*BB$12))*BI19 -> 0 | BO19: =((AY19*BO$6)+(AY19*BA$6)+(AY19*BB$6))*BJ19 -> 0 | BP19: =((AY19*BP$12)+(AY19*BA$12)+(AY19*BB$12))*BK19 -> 0 | BQ19: =SUM(BL19:BP19) -> 0 | BR19: 0 | BS19: =IF(AW19=1,($C$1*$W$6),0) -> 0 | BT19: =BF19+BQ19+BR19+BS19 -> 0 | BU19: 0 | BW19: =BX19/$AY$4 -> 0 | BX19: 0 | BY19: =BX19*BY$12 -> 0 | BZ19: =BX19*BZ$12 -> 0 | CA19: =BX19/CA$12 -> 0 | CB19: =CA19/CB$12 -> 0 | CC19: =BX19/CC$12 -> 0 | CD19: =SUM(BX19:CC19) -> 0 | CJ19: =((BW19*CJ$12)+(BW19*BY$12)+(BW19*BZ$12))*CE19 -> 0 | CK19: =((BW19*CK$12)+(BW19*BY$12)+(BW19*BZ$12))*CF19 -> 0 | CL19: =((BW19*CL$12)+(BW19*BY$12)+(BW19*BZ$12))*CG19 -> 0 | CM19: =((BW19*CM$6)+(BW19*BY$6)+(BW19*BZ$6))*CH19 -> 0 | CN19: =((BW19*CN$12)+(BW19*BY$12)+(BW19*BZ$12))*CI19 -> 0 | CO19: =SUM(CJ19:CN19) -> 0 | CP19: 0 | CQ19: =IF(BU19=1,($C$1*$W$6),0) -> 0 | CR19: =CD19+CO19+CP19+CQ19 -> 0 | CS19: 0 | CU19: =CV19/$AY$4 -> 0 | CV19: 0 | CW19: =CV19*CW$12 -> 0 | CX19: =CV19*CX$12 -> 0 | CY19: =CV19/CY$12 -> 0 | CZ19: =CY19/CZ$12 -> 0 | DA19: =CV19/DA$12 -> 0 | DB19: =SUM(CV19:DA19) -> 0 | DH19: =((CU19*DH$12)+(CU19*CW$12)+(CU19*CX$12))*DC19 -> 0 | DI19: =((CU19*DI$12)+(CU19*CW$12)+(CU19*CX$12))*DD19 -> 0 | DJ19: =((CU19*DJ$12)+(CU19*CW$12)+(CU19*CX$12))*DE19 -> 0 | DK19: =((CU19*DK$6)+(CU19*CW$6)+(CU19*CX$6))*DF19 -> 0 | DL19: =((CU19*DL$12)+(CU19*CW$12)+(CU19*CX$12))*DG19 -> 0 | DM19: =SUM(DH19:DL19) -> 0 | DN19: 0 | DO19: =IF(CS19=1,($C$1*$W$6),0) -> 0 | DP19: =DB19+DM19+DN19+DO19 -> 0 | DQ19: 0 | DS19: =DT19/$AY$4 -> 0 | DT19: 0 | DU19: =DT19*DU$12 -> 0 | DV19: =DT19*DV$12 -> 0 | DW19: =DT19/DW$12 -> 0 | DX19: =DW19/DX$12 -> 0 | DY19: =DT19/DY$12 -> 0 | DZ19: =SUM(DT19:DY19) -> 0 | EF19: =((DS19*EF$12)+(DS19*DU$12)+(DS19*DV$12))*EA19 -> 0 | EG19: =((DS19*EG$12)+(DS19*DU$12)+(DS19*DV$12))*EB19 -> 0 | EH19: =((DS19*EH$12)+(DS19*DU$12)+(DS19*DV$12))*EC19 -> 0 | EI19: =((DS19*EI$6)+(DS19*DU$6)+(DS19*DV$6))*ED19 -> 0 | EJ19: =((DS19*EJ$12)+(DS19*DU$12)+(DS19*DV$12))*EE19 -> 0 | EK19: =SUM(EF19:EJ19) -> 0 | EL19: 0 | EM19: =IF(DQ19=1,($C$1*$W$6),0) -> 0 | EN19: =DZ19+EK19+EL19+EM19 -> 0 | EO19: 0 | EQ19: =ER19/$AY$4 -> 0 | ER19: 0 | ES19: =ER19*ES$12 -> 0 | ET19: =ER19*ET$12 -> 0 | EU19: =ER19/EU$12 -> 0 | EV19: =EU19/EV$12 -> 0 | EW19: =ER19/EW$12 -> 0 | EX19: =SUM(ER19:EW19) -> 0 | FD19: =((EQ19*FD$12)+(EQ19*ES$12)+(EQ19*ET$12))*EY19 -> 0 | FE19: =((EQ19*FE$12)+(EQ19*ES$12)+(EQ19*ET$12))*EZ19 -> 0 | FF19: =((EQ19*FF$12)+(EQ19*ES$12)+(EQ19*ET$12))*FA19 -> 0 | FG19: =((EQ19*FG$6)+(EQ19*ES$6)+(EQ19*ET$6))*FB19 -> 0 | FH19: =((EQ19*FH$12)+(EQ19*ES$12)+(EQ19*ET$12))*FC19 -> 0 | FI19: =SUM(FD19:FH19) -> 0 | FJ19: 0 | FK19: =IF(EO19=1,($C$1*$W$6),0) -> 0 | FL19: =EX19+FI19+FJ19+FK19 -> 0 | FM19: 0 | FO19: =FP19/$AY$4 -> 0 | FP19: 0 | FQ19: =FP19*FQ$12 -> 0 | FR19: =FP19*FR$12 -> 0 | FS19: =FP19/FS$12 -> 0 | FT19: =FS19/FT$12 -> 0 | FU19: =FP19/FU$12 -> 0 | FV19: =SUM(FP19:FU19) -> 0 | GB19: =((FO19*GB$12)+(FO19*FQ$12)+(FO19*FR$12))*FW19 -> 0 | GC19: =((FO19*GC$12)+(FO19*FQ$12)+(FO19*FR$12))*FX19 -> 0 | GD19: =((FO19*GD$12)+(FO19*FQ$12)+(FO19*FR$12))*FY19 -> 0 | GE19: =((FO19*GE$6)+(FO19*FQ$6)+(FO19*FR$6))*FZ19 -> 0 | GF19: =((FO19*GF$12)+(FO19*FQ$12)+(FO19*FR$12))*GA19 -> 0 | GG19: =SUM(GB19:GF19) -> 0 | GH19: 0 | GI19: =IF(FM19=1,($C$1*$W$6),0) -> 0 | GJ19: =FV19+GG19+GH19+GI19 -> 0 | GK19: 0 | GM19: =GN19/$AY$4 -> 0 | GN19: 0 | GO19: =GN19*GO$12 -> 0 | GP19: =GN19*GP$12 -> 0 | GQ19: =GN19/GQ$12 -> 0 | GR19: =GQ19/GR$12 -> 0 | GS19: =GN19/GS$12 -> 0 | GT19: =SUM(GN19:GS19) -> 0 | GZ19: =((GM19*GZ$12)+(GM19*GO$12)+(GM19*GP$12))*GU19 -> 0 | HA19: =((GM19*HA$12)+(GM19*GO$12)+(GM19*GP$12))*GV19 -> 0 | HB19: =((GM19*HB$12)+(GM19*GO$12)+(GM19*GP$12))*GW19 -> 0 | HC19: =((GM19*HC$6)+(GM19*GO$6)+(GM19*GP$6))*GX19 -> 0 | HD19: =((GM19*HD$12)+(GM19*GO$12)+(GM19*GP$12))*GY19 -> 0 | HE19: =SUM(GZ19:HD19) -> 0 | HF19: 0 | HG19: =IF(GK19=1,($C$1*$W$6),0) -> 0 | HH19: =GT19+HE19+HF19+HG19 -> 0 | HI19: 0 | HK19: =HL19/$AY$4 -> 0 | HL19: 0 | HM19: =HL19*HM$12 -> 0 | HN19: =HL19*HN$12 -> 0 | HO19: =HL19/HO$12 -> 0 | HP19: =HO19/HP$12 -> 0 | HQ19: =HL19/HQ$12 -> 0 | HR19: =SUM(HL19:HQ19) -> 0 | HX19: =((HK19*HX$12)+(HK19*HM$12)+(HK19*HN$12))*HS19 -> 0 | HY19: =((HK19*HY$12)+(HK19*HM$12)+(HK19*HN$12))*HT19 -> 0 | HZ19: =((HK19*HZ$12)+(HK19*HM$12)+(HK19*HN$12))*HU19 -> 0 | IA19: =((HK19*IA$6)+(HK19*HM$6)+(HK19*HN$6))*HV19 -> 0 | IB19: =((HK19*IB$12)+(HK19*HM$12)+(HK19*HN$12))*HW19 -> 0 | IC19: =SUM(HX19:IB19) -> 0 | ID19: 0 | IE19: =IF(HI19=1,($C$1*$W$6),0) -> 0 | IF19: =HR19+IC19+ID19+IE19 -> 0 | IG19: 0 | II19: =IJ19/$AY$4 -> 0 | IJ19: 0 | IK19: =IJ19*IK$12 -> 0 | IL19: =IJ19*IL$12 -> 0 | IM19: =IJ19/IM$12 -> 0 | IN19: =IM19/IN$12 -> 0 | IO19: =IJ19/IO$12 -> 0 | IP19: =SUM(IJ19:IO19) -> 0 | IV19: =((II19*IV$12)+(II19*IK$12)+(II19*IL$12))*IQ19 -> 0 | IW19: =((II19*IW$12)+(II19*IK$12)+(II19*IL$12))*IR19 -> 0 | IX19: =((II19*IX$12)+(II19*IK$12)+(II19*IL$12))*IS19 -> 0 | IY19: =((II19*IY$6)+(II19*IK$6)+(II19*IL$6))*IT19 -> 0 | IZ19: =((II19*IZ$12)+(II19*IK$12)+(II19*IL$12))*IU19 -> 0 | JA19: =SUM(IV19:IZ19) -> 0 | JB19: 0 | JC19: =IF(IG19=1,($C$1*$W$6),0) -> 0 | JD19: =IP19+JA19+JB19+JC19 -> 0 | JE19: 0 | JG19: =JH19/$AY$4 -> 0 | JH19: 0 | JI19: =JH19*JI$12 -> 0 | JJ19: =JH19*JJ$12 -> 0 | JK19: =JH19/JK$12 -> 0 | JL19: =JK19/JL$12 -> 0 | JM19: =JH19/JM$12 -> 0 | JN19: =SUM(JH19:JM19) -> 0 | JT19: =((JG19*JT$12)+(JG19*JI$12)+(JG19*JJ$12))*JO19 -> 0 | JU19: =((JG19*JU$12)+(JG19*JI$12)+(JG19*JJ$12))*JP19 -> 0 | JV19: =((JG19*JV$12)+(JG19*JI$12)+(JG19*JJ$12))*JQ19 -> 0 | JW19: =((JG19*JW$6)+(JG19*JI$6)+(JG19*JJ$6))*JR19 -> 0 | JX19: =((JG19*JX$12)+(JG19*JI$12)+(JG19*JJ$12))*JS19 -> 0 | JY19: =SUM(JT19:JX19) -> 0 | JZ19: 0 | KA19: =IF(JE19=1,($C$1*$W$6),0) -> 0 | KB19: =JN19+JY19+JZ19+KA19 -> 0
W20: Total | X20: =SUM(X14:X19) -> 5410.4043 | AU20: Total | AV20: =SUM(AV14:AV19) -> 5410.4043 | BS20: Total | BT20: =SUM(BT14:BT19) -> 5410.4043 | CQ20: Total | CR20: =SUM(CR14:CR19) -> 5410.4043 | DO20: Total | DP20: =SUM(DP14:DP19) -> 5410.4043 | EM20: Total | EN20: =SUM(EN14:EN19) -> 5410.4043 | FK20: Total | FL20: =SUM(FL14:FL19) -> 5410.4043 | GI20: Total | GJ20: =SUM(GJ14:GJ19) -> 5410.4043 | HG20: Total | HH20: =SUM(HH14:HH19) -> 5410.4043 | IE20: Total | IF20: =SUM(IF14:IF19) -> 5410.4043 | JC20: Total | JD20: =SUM(JD14:JD19) -> 5410.4043 | KA20: Total | KB20: =SUM(KB14:KB19) -> 5410.4043
B21: Funcionário | C21: Sal/Hora | D21: Salario Mensal | E21: 0.1 | F21: 0.08 | G21: 12 | H21: 3 | I21: 12 | J21: - | K21: 0.5 | L21: 0.6 | M21: 0.8 | N21: 1 | O21: 1.5 | P21: 1.5 | Q21: 1.6 | R21: 1.8 | S21: 2 | T21: 2.5 | U21: - | V21: - | W21: 0.2 | X21: - | Z21: Funcionário | AA21: Sal/Hora | AB21: Salario Mensal | AC21: 0.1 | AD21: 0.08 | AE21: 12 | AF21: 3 | AG21: 12 | AH21: - | AI21: 0.5 | AJ21: 0.6 | AK21: 0.8 | AL21: 1 | AM21: 1.5 | AN21: 1.5 | AO21: 1.6 | AP21: 1.8 | AQ21: 2 | AR21: 2.5 | AS21: - | AT21: - | AU21: 0.2 | AV21: - | AX21: Funcionário | AY21: Sal/Hora | AZ21: Salario Mensal | BA21: 0.1 | BB21: 0.08 | BC21: 12 | BD21: 3 | BE21: 12 | BF21: - | BG21: 0.5 | BH21: 0.6 | BI21: 0.8 | BJ21: 1 | BK21: 1.5 | BL21: 1.5 | BM21: 1.6 | BN21: 1.8 | BO21: 2 | BP21: 2.5 | BQ21: - | BR21: - | BS21: 0.2 | BT21: - | BV21: Funcionário | BW21: Sal/Hora | BX21: Salario Mensal | BY21: 0.1 | BZ21: 0.08 | CA21: 12 | CB21: 3 | CC21: 12 | CD21: - | CE21: 0.5 | CF21: 0.6 | CG21: 0.8 | CH21: 1 | CI21: 1.5 | CJ21: 1.5 | CK21: 1.6 | CL21: 1.8 | CM21: 2 | CN21: 2.5 | CO21: - | CP21: - | CQ21: 0.2 | CR21: - | CT21: Funcionário | CU21: Sal/Hora | CV21: Salario Mensal | CW21: 0.1 | CX21: 0.08 | CY21: 12 | CZ21: 3 | DA21: 12 | DB21: - | DC21: 0.5 | DD21: 0.6 | DE21: 0.8 | DF21: 1 | DG21: 1.5 | DH21: 1.5 | DI21: 1.6 | DJ21: 1.8 | DK21: 2 | DL21: 2.5 | DM21: - | DN21: - | DO21: 0.2 | DP21: - | DR21: Funcionário | DS21: Sal/Hora | DT21: Salario Mensal | DU21: 0.1 | DV21: 0.08 | DW21: 12 | DX21: 3 | DY21: 12 | DZ21: - | EA21: 0.5 | EB21: 0.6 | EC21: 0.8 | ED21: 1 | EE21: 1.5 | EF21: 1.5 | EG21: 1.6 | EH21: 1.8 | EI21: 2 | EJ21: 2.5 | EK21: - | EL21: - | EM21: 0.2 | EN21: - | EP21: Funcionário | EQ21: Sal/Hora | ER21: Salario Mensal | ES21: 0.1 | ET21: 0.08 | EU21: 12 | EV21: 3 | EW21: 12 | EX21: - | EY21: 0.5 | EZ21: 0.6 | FA21: 0.8 | FB21: 1 | FC21: 1.5 | FD21: 1.5 | FE21: 1.6 | FF21: 1.8 | FG21: 2 | FH21: 2.5 | FI21: - | FJ21: - | FK21: 0.2 | FL21: - | FN21: Funcionário | FO21: Sal/Hora | FP21: Salario Mensal | FQ21: 0.1 | FR21: 0.08 | FS21: 12 | FT21: 3 | FU21: 12 | FV21: - | FW21: 0.5 | FX21: 0.6 | FY21: 0.8 | FZ21: 1 | GA21: 1.5 | GB21: 1.5 | GC21: 1.6 | GD21: 1.8 | GE21: 2 | GF21: 2.5 | GG21: - | GH21: - | GI21: 0.2 | GJ21: - | GL21: Funcionário | GM21: Sal/Hora | GN21: Salario Mensal | GO21: 0.1 | GP21: 0.08 | GQ21: 12 | GR21: 3 | GS21: 12 | GT21: - | GU21: 0.5 | GV21: 0.6 | GW21: 0.8 | GX21: 1 | GY21: 1.5 | GZ21: 1.5 | HA21: 1.6 | HB21: 1.8 | HC21: 2 | HD21: 2.5 | HE21: - | HF21: - | HG21: 0.2 | HH21: - | HJ21: Funcionário | HK21: Sal/Hora | HL21: Salario Mensal | HM21: 0.1 | HN21: 0.08 | HO21: 12 | HP21: 3 | HQ21: 12 | HR21: - | HS21: 0.5 | HT21: 0.6 | HU21: 0.8 | HV21: 1 | HW21: 1.5 | HX21: 1.5 | HY21: 1.6 | HZ21: 1.8 | IA21: 2 | IB21: 2.5 | IC21: - | ID21: - | IE21: 0.2 | IF21: - | IH21: Funcionário | II21: Sal/Hora | IJ21: Salario Mensal | IK21: 0.1 | IL21: 0.08 | IM21: 12 | IN21: 3 | IO21: 12 | IP21: - | IQ21: 0.5 | IR21: 0.6 | IS21: 0.8 | IT21: 1 | IU21: 1.5 | IV21: 1.5 | IW21: 1.6 | IX21: 1.8 | IY21: 2 | IZ21: 2.5 | JA21: - | JB21: - | JC21: 0.2 | JD21: - | JF21: Funcionário | JG21: Sal/Hora | JH21: Salario Mensal | JI21: 0.1 | JJ21: 0.08 | JK21: 12 | JL21: 3 | JM21: 12 | JN21: - | JO21: 0.5 | JP21: 0.6 | JQ21: 0.8 | JR21: 1 | JS21: 1.5 | JT21: 1.5 | JU21: 1.6 | JV21: 1.8 | JW21: 2 | JX21: 2.5 | JY21: - | JZ21: - | KA21: 0.2 | KB21: -
E22: Linha 3 Zn Alc.Aut | AC22: Linha 3 Zn Alc.Aut | BA22: Linha 3 Zn Alc.Aut | BY22: Linha 3 Zn Alc.Aut | CW22: Linha 3 Zn Alc.Aut | DU22: Linha 3 Zn Alc.Aut | ES22: Linha 3 Zn Alc.Aut | FQ22: Linha 3 Zn Alc.Aut | GO22: Linha 3 Zn Alc.Aut | HM22: Linha 3 Zn Alc.Aut | IK22: Linha 3 Zn Alc.Aut | JI22: Linha 3 Zn Alc.Aut
A23: 0 | B23: Sérgio Op. A | C23: =D23/$AY$4 -> 13.321409 | D23: 2930.71 | E23: =D23*E$21 -> 293.071 | F23: =D23*F$21 -> 234.4568 | G23: =D23/G$21 -> 244.22583 | H23: =G23/H$21 -> 81.408611 | I23: =D23/I$21 -> 244.22583 | J23: =SUM(D23:I23) -> 4028.0981 | P23: =((C23*P$21)+(C23*E$21)+(C23*F$21))*K23 -> 0 | Q23: =((C23*Q$21)+(C23*E$21)+(C23*F$21))*L23 -> 0 | R23: =((C23*R$21)+(C23*F$21)+(C23*E$21))*M23 -> 0 | S23: =((C23*S$21)+(C23*E$21)+(C23*F$21))*N23 -> 0 | T23: =((C23*T$21)+(C23*E$21)+(C23*F$21))*O23 -> 0 | U23: =SUM(P23:T23) -> 0 | V23: 0 | W23: =IF(A23=1,($C$1*$W$6),0) -> 0 | X23: =J23+U23+V23+W23 -> 4028.0981 | Y23: 0 | Z23: Sérgio Op. A | AA23: =AB23/$AY$4 -> 13.321409 | AB23: 2930.71 | AC23: =AB23*AC$21 -> 293.071 | AD23: =AB23*AD$21 -> 234.4568 | AE23: =AB23/AE$21 -> 244.22583 | AF23: =AE23/AF$21 -> 81.408611 | AG23: =AB23/AG$21 -> 244.22583 | AH23: =SUM(AB23:AG23) -> 4028.0981 | AN23: =((AA23*AN$21)+(AA23*AC$21)+(AA23*AD$21))*AI23 -> 0 | AO23: =((AA23*AO$21)+(AA23*AC$21)+(AA23*AD$21))*AJ23 -> 0 | AP23: =((AA23*AP$21)+(AA23*AD$21)+(AA23*AC$21))*AK23 -> 0 | AQ23: =((AA23*AQ$21)+(AA23*AC$21)+(AA23*AD$21))*AL23 -> 0 | AR23: =((AA23*AR$21)+(AA23*AC$21)+(AA23*AD$21))*AM23 -> 0 | AS23: =SUM(AN23:AR23) -> 0 | AT23: 0 | AU23: =IF(Y23=1,($C$1*$W$6),0) -> 0 | AV23: =AH23+AS23+AT23+AU23 -> 4028.0981 | AW23: 0 | AX23: Sérgio Op. A | AY23: =AZ23/$AY$4 -> 13.321409 | AZ23: 2930.71 | BA23: =AZ23*BA$21 -> 293.071 | BB23: =AZ23*BB$21 -> 234.4568 | BC23: =AZ23/BC$21 -> 244.22583 | BD23: =BC23/BD$21 -> 81.408611 | BE23: =AZ23/BE$21 -> 244.22583 | BF23: =SUM(AZ23:BE23) -> 4028.0981 | BL23: =((AY23*BL$21)+(AY23*BA$21)+(AY23*BB$21))*BG23 -> 0 | BM23: =((AY23*BM$21)+(AY23*BA$21)+(AY23*BB$21))*BH23 -> 0 | BN23: =((AY23*BN$21)+(AY23*BB$21)+(AY23*BA$21))*BI23 -> 0 | BO23: =((AY23*BO$21)+(AY23*BA$21)+(AY23*BB$21))*BJ23 -> 0 | BP23: =((AY23*BP$21)+(AY23*BA$21)+(AY23*BB$21))*BK23 -> 0 | BQ23: =SUM(BL23:BP23) -> 0 | BR23: 0 | BS23: =IF(AW23=1,($C$1*$W$6),0) -> 0 | BT23: =BF23+BQ23+BR23+BS23 -> 4028.0981 | BU23: 0 | BV23: Sérgio Op. A | BW23: =BX23/$AY$4 -> 13.321409 | BX23: 2930.71 | BY23: =BX23*BY$21 -> 293.071 | BZ23: =BX23*BZ$21 -> 234.4568 | CA23: =BX23/CA$21 -> 244.22583 | CB23: =CA23/CB$21 -> 81.408611 | CC23: =BX23/CC$21 -> 244.22583 | CD23: =SUM(BX23:CC23) -> 4028.0981 | CJ23: =((BW23*CJ$21)+(BW23*BY$21)+(BW23*BZ$21))*CE23 -> 0 | CK23: =((BW23*CK$21)+(BW23*BY$21)+(BW23*BZ$21))*CF23 -> 0 | CL23: =((BW23*CL$21)+(BW23*BZ$21)+(BW23*BY$21))*CG23 -> 0 | CM23: =((BW23*CM$21)+(BW23*BY$21)+(BW23*BZ$21))*CH23 -> 0 | CN23: =((BW23*CN$21)+(BW23*BY$21)+(BW23*BZ$21))*CI23 -> 0 | CO23: =SUM(CJ23:CN23) -> 0 | CP23: 0 | CQ23: =IF(BU23=1,($C$1*$W$6),0) -> 0 | CR23: =CD23+CO23+CP23+CQ23 -> 4028.0981 | CS23: 0 | CT23: Sérgio Op. A | CU23: =CV23/$AY$4 -> 13.321409 | CV23: 2930.71 | CW23: =CV23*CW$21 -> 293.071 | CX23: =CV23*CX$21 -> 234.4568 | CY23: =CV23/CY$21 -> 244.22583 | CZ23: =CY23/CZ$21 -> 81.408611 | DA23: =CV23/DA$21 -> 244.22583 | DB23: =SUM(CV23:DA23) -> 4028.0981 | DH23: =((CU23*DH$21)+(CU23*CW$21)+(CU23*CX$21))*DC23 -> 0 | DI23: =((CU23*DI$21)+(CU23*CW$21)+(CU23*CX$21))*DD23 -> 0 | DJ23: =((CU23*DJ$21)+(CU23*CX$21)+(CU23*CW$21))*DE23 -> 0 | DK23: =((CU23*DK$21)+(CU23*CW$21)+(CU23*CX$21))*DF23 -> 0 | DL23: =((CU23*DL$21)+(CU23*CW$21)+(CU23*CX$21))*DG23 -> 0 | DM23: =SUM(DH23:DL23) -> 0 | DN23: 0 | DO23: =IF(CS23=1,($C$1*$W$6),0) -> 0 | DP23: =DB23+DM23+DN23+DO23 -> 4028.0981 | DQ23: 0 | DR23: Sérgio Op. A | DS23: =DT23/$AY$4 -> 13.321409 | DT23: 2930.71 | DU23: =DT23*DU$21 -> 293.071 | DV23: =DT23*DV$21 -> 234.4568 | DW23: =DT23/DW$21 -> 244.22583 | DX23: =DW23/DX$21 -> 81.408611 | DY23: =DT23/DY$21 -> 244.22583 | DZ23: =SUM(DT23:DY23) -> 4028.0981 | EF23: =((DS23*EF$21)+(DS23*DU$21)+(DS23*DV$21))*EA23 -> 0 | EG23: =((DS23*EG$21)+(DS23*DU$21)+(DS23*DV$21))*EB23 -> 0 | EH23: =((DS23*EH$21)+(DS23*DV$21)+(DS23*DU$21))*EC23 -> 0 | EI23: =((DS23*EI$21)+(DS23*DU$21)+(DS23*DV$21))*ED23 -> 0 | EJ23: =((DS23*EJ$21)+(DS23*DU$21)+(DS23*DV$21))*EE23 -> 0 | EK23: =SUM(EF23:EJ23) -> 0 | EL23: 0 | EM23: =IF(DQ23=1,($C$1*$W$6),0) -> 0 | EN23: =DZ23+EK23+EL23+EM23 -> 4028.0981 | EO23: 0 | EP23: Sérgio Op. A | EQ23: =ER23/$AY$4 -> 13.321409 | ER23: 2930.71 | ES23: =ER23*ES$21 -> 293.071 | ET23: =ER23*ET$21 -> 234.4568 | EU23: =ER23/EU$21 -> 244.22583 | EV23: =EU23/EV$21 -> 81.408611 | EW23: =ER23/EW$21 -> 244.22583 | EX23: =SUM(ER23:EW23) -> 4028.0981 | FD23: =((EQ23*FD$21)+(EQ23*ES$21)+(EQ23*ET$21))*EY23 -> 0 | FE23: =((EQ23*FE$21)+(EQ23*ES$21)+(EQ23*ET$21))*EZ23 -> 0 | FF23: =((EQ23*FF$21)+(EQ23*ET$21)+(EQ23*ES$21))*FA23 -> 0 | FG23: =((EQ23*FG$21)+(EQ23*ES$21)+(EQ23*ET$21))*FB23 -> 0 | FH23: =((EQ23*FH$21)+(EQ23*ES$21)+(EQ23*ET$21))*FC23 -> 0 | FI23: =SUM(FD23:FH23) -> 0 | FJ23: 0 | FK23: =IF(EO23=1,($C$1*$W$6),0) -> 0 | FL23: =EX23+FI23+FJ23+FK23 -> 4028.0981 | FM23: 0 | FN23: Sérgio Op. A | FO23: =FP23/$AY$4 -> 13.321409 | FP23: 2930.71 | FQ23: =FP23*FQ$21 -> 293.071 | FR23: =FP23*FR$21 -> 234.4568 | FS23: =FP23/FS$21 -> 244.22583 | FT23: =FS23/FT$21 -> 81.408611 | FU23: =FP23/FU$21 -> 244.22583 | FV23: =SUM(FP23:FU23) -> 4028.0981 | GB23: =((FO23*GB$21)+(FO23*FQ$21)+(FO23*FR$21))*FW23 -> 0 | GC23: =((FO23*GC$21)+(FO23*FQ$21)+(FO23*FR$21))*FX23 -> 0 | GD23: =((FO23*GD$21)+(FO23*FR$21)+(FO23*FQ$21))*FY23 -> 0 | GE23: =((FO23*GE$21)+(FO23*FQ$21)+(FO23*FR$21))*FZ23 -> 0 | GF23: =((FO23*GF$21)+(FO23*FQ$21)+(FO23*FR$21))*GA23 -> 0 | GG23: =SUM(GB23:GF23) -> 0 | GH23: 0 | GI23: =IF(FM23=1,($C$1*$W$6),0) -> 0 | GJ23: =FV23+GG23+GH23+GI23 -> 4028.0981 | GK23: 0 | GL23: Sérgio Op. A | GM23: =GN23/$AY$4 -> 13.321409 | GN23: 2930.71 | GO23: =GN23*GO$21 -> 293.071 | GP23: =GN23*GP$21 -> 234.4568 | GQ23: =GN23/GQ$21 -> 244.22583 | GR23: =GQ23/GR$21 -> 81.408611 | GS23: =GN23/GS$21 -> 244.22583 | GT23: =SUM(GN23:GS23) -> 4028.0981 | GZ23: =((GM23*GZ$21)+(GM23*GO$21)+(GM23*GP$21))*GU23 -> 0 | HA23: =((GM23*HA$21)+(GM23*GO$21)+(GM23*GP$21))*GV23 -> 0 | HB23: =((GM23*HB$21)+(GM23*GP$21)+(GM23*GO$21))*GW23 -> 0 | HC23: =((GM23*HC$21)+(GM23*GO$21)+(GM23*GP$21))*GX23 -> 0 | HD23: =((GM23*HD$21)+(GM23*GO$21)+(GM23*GP$21))*GY23 -> 0 | HE23: =SUM(GZ23:HD23) -> 0 | HF23: 0 | HG23: =IF(GK23=1,($C$1*$W$6),0) -> 0 | HH23: =GT23+HE23+HF23+HG23 -> 4028.0981 | HI23: 0 | HJ23: Sérgio Op. A | HK23: =HL23/$AY$4 -> 13.321409 | HL23: 2930.71 | HM23: =HL23*HM$21 -> 293.071 | HN23: =HL23*HN$21 -> 234.4568 | HO23: =HL23/HO$21 -> 244.22583 | HP23: =HO23/HP$21 -> 81.408611 | HQ23: =HL23/HQ$21 -> 244.22583 | HR23: =SUM(HL23:HQ23) -> 4028.0981 | HX23: =((HK23*HX$21)+(HK23*HM$21)+(HK23*HN$21))*HS23 -> 0 | HY23: =((HK23*HY$21)+(HK23*HM$21)+(HK23*HN$21))*HT23 -> 0 | HZ23: =((HK23*HZ$21)+(HK23*HN$21)+(HK23*HM$21))*HU23 -> 0 | IA23: =((HK23*IA$21)+(HK23*HM$21)+(HK23*HN$21))*HV23 -> 0 | IB23: =((HK23*IB$21)+(HK23*HM$21)+(HK23*HN$21))*HW23 -> 0 | IC23: =SUM(HX23:IB23) -> 0 | ID23: 0 | IE23: =IF(HI23=1,($C$1*$W$6),0) -> 0 | IF23: =HR23+IC23+ID23+IE23 -> 4028.0981 | IG23: 0 | IH23: Sérgio Op. A | II23: =IJ23/$AY$4 -> 13.321409 | IJ23: 2930.71 | IK23: =IJ23*IK$21 -> 293.071 | IL23: =IJ23*IL$21 -> 234.4568 | IM23: =IJ23/IM$21 -> 244.22583 | IN23: =IM23/IN$21 -> 81.408611 | IO23: =IJ23/IO$21 -> 244.22583 | IP23: =SUM(IJ23:IO23) -> 4028.0981 | IV23: =((II23*IV$21)+(II23*IK$21)+(II23*IL$21))*IQ23 -> 0 | IW23: =((II23*IW$21)+(II23*IK$21)+(II23*IL$21))*IR23 -> 0 | IX23: =((II23*IX$21)+(II23*IL$21)+(II23*IK$21))*IS23 -> 0 | IY23: =((II23*IY$21)+(II23*IK$21)+(II23*IL$21))*IT23 -> 0 | IZ23: =((II23*IZ$21)+(II23*IK$21)+(II23*IL$21))*IU23 -> 0 | JA23: =SUM(IV23:IZ23) -> 0 | JB23: 0 | JC23: =IF(IG23=1,($C$1*$W$6),0) -> 0 | JD23: =IP23+JA23+JB23+JC23 -> 4028.0981 | JE23: 0 | JF23: Sérgio Op. A | JG23: =JH23/$AY$4 -> 13.321409 | JH23: 2930.71 | JI23: =JH23*JI$21 -> 293.071 | JJ23: =JH23*JJ$21 -> 234.4568 | JK23: =JH23/JK$21 -> 244.22583 | JL23: =JK23/JL$21 -> 81.408611 | JM23: =JH23/JM$21 -> 244.22583 | JN23: =SUM(JH23:JM23) -> 4028.0981 | JT23: =((JG23*JT$21)+(JG23*JI$21)+(JG23*JJ$21))*JO23 -> 0 | JU23: =((JG23*JU$21)+(JG23*JI$21)+(JG23*JJ$21))*JP23 -> 0 | JV23: =((JG23*JV$21)+(JG23*JJ$21)+(JG23*JI$21))*JQ23 -> 0 | JW23: =((JG23*JW$21)+(JG23*JI$21)+(JG23*JJ$21))*JR23 -> 0 | JX23: =((JG23*JX$21)+(JG23*JI$21)+(JG23*JJ$21))*JS23 -> 0 | JY23: =SUM(JT23:JX23) -> 0 | JZ23: 0 | KA23: =IF(JE23=1,($C$1*$W$6),0) -> 0 | KB23: =JN23+JY23+JZ23+KA23 -> 4028.0981
